Workbook

Sheet Intro
A19: STEPS:
A20: 1) enter financial data on the Financial Statements sheet,
A21: 2) examine the Ratio Analysis and Cash Flow Analysis,
A22: 3) enter forecasts on the Forecasting Assumptions sheet to predict the future Financial Statements,
A23: 4) enter cost of capital assumptions on the Valuation Parameters Sheet to determine the company's value,
A24: 5) evaluate the details of the resulting valuation using either the Residual Income or Discounted Cash Flow Valuations.

Sheet Financial Statements
A1: Financial Statements | B1: ($000s) | C1: Data can be entered manually in financial statements or as a block cut-and-paste from the Case Data Sheet to the Raw Data Input section below.
C3: Jump to Raw Data Input
A4: Company Name, Ticker and SIC | B4: =B82 -> DOLLAR TREE 2021 | D4: =D82 -> DLTR | E4: =F82 -> 5331 | F4: =IF(D4="","",HYPERLINK(CONCATENATE("http://www.sec.gov/cgi-bin/browse-edgar?type=10-K&action=getcompany&CIK=",D4),"Link to Form 10-Ks")) -> Link to Form 10-Ks
A5: Common Shares Outstanding | B5: =B83 -> 225100.2 | C5: (in 000s at most recent fiscal year end) | F5: Link to Industry Comps
A6: ="Estimated Price/Share="&DOLLAR('Valuation Parameters'!B24) -> Estimated Price/Share=£105.41
B7: Actual | C7: Actual | D7: Actual | E7: Actual | F7: Actual | G7: Forecast | H7: Forecast | I7: Forecast | J7: Forecast | K7: Forecast | L7: Forecast | M7: Forecast | N7: Forecast | O7: Forecast | P7: Forecast | Q7: Forecast | R7: Forecast
A8: Fiscal Year End (YYYY-MM-DD) | B8: =B84 -> 41669 | C8: =C84 -> 42034 | D8: =D84 -> 42399 | E8: =E84 -> 42765 | F8: =F84 -> 43130 | G8: =DATE(YEAR(F8)+1,MONTH(F8),DAY(F8)) -> 43495 | H8: =DATE(YEAR(G8)+1,MONTH(G8),DAY(G8)) -> 43860 | I8: =DATE(YEAR(H8)+1,MONTH(H8),DAY(H8)) -> 44226 | J8: =DATE(YEAR(I8)+1,MONTH(I8),DAY(I8)) -> 44591 | K8: =DATE(YEAR(J8)+1,MONTH(J8),DAY(J8)) -> 44956 | L8: =DATE(YEAR(K8)+1,MONTH(K8),DAY(K8)) -> 45321 | M8: =DATE(YEAR(L8)+1,MONTH(L8),DAY(L8)) -> 45687 | N8: =DATE(YEAR(M8)+1,MONTH(M8),DAY(M8)) -> 46052 | ... R8: =DATE(YEAR(Q8)+1,MONTH(Q8),DAY(Q8)) -> 47513
A10: Income Statement
A12: Sales (Net) | B12: =B85 -> 22245500 | C12: =C85 -> 22823300 | D12: =D85 -> 23610800 | E12: =E85 -> 25509300 | F12: =F85 -> 26321200 | G12: =F12*(1+'Forecasting Assumptions'!G14) -> 27154568 | H12: =G12*(1+'Forecasting Assumptions'!H14) -> 28009809 | I12: =H12*(1+'Forecasting Assumptions'!I14) -> 28887333 | J12: =I12*(1+'Forecasting Assumptions'!J14) -> 29787550 | K12: =J12*(1+'Forecasting Assumptions'!K14) -> 30710871 | L12: =K12*(1+'Forecasting Assumptions'!L14) -> 31657710 | M12: =L12*(1+'Forecasting Assumptions'!M14) -> 32628480 | N12: =M12*(1+'Forecasting Assumptions'!N14) -> 33623598 | ... R12: =Q12*(1+'Forecasting Assumptions'!R14) -> 37861971
A13: Cost of Goods Sold | B13: =B86 -> -15223600 | C13: =C86 -> -15875800 | D13: =D86 -> -16570100 | E13: =E86 -> -17721900 | F13: =F86 -> -18595300 | G13: =-G12*'Forecasting Assumptions'!G15 -> -19184054 | H13: =-H12*'Forecasting Assumptions'!H15 -> -19788262 | I13: =-I12*'Forecasting Assumptions'!I15 -> -20408212 | J13: =-J12*'Forecasting Assumptions'!J15 -> -21044194 | K13: =-K12*'Forecasting Assumptions'!K15 -> -21696498 | L13: =-L12*'Forecasting Assumptions'!L15 -> -22365417 | M13: =-M12*'Forecasting Assumptions'!M15 -> -23051243 | N13: =-N12*'Forecasting Assumptions'!N15 -> -23754270 | ... R13: =-R12*'Forecasting Assumptions'!R15 -> -26748579
A14: Gross Profit | B14: =B12+B13 -> 7021900 | C14: =C12+C13 -> 6947500 | D14: =D12+D13 -> 7040700 | E14: =E12+E13 -> 7787400 | F14: =F12+F13 -> 7725900 | G14: =G12+G13 -> 7970513.3 | H14: =H12+H13 -> 8221547.1 | I14: =I12+I13 -> 8479121.4 | ... R14: =R12+R13 -> 11113392
A15: R&D Expense | B15: =B87 -> 0 | C15: =C87 -> 0 | D15: =D87 -> 0 | E15: =E87 -> 0 | F15: =F87 -> 0 | G15: =-G12*'Forecasting Assumptions'!G16 -> 0 | H15: =-H12*'Forecasting Assumptions'!H16 -> 0 | I15: =-I12*'Forecasting Assumptions'!I16 -> 0 | J15: =-J12*'Forecasting Assumptions'!J16 -> 0 | K15: =-K12*'Forecasting Assumptions'!K16 -> 0 | L15: =-L12*'Forecasting Assumptions'!L16 -> 0 | M15: =-M12*'Forecasting Assumptions'!M16 -> 0 | N15: =-N12*'Forecasting Assumptions'!N16 -> 0 | ... R15: =-R12*'Forecasting Assumptions'!R16 -> 0
A16: SG&A Expense | B16: =B88 -> -4953600 | C16: =C88 -> -7887000 | D16: =D88 -> -5778500 | E16: =E88 -> -5899500 | F16: =F88 -> -5914500 | G16: =-G12*'Forecasting Assumptions'!G17 -> -6101761.7 | H16: =-H12*'Forecasting Assumptions'!H17 -> -6293938.6 | I16: =-I12*'Forecasting Assumptions'!I17 -> -6491122.5 | J16: =-J12*'Forecasting Assumptions'!J17 -> -6693405.5 | K16: =-K12*'Forecasting Assumptions'!K17 -> -6900880.2 | L16: =-L12*'Forecasting Assumptions'!L17 -> -7113639.3 | M16: =-M12*'Forecasting Assumptions'!M17 -> -7331776.1 | N16: =-N12*'Forecasting Assumptions'!N17 -> -7555383.9 | ... R16: =-R12*'Forecasting Assumptions'!R17 -> -8507766.6
A17: EBITDA | B17: =B14+B15+B16 -> 2068300 | C17: =C14+C15+C16 -> -939500 | D17: =D14+D15+D16 -> 1262200 | E17: =E14+E15+E16 -> 1887900 | F17: =F14+F15+F16 -> 1811400 | G17: =G14+G15+G16 -> 1868751.6 | H17: =H14+H15+H16 -> 1927608.5 | I17: =I14+I15+I16 -> 1987998.9 | ... R17: =R14+R15+R16 -> 2605624.9
A18: Depreciation & Amortization | B18: =B89 -> -69200 | C18: =C89 -> 0 | D18: =D89 -> 0 | E18: =E89 -> 0 | F18: =F89 -> 0 | G18: =-((F38+G38+F40+G40)/2)*'Forecasting Assumptions'!G18 -> 0 | H18: =-((G38+H38+G40+H40)/2)*'Forecasting Assumptions'!H18 -> 0 | I18: =-((H38+I38+H40+I40)/2)*'Forecasting Assumptions'!I18 -> 0 | J18: =-((I38+J38+I40+J40)/2)*'Forecasting Assumptions'!J18 -> 0 | K18: =-((J38+K38+J40+K40)/2)*'Forecasting Assumptions'!K18 -> 0 | L18: =-((K38+L38+K40+L40)/2)*'Forecasting Assumptions'!L18 -> 0 | M18: =-((L38+M38+L40+M40)/2)*'Forecasting Assumptions'!M18 -> 0 | N18: =-((M38+N38+M40+N40)/2)*'Forecasting Assumptions'!N18 -> 0 | ... R18: =-((Q38+R38+Q40+R40)/2)*'Forecasting Assumptions'!R18 -> 0
A19: EBIT | B19: =B17+B18 -> 1999100 | C19: =C17+C18 -> -939500 | D19: =D17+D18 -> 1262200 | E19: =E17+E18 -> 1887900 | F19: =F17+F18 -> 1811400 | G19: =G17+G18 -> 1868751.6 | H19: =H17+H18 -> 1927608.5 | I19: =I17+I18 -> 1987998.9 | ... R19: =R17+R18 -> 2605624.9
A20: Net Interest Expense | B20: =B90 -> -301800 | C20: =C90 -> -370000 | D20: =D90 -> -162100 | E20: =E90 -> -147300 | F20: =F90 -> -178900 | G20: =-((F44+G44+F49+G49)/2)*'Forecasting Assumptions'!G19 -> -186951.66 | H20: =-((G44+H44+G49+H49)/2)*'Forecasting Assumptions'!H19 -> -192855.05 | I20: =-((H44+I44+H49+I49)/2)*'Forecasting Assumptions'!I19 -> -198912.82 | J20: =-((I44+J44+I49+J49)/2)*'Forecasting Assumptions'!J19 -> -205127.81 | K20: =-((J44+K44+J49+K49)/2)*'Forecasting Assumptions'!K19 -> -211502.91 | L20: =-((K44+L44+K49+L49)/2)*'Forecasting Assumptions'!L19 -> -218041 | M20: =-((L44+M44+L49+M49)/2)*'Forecasting Assumptions'!M19 -> -224744.98 | N20: =-((M44+N44+M49+N49)/2)*'Forecasting Assumptions'!N19 -> -231617.74 | ... R20: =-((Q44+R44+Q49+R49)/2)*'Forecasting Assumptions'!R19 -> -260876.13
A21: Non-Operating Income (Loss) | B21: =B91 -> 6700 | C21: =C91 -> 500 | D21: =D91 -> -1400 | E21: =E91 -> -800 | F21: =F91 -> -300 | G21: =G12*'Forecasting Assumptions'!G20 -> -309.49844 | H21: =H12*'Forecasting Assumptions'!H20 -> -319.24619 | I21: =I12*'Forecasting Assumptions'!I20 -> -329.24791 | J21: =J12*'Forecasting Assumptions'!J20 -> -339.50827 | K21: =K12*'Forecasting Assumptions'!K20 -> -350.03196 | L21: =L12*'Forecasting Assumptions'!L20 -> -360.82371 | M21: =M12*'Forecasting Assumptions'!M20 -> -371.88821 | N21: =N12*'Forecasting Assumptions'!N20 -> -383.23022 | ... R21: =R12*'Forecasting Assumptions'!R20 -> -431.53774
A22: EBT | B22: =B19+B20+B21 -> 1704000 | C22: =C19+C20+C21 -> -1309000 | D22: =D19+D20+D21 -> 1098700 | E22: =E19+E20+E21 -> 1739800 | F22: =F19+F20+F21 -> 1632200 | G22: =G19+G20+G21 -> 1681490.4 | H22: =H19+H20+H21 -> 1734434.2 | I22: =I19+I20+I21 -> 1788756.8 | ... R22: =R19+R20+R21 -> 2344317.2
A23: Income Taxes | B23: =B92 -> 10300 | C23: =C92 -> -281800 | D23: =D92 -> -271700 | E23: =E92 -> -397900 | F23: =F92 -> -304300 | G23: =-G22*'Forecasting Assumptions'!G21 -> -313489.48 | H23: =-H22*'Forecasting Assumptions'!H21 -> -323360.08 | I23: =-I22*'Forecasting Assumptions'!I21 -> -333487.74 | J23: =-J22*'Forecasting Assumptions'!J21 -> -343877.2 | K23: =-K22*'Forecasting Assumptions'!K21 -> -354533.19 | L23: =-L22*'Forecasting Assumptions'!L21 -> -365460.48 | M23: =-M22*'Forecasting Assumptions'!M21 -> -376663.85 | N23: =-N22*'Forecasting Assumptions'!N21 -> -388148.08 | ... R23: =-R22*'Forecasting Assumptions'!R21 -> -437063.92
A24: Other Income (Loss) | B24: =B94 -> 0 | C24: =C94 -> 0 | D24: =D94 -> 0 | E24: =E94 -> 0 | F24: =F94 -> 0 | G24: =G12*'Forecasting Assumptions'!G23 -> 0 | H24: =H12*'Forecasting Assumptions'!H23 -> 0 | I24: =I12*'Forecasting Assumptions'!I23 -> 0 | J24: =J12*'Forecasting Assumptions'!J23 -> 0 | K24: =K12*'Forecasting Assumptions'!K23 -> 0 | L24: =L12*'Forecasting Assumptions'!L23 -> 0 | M24: =M12*'Forecasting Assumptions'!M23 -> 0 | N24: =N12*'Forecasting Assumptions'!N23 -> 0 | ... R24: =R12*'Forecasting Assumptions'!R23 -> 0
A25: Net Income Before Ext. Items | B25: =B22+B23+B24 -> 1714300 | C25: =C22+C23+C24 -> -1590800 | D25: =D22+D23+D24 -> 827000 | E25: =E22+E23+E24 -> 1341900 | F25: =F22+F23+F24 -> 1327900 | G25: =G22+G23+G24 -> 1368000.9 | H25: =H22+H23+H24 -> 1411074.1 | I25: =I22+I23+I24 -> 1455269.1 | ... R25: =R22+R23+R24 -> 1907253.3
A26: Ext. Items & Disc. Ops. | B26: =B95 -> 0 | C26: =C95 -> 0 | D26: =D95 -> 0 | E26: =E95 -> 0 | F26: =F95 -> 0 | G26: =G12*'Forecasting Assumptions'!G24 -> 0 | H26: =H12*'Forecasting Assumptions'!H24 -> 0 | I26: =I12*'Forecasting Assumptions'!I24 -> 0 | J26: =J12*'Forecasting Assumptions'!J24 -> 0 | K26: =K12*'Forecasting Assumptions'!K24 -> 0 | L26: =L12*'Forecasting Assumptions'!L24 -> 0 | M26: =M12*'Forecasting Assumptions'!M24 -> 0 | N26: =N12*'Forecasting Assumptions'!N24 -> 0 | ... R26: =R12*'Forecasting Assumptions'!R24 -> 0
A27: Noncontrolling Interest in Earnings | B27: =B93 -> 0 | C27: =C93 -> 0 | D27: =D93 -> 0 | E27: =E93 -> 0 | F27: =F93 -> 0 | G27: =-(G22+G23)*'Forecasting Assumptions'!G22 -> 0 | H27: =-(H22+H23)*'Forecasting Assumptions'!H22 -> 0 | I27: =-(I22+I23)*'Forecasting Assumptions'!I22 -> 0 | J27: =-(J22+J23)*'Forecasting Assumptions'!J22 -> 0 | K27: =-(K22+K23)*'Forecasting Assumptions'!K22 -> 0 | L27: =-(L22+L23)*'Forecasting Assumptions'!L22 -> 0 | M27: =-(M22+M23)*'Forecasting Assumptions'!M22 -> 0 | N27: =-(N22+N23)*'Forecasting Assumptions'!N22 -> 0 | ... R27: =-(R22+R23)*'Forecasting Assumptions'!R22 -> 0
A28: Preferred Dividends | B28: =B96 -> 0 | C28: =C96 -> 0 | D28: =D96 -> 0 | E28: =E96 -> 0 | F28: =F96 -> 0 | G28: =-((G54+F54)/2)*'Forecasting Assumptions'!G25 -> 0 | H28: =-((H54+G54)/2)*'Forecasting Assumptions'!H25 -> 0 | I28: =-((I54+H54)/2)*'Forecasting Assumptions'!I25 -> 0 | J28: =-((J54+I54)/2)*'Forecasting Assumptions'!J25 -> 0 | K28: =-((K54+J54)/2)*'Forecasting Assumptions'!K25 -> 0 | L28: =-((L54+K54)/2)*'Forecasting Assumptions'!L25 -> 0 | M28: =-((M54+L54)/2)*'Forecasting Assumptions'!M25 -> 0 | N28: =-((N54+M54)/2)*'Forecasting Assumptions'!N25 -> 0 | ... R28: =-((R54+Q54)/2)*'Forecasting Assumptions'!R25 -> 0
A29: Net Income (available to common) | B29: =B25+B26+B27+B28 -> 1714300 | C29: =C25+C26+C27+C28 -> -1590800 | D29: =D25+D26+D27+D28 -> 827000 | E29: =E25+E26+E27+E28 -> 1341900 | F29: =F25+F26+F27+F28 -> 1327900 | G29: =G25+G26+G27+G28 -> 1368000.9 | H29: =H25+H26+H27+H28 -> 1411074.1 | I29: =I25+I26+I27+I28 -> 1455269.1 | ... R29: =R25+R26+R27+R28 -> 1907253.3
B30: =IF(B13>0,"Error! -Exp?",IF(B15>0,"Error! -Exp?",IF(B16>0,"Error! -Exp?","")))
A31: Balance Sheet
A33: Operating Cash and Market. Sec. | B33: =B97 -> 1097800 | C33: =C97 -> 446700 | D33: =D97 -> 586000 | E33: =E97 -> 1463600 | F33: =F97 -> 1038300 | G33: =G12*'Forecasting Assumptions'!G29 -> 1071174.1 | H33: =H12*'Forecasting Assumptions'!H29 -> 1104911.1 | I33: =I12*'Forecasting Assumptions'!I29 -> 1139527 | J33: =J12*'Forecasting Assumptions'!J29 -> 1175038.1 | K33: =K12*'Forecasting Assumptions'!K29 -> 1211460.6 | L33: =L12*'Forecasting Assumptions'!L29 -> 1248810.8 | M33: =M12*'Forecasting Assumptions'!M29 -> 1287105.1 | N33: =N12*'Forecasting Assumptions'!N29 -> 1326359.8 | ... R33: =R12*'Forecasting Assumptions'!R29 -> 1493552.1
A34: Receivables | B34: =B98 -> 0 | C34: =C98 -> 100900 | D34: =D98 -> 0 | E34: =E98 -> 0 | F34: =F98 -> 0 | G34: =G12*'Forecasting Assumptions'!G30 -> 0 | H34: =H12*'Forecasting Assumptions'!H30 -> 0 | I34: =I12*'Forecasting Assumptions'!I30 -> 0 | J34: =J12*'Forecasting Assumptions'!J30 -> 0 | K34: =K12*'Forecasting Assumptions'!K30 -> 0 | L34: =L12*'Forecasting Assumptions'!L30 -> 0 | M34: =M12*'Forecasting Assumptions'!M30 -> 0 | N34: =N12*'Forecasting Assumptions'!N30 -> 0 | ... R34: =R12*'Forecasting Assumptions'!R30 -> 0
A35: Inventories | B35: =B99 -> 3169300 | C35: =C99 -> 3536000 | D35: =D99 -> 3522000 | E35: =E99 -> 3427000 | F35: =F99 -> 4367300 | G35: =-G13*'Forecasting Assumptions'!G31 -> 4505575.1 | H35: =-H13*'Forecasting Assumptions'!H31 -> 4647479.6 | I35: =-I13*'Forecasting Assumptions'!I31 -> 4793081.3 | J35: =-J13*'Forecasting Assumptions'!J31 -> 4942448.2 | K35: =-K13*'Forecasting Assumptions'!K31 -> 5095648.7 | L35: =-L13*'Forecasting Assumptions'!L31 -> 5252751.2 | M35: =-M13*'Forecasting Assumptions'!M31 -> 5413824.7 | N35: =-N13*'Forecasting Assumptions'!N31 -> 5578937.9 | ... R35: =-R13*'Forecasting Assumptions'!R31 -> 6282182.6
A36: Other Current Assets | B36: =B100 -> 309200 | C36: =C100 -> 209700 | D36: =D100 -> 161400 | E36: =E100 -> 160200 | F36: =F100 -> 203600 | G36: =G12*'Forecasting Assumptions'!G32 -> 210046.27 | H36: =H12*'Forecasting Assumptions'!H32 -> 216661.75 | I36: =I12*'Forecasting Assumptions'!I32 -> 223449.58 | J36: =J12*'Forecasting Assumptions'!J32 -> 230412.94 | K36: =K12*'Forecasting Assumptions'!K32 -> 237555.03 | L36: =L12*'Forecasting Assumptions'!L32 -> 244879.02 | M36: =M12*'Forecasting Assumptions'!M32 -> 252388.13 | N36: =N12*'Forecasting Assumptions'!N32 -> 260085.58 | ... R36: =R12*'Forecasting Assumptions'!R32 -> 292870.28
A37: Total Current Assets | B37: =SUM(B33:B36) -> 4576300 | C37: =SUM(C33:C36) -> 4293300 | D37: =SUM(D33:D36) -> 4269400 | E37: =SUM(E33:E36) -> 5050800 | F37: =SUM(F33:F36) -> 5609200 | G37: =SUM(G33:G36) -> 5786795.5 | H37: =SUM(H33:H36) -> 5969052.4 | I37: =SUM(I33:I36) -> 6156057.9 | ... R37: =SUM(R33:R36) -> 8068605.1
A38: PP&E (Net) | B38: =B101 -> 3200700 | C38: =C101 -> 3445300 | D38: =D101 -> 3881800 | E38: =E101 -> 4116300 | F38: =F101 -> 4477300 | G38: =G12*'Forecasting Assumptions'!G37 -> 4619057.9 | H38: =H12*'Forecasting Assumptions'!H37 -> 4764536.5 | I38: =I12*'Forecasting Assumptions'!I37 -> 4913805.5 | J38: =J12*'Forecasting Assumptions'!J37 -> 5066934.6 | K38: =K12*'Forecasting Assumptions'!K37 -> 5223993.7 | L38: =L12*'Forecasting Assumptions'!L37 -> 5385053.2 | M38: =M12*'Forecasting Assumptions'!M37 -> 5550183.7 | N38: =N12*'Forecasting Assumptions'!N37 -> 5719455.6 | ... R38: =R12*'Forecasting Assumptions'!R37 -> 6440413.2
A39: Investments | B39: =B102 -> 0 | C39: =C102 -> 0 | D39: =D102 -> 0 | E39: =E102 -> 0 | F39: =F102 -> 0 | G39: =G12*'Forecasting Assumptions'!G38 -> 0 | H39: =H12*'Forecasting Assumptions'!H38 -> 0 | I39: =I12*'Forecasting Assumptions'!I38 -> 0 | J39: =J12*'Forecasting Assumptions'!J38 -> 0 | K39: =K12*'Forecasting Assumptions'!K38 -> 0 | L39: =L12*'Forecasting Assumptions'!L38 -> 0 | M39: =M12*'Forecasting Assumptions'!M38 -> 0 | N39: =N12*'Forecasting Assumptions'!N38 -> 0 | ... R39: =R12*'Forecasting Assumptions'!R38 -> 0
A40: Intangibles | B40: =B103 -> 5025200 | C40: =C103 -> 5685300 | D40: =D103 -> 5083300 | E40: =E103 -> 5084400 | F40: =F103 -> 5084400 | G40: =G12*'Forecasting Assumptions'!G39 -> 5245379.5 | H40: =H12*'Forecasting Assumptions'!H39 -> 5410584.4 | I40: =I12*'Forecasting Assumptions'!I39 -> 5580093.5 | J40: =J12*'Forecasting Assumptions'!J39 -> 5753986.1 | K40: =K12*'Forecasting Assumptions'!K39 -> 5932341.7 | L40: =L12*'Forecasting Assumptions'!L39 -> 6115240.2 | M40: =M12*'Forecasting Assumptions'!M39 -> 6302761.5 | N40: =N12*'Forecasting Assumptions'!N39 -> 6494985.8 | ... R40: =R12*'Forecasting Assumptions'!R39 -> 7313701.7
A41: Other Assets | B41: =B104 -> 3530600 | C41: =C104 -> 77300 | D41: =D104 -> 6340100 | E41: =E104 -> 6444500 | F41: =F104 -> 6550900 | G41: =G12*'Forecasting Assumptions'!G40 -> 6758311.1 | H41: =H12*'Forecasting Assumptions'!H40 -> 6971166.2 | I41: =I12*'Forecasting Assumptions'!I40 -> 7189567.1 | J41: =J12*'Forecasting Assumptions'!J40 -> 7413615.7 | K41: =K12*'Forecasting Assumptions'!K40 -> 7643414.6 | L41: =L12*'Forecasting Assumptions'!L40 -> 7879066.7 | M41: =M12*'Forecasting Assumptions'!M40 -> 8120675 | N41: =N12*'Forecasting Assumptions'!N40 -> 8368342.9 | ... R41: =R12*'Forecasting Assumptions'!R40 -> 9423202
A42: Total Assets | B42: =SUM(B37:B41) -> 16332800 | C42: =SUM(C37:C41) -> 13501200 | D42: =SUM(D37:D41) -> 19574600 | E42: =SUM(E37:E41) -> 20696000 | F42: =SUM(F37:F41) -> 21721800 | G42: =G37+G38+G39+G40+G41 -> 22409544 | H42: =H37+H38+H39+H40+H41 -> 23115340 | I42: =I37+I38+I39+I40+I41 -> 23839524 | J42: =J37+J38+J39+J40+J41 -> 24582436 | K42: =K37+K38+K39+K40+K41 -> 25344414 | L42: =L37+L38+L39+L40+L41 -> 26125801 | M42: =M37+M38+M39+M40+M41 -> 26926938 | N42: =N37+N38+N39+N40+N41 -> 27748168 | ... R42: =R37+R38+R39+R40+R41 -> 31245922
A44: Current Debt | B44: =B105 -> 915900 | C44: =C105 -> 0 | D44: =D105 -> 250000 | E44: =E105 -> 0 | F44: =F105 -> 0 | G44: =G42*'Forecasting Assumptions'!G45 -> 0 | H44: =H42*'Forecasting Assumptions'!H45 -> 0 | I44: =I42*'Forecasting Assumptions'!I45 -> 0 | J44: =J42*'Forecasting Assumptions'!J45 -> 0 | K44: =K42*'Forecasting Assumptions'!K45 -> 0 | L44: =L42*'Forecasting Assumptions'!L45 -> 0 | M44: =M42*'Forecasting Assumptions'!M45 -> 0 | N44: =N42*'Forecasting Assumptions'!N45 -> 0 | ... R44: =R42*'Forecasting Assumptions'!R45 -> 0
A45: Accounts Payable | B45: =B106 -> 1174800 | C45: =C106 -> 1416400 | D45: =D106 -> 1336500 | E45: =E106 -> 1480500 | F45: =F106 -> 1884200 | G45: =-G13*'Forecasting Assumptions'!G33 -> 1943856.5 | H45: =-H13*'Forecasting Assumptions'!H33 -> 2005078.9 | I45: =-I13*'Forecasting Assumptions'!I33 -> 2067896.4 | J45: =-J13*'Forecasting Assumptions'!J33 -> 2132338.3 | K45: =-K13*'Forecasting Assumptions'!K33 -> 2198434.1 | L45: =-L13*'Forecasting Assumptions'!L33 -> 2266213.4 | M45: =-M13*'Forecasting Assumptions'!M33 -> 2335705.9 | N45: =-N13*'Forecasting Assumptions'!N33 -> 2406941.3 | ... R45: =-R13*'Forecasting Assumptions'!R33 -> 2710344.7
A46: Income Taxes Payable | B46: =B107 -> 31500 | C46: =C107 -> 60000 | D46: =D107 -> 62700 | E46: =E107 -> 86300 | F46: =F107 -> 82600 | G46: =G12*'Forecasting Assumptions'!G34 -> 85215.237 | H46: =H12*'Forecasting Assumptions'!H34 -> 87899.118 | I46: =I12*'Forecasting Assumptions'!I34 -> 90652.924 | J46: =J12*'Forecasting Assumptions'!J34 -> 93477.943 | K46: =K12*'Forecasting Assumptions'!K34 -> 96375.467 | L46: =L12*'Forecasting Assumptions'!L34 -> 99346.793 | M46: =M12*'Forecasting Assumptions'!M34 -> 102393.22 | N46: =N12*'Forecasting Assumptions'!N34 -> 105516.05 | ... R46: =R12*'Forecasting Assumptions'!R34 -> 118816.73
A47: Other Current Liabilities | B47: =B108 -> 736900 | C47: =C108 -> 619300 | D47: =D108 -> 1897300 | E47: =E108 -> 2163500 | F47: =F108 -> 2209800 | G47: =G12*'Forecasting Assumptions'!G35 -> 2279765.5 | H47: =H12*'Forecasting Assumptions'!H35 -> 2351567.4 | I47: =I12*'Forecasting Assumptions'!I35 -> 2425240.1 | J47: =J12*'Forecasting Assumptions'!J35 -> 2500817.9 | K47: =K12*'Forecasting Assumptions'!K35 -> 2578335.4 | L47: =L12*'Forecasting Assumptions'!L35 -> 2657827.4 | M47: =M12*'Forecasting Assumptions'!M35 -> 2739328.6 | N47: =N12*'Forecasting Assumptions'!N35 -> 2822873.8 | ... R47: =R12*'Forecasting Assumptions'!R35 -> 3178707
A48: Total Current Liabilities | B48: =SUM(B44:B47) -> 2859100 | C48: =SUM(C44:C47) -> 2095700 | D48: =SUM(D44:D47) -> 3546500 | E48: =SUM(E44:E47) -> 3730300 | F48: =SUM(F44:F47) -> 4176600 | G48: =G44+G45+G46+G47 -> 4308837.3 | H48: =H44+H45+H46+H47 -> 4444545.5 | I48: =I44+I45+I46+I47 -> 4583789.4 | J48: =J44+J45+J46+J47 -> 4726634.1 | K48: =K44+K45+K46+K47 -> 4873145 | L48: =L44+L45+L46+L47 -> 5023387.6 | M48: =M44+M45+M46+M47 -> 5177427.7 | N48: =N44+N45+N46+N47 -> 5335331.2 | ... R48: =R44+R45+R46+R47 -> 6007868.5
A49: Long-Term Debt | B49: =B109 -> 4762100 | C49: =C109 -> 4265300 | D49: =D109 -> 3522200 | E49: =E109 -> 3226200 | F49: =F109 -> 3417000 | G49: =G42*'Forecasting Assumptions'!G46 -> 3525187.2 | H49: =H42*'Forecasting Assumptions'!H46 -> 3636214.1 | I49: =I42*'Forecasting Assumptions'!I46 -> 3750133.7 | J49: =J42*'Forecasting Assumptions'!J46 -> 3866999.2 | K49: =K42*'Forecasting Assumptions'!K46 -> 3986864.1 | L49: =L42*'Forecasting Assumptions'!L46 -> 4109782 | M49: =M42*'Forecasting Assumptions'!M46 -> 4235806.8 | N49: =N42*'Forecasting Assumptions'!N46 -> 4364992.3 | ... R49: =R42*'Forecasting Assumptions'!R46 -> 4915214.9
A50: Other Liabilities | B50: =B110 -> 544100 | C50: =C110 -> 524100 | D50: =D110 -> 5266400 | E50: =E110 -> 5440700 | F50: =F110 -> 5422500 | G50: =G12*'Forecasting Assumptions'!G42 -> 5594184.3 | H50: =H12*'Forecasting Assumptions'!H42 -> 5770374.9 | I50: =I12*'Forecasting Assumptions'!I42 -> 5951155.9 | J50: =J12*'Forecasting Assumptions'!J42 -> 6136611.9 | K50: =K12*'Forecasting Assumptions'!K42 -> 6326827.7 | L50: =L12*'Forecasting Assumptions'!L42 -> 6521888.5 | M50: =M12*'Forecasting Assumptions'!M42 -> 6721879.5 | N50: =N12*'Forecasting Assumptions'!N42 -> 6926886.3 | ... R50: =R12*'Forecasting Assumptions'!R42 -> 7800044.7
A51: Deferred Taxes | B51: =B111 -> 985200 | C51: =C111 -> 973200 | D51: =D111 -> 984700 | E51: =E111 -> 1013500 | F51: =F111 -> 987200 | G51: =G12*'Forecasting Assumptions'!G43 -> 1018456.2 | H51: =H12*'Forecasting Assumptions'!H43 -> 1050532.8 | I51: =I12*'Forecasting Assumptions'!I43 -> 1083445.1 | J51: =J12*'Forecasting Assumptions'!J43 -> 1117208.5 | K51: =K12*'Forecasting Assumptions'!K43 -> 1151838.5 | L51: =L12*'Forecasting Assumptions'!L43 -> 1187350.5 | M51: =M12*'Forecasting Assumptions'!M43 -> 1223760.1 | N51: =N12*'Forecasting Assumptions'!N43 -> 1261082.9 | ... R51: =R12*'Forecasting Assumptions'!R43 -> 1420046.9
A52: Total Liabilities | B52: =SUM(B48:B51) -> 9150500 | C52: =SUM(C48:C51) -> 7858300 | D52: =SUM(D48:D51) -> 13319800 | E52: =SUM(E48:E51) -> 13410700 | F52: =SUM(F48:F51) -> 14003300 | G52: =SUM(G48:G51) -> 14446665 | H52: =SUM(H48:H51) -> 14901667 | I52: =SUM(I48:I51) -> 15368524 | ... R52: =SUM(R48:R51) -> 20143175
A53: Noncontrolling Interest | B53: =B112 -> 0 | C53: =C112 -> 0 | D53: =D112 -> 0 | E53: =E112 -> 0 | F53: =F112 -> 0 | G53: =G42*'Forecasting Assumptions'!G47 -> 0 | H53: =H42*'Forecasting Assumptions'!H47 -> 0 | I53: =I42*'Forecasting Assumptions'!I47 -> 0 | J53: =J42*'Forecasting Assumptions'!J47 -> 0 | K53: =K42*'Forecasting Assumptions'!K47 -> 0 | L53: =L42*'Forecasting Assumptions'!L47 -> 0 | M53: =M42*'Forecasting Assumptions'!M47 -> 0 | N53: =N42*'Forecasting Assumptions'!N47 -> 0 | ... R53: =R42*'Forecasting Assumptions'!R47 -> 0
A54: Preferred Stock | B54: =B113 -> 0 | C54: =C113 -> 0 | D54: =D113 -> 0 | E54: =E113 -> 0 | F54: =F113 -> 0 | G54: =G42*'Forecasting Assumptions'!G48 -> 0 | H54: =H42*'Forecasting Assumptions'!H48 -> 0 | I54: =I42*'Forecasting Assumptions'!I48 -> 0 | J54: =J42*'Forecasting Assumptions'!J48 -> 0 | K54: =K42*'Forecasting Assumptions'!K48 -> 0 | L54: =L42*'Forecasting Assumptions'!L48 -> 0 | M54: =M42*'Forecasting Assumptions'!M48 -> 0 | N54: =N42*'Forecasting Assumptions'!N48 -> 0 | ... R54: =R42*'Forecasting Assumptions'!R48 -> 0
A55: Paid in Common Capital (Net) | B55: =B114 -> 2515400 | C55: =C114 -> 2566800 | D55: =D114 -> 2417000 | E55: =E114 -> 2105600 | F55: =F114 -> 1210900 | G55: =G57-G56 -> 87278.065 | H55: =H57-H56 -> -1073002.7 | I55: =I57-I56 -> -2270944.2 | J55: =J57-J56 -> -3507568.6 | K55: =K57-K56 -> -4783918.3 | L55: =L57-L56 -> -6101056 | M55: =M57-M56 -> -7460065 | N55: =N57-N56 -> -8862049 | ... R55: =R57-R56 -> -14921074
A56: Retained Earnings | B56: =B115 -> 4666900 | C56: =C115 -> 3076100 | D56: =D115 -> 3837800 | E56: =E115 -> 5179700 | F56: =F115 -> 6507600 | G56: =G66 -> 7875600.9 | H56: =H66 -> 9286675 | I56: =I66 -> 10741944 | J56: =J66 -> 12242551 | K56: =K66 -> 13789657 | L56: =L66 -> 15384449 | M56: =M66 -> 17028129 | N56: =N66 -> 18721924 | ... R56: =R66 -> 26023821
A57: Total Common Equity | B57: =SUM(B55:B56) -> 7182300 | C57: =SUM(C55:C56) -> 5642900 | D57: =SUM(D55:D56) -> 6254800 | E57: =SUM(E55:E56) -> 7285300 | F57: =SUM(F55:F56) -> 7718500 | G57: =G58-G52-G53-G54 -> 7962879 | H57: =H58-H52-H53-H54 -> 8213672.4 | I57: =I58-I52-I53-I54 -> 8470999.9 | J57: =J58-J52-J53-J54 -> 8734981.9 | K57: =K58-K52-K53-K54 -> 9005739 | L57: =L58-L52-L53-L54 -> 9283392.6 | M57: =M58-M52-M53-M54 -> 9568063.9 | N57: =N58-N52-N53-N54 -> 9859874.9 | ... R57: =R58-R52-R53-R54 -> 11102747
A58: Total Liabilities and Equity | B58: =SUM(B52:B56) -> 16332800 | C58: =SUM(C52:C56) -> 13501200 | D58: =SUM(D52:D56) -> 19574600 | E58: =SUM(E52:E56) -> 20696000 | F58: =SUM(F52:F56) -> 21721800 | G58: =G42 -> 22409544 | H58: =H42 -> 23115340 | I58: =I42 -> 23839524 | J58: =J42 -> 24582436 | K58: =K42 -> 25344414 | L58: =L42 -> 26125801 | M58: =M42 -> 26926938 | N58: =N42 -> 27748168 | ... R58: =R42 -> 31245922
B59: =IF(B58=B42," ","Error! A =L+E?") | C59: =IF(C58=C42," ","Error! A =L+E?") | D59: =IF(D58=D42," ","Error! A =L+E?") | E59: =IF(E58=E42," ","Error! A =L+E?") | F59: =IF(F58=F42," ","Error! A =L+E?") | G59: =IF(G58=G42," ","Error! A =L+E?") | H59: =IF(H58=H42," ","Error! A =L+E?") | I59: =IF(I58=I42," ","Error! A =L+E?") | ... R59: =IF(R58=R42," ","Error! A =L+E?")
A60: Statement of Retained Earnings
A62: Beg. Retained Earnings | C62: =B56 -> 4666900 | D62: =C56 -> 3076100 | E62: =D56 -> 3837800 | F62: =E56 -> 5179700 | G62: =F56 -> 6507600 | H62: =G56 -> 7875600.9 | I62: =H56 -> 9286675 | J62: =I56 -> 10741944 | ... R62: =Q56 -> 24116568
A63: +Net Income | C63: =C29 -> -1590800 | D63: =D29 -> 827000 | E63: =E29 -> 1341900 | F63: =F29 -> 1327900 | G63: =G29 -> 1368000.9 | H63: =H29 -> 1411074.1 | I63: =I29 -> 1455269.1 | J63: =J29 -> 1500606.4 | ... R63: =R29 -> 1907253.3
A64: -Common Dividends | B64: =-B116 -> 0 | C64: =-C116 -> 0 | D64: =-D116 -> 0 | E64: =-E116 -> 0 | F64: =-F116 -> 0 | G64: =-G29*'Forecasting Assumptions'!G49 -> 0 | H64: =-H29*'Forecasting Assumptions'!H49 -> 0 | I64: =-I29*'Forecasting Assumptions'!I49 -> 0 | J64: =-J29*'Forecasting Assumptions'!J49 -> 0 | K64: =-K29*'Forecasting Assumptions'!K49 -> 0 | L64: =-L29*'Forecasting Assumptions'!L49 -> 0 | M64: =-M29*'Forecasting Assumptions'!M49 -> 0 | N64: =-N29*'Forecasting Assumptions'!N49 -> 0 | ... R64: =-R29*'Forecasting Assumptions'!R49 -> 0
A65: +/-Clean Surplus Plug (Ignore) | C65: =C66-C62-C63-C64 -> 0 | D65: =D66-D62-D63-D64 -> -65300 | E65: =E66-E62-E63-E64 -> 0 | F65: =F66-F62-F63-F64 -> 0 | G65: 0 | H65: 0 | I65: 0 | J65: 0 | K65: 0 | L65: 0 | M65: 0 | N65: 0 | O65: 0 | P65: 0 | Q65: 0 | R65: 0
A66: =End. Retained Earnings | C66: =C56 -> 3076100 | D66: =D56 -> 3837800 | E66: =E56 -> 5179700 | F66: =F56 -> 6507600 | G66: =G62+G63+G64+G65 -> 7875600.9 | H66: =H62+H63+H64+H65 -> 9286675 | I66: =I62+I63+I64+I65 -> 10741944 | J66: =J62+J63+J64+J65 -> 12242551 | K66: =K62+K63+K64+K65 -> 13789657 | L66: =L62+L63+L64+L65 -> 15384449 | M66: =M62+M63+M64+M65 -> 17028129 | N66: =N62+N63+N64+N65 -> 18721924 | ... R66: =R62+R63+R64+R65 -> 26023821
A69: Values for Dupont Analysis and Valuation
A71: Net Operating Income | B71: =B73-B72 -> 2017924.3 | C71: =C73-C72 -> -1141146.8 | D71: =D73-D72 -> 949013.93 | E71: =E73-E72 -> 1455511.8 | F71: =F73-F72 -> 1473446.7 | G71: =G73-G72 -> 1520098.2 | H71: =H73-H72 -> 1567974.1 | I71: =I73-I72 -> 1617097.5 | ... R71: =R73-R72 -> 2119492.9
A72: Net Financial Expense | B72: =B20*(1-B74)+B28+B27 -> -303624.26 | C72: =C20*(1-C74)+C28+C27 -> -449653.17 | D72: =D20*(1-D74)+D28+D27 -> -122013.93 | E72: =E20*(1-E74)+E28+E27 -> -113611.83 | F72: =F20*(1-F74)+F28+F27 -> -145546.69 | G72: =G20*(1-G74)+G28+G27 -> -152097.24 | H72: =H20*(1-H74)+H28+H27 -> -156900.03 | I72: =I20*(1-I74)+I28+I27 -> -161828.41 | ... R72: =R20*(1-R74)+R28+R27 -> -212239.56
A73: Net Income | B73: =B29 -> 1714300 | C73: =C29 -> -1590800 | D73: =D29 -> 827000 | E73: =E29 -> 1341900 | F73: =F29 -> 1327900 | G73: =G29 -> 1368000.9 | H73: =H29 -> 1411074.1 | I73: =I29 -> 1455269.1 | ... R73: =R29 -> 1907253.3
A74: Effective Tax Rate | B74: =-B23/B22 -> -0.0060446009 | C74: =-C23/C22 -> -0.21527884 | D74: =-D23/D22 -> 0.24729225 | E74: =-E23/E22 -> 0.22870445 | F74: =-F23/F22 -> 0.18643549 | G74: =-G23/G22 -> 0.18643549 | H74: =-H23/H22 -> 0.18643549 | I74: =-I23/I22 -> 0.18643549 | ... R74: =-R23/R22 -> 0.18643549
A75: Net Operating Assets | B75: =B77+B76 -> 12860300 | C75: =C77+C76 -> 9908200 | D75: =D77+D76 -> 10027000 | E75: =E77+E76 -> 10511500 | F75: =F77+F76 -> 11135500 | G75: =G77+G76 -> 11488066 | H75: =H77+H76 -> 11849886 | I75: =I77+I76 -> 12221134 | ... R75: =R77+R76 -> 16017962
A76: Net Financial Obligations | B76: =B44+B49+B54+B53 -> 5678000 | C76: =C44+C49+C54+C53 -> 4265300 | D76: =D44+D49+D54+D53 -> 3772200 | E76: =E44+E49+E54+E53 -> 3226200 | F76: =F44+F49+F54+F53 -> 3417000 | G76: =G44+G49+G54+G53 -> 3525187.2 | H76: =H44+H49+H54+H53 -> 3636214.1 | I76: =I44+I49+I54+I53 -> 3750133.7 | ... R76: =R44+R49+R54+R53 -> 4915214.9
A77: Total Common Equity | B77: =B57 -> 7182300 | C77: =C57 -> 5642900 | D77: =D57 -> 6254800 | E77: =E57 -> 7285300 | F77: =F57 -> 7718500 | G77: =G57 -> 7962879 | H77: =H57 -> 8213672.4 | I77: =I57 -> 8470999.9 | ... R77: =R57 -> 11102747
A80: Raw Data Inputs | B80: cut-and-paste raw data block from DataMaker file here
A82: Company Name and Ticker | B82: DOLLAR TREE 2021 | D82: DLTR | F82: 5331 | G82: A Windows vs Macintosh issue can cause the fiscal year end dates to be off by roughly 4 years. If this occurs, select and copy the 1462 cell below, select the cells with the dates, choose Paste Special Values and select Subtract or Add.
A83: Common Shares Outstanding | B83: 225100.2
A84: Fiscal Year End (YYYY-MM-DD) | B84: 41669 | C84: 42034 | D84: 42399 | E84: 42765 | F84: 43130
A85: Sales (Net) | B85: 22245500 | C85: 22823300 | D85: 23610800 | E85: 25509300 | F85: 26321200
A86: Cost of Goods Sold | B86: -15223600 | C86: -15875800 | D86: -16570100 | E86: -17721900 | F86: -18595300
A87: R&D Expense | B87: 0 | C87: 0 | D87: 0 | E87: 0 | F87: 0 | G87: 1462
A88: SG&A Expense | B88: -4953600 | C88: -7887000 | D88: -5778500 | E88: -5899500 | F88: -5914500
A89: Depreciation & Amortization | B89: -69200 | C89: 0 | D89: 0 | E89: 0 | F89: 0
A90: Interest Expense | B90: -301800 | C90: -370000 | D90: -162100 | E90: -147300 | F90: -178900
A91: Non-Operating Income (Loss) | B91: 6700 | C91: 500 | D91: -1400 | E91: -800 | F91: -300
A92: Income Taxes | B92: 10300 | C92: -281800 | D92: -271700 | E92: -397900 | F92: -304300
A93: Noncontrolling Interest in Earnings | B93: 0 | C93: 0 | D93: 0 | E93: 0 | F93: 0
A94: Other Income (Loss) | B94: 0 | C94: 0 | D94: 0 | E94: 0 | F94: 0
A95: Ext. Items & Disc. Ops. | B95: 0 | C95: 0 | D95: 0 | E95: 0 | F95: 0
A96: Preferred Dividends | B96: 0 | C96: 0 | D96: 0 | E96: 0 | F96: 0
A97: Operating Cash and Market. Sec. | B97: 1097800 | C97: 446700 | D97: 586000 | E97: 1463600 | F97: 1038300
A98: Receivables | B98: 0 | C98: 100900 | D98: 0 | E98: 0 | F98: 0
A99: Inventories | B99: 3169300 | C99: 3536000 | D99: 3522000 | E99: 3427000 | F99: 4367300
... A116: Common Dividends | B116: 0 | C116: 0 | D116: 0 | E116: 0 | F116: 0
A119: Industry Analysis | B119: Link to Financial Statements
A121: Sector (Fama-French 12 Industry) | B121: =VLOOKUP(E4,Master!$F$1:$I$445,2,FALSE) -> RETAIL & WHOLESALE
A122: Industry (Fama-French 49 Industry) | B122: =VLOOKUP(E4,Master!$F$1:$I$445,3,FALSE) -> RETAIL
A123: Sub-Industry (SEC SIC Code Title) | B123: =VLOOKUP(E4,Master!$F$1:$I$445,4,FALSE) -> RETAIL-VARIETY STORES
A125: Comparables (Same SIC Code)
A126: Ticker | B126: Company Name
A127: {=_xlfn._xlws.FILTER(Master!B1:C4184,Master!D1:D4184='Financial Statements'!E4)} -> BIG | B127: BIG LOTS INC
A128: BJ | B128: BJ'S WHOLESALE CLUB HOLDINGS, INC.
A129: COST | B129: COSTCO WHOLESALE CORP /NEW
A130: DG | B130: DOLLAR GENERAL CORP
A131: DLTR | B131: DOLLAR TREE, INC.
A132: FIVE | B132: FIVE BELOW, INC
...

Sheet Ratio Analysis
A1: Ratio Analysis
A4: Company Name | B4: ='Financial Statements'!B4 -> DOLLAR TREE 2021
B6: Actual | C6: Actual | D6: Actual | E6: Actual | F6: Actual | G6: Forecast | H6: Forecast | I6: Forecast | J6: Forecast | K6: Forecast | L6: Forecast | M6: Forecast | N6: Forecast | O6: Forecast | P6: Forecast | Q6: Forecast | R6: Forecast
A7: Fiscal Year End Date | B7: ='Financial Statements'!B8 -> 41669 | C7: ='Financial Statements'!C8 -> 42034 | D7: ='Financial Statements'!D8 -> 42399 | E7: ='Financial Statements'!E8 -> 42765 | F7: ='Financial Statements'!F8 -> 43130 | G7: ='Financial Statements'!G8 -> 43495 | H7: ='Financial Statements'!H8 -> 43860 | I7: ='Financial Statements'!I8 -> 44226 | ... R7: ='Financial Statements'!R8 -> 47513
A9: Annual Growth Rates
A10: Sales | C10: ='Financial Statements'!C12/'Financial Statements'!B12-1 -> 0.025973792 | D10: ='Financial Statements'!D12/'Financial Statements'!C12-1 -> 0.034504213 | E10: ='Financial Statements'!E12/'Financial Statements'!D12-1 -> 0.080408118 | F10: ='Financial Statements'!F12/'Financial Statements'!E12-1 -> 0.031827608 | G10: ='Financial Statements'!G12/'Financial Statements'!F12-1 -> 0.031661462 | H10: ='Financial Statements'!H12/'Financial Statements'!G12-1 -> 0.031495316 | I10: ='Financial Statements'!I12/'Financial Statements'!H12-1 -> 0.031329169 | J10: ='Financial Statements'!J12/'Financial Statements'!I12-1 -> 0.031163023 | ... R10: ='Financial Statements'!R12/'Financial Statements'!Q12-1 -> 0.03
A11: Assets | C11: =IF('Financial Statements'!B42<=0,#N/A,'Financial Statements'!C42/'Financial Statements'!B42-1) -> -0.17336893 | D11: =IF('Financial Statements'!C42<=0,#N/A,'Financial Statements'!D42/'Financial Statements'!C42-1) -> 0.4498415 | E11: =IF('Financial Statements'!D42<=0,#N/A,'Financial Statements'!E42/'Financial Statements'!D42-1) -> 0.057288527 | F11: =IF('Financial Statements'!E42<=0,#N/A,'Financial Statements'!F42/'Financial Statements'!E42-1) -> 0.049565133 | G11: =IF('Financial Statements'!F42<=0,#N/A,'Financial Statements'!G42/'Financial Statements'!F42-1) -> 0.031661462 | H11: =IF('Financial Statements'!G42<=0,#N/A,'Financial Statements'!H42/'Financial Statements'!G42-1) -> 0.031495316 | I11: =IF('Financial Statements'!H42<=0,#N/A,'Financial Statements'!I42/'Financial Statements'!H42-1) -> 0.031329169 | J11: =IF('Financial Statements'!I42<=0,#N/A,'Financial Statements'!J42/'Financial Statements'!I42-1) -> 0.031163023 | ... R11: =IF('Financial Statements'!Q42<=0,#N/A,'Financial Statements'!R42/'Financial Statements'!Q42-1) -> 0.03
A12: Common Equity | C12: =IF('Financial Statements'!B57<=0,#N/A,'Financial Statements'!C57/'Financial Statements'!B57-1) -> -0.21433246 | D12: =IF('Financial Statements'!C57<=0,#N/A,'Financial Statements'!D57/'Financial Statements'!C57-1) -> 0.10843715 | E12: =IF('Financial Statements'!D57<=0,#N/A,'Financial Statements'!E57/'Financial Statements'!D57-1) -> 0.16475347 | F12: =IF('Financial Statements'!E57<=0,#N/A,'Financial Statements'!F57/'Financial Statements'!E57-1) -> 0.059462205 | G12: =IF('Financial Statements'!F57<=0,#N/A,'Financial Statements'!G57/'Financial Statements'!F57-1) -> 0.031661462 | H12: =IF('Financial Statements'!G57<=0,#N/A,'Financial Statements'!H57/'Financial Statements'!G57-1) -> 0.031495316 | I12: =IF('Financial Statements'!H57<=0,#N/A,'Financial Statements'!I57/'Financial Statements'!H57-1) -> 0.031329169 | J12: =IF('Financial Statements'!I57<=0,#N/A,'Financial Statements'!J57/'Financial Statements'!I57-1) -> 0.031163023 | ... R12: =IF('Financial Statements'!Q57<=0,#N/A,'Financial Statements'!R57/'Financial Statements'!Q57-1) -> 0.03
A13: Earnings | C13: =IF('Financial Statements'!B29<=0,#N/A,'Financial Statements'!C29/'Financial Statements'!B29-1) -> -1.9279589 | D13: =IF('Financial Statements'!C29<=0,#N/A,'Financial Statements'!D29/'Financial Statements'!C29-1) -> #N/A | E13: =IF('Financial Statements'!D29<=0,#N/A,'Financial Statements'!E29/'Financial Statements'!D29-1) -> 0.62261185 | F13: =IF('Financial Statements'!E29<=0,#N/A,'Financial Statements'!F29/'Financial Statements'!E29-1) -> -0.010432968 | G13: =IF('Financial Statements'!F29<=0,#N/A,'Financial Statements'!G29/'Financial Statements'!F29-1) -> 0.030198756 | H13: =IF('Financial Statements'!G29<=0,#N/A,'Financial Statements'!H29/'Financial Statements'!G29-1) -> 0.031486223 | I13: =IF('Financial Statements'!H29<=0,#N/A,'Financial Statements'!I29/'Financial Statements'!H29-1) -> 0.031320076 | J13: =IF('Financial Statements'!I29<=0,#N/A,'Financial Statements'!J29/'Financial Statements'!I29-1) -> 0.031153928 | ... R13: =IF('Financial Statements'!Q29<=0,#N/A,'Financial Statements'!R29/'Financial Statements'!Q29-1) -> 0.03
A14: Free Cash Flow to Investors | D14: =IF('Cash Flow Analysis'!B116<=0,#N/A,'Cash Flow Analysis'!C116/'Cash Flow Analysis'!B116-1) -> -0.57761805 | E14: =IF('Cash Flow Analysis'!C116<=0,#N/A,'Cash Flow Analysis'!D116/'Cash Flow Analysis'!C116-1) -> 0.26943935 | F14: =IF('Cash Flow Analysis'!D116<=0,#N/A,'Cash Flow Analysis'!E116/'Cash Flow Analysis'!D116-1) -> -0.1251943 | G14: =IF('Cash Flow Analysis'!E116<=0,#N/A,'Cash Flow Analysis'!F116/'Cash Flow Analysis'!E116-1) -> 0.37446172 | H14: =IF('Cash Flow Analysis'!F116<=0,#N/A,'Cash Flow Analysis'!G116/'Cash Flow Analysis'!F116-1) -> 0.033079958 | I14: =IF('Cash Flow Analysis'!G116<=0,#N/A,'Cash Flow Analysis'!H116/'Cash Flow Analysis'!G116-1) -> 0.032911636 | J14: =IF('Cash Flow Analysis'!H116<=0,#N/A,'Cash Flow Analysis'!I116/'Cash Flow Analysis'!H116-1) -> 0.03274332 | K14: =IF('Cash Flow Analysis'!I116<=0,#N/A,'Cash Flow Analysis'!J116/'Cash Flow Analysis'!I116-1) -> 0.03257501 | ... R14: =IF('Cash Flow Analysis'!P116<=0,#N/A,'Cash Flow Analysis'!Q116/'Cash Flow Analysis'!P116-1) -> 0.03
A15: Sustainable Growth Rate | D15: =D19*(1-'Forecasting Assumptions'!D49) -> 0.13901847 | E15: =E19*(1-'Forecasting Assumptions'!E49) -> 0.19821124 | F15: =F19*(1-'Forecasting Assumptions'!F49) -> 0.17700849 | G15: =G19*(1-'Forecasting Assumptions'!G49) -> 0.17447457 | H15: =H19*(1-'Forecasting Assumptions'!H49) -> 0.1744592 | I15: =I19*(1-'Forecasting Assumptions'!I49) -> 0.17444383 | J15: =J19*(1-'Forecasting Assumptions'!J49) -> 0.17442845 | K15: =K19*(1-'Forecasting Assumptions'!K49) -> 0.17441308 | ... R15: =R19*(1-'Forecasting Assumptions'!R49) -> 0.17432076
A18: Profitability
A19: Return on Equity | C19: ='Financial Statements'!C73/(('Financial Statements'!B77+'Financial Statements'!C77)/2) -> -0.2480741 | D19: ='Financial Statements'!D73/(('Financial Statements'!C77+'Financial Statements'!D77)/2) -> 0.13901847 | E19: ='Financial Statements'!E73/(('Financial Statements'!D77+'Financial Statements'!E77)/2) -> 0.19821124 | F19: ='Financial Statements'!F73/(('Financial Statements'!E77+'Financial Statements'!F77)/2) -> 0.17700849 | G19: ='Financial Statements'!G73/(('Financial Statements'!F77+'Financial Statements'!G77)/2) -> 0.17447457 | H19: ='Financial Statements'!H73/(('Financial Statements'!G77+'Financial Statements'!H77)/2) -> 0.1744592 | I19: ='Financial Statements'!I73/(('Financial Statements'!H77+'Financial Statements'!I77)/2) -> 0.17444383 | J19: ='Financial Statements'!J73/(('Financial Statements'!I77+'Financial Statements'!J77)/2) -> 0.17442845 | ... R19: ='Financial Statements'!R73/(('Financial Statements'!Q77+'Financial Statements'!R77)/2) -> 0.17432076
A20: Return on Equity (b4 non-recurring) | C20: =('Financial Statements'!C29-'Financial Statements'!C26-'Financial Statements'!C24-((IF('Financial Statements'!C22=0,0,('Financial Statements'!C22+'Financial Statements'!C23)/'Financial Statements'!C22))*'Financial Statements'!C21))/(('Financial Statements'!B77+'Financial Statements'!C77)/2) -> -0.24816886 | D20: =('Financial Statements'!D29-'Financial Statements'!D26-'Financial Statements'!D24-((IF('Financial Statements'!D22=0,0,('Financial Statements'!D22+'Financial Statements'!D23)/'Financial Statements'!D22))*'Financial Statements'!D21))/(('Financial Statements'!C77+'Financial Statements'!D77)/2) -> 0.13919561 | E20: =('Financial Statements'!E29-'Financial Statements'!E26-'Financial Statements'!E24-((IF('Financial Statements'!E22=0,0,('Financial Statements'!E22+'Financial Statements'!E23)/'Financial Statements'!E22))*'Financial Statements'!E21))/(('Financial Statements'!D77+'Financial Statements'!E77)/2) -> 0.19830238 | F20: =('Financial Statements'!F29-'Financial Statements'!F26-'Financial Statements'!F24-((IF('Financial Statements'!F22=0,0,('Financial Statements'!F22+'Financial Statements'!F23)/'Financial Statements'!F22))*'Financial Statements'!F21))/(('Financial Statements'!E77+'Financial Statements'!F77)/2) -> 0.17704103 | G20: =('Financial Statements'!G29-'Financial Statements'!G26-'Financial Statements'!G24-((IF('Financial Statements'!G22=0,0,('Financial Statements'!G22+'Financial Statements'!G23)/'Financial Statements'!G22))*'Financial Statements'!G21))/(('Financial Statements'!F77+'Financial Statements'!G77)/2) -> 0.17450668 | H20: =('Financial Statements'!H29-'Financial Statements'!H26-'Financial Statements'!H24-((IF('Financial Statements'!H22=0,0,('Financial Statements'!H22+'Financial Statements'!H23)/'Financial Statements'!H22))*'Financial Statements'!H21))/(('Financial Statements'!G77+'Financial Statements'!H77)/2) -> 0.17449131 | I20: =('Financial Statements'!I29-'Financial Statements'!I26-'Financial Statements'!I24-((IF('Financial Statements'!I22=0,0,('Financial Statements'!I22+'Financial Statements'!I23)/'Financial Statements'!I22))*'Financial Statements'!I21))/(('Financial Statements'!H77+'Financial Statements'!I77)/2) -> 0.17447594 | J20: =('Financial Statements'!J29-'Financial Statements'!J26-'Financial Statements'!J24-((IF('Financial Statements'!J22=0,0,('Financial Statements'!J22+'Financial Statements'!J23)/'Financial Statements'!J22))*'Financial Statements'!J21))/(('Financial Statements'!I77+'Financial Statements'!J77)/2) -> 0.17446056 | ... R20: =('Financial Statements'!R29-'Financial Statements'!R26-'Financial Statements'!R24-((IF('Financial Statements'!R22=0,0,('Financial Statements'!R22+'Financial Statements'!R23)/'Financial Statements'!R22))*'Financial Statements'!R21))/(('Financial Statements'!Q77+'Financial Statements'!R77)/2) -> 0.17435285
A21: Return on Net Operating Assets | C21: ='Financial Statements'!C71/(('Financial Statements'!B75+'Financial Statements'!C75)/2) -> -0.10023909 | D21: ='Financial Statements'!D71/(('Financial Statements'!C75+'Financial Statements'!D75)/2) -> 0.095209873 | E21: ='Financial Statements'!E71/(('Financial Statements'!D75+'Financial Statements'!E75)/2) -> 0.14173497 | F21: ='Financial Statements'!F71/(('Financial Statements'!E75+'Financial Statements'!F75)/2) -> 0.13613403 | G21: ='Financial Statements'!G71/(('Financial Statements'!F75+'Financial Statements'!G75)/2) -> 0.13438183 | H21: ='Financial Statements'!H71/(('Financial Statements'!G75+'Financial Statements'!H75)/2) -> 0.13437118 | I21: ='Financial Statements'!I71/(('Financial Statements'!H75+'Financial Statements'!I75)/2) -> 0.13436053 | J21: ='Financial Statements'!J71/(('Financial Statements'!I75+'Financial Statements'!J75)/2) -> 0.13434987 | ... R21: ='Financial Statements'!R71/(('Financial Statements'!Q75+'Financial Statements'!R75)/2) -> 0.13427522
A23: Basic Dupont Model
A24: Net Profit Margin | B24: ='Financial Statements'!B29/'Financial Statements'!B12 -> 0.077062777 | C24: ='Financial Statements'!C29/'Financial Statements'!C12 -> -0.069700701 | D24: ='Financial Statements'!D29/'Financial Statements'!D12 -> 0.035026344 | E24: ='Financial Statements'!E29/'Financial Statements'!E12 -> 0.052604344 | F24: ='Financial Statements'!F29/'Financial Statements'!F12 -> 0.050449828 | G24: ='Financial Statements'!G29/'Financial Statements'!G12 -> 0.050378299 | H24: ='Financial Statements'!H29/'Financial Statements'!H12 -> 0.050377855 | I24: ='Financial Statements'!I29/'Financial Statements'!I12 -> 0.050377411 | ... R24: ='Financial Statements'!R29/'Financial Statements'!R12 -> 0.050373852
A25: x Total Asset Turnover | C25: ='Financial Statements'!C12/(('Financial Statements'!B42+'Financial Statements'!C42)/2) -> 1.5300194 | D25: ='Financial Statements'!D12/(('Financial Statements'!C42+'Financial Statements'!D42)/2) -> 1.4276782 | E25: ='Financial Statements'!E12/(('Financial Statements'!D42+'Financial Statements'!E42)/2) -> 1.2668945 | F25: ='Financial Statements'!F12/(('Financial Statements'!E42+'Financial Statements'!F42)/2) -> 1.241045 | G25: ='Financial Statements'!G12/(('Financial Statements'!F42+'Financial Statements'!G42)/2) -> 1.230625 | H25: ='Financial Statements'!H12/(('Financial Statements'!G42+'Financial Statements'!H42)/2) -> 1.2305274 | I25: ='Financial Statements'!I12/(('Financial Statements'!H42+'Financial Statements'!I42)/2) -> 1.2304299 | J25: ='Financial Statements'!J12/(('Financial Statements'!I42+'Financial Statements'!J42)/2) -> 1.2303323 | ... R25: ='Financial Statements'!R12/(('Financial Statements'!Q42+'Financial Statements'!R42)/2) -> 1.2296487
A26: x Total Leverage | C26: =('Financial Statements'!B58+'Financial Statements'!C58)/('Financial Statements'!B57+'Financial Statements'!C57) -> 2.3262015 | D26: =('Financial Statements'!C58+'Financial Statements'!D58)/('Financial Statements'!C57+'Financial Statements'!D57) -> 2.7800163 | E26: =('Financial Statements'!D58+'Financial Statements'!E58)/('Financial Statements'!D57+'Financial Statements'!E57) -> 2.974173 | F26: =('Financial Statements'!E58+'Financial Statements'!F58)/('Financial Statements'!E57+'Financial Statements'!F57) -> 2.8271371 | G26: =('Financial Statements'!F58+'Financial Statements'!G58)/('Financial Statements'!F57+'Financial Statements'!G57) -> 2.8142515 | H26: =('Financial Statements'!G58+'Financial Statements'!H58)/('Financial Statements'!G57+'Financial Statements'!H57) -> 2.8142515 | I26: =('Financial Statements'!H58+'Financial Statements'!I58)/('Financial Statements'!H57+'Financial Statements'!I57) -> 2.8142515 | J26: =('Financial Statements'!I58+'Financial Statements'!J58)/('Financial Statements'!I57+'Financial Statements'!J57) -> 2.8142515 | ... R26: =('Financial Statements'!Q58+'Financial Statements'!R58)/('Financial Statements'!Q57+'Financial Statements'!R57) -> 2.8142515
A27: = Return on Equity | C27: =C24*C25*C26 -> -0.2480741 | D27: =D24*D25*D26 -> 0.13901847 | E27: =E24*E25*E26 -> 0.19821124 | F27: =F24*F25*F26 -> 0.17700849 | G27: =G24*G25*G26 -> 0.17447457 | H27: =H24*H25*H26 -> 0.1744592 | I27: =I24*I25*I26 -> 0.17444383 | J27: =J24*J25*J26 -> 0.17442845 | ... R27: =R24*R25*R26 -> 0.17432076
A29: Advanced Dupont Model
A30: Net Operating Margin | B30: ='Financial Statements'!B71/'Financial Statements'!B12 -> 0.090711571 | C30: ='Financial Statements'!C71/'Financial Statements'!C12 -> -0.049999204 | D30: ='Financial Statements'!D71/'Financial Statements'!D12 -> 0.040194061 | E30: ='Financial Statements'!E71/'Financial Statements'!E12 -> 0.057058086 | F30: ='Financial Statements'!F71/'Financial Statements'!F12 -> 0.055979465 | G30: ='Financial Statements'!G71/'Financial Statements'!G12 -> 0.055979465 | H30: ='Financial Statements'!H71/'Financial Statements'!H12 -> 0.055979465 | I30: ='Financial Statements'!I71/'Financial Statements'!I12 -> 0.055979465 | ... R30: ='Financial Statements'!R71/'Financial Statements'!R12 -> 0.055979465
A31: x Net Operating Asset Turnover | C31: ='Financial Statements'!C12/(('Financial Statements'!B75+'Financial Statements'!C75)/2) -> 2.0048137 | D31: ='Financial Statements'!D12/(('Financial Statements'!C75+'Financial Statements'!D75)/2) -> 2.3687548 | E31: ='Financial Statements'!E12/(('Financial Statements'!D75+'Financial Statements'!E75)/2) -> 2.484047 | F31: ='Financial Statements'!F12/(('Financial Statements'!E75+'Financial Statements'!F75)/2) -> 2.4318566 | G31: ='Financial Statements'!G12/(('Financial Statements'!F75+'Financial Statements'!G75)/2) -> 2.4005559 | H31: ='Financial Statements'!H12/(('Financial Statements'!G75+'Financial Statements'!H75)/2) -> 2.4003656 | I31: ='Financial Statements'!I12/(('Financial Statements'!H75+'Financial Statements'!I75)/2) -> 2.4001753 | J31: ='Financial Statements'!J12/(('Financial Statements'!I75+'Financial Statements'!J75)/2) -> 2.3999849 | ... R31: ='Financial Statements'!R12/(('Financial Statements'!Q75+'Financial Statements'!R75)/2) -> 2.3986515
A32: = Return on Net Operating Assets | C32: =C30*C31 -> -0.10023909 | D32: =D30*D31 -> 0.095209873 | E32: =E30*E31 -> 0.14173497 | F32: =F30*F31 -> 0.13613403 | G32: =G30*G31 -> 0.13438183 | H32: =H30*H31 -> 0.13437118 | I32: =I30*I31 -> 0.13436053 | J32: =J30*J31 -> 0.13434987 | ... R32: =R30*R31 -> 0.13427522
A33: Net Borrowing Cost (NBC) | C33: =-'Financial Statements'!C72/(('Financial Statements'!B76+'Financial Statements'!C76)/2) -> 0.090443448 | D33: =-'Financial Statements'!D72/(('Financial Statements'!C76+'Financial Statements'!D76)/2) -> 0.030361163 | E33: =-'Financial Statements'!E72/(('Financial Statements'!D76+'Financial Statements'!E76)/2) -> 0.032467945 | F33: =-'Financial Statements'!F72/(('Financial Statements'!E76+'Financial Statements'!F76)/2) -> 0.043818248 | G33: =-'Financial Statements'!G72/(('Financial Statements'!F76+'Financial Statements'!G76)/2) -> 0.043818248 | H33: =-'Financial Statements'!H72/(('Financial Statements'!G76+'Financial Statements'!H76)/2) -> 0.043818248 | I33: =-'Financial Statements'!I72/(('Financial Statements'!H76+'Financial Statements'!I76)/2) -> 0.043818248 | J33: =-'Financial Statements'!J72/(('Financial Statements'!I76+'Financial Statements'!J76)/2) -> 0.043818248 | ... R33: =-'Financial Statements'!R72/(('Financial Statements'!Q76+'Financial Statements'!R76)/2) -> 0.043818248
A34: Spread (RNOA - NBC) | C34: =C32-C33 -> -0.19068254 | D34: =D32-D33 -> 0.064848709 | E34: =E32-E33 -> 0.10926702 | F34: =F32-F33 -> 0.092315784 | G34: =G32-G33 -> 0.090563587 | H34: =H32-H33 -> 0.090552934 | I34: =I32-I33 -> 0.090542279 | J34: =J32-J33 -> 0.090531622 | ... R34: =R32-R33 -> 0.090456977
A35: Financial Leverage (LEV) | C35: =('Financial Statements'!B76+'Financial Statements'!C76)/('Financial Statements'!B77+'Financial Statements'!C77) -> 0.77529395 | D35: =('Financial Statements'!C76+'Financial Statements'!D76)/('Financial Statements'!C77+'Financial Statements'!D77) -> 0.67555074 | E35: =('Financial Statements'!D76+'Financial Statements'!E76)/('Financial Statements'!D77+'Financial Statements'!E77) -> 0.51686472 | F35: =('Financial Statements'!E76+'Financial Statements'!F76)/('Financial Statements'!E77+'Financial Statements'!F77) -> 0.44276783 | G35: =('Financial Statements'!F76+'Financial Statements'!G76)/('Financial Statements'!F77+'Financial Statements'!G77) -> 0.4427026 | H35: =('Financial Statements'!G76+'Financial Statements'!H76)/('Financial Statements'!G77+'Financial Statements'!H77) -> 0.4427026 | I35: =('Financial Statements'!H76+'Financial Statements'!I76)/('Financial Statements'!H77+'Financial Statements'!I77) -> 0.4427026 | J35: =('Financial Statements'!I76+'Financial Statements'!J76)/('Financial Statements'!I77+'Financial Statements'!J77) -> 0.4427026 | ... R35: =('Financial Statements'!Q76+'Financial Statements'!R76)/('Financial Statements'!Q77+'Financial Statements'!R77) -> 0.4427026
A36: ROE = RNOA + LEV*Spread | C36: =C32+(C35*C34) -> -0.2480741 | D36: =D32+(D35*D34) -> 0.13901847 | E36: =E32+(E35*E34) -> 0.19821124 | F36: =F32+(F35*F34) -> 0.17700849 | G36: =G32+(G35*G34) -> 0.17447457 | H36: =H32+(H35*H34) -> 0.1744592 | I36: =I32+(I35*I34) -> 0.17444383 | J36: =J32+(J35*J34) -> 0.17442845 | ... R36: =R32+(R35*R34) -> 0.17432076
A39: Margin Analysis
A40: Gross Margin | B40: ='Financial Statements'!B14/'Financial Statements'!B12 -> 0.31565485 | C40: ='Financial Statements'!C14/'Financial Statements'!C12 -> 0.30440383 | D40: ='Financial Statements'!D14/'Financial Statements'!D12 -> 0.29819828 | E40: ='Financial Statements'!E14/'Financial Statements'!E12 -> 0.3052769 | F40: ='Financial Statements'!F14/'Financial Statements'!F12 -> 0.29352385 | G40: ='Financial Statements'!G14/'Financial Statements'!G12 -> 0.29352385 | H40: ='Financial Statements'!H14/'Financial Statements'!H12 -> 0.29352385 | I40: ='Financial Statements'!I14/'Financial Statements'!I12 -> 0.29352385 | ... R40: ='Financial Statements'!R14/'Financial Statements'!R12 -> 0.29352385
A41: EBITDA Margin | B41: ='Financial Statements'!B17/'Financial Statements'!B12 -> 0.092976108 | C41: ='Financial Statements'!C17/'Financial Statements'!C12 -> -0.041164074 | D41: ='Financial Statements'!D17/'Financial Statements'!D12 -> 0.053458587 | E41: ='Financial Statements'!E17/'Financial Statements'!E12 -> 0.074008303 | F41: ='Financial Statements'!F17/'Financial Statements'!F12 -> 0.068819051 | G41: ='Financial Statements'!G17/'Financial Statements'!G12 -> 0.068819051 | H41: ='Financial Statements'!H17/'Financial Statements'!H12 -> 0.068819051 | I41: ='Financial Statements'!I17/'Financial Statements'!I12 -> 0.068819051 | ... R41: ='Financial Statements'!R17/'Financial Statements'!R12 -> 0.068819051
A42: EBIT Margin | B42: ='Financial Statements'!B19/'Financial Statements'!B12 -> 0.089865366 | C42: ='Financial Statements'!C19/'Financial Statements'!C12 -> -0.041164074 | D42: ='Financial Statements'!D19/'Financial Statements'!D12 -> 0.053458587 | E42: ='Financial Statements'!E19/'Financial Statements'!E12 -> 0.074008303 | F42: ='Financial Statements'!F19/'Financial Statements'!F12 -> 0.068819051 | G42: ='Financial Statements'!G19/'Financial Statements'!G12 -> 0.068819051 | H42: ='Financial Statements'!H19/'Financial Statements'!H12 -> 0.068819051 | I42: ='Financial Statements'!I19/'Financial Statements'!I12 -> 0.068819051 | ... R42: ='Financial Statements'!R19/'Financial Statements'!R12 -> 0.068819051
A43: Net Operating Margin (b4 non-rec.) | B43: =('Financial Statements'!B71-'Financial Statements'!B21*(1-'Forecasting Assumptions'!B21)-'Financial Statements'!B26-'Financial Statements'!B24)/'Financial Statements'!B12 -> 0.090408566 | C43: =('Financial Statements'!C71-'Financial Statements'!C21*(1-'Forecasting Assumptions'!C21)-'Financial Statements'!C26-'Financial Statements'!C24)/'Financial Statements'!C12 -> -0.050025828 | D43: =('Financial Statements'!D71-'Financial Statements'!D21*(1-'Forecasting Assumptions'!D21)-'Financial Statements'!D26-'Financial Statements'!D24)/'Financial Statements'!D12 -> 0.040238692 | E43: =('Financial Statements'!E71-'Financial Statements'!E21*(1-'Forecasting Assumptions'!E21)-'Financial Statements'!E26-'Financial Statements'!E24)/'Financial Statements'!E12 -> 0.057082275 | F43: =('Financial Statements'!F71-'Financial Statements'!F21*(1-'Forecasting Assumptions'!F21)-'Financial Statements'!F26-'Financial Statements'!F24)/'Financial Statements'!F12 -> 0.055988738 | G43: =('Financial Statements'!G71-'Financial Statements'!G21*(1-'Forecasting Assumptions'!G21)-'Financial Statements'!G26-'Financial Statements'!G24)/'Financial Statements'!G12 -> 0.055988738 | H43: =('Financial Statements'!H71-'Financial Statements'!H21*(1-'Forecasting Assumptions'!H21)-'Financial Statements'!H26-'Financial Statements'!H24)/'Financial Statements'!H12 -> 0.055988738 | I43: =('Financial Statements'!I71-'Financial Statements'!I21*(1-'Forecasting Assumptions'!I21)-'Financial Statements'!I26-'Financial Statements'!I24)/'Financial Statements'!I12 -> 0.055988738 | ... R43: =('Financial Statements'!R71-'Financial Statements'!R21*(1-'Forecasting Assumptions'!R21)-'Financial Statements'!R26-'Financial Statements'!R24)/'Financial Statements'!R12 -> 0.055988738
A44: Net Operating Margin | B44: ='Financial Statements'!B71/'Financial Statements'!B12 -> 0.090711571 | C44: ='Financial Statements'!C71/'Financial Statements'!C12 -> -0.049999204 | D44: ='Financial Statements'!D71/'Financial Statements'!D12 -> 0.040194061 | E44: ='Financial Statements'!E71/'Financial Statements'!E12 -> 0.057058086 | F44: ='Financial Statements'!F71/'Financial Statements'!F12 -> 0.055979465 | G44: ='Financial Statements'!G71/'Financial Statements'!G12 -> 0.055979465 | H44: ='Financial Statements'!H71/'Financial Statements'!H12 -> 0.055979465 | I44: ='Financial Statements'!I71/'Financial Statements'!I12 -> 0.055979465 | ... R44: ='Financial Statements'!R71/'Financial Statements'!R12 -> 0.055979465
A46: Turnover Analysis
A47: Net Operating Asset Turnover | C47: ='Financial Statements'!C12/(('Financial Statements'!C75+'Financial Statements'!B75)/2) -> 2.0048137 | D47: ='Financial Statements'!D12/(('Financial Statements'!D75+'Financial Statements'!C75)/2) -> 2.3687548 | E47: ='Financial Statements'!E12/(('Financial Statements'!E75+'Financial Statements'!D75)/2) -> 2.484047 | F47: ='Financial Statements'!F12/(('Financial Statements'!F75+'Financial Statements'!E75)/2) -> 2.4318566 | G47: ='Financial Statements'!G12/(('Financial Statements'!G75+'Financial Statements'!F75)/2) -> 2.4005559 | H47: ='Financial Statements'!H12/(('Financial Statements'!H75+'Financial Statements'!G75)/2) -> 2.4003656 | I47: ='Financial Statements'!I12/(('Financial Statements'!I75+'Financial Statements'!H75)/2) -> 2.4001753 | J47: ='Financial Statements'!J12/(('Financial Statements'!J75+'Financial Statements'!I75)/2) -> 2.3999849 | ... R47: ='Financial Statements'!R12/(('Financial Statements'!R75+'Financial Statements'!Q75)/2) -> 2.3986515
A48: Net Working Capital Turnover | C48: ='Financial Statements'!C12/(('Financial Statements'!B37-'Financial Statements'!B48+'Financial Statements'!B44+'Financial Statements'!C37-'Financial Statements'!C48+'Financial Statements'!C44)/2) -> 9.4492724 | D48: ='Financial Statements'!D12/(('Financial Statements'!C37-'Financial Statements'!C48+'Financial Statements'!C44+'Financial Statements'!D37-'Financial Statements'!D48+'Financial Statements'!D44)/2) -> 14.894055 | E48: ='Financial Statements'!E12/(('Financial Statements'!D37-'Financial Statements'!D48+'Financial Statements'!D44+'Financial Statements'!E37-'Financial Statements'!E48+'Financial Statements'!E44)/2) -> 22.245836 | F48: ='Financial Statements'!F12/(('Financial Statements'!E37-'Financial Statements'!E48+'Financial Statements'!E44+'Financial Statements'!F37-'Financial Statements'!F48+'Financial Statements'!F44)/2) -> 19.121136 | G48: ='Financial Statements'!G12/(('Financial Statements'!F37-'Financial Statements'!F48+'Financial Statements'!F44+'Financial Statements'!G37-'Financial Statements'!G48+'Financial Statements'!G44)/2) -> 18.659354 | H48: ='Financial Statements'!H12/(('Financial Statements'!G37-'Financial Statements'!G48+'Financial Statements'!G44+'Financial Statements'!H37-'Financial Statements'!H48+'Financial Statements'!H44)/2) -> 18.657875 | I48: ='Financial Statements'!I12/(('Financial Statements'!H37-'Financial Statements'!H48+'Financial Statements'!H44+'Financial Statements'!I37-'Financial Statements'!I48+'Financial Statements'!I44)/2) -> 18.656395 | J48: ='Financial Statements'!J12/(('Financial Statements'!I37-'Financial Statements'!I48+'Financial Statements'!I44+'Financial Statements'!J37-'Financial Statements'!J48+'Financial Statements'!J44)/2) -> 18.654915 | ... R48: ='Financial Statements'!R12/(('Financial Statements'!Q37-'Financial Statements'!Q48+'Financial Statements'!Q44+'Financial Statements'!R37-'Financial Statements'!R48+'Financial Statements'!R44)/2) -> 18.644551
A49: Avge Days to Collect Receivables | C49: =365*((('Financial Statements'!B34+'Financial Statements'!C34)/2)/'Financial Statements'!C12) -> 0.80681803 | D49: =365*((('Financial Statements'!C34+'Financial Statements'!D34)/2)/'Financial Statements'!D12) -> 0.77990792 | E49: =365*((('Financial Statements'!D34+'Financial Statements'!E34)/2)/'Financial Statements'!E12) -> 0 | F49: =365*((('Financial Statements'!E34+'Financial Statements'!F34)/2)/'Financial Statements'!F12) -> 0 | G49: =365*((('Financial Statements'!F34+'Financial Statements'!G34)/2)/'Financial Statements'!G12) -> 0 | H49: =365*((('Financial Statements'!G34+'Financial Statements'!H34)/2)/'Financial Statements'!H12) -> 0 | I49: =365*((('Financial Statements'!H34+'Financial Statements'!I34)/2)/'Financial Statements'!I12) -> 0 | J49: =365*((('Financial Statements'!I34+'Financial Statements'!J34)/2)/'Financial Statements'!J12) -> 0 | ... R49: =365*((('Financial Statements'!Q34+'Financial Statements'!R34)/2)/'Financial Statements'!R12) -> 0
A50: Avge Inventory Holding Period | C50: =-365*((('Financial Statements'!B35+'Financial Statements'!C35)/2)/'Financial Statements'!C13) -> 77.080667 | D50: =-365*((('Financial Statements'!C35+'Financial Statements'!D35)/2)/'Financial Statements'!D13) -> 77.735499 | E50: =-365*((('Financial Statements'!D35+'Financial Statements'!E35)/2)/'Financial Statements'!E13) -> 71.560753 | F50: =-365*((('Financial Statements'!E35+'Financial Statements'!F35)/2)/'Financial Statements'!F13) -> 76.49566 | G50: =-365*((('Financial Statements'!F35+'Financial Statements'!G35)/2)/'Financial Statements'!G13) -> 84.408628 | H50: =-365*((('Financial Statements'!G35+'Financial Statements'!H35)/2)/'Financial Statements'!H13) -> 84.41532 | I50: =-365*((('Financial Statements'!H35+'Financial Statements'!I35)/2)/'Financial Statements'!I13) -> 84.422014 | J50: =-365*((('Financial Statements'!I35+'Financial Statements'!J35)/2)/'Financial Statements'!J13) -> 84.42871 | ... R50: =-365*((('Financial Statements'!Q35+'Financial Statements'!R35)/2)/'Financial Statements'!R13) -> 84.475645
A51: Avge Days to Pay Payables | C51: =365*((('Financial Statements'!B45+'Financial Statements'!C45)/2)/(-'Financial Statements'!C13+'Financial Statements'!C35-'Financial Statements'!B35)) -> 29.114607 | D51: =365*((('Financial Statements'!C45+'Financial Statements'!D45)/2)/(-'Financial Statements'!D13+'Financial Statements'!D35-'Financial Statements'!C35)) -> 30.345567 | E51: =365*((('Financial Statements'!D45+'Financial Statements'!E45)/2)/(-'Financial Statements'!E13+'Financial Statements'!E35-'Financial Statements'!D35)) -> 29.165792 | F51: =365*((('Financial Statements'!E45+'Financial Statements'!F45)/2)/(-'Financial Statements'!F13+'Financial Statements'!F35-'Financial Statements'!E35)) -> 31.432756 | G51: =365*((('Financial Statements'!F45+'Financial Statements'!G45)/2)/(-'Financial Statements'!G13+'Financial Statements'!G35-'Financial Statements'!F35)) -> 36.156112 | H51: =365*((('Financial Statements'!G45+'Financial Statements'!H45)/2)/(-'Financial Statements'!H13+'Financial Statements'!H35-'Financial Statements'!G35)) -> 36.160295 | I51: =365*((('Financial Statements'!H45+'Financial Statements'!I45)/2)/(-'Financial Statements'!I13+'Financial Statements'!I35-'Financial Statements'!H35)) -> 36.16448 | J51: =365*((('Financial Statements'!I45+'Financial Statements'!J45)/2)/(-'Financial Statements'!J13+'Financial Statements'!J35-'Financial Statements'!I35)) -> 36.168666 | ... R51: =365*((('Financial Statements'!Q45+'Financial Statements'!R45)/2)/(-'Financial Statements'!R13+'Financial Statements'!R35-'Financial Statements'!Q35)) -> 36.198017
A52: PP&E Turnover | C52: ='Financial Statements'!C12/(('Financial Statements'!B38+'Financial Statements'!C38)/2) -> 6.8682817 | D52: ='Financial Statements'!D12/(('Financial Statements'!C38+'Financial Statements'!D38)/2) -> 6.4447872 | E52: ='Financial Statements'!E12/(('Financial Statements'!D38+'Financial Statements'!E38)/2) -> 6.37884 | F52: ='Financial Statements'!F12/(('Financial Statements'!E38+'Financial Statements'!F38)/2) -> 6.125768 | G52: ='Financial Statements'!G12/(('Financial Statements'!F38+'Financial Statements'!G38)/2) -> 5.9704264 | H52: ='Financial Statements'!H12/(('Financial Statements'!G38+'Financial Statements'!H38)/2) -> 5.9699531 | I52: ='Financial Statements'!I12/(('Financial Statements'!H38+'Financial Statements'!I38)/2) -> 5.9694797 | J52: ='Financial Statements'!J12/(('Financial Statements'!I38+'Financial Statements'!J38)/2) -> 5.9690063 | ... R52: ='Financial Statements'!R12/(('Financial Statements'!Q38+'Financial Statements'!R38)/2) -> 5.9656899
A54: Analysis of Leverage
A55: - Long-Term Capital Structure
A56: Debt to Equity Ratio | B56: =('Financial Statements'!B44+'Financial Statements'!B49)/('Financial Statements'!B57) -> 0.79055456 | C56: =('Financial Statements'!C44+'Financial Statements'!C49)/('Financial Statements'!C57) -> 0.75587021 | D56: =('Financial Statements'!D44+'Financial Statements'!D49)/('Financial Statements'!D57) -> 0.60308883 | E56: =('Financial Statements'!E44+'Financial Statements'!E49)/('Financial Statements'!E57) -> 0.44283695 | F56: =('Financial Statements'!F44+'Financial Statements'!F49)/('Financial Statements'!F57) -> 0.4427026 | G56: =('Financial Statements'!G44+'Financial Statements'!G49)/('Financial Statements'!G57) -> 0.4427026 | H56: =('Financial Statements'!H44+'Financial Statements'!H49)/('Financial Statements'!H57) -> 0.4427026 | I56: =('Financial Statements'!I44+'Financial Statements'!I49)/('Financial Statements'!I57) -> 0.4427026 | ... R56: =('Financial Statements'!R44+'Financial Statements'!R49)/('Financial Statements'!R57) -> 0.4427026
A57: FFO to Total Debt | C57: ='Cash Flow Analysis'!B17/(('Financial Statements'!C44+'Financial Statements'!C49+'Financial Statements'!B44+'Financial Statements'!B49)/2) -> -0.32641075 | D57: ='Cash Flow Analysis'!C17/(('Financial Statements'!D44+'Financial Statements'!D49+'Financial Statements'!C44+'Financial Statements'!C49)/2) -> 1.3886905 | E57: ='Cash Flow Analysis'!D17/(('Financial Statements'!E44+'Financial Statements'!E49+'Financial Statements'!D44+'Financial Statements'!D49)/2) -> 0.44152949 | F57: ='Cash Flow Analysis'!E17/(('Financial Statements'!F44+'Financial Statements'!F49+'Financial Statements'!E44+'Financial Statements'!E49)/2) -> 0.38638006 | G57: ='Cash Flow Analysis'!F17/(('Financial Statements'!G44+'Financial Statements'!G49+'Financial Statements'!F44+'Financial Statements'!F49)/2) -> 0.45257823 | H57: ='Cash Flow Analysis'!G17/(('Financial Statements'!H44+'Financial Statements'!H49+'Financial Statements'!G44+'Financial Statements'!G49)/2) -> 0.45224146 | I57: ='Cash Flow Analysis'!H17/(('Financial Statements'!I44+'Financial Statements'!I49+'Financial Statements'!H44+'Financial Statements'!H49)/2) -> 0.45190464 | J57: ='Cash Flow Analysis'!I17/(('Financial Statements'!J44+'Financial Statements'!J49+'Financial Statements'!I44+'Financial Statements'!I49)/2) -> 0.45156777 | ... R57: ='Cash Flow Analysis'!Q17/(('Financial Statements'!R44+'Financial Statements'!R49+'Financial Statements'!Q44+'Financial Statements'!Q49)/2) -> 0.4492081
A58: CFO to Total Debt | C58: ='Cash Flow Analysis'!B24/(('Financial Statements'!C44+'Financial Statements'!C49+'Financial Statements'!B44+'Financial Statements'!B49)/2) -> -0.36977663 | D58: ='Cash Flow Analysis'!C24/(('Financial Statements'!D44+'Financial Statements'!D49+'Financial Statements'!C44+'Financial Statements'!C49)/2) -> 1.7280995 | E58: ='Cash Flow Analysis'!D24/(('Financial Statements'!E44+'Financial Statements'!E49+'Financial Statements'!D44+'Financial Statements'!D49)/2) -> 0.59299268 | F58: ='Cash Flow Analysis'!E24/(('Financial Statements'!F44+'Financial Statements'!F49+'Financial Statements'!E44+'Financial Statements'!E49)/2) -> 0.22459056 | G58: ='Cash Flow Analysis'!F24/(('Financial Statements'!G44+'Financial Statements'!G49+'Financial Statements'!F44+'Financial Statements'!F49)/2) -> 0.44898164 | H58: ='Cash Flow Analysis'!G24/(('Financial Statements'!H44+'Financial Statements'!H49+'Financial Statements'!G44+'Financial Statements'!G49)/2) -> 0.44866345 | I58: ='Cash Flow Analysis'!H24/(('Financial Statements'!I44+'Financial Statements'!I49+'Financial Statements'!H44+'Financial Statements'!H49)/2) -> 0.44834522 | J58: ='Cash Flow Analysis'!I24/(('Financial Statements'!J44+'Financial Statements'!J49+'Financial Statements'!I44+'Financial Statements'!I49)/2) -> 0.44802693 | ... R58: ='Cash Flow Analysis'!Q24/(('Financial Statements'!R44+'Financial Statements'!R49+'Financial Statements'!Q44+'Financial Statements'!Q49)/2) -> 0.44579745
A60: Analysis of Leverage
A61: - Short-Term Liquidity
A62: Current Ratio | B62: ='Financial Statements'!B37/'Financial Statements'!B48 -> 1.6006086 | C62: ='Financial Statements'!C37/'Financial Statements'!C48 -> 2.0486234 | D62: ='Financial Statements'!D37/'Financial Statements'!D48 -> 1.2038348 | E62: ='Financial Statements'!E37/'Financial Statements'!E48 -> 1.353993 | F62: ='Financial Statements'!F37/'Financial Statements'!F48 -> 1.3430063 | G62: ='Financial Statements'!G37/'Financial Statements'!G48 -> 1.3430063 | H62: ='Financial Statements'!H37/'Financial Statements'!H48 -> 1.3430063 | I62: ='Financial Statements'!I37/'Financial Statements'!I48 -> 1.3430063 | ... R62: ='Financial Statements'!R37/'Financial Statements'!R48 -> 1.3430063
A63: Quick Ratio | B63: =('Financial Statements'!B33+'Financial Statements'!B34)/'Financial Statements'!B48 -> 0.38396698 | C63: =('Financial Statements'!C33+'Financial Statements'!C34)/'Financial Statements'!C48 -> 0.26129694 | D63: =('Financial Statements'!D33+'Financial Statements'!D34)/'Financial Statements'!D48 -> 0.16523333 | E63: =('Financial Statements'!E33+'Financial Statements'!E34)/'Financial Statements'!E48 -> 0.3923545 | F63: =('Financial Statements'!F33+'Financial Statements'!F34)/'Financial Statements'!F48 -> 0.24859934 | G63: =('Financial Statements'!G33+'Financial Statements'!G34)/'Financial Statements'!G48 -> 0.24859934 | H63: =('Financial Statements'!H33+'Financial Statements'!H34)/'Financial Statements'!H48 -> 0.24859934 | I63: =('Financial Statements'!I33+'Financial Statements'!I34)/'Financial Statements'!I48 -> 0.24859934 | ... R63: =('Financial Statements'!R33+'Financial Statements'!R34)/'Financial Statements'!R48 -> 0.24859934
A64: EBIT Interest Coverage | B64: =-'Financial Statements'!B19/'Financial Statements'!B20 -> 6.6239231 | C64: =-'Financial Statements'!C19/'Financial Statements'!C20 -> -2.5391892 | D64: =-'Financial Statements'!D19/'Financial Statements'!D20 -> 7.7865515 | E64: =-'Financial Statements'!E19/'Financial Statements'!E20 -> 12.816701 | F64: =-'Financial Statements'!F19/'Financial Statements'!F20 -> 10.12521 | G64: =-'Financial Statements'!G19/'Financial Statements'!G20 -> 9.9959077 | H64: =-'Financial Statements'!H19/'Financial Statements'!H20 -> 9.9951153 | I64: =-'Financial Statements'!I19/'Financial Statements'!I20 -> 9.9943227 | ... R64: =-'Financial Statements'!R19/'Financial Statements'!R20 -> 9.9879776
A65: EBITDA Interest Coverage | B65: =-'Financial Statements'!B17/'Financial Statements'!B20 -> 6.853214 | C65: =-'Financial Statements'!C17/'Financial Statements'!C20 -> -2.5391892 | D65: =-'Financial Statements'!D17/'Financial Statements'!D20 -> 7.7865515 | E65: =-'Financial Statements'!E17/'Financial Statements'!E20 -> 12.816701 | F65: =-'Financial Statements'!F17/'Financial Statements'!F20 -> 10.12521 | G65: =-'Financial Statements'!G17/'Financial Statements'!G20 -> 9.9959077 | H65: =-'Financial Statements'!H17/'Financial Statements'!H20 -> 9.9951153 | I65: =-'Financial Statements'!I17/'Financial Statements'!I20 -> 9.9943227 | ... R65: =-'Financial Statements'!R17/'Financial Statements'!R20 -> 9.9879776
A67: Fiscal Year | B67: =IF(MONTH(B7)>6,YEAR(B7),YEAR(B7)-1) -> 2017 | C67: =IF(MONTH(C7)>6,YEAR(C7),YEAR(C7)-1) -> 2018 | D67: =IF(MONTH(D7)>6,YEAR(D7),YEAR(D7)-1) -> 2019 | E67: =IF(MONTH(E7)>6,YEAR(E7),YEAR(E7)-1) -> 2020 | F67: =IF(MONTH(F7)>6,YEAR(F7),YEAR(F7)-1) -> 2021 | G67: =IF(MONTH(G7)>6,YEAR(G7),YEAR(G7)-1) -> 2022 | H67: =IF(MONTH(H7)>6,YEAR(H7),YEAR(H7)-1) -> 2023 | I67: =IF(MONTH(I7)>6,YEAR(I7),YEAR(I7)-1) -> 2024 | ... R67: =IF(MONTH(R7)>6,YEAR(R7),YEAR(R7)-1) -> 2033

Sheet Cash Flow Analysis
A1: Cash Flow Analysis | B1: ($000)
A4: Company Name | B4: ='Financial Statements'!B4 -> DOLLAR TREE 2021
B6: Actual | C6: Actual | D6: Actual | E6: Actual | F6: Forecast | G6: Forecast | H6: Forecast | I6: Forecast | J6: Forecast | K6: Forecast | L6: Forecast | M6: Forecast | N6: Forecast | O6: Forecast | P6: Forecast | Q6: Forecast
A7: Fiscal Year End Date | B7: ='Financial Statements'!C8 -> 42034 | C7: ='Financial Statements'!D8 -> 42399 | D7: ='Financial Statements'!E8 -> 42765 | E7: ='Financial Statements'!F8 -> 43130 | F7: ='Financial Statements'!G8 -> 43495 | G7: ='Financial Statements'!H8 -> 43860 | H7: ='Financial Statements'!I8 -> 44226 | I7: ='Financial Statements'!J8 -> 44591 | ... Q7: ='Financial Statements'!R8 -> 47513
A8: Pro Forma Statement of Cash Flows
A10: Operating:
A11: Net Income | B11: ='Financial Statements'!C29 -> -1590800 | C11: ='Financial Statements'!D29 -> 827000 | D11: ='Financial Statements'!E29 -> 1341900 | E11: ='Financial Statements'!F29 -> 1327900 | F11: ='Financial Statements'!G29 -> 1368000.9 | G11: ='Financial Statements'!H29 -> 1411074.1 | H11: ='Financial Statements'!I29 -> 1455269.1 | I11: ='Financial Statements'!J29 -> 1500606.4 | ... Q11: ='Financial Statements'!R29 -> 1907253.3
A12: +Depreciation & Amortization | B12: =-'Financial Statements'!C18 -> 0 | C12: =-'Financial Statements'!D18 -> 0 | D12: =-'Financial Statements'!E18 -> 0 | E12: =-'Financial Statements'!F18 -> 0 | F12: =-'Financial Statements'!G18 -> 0 | G12: =-'Financial Statements'!H18 -> 0 | H12: =-'Financial Statements'!I18 -> 0 | I12: =-'Financial Statements'!J18 -> 0 | ... Q12: =-'Financial Statements'!R18 -> 0
A13: +Increase in Deferred Taxes | B13: ='Financial Statements'!C51-'Financial Statements'!B51 -> -12000 | C13: ='Financial Statements'!D51-'Financial Statements'!C51 -> 11500 | D13: ='Financial Statements'!E51-'Financial Statements'!D51 -> 28800 | E13: ='Financial Statements'!F51-'Financial Statements'!E51 -> -26300 | F13: ='Financial Statements'!G51-'Financial Statements'!F51 -> 31256.195 | G13: ='Financial Statements'!H51-'Financial Statements'!G51 -> 32076.599 | H13: ='Financial Statements'!I51-'Financial Statements'!H51 -> 32912.32 | I13: ='Financial Statements'!J51-'Financial Statements'!I51 -> 33763.425 | ... Q13: ='Financial Statements'!R51-'Financial Statements'!Q51 -> 41360.589
A14: +Increase in Other Liabilities | B14: ='Financial Statements'!C50-'Financial Statements'!B50 -> -20000 | C14: ='Financial Statements'!D50-'Financial Statements'!C50 -> 4742300 | D14: ='Financial Statements'!E50-'Financial Statements'!D50 -> 174300 | E14: ='Financial Statements'!F50-'Financial Statements'!E50 -> -18200 | F14: ='Financial Statements'!G50-'Financial Statements'!F50 -> 171684.28 | G14: ='Financial Statements'!H50-'Financial Statements'!G50 -> 176190.6 | H14: ='Financial Statements'!I50-'Financial Statements'!H50 -> 180781.05 | I14: ='Financial Statements'!J50-'Financial Statements'!I50 -> 185456.01 | ... Q14: ='Financial Statements'!R50-'Financial Statements'!Q50 -> 227185.77
A15: +Noncontrolling Interest in Earnings | B15: =-'Financial Statements'!C27 -> 0 | C15: =-'Financial Statements'!D27 -> 0 | D15: =-'Financial Statements'!E27 -> 0 | E15: =-'Financial Statements'!F27 -> 0 | F15: =-'Financial Statements'!G27 -> 0 | G15: =-'Financial Statements'!H27 -> 0 | H15: =-'Financial Statements'!I27 -> 0 | I15: =-'Financial Statements'!J27 -> 0 | ... Q15: =-'Financial Statements'!R27 -> 0
A16: +Preferred Dividends | B16: =-'Financial Statements'!C28 -> 0 | C16: =-'Financial Statements'!D28 -> 0 | D16: =-'Financial Statements'!E28 -> 0 | E16: =-'Financial Statements'!F28 -> 0 | F16: =-'Financial Statements'!G28 -> 0 | G16: =-'Financial Statements'!H28 -> 0 | H16: =-'Financial Statements'!I28 -> 0 | I16: =-'Financial Statements'!J28 -> 0 | ... Q16: =-'Financial Statements'!R28 -> 0
A17: =Funds From Operations | B17: =B11+B12+B13+B14+B15+B16 -> -1622800 | C17: =C11+C12+C13+C14+C15+C16 -> 5580800 | D17: =D11+D12+D13+D14+D15+D16 -> 1545000 | E17: =E11+E12+E13+E14+E15+E16 -> 1283400 | F17: =F11+F12+F13+F14+F15+F16 -> 1570941.4 | G17: =G11+G12+G13+G14+G15+G16 -> 1619341.3 | H17: =H11+H12+H13+H14+H15+H16 -> 1668962.4 | I17: =I11+I12+I13+I14+I15+I16 -> 1719825.8 | ... Q17: =Q11+Q12+Q13+Q14+Q15+Q16 -> 2175799.7
A18: -Increase in Receivables | B18: =-('Financial Statements'!C34-'Financial Statements'!B34) -> -100900 | C18: =-('Financial Statements'!D34-'Financial Statements'!C34) -> 100900 | D18: =-('Financial Statements'!E34-'Financial Statements'!D34) -> 0 | E18: =-('Financial Statements'!F34-'Financial Statements'!E34) -> 0 | F18: =-('Financial Statements'!G34-'Financial Statements'!F34) -> 0 | G18: =-('Financial Statements'!H34-'Financial Statements'!G34) -> 0 | H18: =-('Financial Statements'!I34-'Financial Statements'!H34) -> 0 | I18: =-('Financial Statements'!J34-'Financial Statements'!I34) -> 0 | ... Q18: =-('Financial Statements'!R34-'Financial Statements'!Q34) -> 0
A19: -Increase in Inventory | B19: =-('Financial Statements'!C35-'Financial Statements'!B35) -> -366700 | C19: =-('Financial Statements'!D35-'Financial Statements'!C35) -> 14000 | D19: =-('Financial Statements'!E35-'Financial Statements'!D35) -> 95000 | E19: =-('Financial Statements'!F35-'Financial Statements'!E35) -> -940300 | F19: =-('Financial Statements'!G35-'Financial Statements'!F35) -> -138275.1 | G19: =-('Financial Statements'!H35-'Financial Statements'!G35) -> -141904.51 | H19: =-('Financial Statements'!I35-'Financial Statements'!H35) -> -145601.68 | I19: =-('Financial Statements'!J35-'Financial Statements'!I35) -> -149366.9 | ... Q19: =-('Financial Statements'!R35-'Financial Statements'!Q35) -> -182976.19
A20: -Increase in Other Current Assets | B20: =-('Financial Statements'!C36-'Financial Statements'!B36) -> 99500 | C20: =-('Financial Statements'!D36-'Financial Statements'!C36) -> 48300 | D20: =-('Financial Statements'!E36-'Financial Statements'!D36) -> 1200 | E20: =-('Financial Statements'!F36-'Financial Statements'!E36) -> -43400 | F20: =-('Financial Statements'!G36-'Financial Statements'!F36) -> -6446.2736 | G20: =-('Financial Statements'!H36-'Financial Statements'!G36) -> -6615.4737 | H20: =-('Financial Statements'!I36-'Financial Statements'!H36) -> -6787.8326 | I20: =-('Financial Statements'!J36-'Financial Statements'!I36) -> -6963.3645 | ... Q20: =-('Financial Statements'!R36-'Financial Statements'!Q36) -> -8530.2024
A21: +Increase in Accounts Payable | B21: =('Financial Statements'!C45-'Financial Statements'!B45) -> 241600 | C21: =('Financial Statements'!D45-'Financial Statements'!C45) -> -79900 | D21: =('Financial Statements'!E45-'Financial Statements'!D45) -> 144000 | E21: =('Financial Statements'!F45-'Financial Statements'!E45) -> 403700 | F21: =('Financial Statements'!G45-'Financial Statements'!F45) -> 59656.526 | G21: =('Financial Statements'!H45-'Financial Statements'!G45) -> 61222.375 | H21: =('Financial Statements'!I45-'Financial Statements'!H45) -> 62817.457 | I21: =('Financial Statements'!J45-'Financial Statements'!I45) -> 64441.902 | ... Q21: =('Financial Statements'!R45-'Financial Statements'!Q45) -> 78942.08
A22: +Increase in Taxes Payable | B22: =('Financial Statements'!C46-'Financial Statements'!B46) -> 28500 | C22: =('Financial Statements'!D46-'Financial Statements'!C46) -> 2700 | D22: =('Financial Statements'!E46-'Financial Statements'!D46) -> 23600 | E22: =('Financial Statements'!F46-'Financial Statements'!E46) -> -3700 | F22: =('Financial Statements'!G46-'Financial Statements'!F46) -> 2615.2367 | G22: =('Financial Statements'!H46-'Financial Statements'!G46) -> 2683.8808 | H22: =('Financial Statements'!I46-'Financial Statements'!H46) -> 2753.8063 | I22: =('Financial Statements'!J46-'Financial Statements'!I46) -> 2825.0192 | ... Q22: =('Financial Statements'!R46-'Financial Statements'!Q46) -> 3460.6813
A23: +Increase in Other Curr. Liabilities | B23: =('Financial Statements'!C47-'Financial Statements'!B47) -> -117600 | C23: =('Financial Statements'!D47-'Financial Statements'!C47) -> 1278000 | D23: =('Financial Statements'!E47-'Financial Statements'!D47) -> 266200 | E23: =('Financial Statements'!F47-'Financial Statements'!E47) -> 46300 | F23: =('Financial Statements'!G47-'Financial Statements'!F47) -> 69965.498 | G23: =('Financial Statements'!H47-'Financial Statements'!G47) -> 71801.934 | H23: =('Financial Statements'!I47-'Financial Statements'!H47) -> 73672.655 | I23: =('Financial Statements'!J47-'Financial Statements'!I47) -> 75577.813 | ... Q23: =('Financial Statements'!R47-'Financial Statements'!Q47) -> 92583.7
A24: =Cash From Operations | B24: =B17+B18+B19+B20+B21+B22+B23 -> -1838400 | C24: =C17+C18+C19+C20+C21+C22+C23 -> 6944800 | D24: =D17+D18+D19+D20+D21+D22+D23 -> 2075000 | E24: =E17+E18+E19+E20+E21+E22+E23 -> 746000 | F24: =F17+F18+F19+F20+F21+F22+F23 -> 1558457.3 | G24: =G17+G18+G19+G20+G21+G22+G23 -> 1606529.5 | H24: =H17+H18+H19+H20+H21+H22+H23 -> 1655816.8 | I24: =I17+I18+I19+I20+I21+I22+I23 -> 1706340.3 | ... Q24: =Q17+Q18+Q19+Q20+Q21+Q22+Q23 -> 2159279.7
A26: Investing:
A27: -Capital Expenditures | B27: =-('Financial Statements'!C38-'Financial Statements'!B38-'Financial Statements'!C18) -> -244600 | C27: =-('Financial Statements'!D38-'Financial Statements'!C38-'Financial Statements'!D18) -> -436500 | D27: =-('Financial Statements'!E38-'Financial Statements'!D38-'Financial Statements'!E18) -> -234500 | E27: =-('Financial Statements'!F38-'Financial Statements'!E38-'Financial Statements'!F18) -> -361000 | F27: =-('Financial Statements'!G38-'Financial Statements'!F38-'Financial Statements'!G18) -> -141757.86 | G27: =-('Financial Statements'!H38-'Financial Statements'!G38-'Financial Statements'!H18) -> -145478.69 | H27: =-('Financial Statements'!I38-'Financial Statements'!H38-'Financial Statements'!I18) -> -149268.97 | I27: =-('Financial Statements'!J38-'Financial Statements'!I38-'Financial Statements'!J18) -> -153129.04 | ... Q27: =-('Financial Statements'!R38-'Financial Statements'!Q38-'Financial Statements'!R18) -> -187584.85
A28: -Increase in Investments | B28: =-('Financial Statements'!C39-'Financial Statements'!B39) -> 0 | C28: =-('Financial Statements'!D39-'Financial Statements'!C39) -> 0 | D28: =-('Financial Statements'!E39-'Financial Statements'!D39) -> 0 | E28: =-('Financial Statements'!F39-'Financial Statements'!E39) -> 0 | F28: =-('Financial Statements'!G39-'Financial Statements'!F39) -> 0 | G28: =-('Financial Statements'!H39-'Financial Statements'!G39) -> 0 | H28: =-('Financial Statements'!I39-'Financial Statements'!H39) -> 0 | I28: =-('Financial Statements'!J39-'Financial Statements'!I39) -> 0 | ... Q28: =-('Financial Statements'!R39-'Financial Statements'!Q39) -> 0
A29: -Purchases of Intangibles | B29: =-('Financial Statements'!C40-'Financial Statements'!B40) -> -660100 | C29: =-('Financial Statements'!D40-'Financial Statements'!C40) -> 602000 | D29: =-('Financial Statements'!E40-'Financial Statements'!D40) -> -1100 | E29: =-('Financial Statements'!F40-'Financial Statements'!E40) -> 0 | F29: =-('Financial Statements'!G40-'Financial Statements'!F40) -> -160979.54 | G29: =-('Financial Statements'!H40-'Financial Statements'!G40) -> -165204.88 | H29: =-('Financial Statements'!I40-'Financial Statements'!H40) -> -169509.12 | I29: =-('Financial Statements'!J40-'Financial Statements'!I40) -> -173892.58 | ... Q29: =-('Financial Statements'!R40-'Financial Statements'!Q40) -> -213020.44
A30: -Increase in Other Assets | B30: =-('Financial Statements'!C41-'Financial Statements'!B41) -> 3453300 | C30: =-('Financial Statements'!D41-'Financial Statements'!C41) -> -6262800 | D30: =-('Financial Statements'!E41-'Financial Statements'!D41) -> -104400 | E30: =-('Financial Statements'!F41-'Financial Statements'!E41) -> -106400 | F30: =-('Financial Statements'!G41-'Financial Statements'!F41) -> -207411.07 | G30: =-('Financial Statements'!H41-'Financial Statements'!G41) -> -212855.14 | H30: =-('Financial Statements'!I41-'Financial Statements'!H41) -> -218400.85 | I30: =-('Financial Statements'!J41-'Financial Statements'!I41) -> -224048.65 | ... Q30: =-('Financial Statements'!R41-'Financial Statements'!Q41) -> -274462.2
A31: =Cash From Investing | B31: =B27+B28+B29+B30 -> 2548600 | C31: =C27+C28+C29+C30 -> -6097300 | D31: =D27+D28+D29+D30 -> -340000 | E31: =E27+E28+E29+E30 -> -467400 | F31: =F27+F28+F29+F30 -> -510148.47 | G31: =G27+G28+G29+G30 -> -523538.71 | H31: =H27+H28+H29+H30 -> -537178.94 | I31: =I27+I28+I29+I30 -> -551070.27 | ... Q31: =Q27+Q28+Q29+Q30 -> -675067.48
A33: Financing:
A34: +Increase in Debt | B34: =('Financial Statements'!C44+'Financial Statements'!C49-'Financial Statements'!B44-'Financial Statements'!B49) -> -1412700 | C34: =('Financial Statements'!D44+'Financial Statements'!D49-'Financial Statements'!C44-'Financial Statements'!C49) -> -493100 | D34: =('Financial Statements'!E44+'Financial Statements'!E49-'Financial Statements'!D44-'Financial Statements'!D49) -> -546000 | E34: =('Financial Statements'!F44+'Financial Statements'!F49-'Financial Statements'!E44-'Financial Statements'!E49) -> 190800 | F34: =('Financial Statements'!G44+'Financial Statements'!G49-'Financial Statements'!F44-'Financial Statements'!F49) -> 108187.21 | G34: =('Financial Statements'!H44+'Financial Statements'!H49-'Financial Statements'!G44-'Financial Statements'!G49) -> 111026.88 | H34: =('Financial Statements'!I44+'Financial Statements'!I49-'Financial Statements'!H44-'Financial Statements'!H49) -> 113919.57 | I34: =('Financial Statements'!J44+'Financial Statements'!J49-'Financial Statements'!I44-'Financial Statements'!I49) -> 116865.5 | ... Q34: =('Financial Statements'!R44+'Financial Statements'!R49-'Financial Statements'!Q44-'Financial Statements'!Q49) -> 143161.6
A35: -Dividends Paid to Noncontrolling Interest | B35: ='Financial Statements'!C27+'Financial Statements'!C53-'Financial Statements'!B53 -> 0 | C35: ='Financial Statements'!D27+'Financial Statements'!D53-'Financial Statements'!C53 -> 0 | D35: ='Financial Statements'!E27+'Financial Statements'!E53-'Financial Statements'!D53 -> 0 | E35: ='Financial Statements'!F27+'Financial Statements'!F53-'Financial Statements'!E53 -> 0 | F35: ='Financial Statements'!G27+'Financial Statements'!G53-'Financial Statements'!F53 -> 0 | G35: ='Financial Statements'!H27+'Financial Statements'!H53-'Financial Statements'!G53 -> 0 | H35: ='Financial Statements'!I27+'Financial Statements'!I53-'Financial Statements'!H53 -> 0 | I35: ='Financial Statements'!J27+'Financial Statements'!J53-'Financial Statements'!I53 -> 0 | ... Q35: ='Financial Statements'!R27+'Financial Statements'!R53-'Financial Statements'!Q53 -> 0
A36: -Dividends Paid on Preferred | B36: ='Financial Statements'!C28 -> 0 | C36: ='Financial Statements'!D28 -> 0 | D36: ='Financial Statements'!E28 -> 0 | E36: ='Financial Statements'!F28 -> 0 | F36: ='Financial Statements'!G28 -> 0 | G36: ='Financial Statements'!H28 -> 0 | H36: ='Financial Statements'!I28 -> 0 | I36: ='Financial Statements'!J28 -> 0 | ... Q36: ='Financial Statements'!R28 -> 0
A37: +Increase in Pref. Stock | B37: ='Financial Statements'!C54-'Financial Statements'!B54 -> 0 | C37: ='Financial Statements'!D54-'Financial Statements'!C54 -> 0 | D37: ='Financial Statements'!E54-'Financial Statements'!D54 -> 0 | E37: ='Financial Statements'!F54-'Financial Statements'!E54 -> 0 | F37: ='Financial Statements'!G54-'Financial Statements'!F54 -> 0 | G37: ='Financial Statements'!H54-'Financial Statements'!G54 -> 0 | H37: ='Financial Statements'!I54-'Financial Statements'!H54 -> 0 | I37: ='Financial Statements'!J54-'Financial Statements'!I54 -> 0 | ... Q37: ='Financial Statements'!R54-'Financial Statements'!Q54 -> 0
A38: -Dividends Paid on Common | B38: ='Financial Statements'!C64 -> 0 | C38: ='Financial Statements'!D64 -> 0 | D38: ='Financial Statements'!E64 -> 0 | E38: ='Financial Statements'!F64 -> 0 | F38: ='Financial Statements'!G64 -> 0 | G38: ='Financial Statements'!H64 -> 0 | H38: ='Financial Statements'!I64 -> 0 | I38: ='Financial Statements'!J64 -> 0 | ... Q38: ='Financial Statements'!R64 -> 0
A39: +/-Net Issuance of Common Stock | B39: ='Financial Statements'!C55-'Financial Statements'!B55 -> 51400 | C39: ='Financial Statements'!D55-'Financial Statements'!C55 -> -149800 | D39: ='Financial Statements'!E55-'Financial Statements'!D55 -> -311400 | E39: ='Financial Statements'!F55-'Financial Statements'!E55 -> -894700 | F39: ='Financial Statements'!G55-'Financial Statements'!F55 -> -1123621.9 | G39: ='Financial Statements'!H55-'Financial Statements'!G55 -> -1160280.7 | H39: ='Financial Statements'!I55-'Financial Statements'!H55 -> -1197941.5 | I39: ='Financial Statements'!J55-'Financial Statements'!I55 -> -1236624.4 | ... Q39: ='Financial Statements'!R55-'Financial Statements'!Q55 -> -1583872.3
A40: +/-Clean Surplus Plug (Ignore) | B40: ='Financial Statements'!C65 -> 0 | C40: ='Financial Statements'!D65 -> -65300 | D40: ='Financial Statements'!E65 -> 0 | E40: ='Financial Statements'!F65 -> 0 | F40: ='Financial Statements'!G65 -> 0 | G40: ='Financial Statements'!H65 -> 0 | H40: ='Financial Statements'!I65 -> 0 | I40: ='Financial Statements'!J65 -> 0 | ... Q40: ='Financial Statements'!R65 -> 0
A41: =Cash From Financing | B41: =SUM(B34:B40) -> -1361300 | C41: =SUM(C34:C40) -> -708200 | D41: =SUM(D34:D40) -> -857400 | E41: =SUM(E34:E40) -> -703900 | F41: =SUM(F34:F40) -> -1015434.7 | G41: =SUM(G34:G40) -> -1049253.8 | H41: =SUM(H34:H40) -> -1084022 | I41: =SUM(I34:I40) -> -1119758.9 | ... Q41: =SUM(Q34:Q40) -> -1440710.7
A43: Net Change in Cash | B43: =B24+B31+B41 -> -651100 | C43: =C24+C31+C41 -> 139300 | D43: =D24+D31+D41 -> 877600 | E43: =E24+E31+E41 -> -425300 | F43: =F24+F31+F41 -> 32874.096 | G43: =G24+G31+G41 -> 33736.966 | H43: =H24+H31+H41 -> 34615.946 | I43: =I24+I31+I41 -> 35511.107 | ... Q43: =Q24+Q31+Q41 -> 43501.518
A44: + Beginning Cash Balance | B44: ='Financial Statements'!B33 -> 1097800 | C44: ='Financial Statements'!C33 -> 446700 | D44: ='Financial Statements'!D33 -> 586000 | E44: ='Financial Statements'!E33 -> 1463600 | F44: ='Financial Statements'!F33 -> 1038300 | G44: ='Financial Statements'!G33 -> 1071174.1 | H44: ='Financial Statements'!H33 -> 1104911.1 | I44: ='Financial Statements'!I33 -> 1139527 | ... Q44: ='Financial Statements'!Q33 -> 1450050.6
A45: = Ending Cash Balance | B45: =B43+B44 -> 446700 | C45: =C43+C44 -> 586000 | D45: =D43+D44 -> 1463600 | E45: =E43+E44 -> 1038300 | F45: =F43+F44 -> 1071174.1 | G45: =G43+G44 -> 1104911.1 | H45: =H43+H44 -> 1139527 | I45: =I43+I44 -> 1175038.1 | ... Q45: =Q43+Q44 -> 1493552.1
A48: Free Cash Flow to Common Equity
A50: Net Income | B50: ='Financial Statements'!C29 -> -1590800 | C50: ='Financial Statements'!D29 -> 827000 | D50: ='Financial Statements'!E29 -> 1341900 | E50: ='Financial Statements'!F29 -> 1327900 | F50: ='Financial Statements'!G29 -> 1368000.9 | G50: ='Financial Statements'!H29 -> 1411074.1 | H50: ='Financial Statements'!I29 -> 1455269.1 | I50: ='Financial Statements'!J29 -> 1500606.4 | ... Q50: ='Financial Statements'!R29 -> 1907253.3
A51: - Increase in Common Equity | B51: =-('Financial Statements'!C57-'Financial Statements'!B57) -> 1539400 | C51: =-('Financial Statements'!D57-'Financial Statements'!C57) -> -611900 | D51: =-('Financial Statements'!E57-'Financial Statements'!D57) -> -1030500 | E51: =-('Financial Statements'!F57-'Financial Statements'!E57) -> -433200 | F51: =-('Financial Statements'!G57-'Financial Statements'!F57) -> -244378.99 | G51: =-('Financial Statements'!H57-'Financial Statements'!G57) -> -250793.39 | H51: =-('Financial Statements'!I57-'Financial Statements'!H57) -> -257327.53 | I51: =-('Financial Statements'!J57-'Financial Statements'!I57) -> -263981.97 | ... Q51: =-('Financial Statements'!R57-'Financial Statements'!Q57) -> -323380.98
A52: +/-Clean Surplus Plug (Ignore) | B52: ='Financial Statements'!C65 -> 0 | C52: ='Financial Statements'!D65 -> -65300 | D52: ='Financial Statements'!E65 -> 0 | E52: ='Financial Statements'!F65 -> 0 | F52: ='Financial Statements'!G65 -> 0 | G52: ='Financial Statements'!H65 -> 0 | H52: ='Financial Statements'!I65 -> 0 | I52: ='Financial Statements'!J65 -> 0 | ... Q52: ='Financial Statements'!R65 -> 0
A53: =Free Cash Flow to Common Equity | B53: =SUM(B50:B52) -> -51400 | C53: =SUM(C50:C52) -> 149800 | D53: =SUM(D50:D52) -> 311400 | E53: =SUM(E50:E52) -> 894700 | F53: =SUM(F50:F52) -> 1123621.9 | G53: =SUM(G50:G52) -> 1160280.7 | H53: =SUM(H50:H52) -> 1197941.5 | I53: =SUM(I50:I52) -> 1236624.4 | ... Q53: =SUM(Q50:Q52) -> 1583872.3
A55: Computation based on SCF:
A56: +Cash From Operations | B56: =B24 -> -1838400 | C56: =C24 -> 6944800 | D56: =D24 -> 2075000 | E56: =E24 -> 746000 | F56: =F24 -> 1558457.3 | G56: =G24 -> 1606529.5 | H56: =H24 -> 1655816.8 | I56: =I24 -> 1706340.3 | ... Q56: =Q24 -> 2159279.7
A57: -Increase in Cash | B57: =-B43 -> 651100 | C57: =-C43 -> -139300 | D57: =-D43 -> -877600 | E57: =-E43 -> 425300 | F57: =-F43 -> -32874.096 | G57: =-G43 -> -33736.966 | H57: =-H43 -> -34615.946 | I57: =-I43 -> -35511.107 | ... Q57: =-Q43 -> -43501.518
A58: +Cash From Investing | B58: =B31 -> 2548600 | C58: =C31 -> -6097300 | D58: =D31 -> -340000 | E58: =E31 -> -467400 | F58: =F31 -> -510148.47 | G58: =G31 -> -523538.71 | H58: =H31 -> -537178.94 | I58: =I31 -> -551070.27 | ... Q58: =Q31 -> -675067.48
A59: +Increase in Debt | B59: =B34 -> -1412700 | C59: =C34 -> -493100 | D59: =D34 -> -546000 | E59: =E34 -> 190800 | F59: =F34 -> 108187.21 | G59: =G34 -> 111026.88 | H59: =H34 -> 113919.57 | I59: =I34 -> 116865.5 | ... Q59: =Q34 -> 143161.6
A60: -Dividends Paid to Noncontrolling Interest | B60: =B35 -> 0 | C60: =C35 -> 0 | D60: =D35 -> 0 | E60: =E35 -> 0 | F60: =F35 -> 0 | G60: =G35 -> 0 | H60: =H35 -> 0 | I60: =I35 -> 0 | ... Q60: =Q35 -> 0
A61: -Dividends Paid on Preferred | B61: ='Financial Statements'!C28 -> 0 | C61: ='Financial Statements'!D28 -> 0 | D61: ='Financial Statements'!E28 -> 0 | E61: ='Financial Statements'!F28 -> 0 | F61: ='Financial Statements'!G28 -> 0 | G61: ='Financial Statements'!H28 -> 0 | H61: ='Financial Statements'!I28 -> 0 | I61: ='Financial Statements'!J28 -> 0 | ... Q61: ='Financial Statements'!R28 -> 0
A62: +Increase in Preferred Stock | B62: =B37 -> 0 | C62: =C37 -> 0 | D62: =D37 -> 0 | E62: =E37 -> 0 | F62: =F37 -> 0 | G62: =G37 -> 0 | H62: =H37 -> 0 | I62: =I37 -> 0 | ... Q62: =Q37 -> 0
A63: +/-Clean Surplus Plug (Ignore) | B63: ='Financial Statements'!C65 -> 0 | C63: ='Financial Statements'!D65 -> -65300 | D63: ='Financial Statements'!E65 -> 0 | E63: ='Financial Statements'!F65 -> 0 | F63: ='Financial Statements'!G65 -> 0 | G63: ='Financial Statements'!H65 -> 0 | H63: ='Financial Statements'!I65 -> 0 | I63: ='Financial Statements'!J65 -> 0 | ... Q63: ='Financial Statements'!R65 -> 0
A64: =Free Cash Flow to Common Equity | B64: =SUM(B56:B63) -> -51400 | C64: =SUM(C56:C63) -> 149800 | D64: =SUM(D56:D63) -> 311400 | E64: =SUM(E56:E63) -> 894700 | F64: =SUM(F56:F63) -> 1123621.9 | G64: =SUM(G56:G63) -> 1160280.7 | H64: =SUM(H56:H63) -> 1197941.5 | I64: =SUM(I56:I63) -> 1236624.4 | ... Q64: =SUM(Q56:Q63) -> 1583872.3
A66: Financing Flows:
A67: +Dividends Paid | B67: =-'Financial Statements'!C64 -> 0 | C67: =-'Financial Statements'!D64 -> 0 | D67: =-'Financial Statements'!E64 -> 0 | E67: =-'Financial Statements'!F64 -> 0 | F67: =-'Financial Statements'!G64 -> 0 | G67: =-'Financial Statements'!H64 -> 0 | H67: =-'Financial Statements'!I64 -> 0 | I67: =-'Financial Statements'!J64 -> 0 | ... Q67: =-'Financial Statements'!R64 -> 0
A68: -Net Issuance of Common Stock | B68: =-('Financial Statements'!C55-'Financial Statements'!B55) -> -51400 | C68: =-('Financial Statements'!D55-'Financial Statements'!C55) -> 149800 | D68: =-('Financial Statements'!E55-'Financial Statements'!D55) -> 311400 | E68: =-('Financial Statements'!F55-'Financial Statements'!E55) -> 894700 | F68: =-('Financial Statements'!G55-'Financial Statements'!F55) -> 1123621.9 | G68: =-('Financial Statements'!H55-'Financial Statements'!G55) -> 1160280.7 | H68: =-('Financial Statements'!I55-'Financial Statements'!H55) -> 1197941.5 | I68: =-('Financial Statements'!J55-'Financial Statements'!I55) -> 1236624.4 | ... Q68: =-('Financial Statements'!R55-'Financial Statements'!Q55) -> 1583872.3
A69: = Free Cash Flow to Common Equity | B69: =B67+B68 -> -51400 | C69: =C67+C68 -> 149800 | D69: =D67+D68 -> 311400 | E69: =E67+E68 -> 894700 | F69: =F67+F68 -> 1123621.9 | G69: =G67+G68 -> 1160280.7 | H69: =H67+H68 -> 1197941.5 | I69: =I67+I68 -> 1236624.4 | ... Q69: =Q67+Q68 -> 1583872.3
A72: Free Cash Flow to all Investors
A74: Net Operating Income | B74: ='Financial Statements'!C71 -> -1141146.8 | C74: ='Financial Statements'!D71 -> 949013.93 | D74: ='Financial Statements'!E71 -> 1455511.8 | E74: ='Financial Statements'!F71 -> 1473446.7 | F74: ='Financial Statements'!G71 -> 1520098.2 | G74: ='Financial Statements'!H71 -> 1567974.1 | H74: ='Financial Statements'!I71 -> 1617097.5 | I74: ='Financial Statements'!J71 -> 1667491.1 | ... Q74: ='Financial Statements'!R71 -> 2119492.9
A75: - Increase in Net Operating Assets | B75: =-('Financial Statements'!C75-'Financial Statements'!B75) -> 2952100 | C75: =-('Financial Statements'!D75-'Financial Statements'!C75) -> -118800 | D75: =-('Financial Statements'!E75-'Financial Statements'!D75) -> -484500 | E75: =-('Financial Statements'!F75-'Financial Statements'!E75) -> -624000 | F75: =-('Financial Statements'!G75-'Financial Statements'!F75) -> -352566.21 | G75: =-('Financial Statements'!H75-'Financial Statements'!G75) -> -361820.27 | H75: =-('Financial Statements'!I75-'Financial Statements'!H75) -> -371247.1 | I75: =-('Financial Statements'!J75-'Financial Statements'!I75) -> -380847.47 | ... Q75: =-('Financial Statements'!R75-'Financial Statements'!Q75) -> -466542.58
A76: +/-Clean Surplus Plug (Ignore) | B76: ='Financial Statements'!C65 -> 0 | C76: ='Financial Statements'!D65 -> -65300 | D76: ='Financial Statements'!E65 -> 0 | E76: ='Financial Statements'!F65 -> 0 | F76: ='Financial Statements'!G65 -> 0 | G76: ='Financial Statements'!H65 -> 0 | H76: ='Financial Statements'!I65 -> 0 | I76: ='Financial Statements'!J65 -> 0 | ... Q76: ='Financial Statements'!R65 -> 0
A77: =Free Cash Flow to Investors | B77: =SUM(B74:B76) -> 1810953.2 | C77: =SUM(C74:C76) -> 764913.93 | D77: =SUM(D74:D76) -> 971011.83 | E77: =SUM(E74:E76) -> 849446.69 | F77: =SUM(F74:F76) -> 1167532 | G77: =SUM(G74:G76) -> 1206153.9 | H77: =SUM(H74:H76) -> 1245850.4 | I77: =SUM(I74:I76) -> 1286643.6 | ... Q77: =SUM(Q74:Q76) -> 1652950.3
A79: Computation based on SCF:
A80: Cash From Operations | B80: =B24 -> -1838400 | C80: =C24 -> 6944800 | D80: =D24 -> 2075000 | E80: =E24 -> 746000 | F80: =F24 -> 1558457.3 | G80: =G24 -> 1606529.5 | H80: =H24 -> 1655816.8 | I80: =I24 -> 1706340.3 | ... Q80: =Q24 -> 2159279.7
A81: -Increase in Operating Cash | B81: =-('Financial Statements'!C33-'Financial Statements'!B33) -> 651100 | C81: =-('Financial Statements'!D33-'Financial Statements'!C33) -> -139300 | D81: =-('Financial Statements'!E33-'Financial Statements'!D33) -> -877600 | E81: =-('Financial Statements'!F33-'Financial Statements'!E33) -> 425300 | F81: =-('Financial Statements'!G33-'Financial Statements'!F33) -> -32874.096 | G81: =-('Financial Statements'!H33-'Financial Statements'!G33) -> -33736.966 | H81: =-('Financial Statements'!I33-'Financial Statements'!H33) -> -34615.946 | I81: =-('Financial Statements'!J33-'Financial Statements'!I33) -> -35511.107 | ... Q81: =-('Financial Statements'!R33-'Financial Statements'!Q33) -> -43501.518
A82: +Cash from Investing | B82: =B31 -> 2548600 | C82: =C31 -> -6097300 | D82: =D31 -> -340000 | E82: =E31 -> -467400 | F82: =F31 -> -510148.47 | G82: =G31 -> -523538.71 | H82: =H31 -> -537178.94 | I82: =I31 -> -551070.27 | ... Q82: =Q31 -> -675067.48
A83: +Interest Expense | B83: =-'Financial Statements'!C20 -> 370000 | C83: =-'Financial Statements'!D20 -> 162100 | D83: =-'Financial Statements'!E20 -> 147300 | E83: =-'Financial Statements'!F20 -> 178900 | F83: =-'Financial Statements'!G20 -> 186951.66 | G83: =-'Financial Statements'!H20 -> 192855.05 | H83: =-'Financial Statements'!I20 -> 198912.82 | I83: =-'Financial Statements'!J20 -> 205127.81 | ... Q83: =-'Financial Statements'!R20 -> 260876.13
A84: -Tax Shield on Interest | B84: =-(IF('Financial Statements'!C22=0,0,(-'Financial Statements'!C23)/'Financial Statements'!C22))*B83 -> 79653.17 | C84: =-(IF('Financial Statements'!D22=0,0,(-'Financial Statements'!D23)/'Financial Statements'!D22))*C83 -> -40086.074 | D84: =-(IF('Financial Statements'!E22=0,0,(-'Financial Statements'!E23)/'Financial Statements'!E22))*D83 -> -33688.165 | E84: =-(IF('Financial Statements'!F22=0,0,(-'Financial Statements'!F23)/'Financial Statements'!F22))*E83 -> -33353.308 | F84: =-(IF('Financial Statements'!G22=0,0,(-'Financial Statements'!G23)/'Financial Statements'!G22))*F83 -> -34854.424 | G84: =-(IF('Financial Statements'!H22=0,0,(-'Financial Statements'!H23)/'Financial Statements'!H22))*G83 -> -35955.026 | H84: =-(IF('Financial Statements'!I22=0,0,(-'Financial Statements'!I23)/'Financial Statements'!I22))*H83 -> -37084.407 | I84: =-(IF('Financial Statements'!J22=0,0,(-'Financial Statements'!J23)/'Financial Statements'!J22))*I83 -> -38243.103 | ... Q84: =-(IF('Financial Statements'!R22=0,0,(-'Financial Statements'!R23)/'Financial Statements'!R22))*Q83 -> -48636.567
A85: +/-Clean Surplus Plug (Ignore) | B85: ='Financial Statements'!C65 -> 0 | C85: ='Financial Statements'!D65 -> -65300 | D85: ='Financial Statements'!E65 -> 0 | E85: ='Financial Statements'!F65 -> 0 | F85: ='Financial Statements'!G65 -> 0 | G85: ='Financial Statements'!H65 -> 0 | H85: ='Financial Statements'!I65 -> 0 | I85: ='Financial Statements'!J65 -> 0 | ... Q85: ='Financial Statements'!R65 -> 0
A86: =Free Cash Flow to Investors | B86: =SUM(B80:B85) -> 1810953.2 | C86: =SUM(C80:C85) -> 764913.93 | D86: =SUM(D80:D85) -> 971011.83 | E86: =SUM(E80:E85) -> 849446.69 | F86: =SUM(F80:F85) -> 1167532 | G86: =SUM(G80:G85) -> 1206153.9 | H86: =SUM(H80:H85) -> 1245850.4 | I86: =SUM(I80:I85) -> 1286643.6 | ... Q86: =SUM(Q80:Q85) -> 1652950.3
A88: Financing Flows:
A89: +Dividends on Common Stock | B89: =-'Financial Statements'!C64 -> 0 | C89: =-'Financial Statements'!D64 -> 0 | D89: =-'Financial Statements'!E64 -> 0 | E89: =-'Financial Statements'!F64 -> 0 | F89: =-'Financial Statements'!G64 -> 0 | G89: =-'Financial Statements'!H64 -> 0 | H89: =-'Financial Statements'!I64 -> 0 | I89: =-'Financial Statements'!J64 -> 0 | ... Q89: =-'Financial Statements'!R64 -> 0
A90: +Interest Expense | B90: =-'Financial Statements'!C20 -> 370000 | C90: =-'Financial Statements'!D20 -> 162100 | D90: =-'Financial Statements'!E20 -> 147300 | E90: =-'Financial Statements'!F20 -> 178900 | F90: =-'Financial Statements'!G20 -> 186951.66 | G90: =-'Financial Statements'!H20 -> 192855.05 | H90: =-'Financial Statements'!I20 -> 198912.82 | I90: =-'Financial Statements'!J20 -> 205127.81 | ... Q90: =-'Financial Statements'!R20 -> 260876.13
A91: -Tax Shield on Interest | B91: =-(IF('Financial Statements'!C22=0,0,(-'Financial Statements'!C23)/'Financial Statements'!C22))*B90 -> 79653.17 | C91: =-(IF('Financial Statements'!D22=0,0,(-'Financial Statements'!D23)/'Financial Statements'!D22))*C90 -> -40086.074 | D91: =-(IF('Financial Statements'!E22=0,0,(-'Financial Statements'!E23)/'Financial Statements'!E22))*D90 -> -33688.165 | E91: =-(IF('Financial Statements'!F22=0,0,(-'Financial Statements'!F23)/'Financial Statements'!F22))*E90 -> -33353.308 | F91: =-(IF('Financial Statements'!G22=0,0,(-'Financial Statements'!G23)/'Financial Statements'!G22))*F90 -> -34854.424 | G91: =-(IF('Financial Statements'!H22=0,0,(-'Financial Statements'!H23)/'Financial Statements'!H22))*G90 -> -35955.026 | H91: =-(IF('Financial Statements'!I22=0,0,(-'Financial Statements'!I23)/'Financial Statements'!I22))*H90 -> -37084.407 | I91: =-(IF('Financial Statements'!J22=0,0,(-'Financial Statements'!J23)/'Financial Statements'!J22))*I90 -> -38243.103 | ... Q91: =-(IF('Financial Statements'!R22=0,0,(-'Financial Statements'!R23)/'Financial Statements'!R22))*Q90 -> -48636.567
A92: +Dividends on Preferred Stock | B92: =-'Financial Statements'!C28 -> 0 | C92: =-'Financial Statements'!D28 -> 0 | D92: =-'Financial Statements'!E28 -> 0 | E92: =-'Financial Statements'!F28 -> 0 | F92: =-'Financial Statements'!G28 -> 0 | G92: =-'Financial Statements'!H28 -> 0 | H92: =-'Financial Statements'!I28 -> 0 | I92: =-'Financial Statements'!J28 -> 0 | ... Q92: =-'Financial Statements'!R28 -> 0
A93: +Dividends Paid to Noncontrolling Interest | B93: =-'Financial Statements'!C27-('Financial Statements'!C53-'Financial Statements'!B53) -> 0 | C93: =-'Financial Statements'!D27-('Financial Statements'!D53-'Financial Statements'!C53) -> 0 | D93: =-'Financial Statements'!E27-('Financial Statements'!E53-'Financial Statements'!D53) -> 0 | E93: =-'Financial Statements'!F27-('Financial Statements'!F53-'Financial Statements'!E53) -> 0 | F93: =-'Financial Statements'!G27-('Financial Statements'!G53-'Financial Statements'!F53) -> 0 | G93: =-'Financial Statements'!H27-('Financial Statements'!H53-'Financial Statements'!G53) -> 0 | H93: =-'Financial Statements'!I27-('Financial Statements'!I53-'Financial Statements'!H53) -> 0 | I93: =-'Financial Statements'!J27-('Financial Statements'!J53-'Financial Statements'!I53) -> 0 | ... Q93: =-'Financial Statements'!R27-('Financial Statements'!R53-'Financial Statements'!Q53) -> 0
A94: -Net Issuance of Common Stock | B94: =-('Financial Statements'!C55-'Financial Statements'!B55) -> -51400 | C94: =-('Financial Statements'!D55-'Financial Statements'!C55) -> 149800 | D94: =-('Financial Statements'!E55-'Financial Statements'!D55) -> 311400 | E94: =-('Financial Statements'!F55-'Financial Statements'!E55) -> 894700 | F94: =-('Financial Statements'!G55-'Financial Statements'!F55) -> 1123621.9 | G94: =-('Financial Statements'!H55-'Financial Statements'!G55) -> 1160280.7 | H94: =-('Financial Statements'!I55-'Financial Statements'!H55) -> 1197941.5 | I94: =-('Financial Statements'!J55-'Financial Statements'!I55) -> 1236624.4 | ... Q94: =-('Financial Statements'!R55-'Financial Statements'!Q55) -> 1583872.3
A95: -Net Issuance of Debt | B95: =-('Financial Statements'!C44+'Financial Statements'!C49-'Financial Statements'!B49-'Financial Statements'!B44) -> 1412700 | C95: =-('Financial Statements'!D44+'Financial Statements'!D49-'Financial Statements'!C49-'Financial Statements'!C44) -> 493100 | D95: =-('Financial Statements'!E44+'Financial Statements'!E49-'Financial Statements'!D49-'Financial Statements'!D44) -> 546000 | E95: =-('Financial Statements'!F44+'Financial Statements'!F49-'Financial Statements'!E49-'Financial Statements'!E44) -> -190800 | F95: =-('Financial Statements'!G44+'Financial Statements'!G49-'Financial Statements'!F49-'Financial Statements'!F44) -> -108187.21 | G95: =-('Financial Statements'!H44+'Financial Statements'!H49-'Financial Statements'!G49-'Financial Statements'!G44) -> -111026.88 | H95: =-('Financial Statements'!I44+'Financial Statements'!I49-'Financial Statements'!H49-'Financial Statements'!H44) -> -113919.57 | I95: =-('Financial Statements'!J44+'Financial Statements'!J49-'Financial Statements'!I49-'Financial Statements'!I44) -> -116865.5 | ... Q95: =-('Financial Statements'!R44+'Financial Statements'!R49-'Financial Statements'!Q49-'Financial Statements'!Q44) -> -143161.6
A96: -Net Issuance of Preferred Stock | B96: =-('Financial Statements'!C54-'Financial Statements'!B54) -> 0 | C96: =-('Financial Statements'!D54-'Financial Statements'!C54) -> 0 | D96: =-('Financial Statements'!E54-'Financial Statements'!D54) -> 0 | E96: =-('Financial Statements'!F54-'Financial Statements'!E54) -> 0 | F96: =-('Financial Statements'!G54-'Financial Statements'!F54) -> 0 | G96: =-('Financial Statements'!H54-'Financial Statements'!G54) -> 0 | H96: =-('Financial Statements'!I54-'Financial Statements'!H54) -> 0 | I96: =-('Financial Statements'!J54-'Financial Statements'!I54) -> 0 | ... Q96: =-('Financial Statements'!R54-'Financial Statements'!Q54) -> 0
A97: =Free Cash Flow to Investors | B97: =SUM(B89:B96) -> 1810953.2 | C97: =SUM(C89:C96) -> 764913.93 | D97: =SUM(D89:D96) -> 971011.83 | E97: =SUM(E89:E96) -> 849446.69 | F97: =SUM(F89:F96) -> 1167532 | G97: =SUM(G89:G96) -> 1206153.9 | H97: =SUM(H89:H96) -> 1245850.4 | I97: =SUM(I89:I96) -> 1286643.6 | ... Q97: =SUM(Q89:Q96) -> 1652950.3
A99: Traditional Computation of FCF:
A100: EBIT | B100: ='Financial Statements'!C19 -> -939500 | C100: ='Financial Statements'!D19 -> 1262200 | D100: ='Financial Statements'!E19 -> 1887900 | E100: ='Financial Statements'!F19 -> 1811400 | F100: ='Financial Statements'!G19 -> 1868751.6 | G100: ='Financial Statements'!H19 -> 1927608.5 | H100: ='Financial Statements'!I19 -> 1987998.9 | I100: ='Financial Statements'!J19 -> 2049950.9 | ... Q100: ='Financial Statements'!R19 -> 2605624.9
A101: -Taxes on EBIT | B101: ='Financial Statements'!C23+(IF('Financial Statements'!C22=0,0,(-'Financial Statements'!C23)/'Financial Statements'!C22))*'Financial Statements'!C20 -> -202146.83 | C101: ='Financial Statements'!D23+(IF('Financial Statements'!D22=0,0,(-'Financial Statements'!D23)/'Financial Statements'!D22))*'Financial Statements'!D20 -> -311786.07 | D101: ='Financial Statements'!E23+(IF('Financial Statements'!E22=0,0,(-'Financial Statements'!E23)/'Financial Statements'!E22))*'Financial Statements'!E20 -> -431588.17 | E101: ='Financial Statements'!F23+(IF('Financial Statements'!F22=0,0,(-'Financial Statements'!F23)/'Financial Statements'!F22))*'Financial Statements'!F20 -> -337653.31 | F101: ='Financial Statements'!G23+(IF('Financial Statements'!G22=0,0,(-'Financial Statements'!G23)/'Financial Statements'!G22))*'Financial Statements'!G20 -> -348343.91 | G101: ='Financial Statements'!H23+(IF('Financial Statements'!H22=0,0,(-'Financial Statements'!H23)/'Financial Statements'!H22))*'Financial Statements'!H20 -> -359315.11 | H101: ='Financial Statements'!I23+(IF('Financial Statements'!I22=0,0,(-'Financial Statements'!I23)/'Financial Statements'!I22))*'Financial Statements'!I20 -> -370572.15 | I101: ='Financial Statements'!J23+(IF('Financial Statements'!J22=0,0,(-'Financial Statements'!J23)/'Financial Statements'!J22))*'Financial Statements'!J20 -> -382120.3 | ... Q101: ='Financial Statements'!R23+(IF('Financial Statements'!R22=0,0,(-'Financial Statements'!R23)/'Financial Statements'!R22))*'Financial Statements'!R20 -> -485700.49
A102: +Increase in Deferred Taxes | B102: ='Financial Statements'!C51-'Financial Statements'!B51 -> -12000 | C102: ='Financial Statements'!D51-'Financial Statements'!C51 -> 11500 | D102: ='Financial Statements'!E51-'Financial Statements'!D51 -> 28800 | E102: ='Financial Statements'!F51-'Financial Statements'!E51 -> -26300 | F102: ='Financial Statements'!G51-'Financial Statements'!F51 -> 31256.195 | G102: ='Financial Statements'!H51-'Financial Statements'!G51 -> 32076.599 | H102: ='Financial Statements'!I51-'Financial Statements'!H51 -> 32912.32 | I102: ='Financial Statements'!J51-'Financial Statements'!I51 -> 33763.425 | ... Q102: ='Financial Statements'!R51-'Financial Statements'!Q51 -> 41360.589
A103: = NOPLAT | B103: =SUM(B100:B102) -> -1153646.8 | C103: =SUM(C100:C102) -> 961913.93 | D103: =SUM(D100:D102) -> 1485111.8 | E103: =SUM(E100:E102) -> 1447446.7 | F103: =SUM(F100:F102) -> 1551663.9 | G103: =SUM(G100:G102) -> 1600370 | H103: =SUM(H100:H102) -> 1650339 | I103: =SUM(I100:I102) -> 1701594 | ... Q103: =SUM(Q100:Q102) -> 2161285
A104: +Depreciation & Amortization | B104: =-'Financial Statements'!C18 -> 0 | C104: =-'Financial Statements'!D18 -> 0 | D104: =-'Financial Statements'!E18 -> 0 | E104: =-'Financial Statements'!F18 -> 0 | F104: =-'Financial Statements'!G18 -> 0 | G104: =-'Financial Statements'!H18 -> 0 | H104: =-'Financial Statements'!I18 -> 0 | I104: =-'Financial Statements'!J18 -> 0 | ... Q104: =-'Financial Statements'!R18 -> 0
A105: +Non-Operating Income (Loss) | B105: ='Financial Statements'!C21 -> 500 | C105: ='Financial Statements'!D21 -> -1400 | D105: ='Financial Statements'!E21 -> -800 | E105: ='Financial Statements'!F21 -> -300 | F105: ='Financial Statements'!G21 -> -309.49844 | G105: ='Financial Statements'!H21 -> -319.24619 | H105: ='Financial Statements'!I21 -> -329.24791 | I105: ='Financial Statements'!J21 -> -339.50827 | ... Q105: ='Financial Statements'!R21 -> -431.53774
A106: +Other Income (Loss) | B106: ='Financial Statements'!C24 -> 0 | C106: ='Financial Statements'!D24 -> 0 | D106: ='Financial Statements'!E24 -> 0 | E106: ='Financial Statements'!F24 -> 0 | F106: ='Financial Statements'!G24 -> 0 | G106: ='Financial Statements'!H24 -> 0 | H106: ='Financial Statements'!I24 -> 0 | I106: ='Financial Statements'!J24 -> 0 | ... Q106: ='Financial Statements'!R24 -> 0
A107: +Ext. Items & Disc. Ops. | B107: ='Financial Statements'!C26 -> 0 | C107: ='Financial Statements'!D26 -> 0 | D107: ='Financial Statements'!E26 -> 0 | E107: ='Financial Statements'!F26 -> 0 | F107: ='Financial Statements'!G26 -> 0 | G107: ='Financial Statements'!H26 -> 0 | H107: ='Financial Statements'!I26 -> 0 | I107: ='Financial Statements'!J26 -> 0 | ... Q107: ='Financial Statements'!R26 -> 0
A108: =Gross Cash Flow | B108: =SUM(B103:B107) -> -1153146.8 | C108: =SUM(C103:C107) -> 960513.93 | D108: =SUM(D103:D107) -> 1484311.8 | E108: =SUM(E103:E107) -> 1447146.7 | F108: =SUM(F103:F107) -> 1551354.4 | G108: =SUM(G103:G107) -> 1600050.7 | H108: =SUM(H103:H107) -> 1650009.8 | I108: =SUM(I103:I107) -> 1701254.5 | ... Q108: =SUM(Q103:Q107) -> 2160853.5
A109: -Increase in Working Capital | B109: =-('Financial Statements'!C37-'Financial Statements'!B37)+('Financial Statements'!C48-'Financial Statements'!C44-'Financial Statements'!B48+'Financial Statements'!B44) -> 435500 | C109: =-('Financial Statements'!D37-'Financial Statements'!C37)+('Financial Statements'!D48-'Financial Statements'!D44-'Financial Statements'!C48+'Financial Statements'!C44) -> 1224700 | D109: =-('Financial Statements'!E37-'Financial Statements'!D37)+('Financial Statements'!E48-'Financial Statements'!E44-'Financial Statements'!D48+'Financial Statements'!D44) -> -347600 | E109: =-('Financial Statements'!F37-'Financial Statements'!E37)+('Financial Statements'!F48-'Financial Statements'!F44-'Financial Statements'!E48+'Financial Statements'!E44) -> -112100 | F109: =-('Financial Statements'!G37-'Financial Statements'!F37)+('Financial Statements'!G48-'Financial Statements'!G44-'Financial Statements'!F48+'Financial Statements'!F44) -> -45358.21 | G109: =-('Financial Statements'!H37-'Financial Statements'!G37)+('Financial Statements'!H48-'Financial Statements'!H44-'Financial Statements'!G48+'Financial Statements'!G44) -> -46548.76 | H109: =-('Financial Statements'!I37-'Financial Statements'!H37)+('Financial Statements'!I48-'Financial Statements'!I44-'Financial Statements'!H48+'Financial Statements'!H44) -> -47761.537 | I109: =-('Financial Statements'!J37-'Financial Statements'!I37)+('Financial Statements'!J48-'Financial Statements'!J44-'Financial Statements'!I48+'Financial Statements'!I44) -> -48996.64 | ... Q109: =-('Financial Statements'!R37-'Financial Statements'!Q37)+('Financial Statements'!R48-'Financial Statements'!R44-'Financial Statements'!Q48+'Financial Statements'!Q44) -> -60021.454
A110: -Capital Expenditures | B110: =-('Financial Statements'!C38-'Financial Statements'!B38-'Financial Statements'!C18) -> -244600 | C110: =-('Financial Statements'!D38-'Financial Statements'!C38-'Financial Statements'!D18) -> -436500 | D110: =-('Financial Statements'!E38-'Financial Statements'!D38-'Financial Statements'!E18) -> -234500 | E110: =-('Financial Statements'!F38-'Financial Statements'!E38-'Financial Statements'!F18) -> -361000 | F110: =-('Financial Statements'!G38-'Financial Statements'!F38-'Financial Statements'!G18) -> -141757.86 | G110: =-('Financial Statements'!H38-'Financial Statements'!G38-'Financial Statements'!H18) -> -145478.69 | H110: =-('Financial Statements'!I38-'Financial Statements'!H38-'Financial Statements'!I18) -> -149268.97 | I110: =-('Financial Statements'!J38-'Financial Statements'!I38-'Financial Statements'!J18) -> -153129.04 | ... Q110: =-('Financial Statements'!R38-'Financial Statements'!Q38-'Financial Statements'!R18) -> -187584.85
A111: -Increase in Investments | B111: =-('Financial Statements'!C39-'Financial Statements'!B39) -> 0 | C111: =-('Financial Statements'!D39-'Financial Statements'!C39) -> 0 | D111: =-('Financial Statements'!E39-'Financial Statements'!D39) -> 0 | E111: =-('Financial Statements'!F39-'Financial Statements'!E39) -> 0 | F111: =-('Financial Statements'!G39-'Financial Statements'!F39) -> 0 | G111: =-('Financial Statements'!H39-'Financial Statements'!G39) -> 0 | H111: =-('Financial Statements'!I39-'Financial Statements'!H39) -> 0 | I111: =-('Financial Statements'!J39-'Financial Statements'!I39) -> 0 | ... Q111: =-('Financial Statements'!R39-'Financial Statements'!Q39) -> 0
A112: -Purchases of Intangibles | B112: =-('Financial Statements'!C40-'Financial Statements'!B40) -> -660100 | C112: =-('Financial Statements'!D40-'Financial Statements'!C40) -> 602000 | D112: =-('Financial Statements'!E40-'Financial Statements'!D40) -> -1100 | E112: =-('Financial Statements'!F40-'Financial Statements'!E40) -> 0 | F112: =-('Financial Statements'!G40-'Financial Statements'!F40) -> -160979.54 | G112: =-('Financial Statements'!H40-'Financial Statements'!G40) -> -165204.88 | H112: =-('Financial Statements'!I40-'Financial Statements'!H40) -> -169509.12 | I112: =-('Financial Statements'!J40-'Financial Statements'!I40) -> -173892.58 | ... Q112: =-('Financial Statements'!R40-'Financial Statements'!Q40) -> -213020.44
A113: -Increase in Other Assets | B113: =-('Financial Statements'!C41-'Financial Statements'!B41) -> 3453300 | C113: =-('Financial Statements'!D41-'Financial Statements'!C41) -> -6262800 | D113: =-('Financial Statements'!E41-'Financial Statements'!D41) -> -104400 | E113: =-('Financial Statements'!F41-'Financial Statements'!E41) -> -106400 | F113: =-('Financial Statements'!G41-'Financial Statements'!F41) -> -207411.07 | G113: =-('Financial Statements'!H41-'Financial Statements'!G41) -> -212855.14 | H113: =-('Financial Statements'!I41-'Financial Statements'!H41) -> -218400.85 | I113: =-('Financial Statements'!J41-'Financial Statements'!I41) -> -224048.65 | ... Q113: =-('Financial Statements'!R41-'Financial Statements'!Q41) -> -274462.2
A114: +Increase in Other Liabilities | B114: =('Financial Statements'!C50-'Financial Statements'!B50) -> -20000 | C114: =('Financial Statements'!D50-'Financial Statements'!C50) -> 4742300 | D114: =('Financial Statements'!E50-'Financial Statements'!D50) -> 174300 | E114: =('Financial Statements'!F50-'Financial Statements'!E50) -> -18200 | F114: =('Financial Statements'!G50-'Financial Statements'!F50) -> 171684.28 | G114: =('Financial Statements'!H50-'Financial Statements'!G50) -> 176190.6 | H114: =('Financial Statements'!I50-'Financial Statements'!H50) -> 180781.05 | I114: =('Financial Statements'!J50-'Financial Statements'!I50) -> 185456.01 | ... Q114: =('Financial Statements'!R50-'Financial Statements'!Q50) -> 227185.77
A115: +/-Clean Surplus Plug (Ignore) | B115: ='Financial Statements'!C65 -> 0 | C115: ='Financial Statements'!D65 -> -65300 | D115: ='Financial Statements'!E65 -> 0 | E115: ='Financial Statements'!F65 -> 0 | F115: ='Financial Statements'!G65 -> 0 | G115: ='Financial Statements'!H65 -> 0 | H115: ='Financial Statements'!I65 -> 0 | I115: ='Financial Statements'!J65 -> 0 | ... Q115: ='Financial Statements'!R65 -> 0
A116: =Free Cash Flow to Investors | B116: =SUM(B108:B115) -> 1810953.2 | C116: =SUM(C108:C115) -> 764913.93 | D116: =SUM(D108:D115) -> 971011.83 | E116: =SUM(E108:E115) -> 849446.69 | F116: =SUM(F108:F115) -> 1167532 | G116: =SUM(G108:G115) -> 1206153.9 | H116: =SUM(H108:H115) -> 1245850.4 | I116: =SUM(I108:I115) -> 1286643.6 | ... Q116: =SUM(Q108:Q115) -> 1652950.3
A118: Analysis of Earnings Quality
A119: (Red Shading = Quality Flag)
...

Sheet Credit Analysis
A1: Credit Analysis
A4: Company Name | B4: ='Financial Statements'!B4 -> DOLLAR TREE 2021
B6: Actual | C6: Actual | D6: Actual | E6: Actual | F6: Actual | G6: Forecast | H6: Forecast | I6: Forecast | J6: Forecast | K6: Forecast | L6: Forecast | M6: Forecast | N6: Forecast | O6: Forecast | P6: Forecast | Q6: Forecast | R6: Forecast
A7: Fiscal Year End Date | B7: ='Financial Statements'!B8 -> 41669 | C7: ='Financial Statements'!C8 -> 42034 | D7: ='Financial Statements'!D8 -> 42399 | E7: ='Financial Statements'!E8 -> 42765 | F7: ='Financial Statements'!F8 -> 43130 | G7: ='Financial Statements'!G8 -> 43495 | H7: ='Financial Statements'!H8 -> 43860 | I7: ='Financial Statements'!I8 -> 44226 | ... R7: ='Financial Statements'!R8 -> 47513
A9: Analysis of Leverage
A10: - Long-Term Capital Structure
A11: Debt to Equity Ratio | B11: =('Financial Statements'!B44+'Financial Statements'!B49)/('Financial Statements'!B57) -> 0.79055456 | C11: =('Financial Statements'!C44+'Financial Statements'!C49)/('Financial Statements'!C57) -> 0.75587021 | D11: =('Financial Statements'!D44+'Financial Statements'!D49)/('Financial Statements'!D57) -> 0.60308883 | E11: =('Financial Statements'!E44+'Financial Statements'!E49)/('Financial Statements'!E57) -> 0.44283695 | F11: =('Financial Statements'!F44+'Financial Statements'!F49)/('Financial Statements'!F57) -> 0.4427026 | G11: =('Financial Statements'!G44+'Financial Statements'!G49)/('Financial Statements'!G57) -> 0.4427026 | H11: =('Financial Statements'!H44+'Financial Statements'!H49)/('Financial Statements'!H57) -> 0.4427026 | I11: =('Financial Statements'!I44+'Financial Statements'!I49)/('Financial Statements'!I57) -> 0.4427026 | ... R11: =('Financial Statements'!R44+'Financial Statements'!R49)/('Financial Statements'!R57) -> 0.4427026
A12: FFO to Total Debt | C12: ='Cash Flow Analysis'!B17/(('Financial Statements'!C44+'Financial Statements'!C49+'Financial Statements'!B44+'Financial Statements'!B49)/2) -> -0.32641075 | D12: ='Cash Flow Analysis'!C17/(('Financial Statements'!D44+'Financial Statements'!D49+'Financial Statements'!C44+'Financial Statements'!C49)/2) -> 1.3886905 | E12: ='Cash Flow Analysis'!D17/(('Financial Statements'!E44+'Financial Statements'!E49+'Financial Statements'!D44+'Financial Statements'!D49)/2) -> 0.44152949 | F12: ='Cash Flow Analysis'!E17/(('Financial Statements'!F44+'Financial Statements'!F49+'Financial Statements'!E44+'Financial Statements'!E49)/2) -> 0.38638006 | G12: ='Cash Flow Analysis'!F17/(('Financial Statements'!G44+'Financial Statements'!G49+'Financial Statements'!F44+'Financial Statements'!F49)/2) -> 0.45257823 | H12: ='Cash Flow Analysis'!G17/(('Financial Statements'!H44+'Financial Statements'!H49+'Financial Statements'!G44+'Financial Statements'!G49)/2) -> 0.45224146 | I12: ='Cash Flow Analysis'!H17/(('Financial Statements'!I44+'Financial Statements'!I49+'Financial Statements'!H44+'Financial Statements'!H49)/2) -> 0.45190464 | J12: ='Cash Flow Analysis'!I17/(('Financial Statements'!J44+'Financial Statements'!J49+'Financial Statements'!I44+'Financial Statements'!I49)/2) -> 0.45156777 | ... R12: ='Cash Flow Analysis'!Q17/(('Financial Statements'!R44+'Financial Statements'!R49+'Financial Statements'!Q44+'Financial Statements'!Q49)/2) -> 0.4492081
A13: CFO to Total Debt | C13: ='Cash Flow Analysis'!B24/(('Financial Statements'!C44+'Financial Statements'!C49+'Financial Statements'!B44+'Financial Statements'!B49)/2) -> -0.36977663 | D13: ='Cash Flow Analysis'!C24/(('Financial Statements'!D44+'Financial Statements'!D49+'Financial Statements'!C44+'Financial Statements'!C49)/2) -> 1.7280995 | E13: ='Cash Flow Analysis'!D24/(('Financial Statements'!E44+'Financial Statements'!E49+'Financial Statements'!D44+'Financial Statements'!D49)/2) -> 0.59299268 | F13: ='Cash Flow Analysis'!E24/(('Financial Statements'!F44+'Financial Statements'!F49+'Financial Statements'!E44+'Financial Statements'!E49)/2) -> 0.22459056 | G13: ='Cash Flow Analysis'!F24/(('Financial Statements'!G44+'Financial Statements'!G49+'Financial Statements'!F44+'Financial Statements'!F49)/2) -> 0.44898164 | H13: ='Cash Flow Analysis'!G24/(('Financial Statements'!H44+'Financial Statements'!H49+'Financial Statements'!G44+'Financial Statements'!G49)/2) -> 0.44866345 | I13: ='Cash Flow Analysis'!H24/(('Financial Statements'!I44+'Financial Statements'!I49+'Financial Statements'!H44+'Financial Statements'!H49)/2) -> 0.44834522 | J13: ='Cash Flow Analysis'!I24/(('Financial Statements'!J44+'Financial Statements'!J49+'Financial Statements'!I44+'Financial Statements'!I49)/2) -> 0.44802693 | ... R13: ='Cash Flow Analysis'!Q24/(('Financial Statements'!R44+'Financial Statements'!R49+'Financial Statements'!Q44+'Financial Statements'!Q49)/2) -> 0.44579745
A15: Analysis of Leverage
A16: - Short-Term Liquidity
A17: Current Ratio | B17: ='Financial Statements'!B37/'Financial Statements'!B48 -> 1.6006086 | C17: ='Financial Statements'!C37/'Financial Statements'!C48 -> 2.0486234 | D17: ='Financial Statements'!D37/'Financial Statements'!D48 -> 1.2038348 | E17: ='Financial Statements'!E37/'Financial Statements'!E48 -> 1.353993 | F17: ='Financial Statements'!F37/'Financial Statements'!F48 -> 1.3430063 | G17: ='Financial Statements'!G37/'Financial Statements'!G48 -> 1.3430063 | H17: ='Financial Statements'!H37/'Financial Statements'!H48 -> 1.3430063 | I17: ='Financial Statements'!I37/'Financial Statements'!I48 -> 1.3430063 | ... R17: ='Financial Statements'!R37/'Financial Statements'!R48 -> 1.3430063
A18: Quick Ratio | B18: =('Financial Statements'!B33+'Financial Statements'!B34)/'Financial Statements'!B48 -> 0.38396698 | C18: =('Financial Statements'!C33+'Financial Statements'!C34)/'Financial Statements'!C48 -> 0.26129694 | D18: =('Financial Statements'!D33+'Financial Statements'!D34)/'Financial Statements'!D48 -> 0.16523333 | E18: =('Financial Statements'!E33+'Financial Statements'!E34)/'Financial Statements'!E48 -> 0.3923545 | F18: =('Financial Statements'!F33+'Financial Statements'!F34)/'Financial Statements'!F48 -> 0.24859934 | G18: =('Financial Statements'!G33+'Financial Statements'!G34)/'Financial Statements'!G48 -> 0.24859934 | H18: =('Financial Statements'!H33+'Financial Statements'!H34)/'Financial Statements'!H48 -> 0.24859934 | I18: =('Financial Statements'!I33+'Financial Statements'!I34)/'Financial Statements'!I48 -> 0.24859934 | ... R18: =('Financial Statements'!R33+'Financial Statements'!R34)/'Financial Statements'!R48 -> 0.24859934
A19: EBIT Interest Coverage | B19: =-'Financial Statements'!B19/'Financial Statements'!B20 -> 6.6239231 | C19: =-'Financial Statements'!C19/'Financial Statements'!C20 -> -2.5391892 | D19: =-'Financial Statements'!D19/'Financial Statements'!D20 -> 7.7865515 | E19: =-'Financial Statements'!E19/'Financial Statements'!E20 -> 12.816701 | F19: =-'Financial Statements'!F19/'Financial Statements'!F20 -> 10.12521 | G19: =-'Financial Statements'!G19/'Financial Statements'!G20 -> 9.9959077 | H19: =-'Financial Statements'!H19/'Financial Statements'!H20 -> 9.9951153 | I19: =-'Financial Statements'!I19/'Financial Statements'!I20 -> 9.9943227 | ... R19: =-'Financial Statements'!R19/'Financial Statements'!R20 -> 9.9879776
A20: EBITDA Interest Coverage | B20: =-'Financial Statements'!B17/'Financial Statements'!B20 -> 6.853214 | C20: =-'Financial Statements'!C17/'Financial Statements'!C20 -> -2.5391892 | D20: =-'Financial Statements'!D17/'Financial Statements'!D20 -> 7.7865515 | E20: =-'Financial Statements'!E17/'Financial Statements'!E20 -> 12.816701 | F20: =-'Financial Statements'!F17/'Financial Statements'!F20 -> 10.12521 | G20: =-'Financial Statements'!G17/'Financial Statements'!G20 -> 9.9959077 | H20: =-'Financial Statements'!H17/'Financial Statements'!H20 -> 9.9951153 | I20: =-'Financial Statements'!I17/'Financial Statements'!I20 -> 9.9943227 | ... R20: =-'Financial Statements'!R17/'Financial Statements'!R20 -> 9.9879776
A22: Analysis of Credit Risk
A23: Net Income to Total Assets | B23: ='Financial Statements'!B25/'Financial Statements'!B42 -> 0.10496057 | C23: ='Financial Statements'!C25/'Financial Statements'!C42 -> -0.11782656 | D23: ='Financial Statements'!D25/'Financial Statements'!D42 -> 0.042248628 | E23: ='Financial Statements'!E25/'Financial Statements'!E42 -> 0.064838616 | F23: ='Financial Statements'!F25/'Financial Statements'!F42 -> 0.061132135 | G23: ='Financial Statements'!G25/'Financial Statements'!G42 -> 0.06104546 | H23: ='Financial Statements'!H25/'Financial Statements'!H42 -> 0.061044922 | I23: ='Financial Statements'!I25/'Financial Statements'!I42 -> 0.061044384 | ... R23: ='Financial Statements'!R25/'Financial Statements'!R42 -> 0.061040072
A24: implied default probability | B24: =IF(B23<$C44,$B45,HLOOKUP(B23,$C44:$K45,2,TRUE)) -> 0.02 | C24: =IF(C23<$C44,$B45,HLOOKUP(C23,$C44:$K45,2,TRUE)) -> 0.072 | D24: =IF(D23<$C44,$B45,HLOOKUP(D23,$C44:$K45,2,TRUE)) -> 0.025 | E24: =IF(E23<$C44,$B45,HLOOKUP(E23,$C44:$K45,2,TRUE)) -> 0.02 | F24: =IF(F23<$C44,$B45,HLOOKUP(F23,$C44:$K45,2,TRUE)) -> 0.02 | G24: =IF(G23<$C44,$B45,HLOOKUP(G23,$C44:$K45,2,TRUE)) -> 0.02 | H24: =IF(H23<$C44,$B45,HLOOKUP(H23,$C44:$K45,2,TRUE)) -> 0.02 | I24: =IF(I23<$C44,$B45,HLOOKUP(I23,$C44:$K45,2,TRUE)) -> 0.02 | ... R24: =IF(R23<$C44,$B45,HLOOKUP(R23,$C44:$K45,2,TRUE)) -> 0.02
A25: Total Liabilities to Total Assets | B25: ='Financial Statements'!B52/'Financial Statements'!B42 -> 0.56025299 | C25: ='Financial Statements'!C52/'Financial Statements'!C42 -> 0.58204456 | D25: ='Financial Statements'!D52/'Financial Statements'!D42 -> 0.68046346 | E25: ='Financial Statements'!E52/'Financial Statements'!E42 -> 0.64798512 | F25: ='Financial Statements'!F52/'Financial Statements'!F42 -> 0.64466573 | G25: ='Financial Statements'!G52/'Financial Statements'!G42 -> 0.64466573 | H25: ='Financial Statements'!H52/'Financial Statements'!H42 -> 0.64466573 | I25: ='Financial Statements'!I52/'Financial Statements'!I42 -> 0.64466573 | ... R25: ='Financial Statements'!R52/'Financial Statements'!R42 -> 0.64466573
A26: implied default probability | B26: =IF(B25<$C46,$B47,HLOOKUP(B25,$C46:$K47,2,TRUE)) -> 0.045 | C26: =IF(C25<$C46,$B47,HLOOKUP(C25,$C46:$K47,2,TRUE)) -> 0.045 | D26: =IF(D25<$C46,$B47,HLOOKUP(D25,$C46:$K47,2,TRUE)) -> 0.055 | E26: =IF(E25<$C46,$B47,HLOOKUP(E25,$C46:$K47,2,TRUE)) -> 0.055 | F26: =IF(F25<$C46,$B47,HLOOKUP(F25,$C46:$K47,2,TRUE)) -> 0.055 | G26: =IF(G25<$C46,$B47,HLOOKUP(G25,$C46:$K47,2,TRUE)) -> 0.055 | H26: =IF(H25<$C46,$B47,HLOOKUP(H25,$C46:$K47,2,TRUE)) -> 0.055 | I26: =IF(I25<$C46,$B47,HLOOKUP(I25,$C46:$K47,2,TRUE)) -> 0.055 | ... R26: =IF(R25<$C46,$B47,HLOOKUP(R25,$C46:$K47,2,TRUE)) -> 0.055
A27: Quick Ratio | B27: =B18 -> 0.38396698 | C27: =C18 -> 0.26129694 | D27: =D18 -> 0.16523333 | E27: =E18 -> 0.3923545 | F27: =F18 -> 0.24859934 | G27: =G18 -> 0.24859934 | H27: =H18 -> 0.24859934 | I27: =I18 -> 0.24859934 | ... R27: =R18 -> 0.24859934
A28: implied default probability | B28: =IF(B27<$C48,$B49,HLOOKUP(B27,$C48:$K49,2,TRUE)) -> 0.065 | C28: =IF(C27<$C48,$B49,HLOOKUP(C27,$C48:$K49,2,TRUE)) -> 0.09 | D28: =IF(D27<$C48,$B49,HLOOKUP(D27,$C48:$K49,2,TRUE)) -> 0.09 | E28: =IF(E27<$C48,$B49,HLOOKUP(E27,$C48:$K49,2,TRUE)) -> 0.065 | F28: =IF(F27<$C48,$B49,HLOOKUP(F27,$C48:$K49,2,TRUE)) -> 0.09 | G28: =IF(G27<$C48,$B49,HLOOKUP(G27,$C48:$K49,2,TRUE)) -> 0.09 | H28: =IF(H27<$C48,$B49,HLOOKUP(H27,$C48:$K49,2,TRUE)) -> 0.09 | I28: =IF(I27<$C48,$B49,HLOOKUP(I27,$C48:$K49,2,TRUE)) -> 0.09 | ... R28: =IF(R27<$C48,$B49,HLOOKUP(R27,$C48:$K49,2,TRUE)) -> 0.09
A29: EBIT to Interest Expense | B29: =B19 -> 6.6239231 | C29: =C19 -> -2.5391892 | D29: =D19 -> 7.7865515 | E29: =E19 -> 12.816701 | F29: =F19 -> 10.12521 | G29: =G19 -> 9.9959077 | H29: =H19 -> 9.9951153 | I29: =I19 -> 9.9943227 | ... R29: =R19 -> 9.9879776
A30: implied default probability | B30: =IF(B29<$C50,$B51,HLOOKUP(B29,$C50:$K51,2,TRUE)) -> 0.018 | C30: =IF(C29<$C50,$B51,HLOOKUP(C29,$C50:$K51,2,TRUE)) -> 0.085 | D30: =IF(D29<$C50,$B51,HLOOKUP(D29,$C50:$K51,2,TRUE)) -> 0.018 | E30: =IF(E29<$C50,$B51,HLOOKUP(E29,$C50:$K51,2,TRUE)) -> 0.015 | F30: =IF(F29<$C50,$B51,HLOOKUP(F29,$C50:$K51,2,TRUE)) -> 0.015 | G30: =IF(G29<$C50,$B51,HLOOKUP(G29,$C50:$K51,2,TRUE)) -> 0.015 | H30: =IF(H29<$C50,$B51,HLOOKUP(H29,$C50:$K51,2,TRUE)) -> 0.015 | I30: =IF(I29<$C50,$B51,HLOOKUP(I29,$C50:$K51,2,TRUE)) -> 0.015 | ... R30: =IF(R29<$C50,$B51,HLOOKUP(R29,$C50:$K51,2,TRUE)) -> 0.015
A31: Inventory Holding Period | B31: =-365*'Financial Statements'!B35/'Financial Statements'!B13 -> 75.986922 | C31: =-365*'Financial Statements'!C35/'Financial Statements'!C13 -> 81.296061 | D31: =-365*'Financial Statements'!D35/'Financial Statements'!D13 -> 77.581306 | E31: =-365*'Financial Statements'!E35/'Financial Statements'!E13 -> 70.582443 | F31: =-365*'Financial Statements'!F35/'Financial Statements'!F13 -> 85.724054 | G31: =-365*'Financial Statements'!G35/'Financial Statements'!G13 -> 85.724054 | H31: =-365*'Financial Statements'!H35/'Financial Statements'!H13 -> 85.724054 | I31: =-365*'Financial Statements'!I35/'Financial Statements'!I13 -> 85.724054 | ... R31: =-365*'Financial Statements'!R35/'Financial Statements'!R13 -> 85.724054
A32: implied default probability | B32: =IF(B31<$C52,$B53,HLOOKUP(B31,$C52:$K53,2,TRUE)) -> 0.049 | C32: =IF(C31<$C52,$B53,HLOOKUP(C31,$C52:$K53,2,TRUE)) -> 0.049 | D32: =IF(D31<$C52,$B53,HLOOKUP(D31,$C52:$K53,2,TRUE)) -> 0.049 | E32: =IF(E31<$C52,$B53,HLOOKUP(E31,$C52:$K53,2,TRUE)) -> 0.049 | F32: =IF(F31<$C52,$B53,HLOOKUP(F31,$C52:$K53,2,TRUE)) -> 0.049 | G32: =IF(G31<$C52,$B53,HLOOKUP(G31,$C52:$K53,2,TRUE)) -> 0.049 | H32: =IF(H31<$C52,$B53,HLOOKUP(H31,$C52:$K53,2,TRUE)) -> 0.049 | I32: =IF(I31<$C52,$B53,HLOOKUP(I31,$C52:$K53,2,TRUE)) -> 0.049 | ... R32: =IF(R31<$C52,$B53,HLOOKUP(R31,$C52:$K53,2,TRUE)) -> 0.049
A33: Annual Sales Growth | B33: ='Ratio Analysis'!B10 -> 0 | C33: ='Ratio Analysis'!C10 -> 0.025973792 | D33: ='Ratio Analysis'!D10 -> 0.034504213 | E33: ='Ratio Analysis'!E10 -> 0.080408118 | F33: ='Ratio Analysis'!F10 -> 0.031827608 | G33: ='Ratio Analysis'!G10 -> 0.031661462 | H33: ='Ratio Analysis'!H10 -> 0.031495316 | I33: ='Ratio Analysis'!I10 -> 0.031329169 | ... R33: ='Ratio Analysis'!R10 -> 0.03
A34: implied default probability | B34: =IF(B33<$C54,$B55,HLOOKUP(B33,$C54:$K55,2,TRUE)) -> 0.042 | C34: =IF(C33<$C54,$B55,HLOOKUP(C33,$C54:$K55,2,TRUE)) -> 0.032 | D34: =IF(D33<$C54,$B55,HLOOKUP(D33,$C54:$K55,2,TRUE)) -> 0.032 | E34: =IF(E33<$C54,$B55,HLOOKUP(E33,$C54:$K55,2,TRUE)) -> 0.03 | F34: =IF(F33<$C54,$B55,HLOOKUP(F33,$C54:$K55,2,TRUE)) -> 0.032 | G34: =IF(G33<$C54,$B55,HLOOKUP(G33,$C54:$K55,2,TRUE)) -> 0.032 | H34: =IF(H33<$C54,$B55,HLOOKUP(H33,$C54:$K55,2,TRUE)) -> 0.032 | I34: =IF(I33<$C54,$B55,HLOOKUP(I33,$C54:$K55,2,TRUE)) -> 0.032 | ... R34: =IF(R33<$C54,$B55,HLOOKUP(R33,$C54:$K55,2,TRUE)) -> 0.032
A35: Average Implied Default Probability | B35: =AVERAGE(B24,B26,B28,B30,B32,B34) -> 0.039833333 | C35: =AVERAGE(C24,C26,C28,C30,C32,C34) -> 0.062166667 | D35: =AVERAGE(D24,D26,D28,D30,D32,D34) -> 0.044833333 | E35: =AVERAGE(E24,E26,E28,E30,E32,E34) -> 0.039 | F35: =AVERAGE(F24,F26,F28,F30,F32,F34) -> 0.0435 | G35: =AVERAGE(G24,G26,G28,G30,G32,G34) -> 0.0435 | H35: =AVERAGE(H24,H26,H28,H30,H32,H34) -> 0.0435 | I35: =AVERAGE(I24,I26,I28,I30,I32,I34) -> 0.0435 | ... R35: =AVERAGE(R24,R26,R28,R30,R32,R34) -> 0.0435
A37: Fiscal Year | B37: =IF(MONTH(B7)>6,YEAR(B7),YEAR(B7)-1) -> 2017 | C37: =IF(MONTH(C7)>6,YEAR(C7),YEAR(C7)-1) -> 2018 | D37: =IF(MONTH(D7)>6,YEAR(D7),YEAR(D7)-1) -> 2019 | E37: =IF(MONTH(E7)>6,YEAR(E7),YEAR(E7)-1) -> 2020 | F37: =IF(MONTH(F7)>6,YEAR(F7),YEAR(F7)-1) -> 2021 | G37: =IF(MONTH(G7)>6,YEAR(G7),YEAR(G7)-1) -> 2022 | H37: =IF(MONTH(H7)>6,YEAR(H7),YEAR(H7)-1) -> 2023 | I37: =IF(MONTH(I7)>6,YEAR(I7),YEAR(I7)-1) -> 2024 | ... R37: =IF(MONTH(R7)>6,YEAR(R7),YEAR(R7)-1) -> 2033
A39: Default Probability Color Scale | B39: Low | C39: Medium | D39: High
A43: Lookup Table of default probability | B43: decile 1 | C43: min decile 2 | D43: min decile 3 | E43: min decile 4 | F43: min decile 5 | G43: min decile 6 | H43: min decile 7 | I43: min decile 8 | J43: min decile 9 | K43: min decile 10 | L43: Min | M43: Max
A44: NI to TA thresholds | C44: -0.448 | D44: -0.161 | E44: -0.049 | F44: 0.001 | G44: 0.022 | H44: 0.038 | I44: 0.056 | J44: 0.079 | K44: 0.118
A45: NI to TA default rates | B45: 0.083 | C45: 0.08 | D45: 0.072 | E45: 0.055 | F45: 0.045 | G45: 0.03 | H45: 0.025 | I45: 0.02 | J45: 0.02 | K45: 0.02 | L45: =K45 -> 0.02 | M45: =B45 -> 0.083 | N45: =AVERAGE(L45:M45) -> 0.0515
A46: TL to TA thresholds | C46: 0.175 | D46: 0.283 | E46: 0.385 | F46: 0.476 | G46: 0.558 | H46: 0.633 | I46: 0.709 | J46: 0.816 | K46: 1.03
A47: TL to TA default rates | B47: 0.02 | C47: 0.022 | D47: 0.025 | E47: 0.03 | F47: 0.035 | G47: 0.045 | H47: 0.055 | I47: 0.07 | J47: 0.09 | K47: 0.1 | L47: =B47 -> 0.02 | M47: =K47 -> 0.1 | N47: =AVERAGE(L47:M47) -> 0.06
A48: Quick Ratio thresholds | C48: 0.382 | D48: 0.522 | E48: 0.809 | F48: 0.994 | G48: 1.2 | H48: 1.47 | I48: 1.89 | J48: 2.53 | K48: 4.55
A49: Quick Ratio default rates | B49: 0.09 | C49: 0.065 | D49: 0.05 | E49: 0.042 | F49: 0.04 | G49: 0.035 | H49: 0.025 | I49: 0.02 | J49: 0.015 | K49: 0.01 | L49: =K49 -> 0.01 | M49: =B49 -> 0.09 | N49: =AVERAGE(L49:M49) -> 0.05
A50: EBIT to Int thresholds | C50: -17.4 | D50: -3.6 | E50: -0.139 | F50: 1.25 | G50: 2.21 | H50: 3.38 | I50: 5.21 | J50: 9.16 | K50: 23.8
A51: EBIT to Int default rates | B51: 0.075 | C51: 0.09 | D51: 0.085 | E51: 0.07 | F51: 0.05 | G51: 0.03 | H51: 0.021 | I51: 0.018 | J51: 0.015 | K51: 0.01 | L51: =K51 -> 0.01 | M51: =B51 -> 0.075 | N51: =AVERAGE(L51:M51) -> 0.0425
A52: Inv Holding thresholds | C52: 0.365 | D52: 2.56 | E52: 14.24 | F52: 31.39 | G52: 50 | H52: 70.08 | I52: 91.98 | J52: 121.54 | K52: 174.47
A53: Inv Holding default rates | B53: 0.03 | C53: 0.035 | D53: 0.039 | E53: 0.04 | F53: 0.042 | G53: 0.045 | H53: 0.049 | I53: 0.055 | J53: 0.06 | K53: 0.07 | L53: =B53 -> 0.03 | M53: =K53 -> 0.07 | N53: =AVERAGE(L53:M53) -> 0.05
A54: Sales Growth thresholds | C54: -0.203 | D54: -0.063 | E54: 0.003 | F54: 0.05 | G54: 0.098 | H54: 0.158 | I54: 0.244 | J54: 0.398 | K54: 0.797
A55: Sales Growth default rates | B55: 0.069 | C55: 0.055 | D55: 0.042 | E55: 0.032 | F55: 0.03 | G55: 0.03 | H55: 0.032 | I55: 0.042 | J55: 0.05 | K55: 0.065 | L55: =F55 -> 0.03 | M55: =B55 -> 0.069 | N55: =AVERAGE(L55:M55) -> 0.0495
L56: =AVERAGE(L45,L47,L49,L51,L53) -> 0.018 | M56: =AVERAGE(M45,M47,M49,M51,M53) -> 0.0836 | N56: =AVERAGE(L56:M56) -> 0.0508

Sheet Forecasting Assumptions
A1: Forecasting Assumptions
A5: Company Name | B5: ='Financial Statements'!B4 -> DOLLAR TREE 2021
Q6: TERMINAL
A7: ="Estimated Price/Share="&DOLLAR('Model Summary'!B22) -> Estimated Price/Share=£105.41 | Q7: YEAR
B8: Actual | C8: Actual | D8: Actual | E8: Actual | F8: Actual | G8: Forecast | H8: Forecast | I8: Forecast | J8: Forecast | K8: Forecast | L8: Forecast | M8: Forecast | N8: Forecast | O8: Forecast | P8: Forecast | Q8: Forecast | R8: Forecast
A9: Fiscal Year End Date | B9: ='Financial Statements'!B8 -> 41669 | C9: ='Financial Statements'!C8 -> 42034 | D9: ='Financial Statements'!D8 -> 42399 | E9: ='Financial Statements'!E8 -> 42765 | F9: ='Financial Statements'!F8 -> 43130 | G9: ='Financial Statements'!G8 -> 43495 | H9: ='Financial Statements'!H8 -> 43860 | I9: ='Financial Statements'!I8 -> 44226 | ... R9: ='Financial Statements'!R8 -> 47513
A11: Implied Return on Equity | C11: ='Financial Statements'!C29/(('Financial Statements'!C57+'Financial Statements'!B57)/2) -> -0.2480741 | D11: ='Financial Statements'!D29/(('Financial Statements'!D57+'Financial Statements'!C57)/2) -> 0.13901847 | E11: ='Financial Statements'!E29/(('Financial Statements'!E57+'Financial Statements'!D57)/2) -> 0.19821124 | F11: ='Financial Statements'!F29/(('Financial Statements'!F57+'Financial Statements'!E57)/2) -> 0.17700849 | G11: ='Financial Statements'!G29/(('Financial Statements'!G57+'Financial Statements'!F57)/2) -> 0.17447457 | H11: ='Financial Statements'!H29/(('Financial Statements'!H57+'Financial Statements'!G57)/2) -> 0.1744592 | I11: ='Financial Statements'!I29/(('Financial Statements'!I57+'Financial Statements'!H57)/2) -> 0.17444383 | J11: ='Financial Statements'!J29/(('Financial Statements'!J57+'Financial Statements'!I57)/2) -> 0.17442845 | ... R11: ='Financial Statements'!R29/(('Financial Statements'!R57+'Financial Statements'!Q57)/2) -> 0.17432076
A13: Income Statement Assumptions
A14: Sales Growth | C14: ='Financial Statements'!C12/'Financial Statements'!B12-1 -> 0.025973792 | D14: ='Financial Statements'!D12/'Financial Statements'!C12-1 -> 0.034504213 | E14: ='Financial Statements'!E12/'Financial Statements'!D12-1 -> 0.080408118 | F14: ='Financial Statements'!F12/'Financial Statements'!E12-1 -> 0.031827608 | G14: =F14-($F14-$Q14)/11 -> 0.031661462 | H14: =G14-($G14-$Q14)/10 -> 0.031495316 | I14: =H14-($H14-$Q14)/9 -> 0.031329169 | J14: =I14-($I14-$Q14)/8 -> 0.031163023 | K14: =J14-($J14-$Q14)/7 -> 0.030996877 | L14: =K14-($K14-$Q14)/6 -> 0.030830731 | M14: =L14-($L14-$Q14)/5 -> 0.030664585 | N14: =M14-($M14-$Q14)/4 -> 0.030498439 | O14: =N14-($N14-$Q14)/3 -> 0.030332292 | P14: =O14-($O14-$Q14)/2 -> 0.030166146 | Q14: 0.03 | R14: =$Q14 -> 0.03
A15: Cost of Goods Sold/Sales | B15: =-'Financial Statements'!B13/'Financial Statements'!B12 -> 0.68434515 | C15: =-'Financial Statements'!C13/'Financial Statements'!C12 -> 0.69559617 | D15: =-'Financial Statements'!D13/'Financial Statements'!D12 -> 0.70180172 | E15: =-'Financial Statements'!E13/'Financial Statements'!E12 -> 0.6947231 | F15: =-'Financial Statements'!F13/'Financial Statements'!F12 -> 0.70647615 | G15: =F15-($F15-$Q15)/11 -> 0.70647615 | H15: =G15-($G15-$Q15)/10 -> 0.70647615 | I15: =H15-($H15-$Q15)/9 -> 0.70647615 | J15: =I15-($I15-$Q15)/8 -> 0.70647615 | K15: =J15-($J15-$Q15)/7 -> 0.70647615 | L15: =K15-($K15-$Q15)/6 -> 0.70647615 | M15: =L15-($L15-$Q15)/5 -> 0.70647615 | N15: =M15-($M15-$Q15)/4 -> 0.70647615 | O15: =N15-($N15-$Q15)/3 -> 0.70647615 | P15: =O15-($O15-$Q15)/2 -> 0.70647615 | Q15: =$F15 -> 0.70647615 | R15: =$Q15 -> 0.70647615
A16: R&D/Sales | B16: =-'Financial Statements'!B15/'Financial Statements'!B12 -> 0 | C16: =-'Financial Statements'!C15/'Financial Statements'!C12 -> 0 | D16: =-'Financial Statements'!D15/'Financial Statements'!D12 -> 0 | E16: =-'Financial Statements'!E15/'Financial Statements'!E12 -> 0 | F16: =-'Financial Statements'!F15/'Financial Statements'!F12 -> 0 | G16: =F16-($F16-$Q16)/11 -> 0 | H16: =G16-($G16-$Q16)/10 -> 0 | I16: =H16-($H16-$Q16)/9 -> 0 | J16: =I16-($I16-$Q16)/8 -> 0 | K16: =J16-($J16-$Q16)/7 -> 0 | L16: =K16-($K16-$Q16)/6 -> 0 | M16: =L16-($L16-$Q16)/5 -> 0 | N16: =M16-($M16-$Q16)/4 -> 0 | O16: =N16-($N16-$Q16)/3 -> 0 | P16: =O16-($O16-$Q16)/2 -> 0 | Q16: =$F16 -> 0 | R16: =$Q16 -> 0
A17: SG&A/Sales | B17: =-'Financial Statements'!B16/'Financial Statements'!B12 -> 0.22267874 | C17: =-'Financial Statements'!C16/'Financial Statements'!C12 -> 0.34556791 | D17: =-'Financial Statements'!D16/'Financial Statements'!D12 -> 0.2447397 | E17: =-'Financial Statements'!E16/'Financial Statements'!E12 -> 0.2312686 | F17: =-'Financial Statements'!F16/'Financial Statements'!F12 -> 0.2247048 | G17: =F17-($F17-$Q17)/11 -> 0.2247048 | H17: =G17-($G17-$Q17)/10 -> 0.2247048 | I17: =H17-($H17-$Q17)/9 -> 0.2247048 | J17: =I17-($I17-$Q17)/8 -> 0.2247048 | K17: =J17-($J17-$Q17)/7 -> 0.2247048 | L17: =K17-($K17-$Q17)/6 -> 0.2247048 | M17: =L17-($L17-$Q17)/5 -> 0.2247048 | N17: =M17-($M17-$Q17)/4 -> 0.2247048 | O17: =N17-($N17-$Q17)/3 -> 0.2247048 | P17: =O17-($O17-$Q17)/2 -> 0.2247048 | Q17: =$F17 -> 0.2247048 | R17: =$Q17 -> 0.2247048
A18: Dep&Amort/Avge PP&E and Intang. | C18: =IF((('Financial Statements'!B38+'Financial Statements'!C38+'Financial Statements'!B40+'Financial Statements'!C40)/2)=0,0,-'Financial Statements'!C18/(('Financial Statements'!B38+'Financial Statements'!C38+'Financial Statements'!B40+'Financial Statements'!C40)/2)) -> 0 | D18: =IF((('Financial Statements'!C38+'Financial Statements'!D38+'Financial Statements'!C40+'Financial Statements'!D40)/2)=0,0,-'Financial Statements'!D18/(('Financial Statements'!C38+'Financial Statements'!D38+'Financial Statements'!C40+'Financial Statements'!D40)/2)) -> 0 | E18: =IF((('Financial Statements'!D38+'Financial Statements'!E38+'Financial Statements'!D40+'Financial Statements'!E40)/2)=0,0,-'Financial Statements'!E18/(('Financial Statements'!D38+'Financial Statements'!E38+'Financial Statements'!D40+'Financial Statements'!E40)/2)) -> 0 | F18: =IF((('Financial Statements'!E38+'Financial Statements'!F38+'Financial Statements'!E40+'Financial Statements'!F40)/2)=0,0,-'Financial Statements'!F18/(('Financial Statements'!E38+'Financial Statements'!F38+'Financial Statements'!E40+'Financial Statements'!F40)/2)) -> 0 | G18: =F18-($F18-$Q18)/11 -> 0 | H18: =G18-($G18-$Q18)/10 -> 0 | I18: =H18-($H18-$Q18)/9 -> 0 | J18: =I18-($I18-$Q18)/8 -> 0 | K18: =J18-($J18-$Q18)/7 -> 0 | L18: =K18-($K18-$Q18)/6 -> 0 | M18: =L18-($L18-$Q18)/5 -> 0 | N18: =M18-($M18-$Q18)/4 -> 0 | O18: =N18-($N18-$Q18)/3 -> 0 | P18: =O18-($O18-$Q18)/2 -> 0 | Q18: =$F18 -> 0 | R18: =$Q18 -> 0
A19: Net Interest Expense/Avge Net Debt | C19: =IF((('Financial Statements'!B44+'Financial Statements'!C44+'Financial Statements'!C49+'Financial Statements'!B49)/2)=0,0,-'Financial Statements'!C20/(('Financial Statements'!B44+'Financial Statements'!C44+'Financial Statements'!C49+'Financial Statements'!B49)/2)) -> 0.074421973 | D19: =IF((('Financial Statements'!C44+'Financial Statements'!D44+'Financial Statements'!D49+'Financial Statements'!C49)/2)=0,0,-'Financial Statements'!D20/(('Financial Statements'!C44+'Financial Statements'!D44+'Financial Statements'!D49+'Financial Statements'!C49)/2)) -> 0.040335925 | E19: =IF((('Financial Statements'!D44+'Financial Statements'!E44+'Financial Statements'!E49+'Financial Statements'!D49)/2)=0,0,-'Financial Statements'!E20/(('Financial Statements'!D44+'Financial Statements'!E44+'Financial Statements'!E49+'Financial Statements'!D49)/2)) -> 0.042095336 | F19: =IF((('Financial Statements'!E44+'Financial Statements'!F44+'Financial Statements'!F49+'Financial Statements'!E49)/2)=0,0,-'Financial Statements'!F20/(('Financial Statements'!E44+'Financial Statements'!F44+'Financial Statements'!F49+'Financial Statements'!E49)/2)) -> 0.053859586 | G19: =F19-($F19-$Q19)/11 -> 0.053859586 | H19: =G19-($G19-$Q19)/10 -> 0.053859586 | I19: =H19-($H19-$Q19)/9 -> 0.053859586 | J19: =I19-($I19-$Q19)/8 -> 0.053859586 | K19: =J19-($J19-$Q19)/7 -> 0.053859586 | L19: =K19-($K19-$Q19)/6 -> 0.053859586 | M19: =L19-($L19-$Q19)/5 -> 0.053859586 | N19: =M19-($M19-$Q19)/4 -> 0.053859586 | O19: =N19-($N19-$Q19)/3 -> 0.053859586 | P19: =O19-($O19-$Q19)/2 -> 0.053859586 | Q19: =$F19 -> 0.053859586 | R19: =$Q19 -> 0.053859586
A20: Non-Operating Income/Sales | B20: ='Financial Statements'!B21/'Financial Statements'!B12 -> 0.00030118451 | C20: ='Financial Statements'!C21/'Financial Statements'!C12 -> 2.1907437e-05 | D20: ='Financial Statements'!D21/'Financial Statements'!D12 -> -5.9294899e-05 | E20: ='Financial Statements'!E21/'Financial Statements'!E12 -> -3.1361111e-05 | F20: ='Financial Statements'!F21/'Financial Statements'!F12 -> -1.1397657e-05 | G20: =F20-($F20-$Q20)/11 -> -1.1397657e-05 | H20: =G20-($G20-$Q20)/10 -> -1.1397657e-05 | I20: =H20-($H20-$Q20)/9 -> -1.1397657e-05 | J20: =I20-($I20-$Q20)/8 -> -1.1397657e-05 | K20: =J20-($J20-$Q20)/7 -> -1.1397657e-05 | L20: =K20-($K20-$Q20)/6 -> -1.1397657e-05 | M20: =L20-($L20-$Q20)/5 -> -1.1397657e-05 | N20: =M20-($M20-$Q20)/4 -> -1.1397657e-05 | O20: =N20-($N20-$Q20)/3 -> -1.1397657e-05 | P20: =O20-($O20-$Q20)/2 -> -1.1397657e-05 | Q20: =$F20 -> -1.1397657e-05 | R20: =$Q20 -> -1.1397657e-05
A21: Effective Tax Rate | B21: =IF('Financial Statements'!B22=0,0,-'Financial Statements'!B23/'Financial Statements'!B22) -> -0.0060446009 | C21: =IF('Financial Statements'!C22=0,0,-'Financial Statements'!C23/'Financial Statements'!C22) -> -0.21527884 | D21: =IF('Financial Statements'!D22=0,0,-'Financial Statements'!D23/'Financial Statements'!D22) -> 0.24729225 | E21: =IF('Financial Statements'!E22=0,0,-'Financial Statements'!E23/'Financial Statements'!E22) -> 0.22870445 | F21: =IF('Financial Statements'!F22=0,0,-'Financial Statements'!F23/'Financial Statements'!F22) -> 0.18643549 | G21: =F21-($F21-$Q21)/11 -> 0.18643549 | H21: =G21-($G21-$Q21)/10 -> 0.18643549 | I21: =H21-($H21-$Q21)/9 -> 0.18643549 | J21: =I21-($I21-$Q21)/8 -> 0.18643549 | K21: =J21-($J21-$Q21)/7 -> 0.18643549 | L21: =K21-($K21-$Q21)/6 -> 0.18643549 | M21: =L21-($L21-$Q21)/5 -> 0.18643549 | N21: =M21-($M21-$Q21)/4 -> 0.18643549 | O21: =N21-($N21-$Q21)/3 -> 0.18643549 | P21: =O21-($O21-$Q21)/2 -> 0.18643549 | Q21: =$F21 -> 0.18643549 | R21: =$Q21 -> 0.18643549
A22: Noncontrolling Interest/After Tax Income | B22: =IF(('Financial Statements'!B22+'Financial Statements'!B23)=0,0,-'Financial Statements'!B27/('Financial Statements'!B22+'Financial Statements'!B23)) -> 0 | C22: =IF(('Financial Statements'!C22+'Financial Statements'!C23)=0,0,-'Financial Statements'!C27/('Financial Statements'!C22+'Financial Statements'!C23)) -> 0 | D22: =IF(('Financial Statements'!D22+'Financial Statements'!D23)=0,0,-'Financial Statements'!D27/('Financial Statements'!D22+'Financial Statements'!D23)) -> 0 | E22: =IF(('Financial Statements'!E22+'Financial Statements'!E23)=0,0,-'Financial Statements'!E27/('Financial Statements'!E22+'Financial Statements'!E23)) -> 0 | F22: =IF(('Financial Statements'!F22+'Financial Statements'!F23)=0,0,-'Financial Statements'!F27/('Financial Statements'!F22+'Financial Statements'!F23)) -> 0 | G22: =F22-($F22-$Q22)/11 -> 0 | H22: =G22-($G22-$Q22)/10 -> 0 | I22: =H22-($H22-$Q22)/9 -> 0 | J22: =I22-($I22-$Q22)/8 -> 0 | K22: =J22-($J22-$Q22)/7 -> 0 | L22: =K22-($K22-$Q22)/6 -> 0 | M22: =L22-($L22-$Q22)/5 -> 0 | N22: =M22-($M22-$Q22)/4 -> 0 | O22: =N22-($N22-$Q22)/3 -> 0 | P22: =O22-($O22-$Q22)/2 -> 0 | Q22: =$F22 -> 0 | R22: =$Q22 -> 0
A23: Other Income/Sales | B23: ='Financial Statements'!B24/'Financial Statements'!B12 -> 0 | C23: ='Financial Statements'!C24/'Financial Statements'!C12 -> 0 | D23: ='Financial Statements'!D24/'Financial Statements'!D12 -> 0 | E23: ='Financial Statements'!E24/'Financial Statements'!E12 -> 0 | F23: ='Financial Statements'!F24/'Financial Statements'!F12 -> 0 | G23: 0 | H23: =G23 -> 0 | I23: =H23 -> 0 | J23: =I23 -> 0 | K23: =J23 -> 0 | L23: =K23 -> 0 | M23: =L23 -> 0 | N23: =M23 -> 0 | O23: =N23 -> 0 | ... Q23: =P23 -> 0 | R23: =$Q23 -> 0
A24: Ext. Items & Disc. Ops./Sales | B24: ='Financial Statements'!B26/'Financial Statements'!B12 -> 0 | C24: ='Financial Statements'!C26/'Financial Statements'!C12 -> 0 | D24: ='Financial Statements'!D26/'Financial Statements'!D12 -> 0 | E24: ='Financial Statements'!E26/'Financial Statements'!E12 -> 0 | F24: ='Financial Statements'!F26/'Financial Statements'!F12 -> 0 | G24: 0 | H24: =G24 -> 0 | I24: =H24 -> 0 | J24: =I24 -> 0 | K24: =J24 -> 0 | L24: =K24 -> 0 | M24: =L24 -> 0 | N24: =M24 -> 0 | O24: =N24 -> 0 | ... Q24: =P24 -> 0 | R24: =$Q24 -> 0
A25: Pref. Dividends/Avge Pref. Stock | C25: =IF((('Financial Statements'!C54+'Financial Statements'!B54)/2)=0,0,-'Financial Statements'!C28/(('Financial Statements'!C54+'Financial Statements'!B54)/2)) -> 0 | D25: =IF((('Financial Statements'!D54+'Financial Statements'!C54)/2)=0,0,-'Financial Statements'!D28/(('Financial Statements'!D54+'Financial Statements'!C54)/2)) -> 0 | E25: =IF((('Financial Statements'!E54+'Financial Statements'!D54)/2)=0,0,-'Financial Statements'!E28/(('Financial Statements'!E54+'Financial Statements'!D54)/2)) -> 0 | F25: =IF((('Financial Statements'!F54+'Financial Statements'!E54)/2)=0,0,-'Financial Statements'!F28/(('Financial Statements'!F54+'Financial Statements'!E54)/2)) -> 0 | G25: =F25-($F25-$Q25)/11 -> 0 | H25: =G25-($G25-$Q25)/10 -> 0 | I25: =H25-($H25-$Q25)/9 -> 0 | J25: =I25-($I25-$Q25)/8 -> 0 | K25: =J25-($J25-$Q25)/7 -> 0 | L25: =K25-($K25-$Q25)/6 -> 0 | M25: =L25-($L25-$Q25)/5 -> 0 | N25: =M25-($M25-$Q25)/4 -> 0 | O25: =N25-($N25-$Q25)/3 -> 0 | P25: =O25-($O25-$Q25)/2 -> 0 | Q25: =$F25 -> 0 | R25: =$Q25 -> 0
A27: Balance Sheet Assumptions
A28: Working Capital Assumptions
A29: Ending Operating Cash/Sales | B29: ='Financial Statements'!B33/'Financial Statements'!B12 -> 0.049349307 | C29: ='Financial Statements'!C33/'Financial Statements'!C12 -> 0.019572104 | D29: ='Financial Statements'!D33/'Financial Statements'!D12 -> 0.024819151 | E29: ='Financial Statements'!E33/'Financial Statements'!E12 -> 0.057375153 | F29: ='Financial Statements'!F33/'Financial Statements'!F12 -> 0.03944729 | G29: =F29-($F29-$Q29)/11 -> 0.03944729 | H29: =G29-($G29-$Q29)/10 -> 0.03944729 | I29: =H29-($H29-$Q29)/9 -> 0.03944729 | J29: =I29-($I29-$Q29)/8 -> 0.03944729 | K29: =J29-($J29-$Q29)/7 -> 0.03944729 | L29: =K29-($K29-$Q29)/6 -> 0.03944729 | M29: =L29-($L29-$Q29)/5 -> 0.03944729 | N29: =M29-($M29-$Q29)/4 -> 0.03944729 | O29: =N29-($N29-$Q29)/3 -> 0.03944729 | P29: =O29-($O29-$Q29)/2 -> 0.03944729 | Q29: =$F29 -> 0.03944729 | R29: =$Q29 -> 0.03944729
A30: Ending Receivables/Sales | B30: ='Financial Statements'!B34/'Financial Statements'!B12 -> 0 | C30: ='Financial Statements'!C34/'Financial Statements'!C12 -> 0.0044209207 | D30: ='Financial Statements'!D34/'Financial Statements'!D12 -> 0 | E30: ='Financial Statements'!E34/'Financial Statements'!E12 -> 0 | F30: ='Financial Statements'!F34/'Financial Statements'!F12 -> 0 | G30: =F30-($F30-$Q30)/11 -> 0 | H30: =G30-($G30-$Q30)/10 -> 0 | I30: =H30-($H30-$Q30)/9 -> 0 | J30: =I30-($I30-$Q30)/8 -> 0 | K30: =J30-($J30-$Q30)/7 -> 0 | L30: =K30-($K30-$Q30)/6 -> 0 | M30: =L30-($L30-$Q30)/5 -> 0 | N30: =M30-($M30-$Q30)/4 -> 0 | O30: =N30-($N30-$Q30)/3 -> 0 | P30: =O30-($O30-$Q30)/2 -> 0 | Q30: =$F30 -> 0 | R30: =$Q30 -> 0
A31: Ending Inventories/COGS | B31: =IF('Financial Statements'!B13=0,0,-'Financial Statements'!B35/'Financial Statements'!B13) -> 0.20818335 | C31: =IF('Financial Statements'!C13=0,0,-'Financial Statements'!C35/'Financial Statements'!C13) -> 0.22272893 | D31: =IF('Financial Statements'!D13=0,0,-'Financial Statements'!D35/'Financial Statements'!D13) -> 0.21255152 | E31: =IF('Financial Statements'!E13=0,0,-'Financial Statements'!E35/'Financial Statements'!E13) -> 0.19337656 | F31: =IF('Financial Statements'!F13=0,0,-'Financial Statements'!F35/'Financial Statements'!F13) -> 0.23486042 | G31: =F31-($F31-$Q31)/11 -> 0.23486042 | H31: =G31-($G31-$Q31)/10 -> 0.23486042 | I31: =H31-($H31-$Q31)/9 -> 0.23486042 | J31: =I31-($I31-$Q31)/8 -> 0.23486042 | K31: =J31-($J31-$Q31)/7 -> 0.23486042 | L31: =K31-($K31-$Q31)/6 -> 0.23486042 | M31: =L31-($L31-$Q31)/5 -> 0.23486042 | N31: =M31-($M31-$Q31)/4 -> 0.23486042 | O31: =N31-($N31-$Q31)/3 -> 0.23486042 | P31: =O31-($O31-$Q31)/2 -> 0.23486042 | Q31: =$F31 -> 0.23486042 | R31: =$Q31 -> 0.23486042
A32: Ending Other Current Assets/Sales | B32: ='Financial Statements'!B36/'Financial Statements'!B12 -> 0.01389944 | C32: ='Financial Statements'!C36/'Financial Statements'!C12 -> 0.009187979 | D32: ='Financial Statements'!D36/'Financial Statements'!D12 -> 0.0068358548 | E32: ='Financial Statements'!E36/'Financial Statements'!E12 -> 0.0062800626 | F32: ='Financial Statements'!F36/'Financial Statements'!F12 -> 0.0077352096 | G32: =F32-($F32-$Q32)/11 -> 0.0077352096 | H32: =G32-($G32-$Q32)/10 -> 0.0077352096 | I32: =H32-($H32-$Q32)/9 -> 0.0077352096 | J32: =I32-($I32-$Q32)/8 -> 0.0077352096 | K32: =J32-($J32-$Q32)/7 -> 0.0077352096 | L32: =K32-($K32-$Q32)/6 -> 0.0077352096 | M32: =L32-($L32-$Q32)/5 -> 0.0077352096 | N32: =M32-($M32-$Q32)/4 -> 0.0077352096 | O32: =N32-($N32-$Q32)/3 -> 0.0077352096 | P32: =O32-($O32-$Q32)/2 -> 0.0077352096 | Q32: =$F32 -> 0.0077352096 | R32: =$Q32 -> 0.0077352096
A33: Ending Accounts Payable/COGS | B33: =IF('Financial Statements'!B13=0,0,-'Financial Statements'!B45/'Financial Statements'!B13) -> 0.077169658 | C33: =IF('Financial Statements'!C13=0,0,-'Financial Statements'!C45/'Financial Statements'!C13) -> 0.089217551 | D33: =IF('Financial Statements'!D13=0,0,-'Financial Statements'!D45/'Financial Statements'!D13) -> 0.080657329 | E33: =IF('Financial Statements'!E13=0,0,-'Financial Statements'!E45/'Financial Statements'!E13) -> 0.083540704 | F33: =IF('Financial Statements'!F13=0,0,-'Financial Statements'!F45/'Financial Statements'!F13) -> 0.10132668 | G33: =F33-($F33-$Q33)/11 -> 0.10132668 | H33: =G33-($G33-$Q33)/10 -> 0.10132668 | I33: =H33-($H33-$Q33)/9 -> 0.10132668 | J33: =I33-($I33-$Q33)/8 -> 0.10132668 | K33: =J33-($J33-$Q33)/7 -> 0.10132668 | L33: =K33-($K33-$Q33)/6 -> 0.10132668 | M33: =L33-($L33-$Q33)/5 -> 0.10132668 | N33: =M33-($M33-$Q33)/4 -> 0.10132668 | O33: =N33-($N33-$Q33)/3 -> 0.10132668 | P33: =O33-($O33-$Q33)/2 -> 0.10132668 | Q33: =$F33 -> 0.10132668 | R33: =$Q33 -> 0.10132668
A34: Ending Taxes Payable/Sales | B34: ='Financial Statements'!B46/'Financial Statements'!B12 -> 0.0014160167 | C34: ='Financial Statements'!C46/'Financial Statements'!C12 -> 0.0026288924 | D34: ='Financial Statements'!D46/'Financial Statements'!D12 -> 0.0026555644 | E34: ='Financial Statements'!E46/'Financial Statements'!E12 -> 0.0033830799 | F34: ='Financial Statements'!F46/'Financial Statements'!F12 -> 0.0031381548 | G34: =F34-($F34-$Q34)/11 -> 0.0031381548 | H34: =G34-($G34-$Q34)/10 -> 0.0031381548 | I34: =H34-($H34-$Q34)/9 -> 0.0031381548 | J34: =I34-($I34-$Q34)/8 -> 0.0031381548 | K34: =J34-($J34-$Q34)/7 -> 0.0031381548 | L34: =K34-($K34-$Q34)/6 -> 0.0031381548 | M34: =L34-($L34-$Q34)/5 -> 0.0031381548 | N34: =M34-($M34-$Q34)/4 -> 0.0031381548 | O34: =N34-($N34-$Q34)/3 -> 0.0031381548 | P34: =O34-($O34-$Q34)/2 -> 0.0031381548 | Q34: =$F34 -> 0.0031381548 | R34: =$Q34 -> 0.0031381548
A35: Ending Other Current Liabs/Sales | B35: ='Financial Statements'!B47/'Financial Statements'!B12 -> 0.033125801 | C35: ='Financial Statements'!C47/'Financial Statements'!C12 -> 0.027134551 | D35: ='Financial Statements'!D47/'Financial Statements'!D12 -> 0.080357294 | E35: ='Financial Statements'!E47/'Financial Statements'!E12 -> 0.084812206 | F35: ='Financial Statements'!F47/'Financial Statements'!F12 -> 0.083955139 | G35: =F35-($F35-$Q35)/11 -> 0.083955139 | H35: =G35-($G35-$Q35)/10 -> 0.083955139 | I35: =H35-($H35-$Q35)/9 -> 0.083955139 | J35: =I35-($I35-$Q35)/8 -> 0.083955139 | K35: =J35-($J35-$Q35)/7 -> 0.083955139 | L35: =K35-($K35-$Q35)/6 -> 0.083955139 | M35: =L35-($L35-$Q35)/5 -> 0.083955139 | N35: =M35-($M35-$Q35)/4 -> 0.083955139 | O35: =N35-($N35-$Q35)/3 -> 0.083955139 | P35: =O35-($O35-$Q35)/2 -> 0.083955139 | Q35: =$F35 -> 0.083955139 | R35: =$Q35 -> 0.083955139
A36: Other Operating Asset Assumptions
A37: Ending Net PP&E/Sales | B37: ='Financial Statements'!B38/'Financial Statements'!B12 -> 0.14388078 | C37: ='Financial Statements'!C38/'Financial Statements'!C12 -> 0.15095538 | D37: ='Financial Statements'!D38/'Financial Statements'!D12 -> 0.16440781 | E37: ='Financial Statements'!E38/'Financial Statements'!E12 -> 0.16136468 | F37: ='Financial Statements'!F38/'Financial Statements'!F12 -> 0.17010243 | G37: =F37-($F37-$Q37)/11 -> 0.17010243 | H37: =G37-($G37-$Q37)/10 -> 0.17010243 | I37: =H37-($H37-$Q37)/9 -> 0.17010243 | J37: =I37-($I37-$Q37)/8 -> 0.17010243 | K37: =J37-($J37-$Q37)/7 -> 0.17010243 | L37: =K37-($K37-$Q37)/6 -> 0.17010243 | M37: =L37-($L37-$Q37)/5 -> 0.17010243 | N37: =M37-($M37-$Q37)/4 -> 0.17010243 | O37: =N37-($N37-$Q37)/3 -> 0.17010243 | P37: =O37-($O37-$Q37)/2 -> 0.17010243 | Q37: =$F37 -> 0.17010243 | R37: =$Q37 -> 0.17010243
A38: Ending Investments/Sales | B38: ='Financial Statements'!B39/'Financial Statements'!B12 -> 0 | C38: ='Financial Statements'!C39/'Financial Statements'!C12 -> 0 | D38: ='Financial Statements'!D39/'Financial Statements'!D12 -> 0 | E38: ='Financial Statements'!E39/'Financial Statements'!E12 -> 0 | F38: ='Financial Statements'!F39/'Financial Statements'!F12 -> 0 | G38: =F38-($F38-$Q38)/11 -> 0 | H38: =G38-($G38-$Q38)/10 -> 0 | I38: =H38-($H38-$Q38)/9 -> 0 | J38: =I38-($I38-$Q38)/8 -> 0 | K38: =J38-($J38-$Q38)/7 -> 0 | L38: =K38-($K38-$Q38)/6 -> 0 | M38: =L38-($L38-$Q38)/5 -> 0 | N38: =M38-($M38-$Q38)/4 -> 0 | O38: =N38-($N38-$Q38)/3 -> 0 | P38: =O38-($O38-$Q38)/2 -> 0 | Q38: =$F38 -> 0 | R38: =$Q38 -> 0
A39: Ending Intangibles/Sales | B39: ='Financial Statements'!B40/'Financial Statements'!B12 -> 0.22589737 | C39: ='Financial Statements'!C40/'Financial Statements'!C12 -> 0.2491007 | D39: ='Financial Statements'!D40/'Financial Statements'!D12 -> 0.21529554 | E39: ='Financial Statements'!E40/'Financial Statements'!E12 -> 0.19931554 | F39: ='Financial Statements'!F40/'Financial Statements'!F12 -> 0.19316748 | G39: =F39-($F39-$Q39)/11 -> 0.19316748 | H39: =G39-($G39-$Q39)/10 -> 0.19316748 | I39: =H39-($H39-$Q39)/9 -> 0.19316748 | J39: =I39-($I39-$Q39)/8 -> 0.19316748 | K39: =J39-($J39-$Q39)/7 -> 0.19316748 | L39: =K39-($K39-$Q39)/6 -> 0.19316748 | M39: =L39-($L39-$Q39)/5 -> 0.19316748 | N39: =M39-($M39-$Q39)/4 -> 0.19316748 | O39: =N39-($N39-$Q39)/3 -> 0.19316748 | P39: =O39-($O39-$Q39)/2 -> 0.19316748 | Q39: =$F39 -> 0.19316748 | R39: =$Q39 -> 0.19316748
A40: Ending Other Assets/Sales | B40: ='Financial Statements'!B41/'Financial Statements'!B12 -> 0.15871075 | C40: ='Financial Statements'!C41/'Financial Statements'!C12 -> 0.0033868897 | D40: ='Financial Statements'!D41/'Financial Statements'!D12 -> 0.26852542 | E40: ='Financial Statements'!E41/'Financial Statements'!E12 -> 0.25263335 | F40: ='Financial Statements'!F41/'Financial Statements'!F12 -> 0.24888303 | G40: =F40-($F40-$Q40)/11 -> 0.24888303 | H40: =G40-($G40-$Q40)/10 -> 0.24888303 | I40: =H40-($H40-$Q40)/9 -> 0.24888303 | J40: =I40-($I40-$Q40)/8 -> 0.24888303 | K40: =J40-($J40-$Q40)/7 -> 0.24888303 | L40: =K40-($K40-$Q40)/6 -> 0.24888303 | M40: =L40-($L40-$Q40)/5 -> 0.24888303 | N40: =M40-($M40-$Q40)/4 -> 0.24888303 | O40: =N40-($N40-$Q40)/3 -> 0.24888303 | P40: =O40-($O40-$Q40)/2 -> 0.24888303 | Q40: =$F40 -> 0.24888303 | R40: =$Q40 -> 0.24888303
A41: Other Operating Liability Assumptions
A42: Other Liabilities/Sales | B42: ='Financial Statements'!B50/'Financial Statements'!B12 -> 0.024458879 | C42: ='Financial Statements'!C50/'Financial Statements'!C12 -> 0.022963375 | D42: ='Financial Statements'!D50/'Financial Statements'!D12 -> 0.22305047 | E42: ='Financial Statements'!E50/'Financial Statements'!E12 -> 0.213283 | F42: ='Financial Statements'!F50/'Financial Statements'!F12 -> 0.20601264 | G42: =F42-($F42-$Q42)/11 -> 0.20601264 | H42: =G42-($G42-$Q42)/10 -> 0.20601264 | I42: =H42-($H42-$Q42)/9 -> 0.20601264 | J42: =I42-($I42-$Q42)/8 -> 0.20601264 | K42: =J42-($J42-$Q42)/7 -> 0.20601264 | L42: =K42-($K42-$Q42)/6 -> 0.20601264 | M42: =L42-($L42-$Q42)/5 -> 0.20601264 | N42: =M42-($M42-$Q42)/4 -> 0.20601264 | O42: =N42-($N42-$Q42)/3 -> 0.20601264 | P42: =O42-($O42-$Q42)/2 -> 0.20601264 | Q42: =$F42 -> 0.20601264 | R42: =$Q42 -> 0.20601264
A43: Deferred Taxes/Sales | B43: ='Financial Statements'!B51/'Financial Statements'!B12 -> 0.044287609 | C43: ='Financial Statements'!C51/'Financial Statements'!C12 -> 0.042640635 | D43: ='Financial Statements'!D51/'Financial Statements'!D12 -> 0.041705491 | E43: ='Financial Statements'!E51/'Financial Statements'!E12 -> 0.039730608 | F43: ='Financial Statements'!F51/'Financial Statements'!F12 -> 0.037505889 | G43: =F43-($F43-$Q43)/11 -> 0.037505889 | H43: =G43-($G43-$Q43)/10 -> 0.037505889 | I43: =H43-($H43-$Q43)/9 -> 0.037505889 | J43: =I43-($I43-$Q43)/8 -> 0.037505889 | K43: =J43-($J43-$Q43)/7 -> 0.037505889 | L43: =K43-($K43-$Q43)/6 -> 0.037505889 | M43: =L43-($L43-$Q43)/5 -> 0.037505889 | N43: =M43-($M43-$Q43)/4 -> 0.037505889 | O43: =N43-($N43-$Q43)/3 -> 0.037505889 | P43: =O43-($O43-$Q43)/2 -> 0.037505889 | Q43: =$F43 -> 0.037505889 | R43: =$Q43 -> 0.037505889
A44: Financing Assumptions
A45: Current Debt/Total Assets | B45: ='Financial Statements'!B44/'Financial Statements'!B42 -> 0.056077341 | C45: ='Financial Statements'!C44/'Financial Statements'!C42 -> 0 | D45: ='Financial Statements'!D44/'Financial Statements'!D42 -> 0.012771653 | E45: ='Financial Statements'!E44/'Financial Statements'!E42 -> 0 | F45: ='Financial Statements'!F44/'Financial Statements'!F42 -> 0 | G45: =F45-($F45-$Q45)/11 -> 0 | H45: =G45-($G45-$Q45)/10 -> 0 | I45: =H45-($H45-$Q45)/9 -> 0 | J45: =I45-($I45-$Q45)/8 -> 0 | K45: =J45-($J45-$Q45)/7 -> 0 | L45: =K45-($K45-$Q45)/6 -> 0 | M45: =L45-($L45-$Q45)/5 -> 0 | N45: =M45-($M45-$Q45)/4 -> 0 | O45: =N45-($N45-$Q45)/3 -> 0 | P45: =O45-($O45-$Q45)/2 -> 0 | Q45: =$F45 -> 0 | R45: =$Q45 -> 0
A46: Long-Term Debt/Total Assets | B46: ='Financial Statements'!B49/'Financial Statements'!B42 -> 0.29156666 | C46: ='Financial Statements'!C49/'Financial Statements'!C42 -> 0.31592007 | D46: ='Financial Statements'!D49/'Financial Statements'!D42 -> 0.17993727 | E46: ='Financial Statements'!E49/'Financial Statements'!E42 -> 0.1558852 | F46: ='Financial Statements'!F49/'Financial Statements'!F42 -> 0.15730741 | G46: =F46-($F46-$Q46)/11 -> 0.15730741 | H46: =G46-($G46-$Q46)/10 -> 0.15730741 | I46: =H46-($H46-$Q46)/9 -> 0.15730741 | J46: =I46-($I46-$Q46)/8 -> 0.15730741 | K46: =J46-($J46-$Q46)/7 -> 0.15730741 | L46: =K46-($K46-$Q46)/6 -> 0.15730741 | M46: =L46-($L46-$Q46)/5 -> 0.15730741 | N46: =M46-($M46-$Q46)/4 -> 0.15730741 | O46: =N46-($N46-$Q46)/3 -> 0.15730741 | P46: =O46-($O46-$Q46)/2 -> 0.15730741 | Q46: =$F46 -> 0.15730741 | R46: =$Q46 -> 0.15730741
A47: Noncontrolling Interest/Total Assets | B47: ='Financial Statements'!B53/'Financial Statements'!B42 -> 0 | C47: ='Financial Statements'!C53/'Financial Statements'!C42 -> 0 | D47: ='Financial Statements'!D53/'Financial Statements'!D42 -> 0 | E47: ='Financial Statements'!E53/'Financial Statements'!E42 -> 0 | F47: ='Financial Statements'!F53/'Financial Statements'!F42 -> 0 | G47: =F47-($F47-$Q47)/11 -> 0 | H47: =G47-($G47-$Q47)/10 -> 0 | I47: =H47-($H47-$Q47)/9 -> 0 | J47: =I47-($I47-$Q47)/8 -> 0 | K47: =J47-($J47-$Q47)/7 -> 0 | L47: =K47-($K47-$Q47)/6 -> 0 | M47: =L47-($L47-$Q47)/5 -> 0 | N47: =M47-($M47-$Q47)/4 -> 0 | O47: =N47-($N47-$Q47)/3 -> 0 | P47: =O47-($O47-$Q47)/2 -> 0 | Q47: =$F47 -> 0 | R47: =$Q47 -> 0
A48: Preferred Stock/Total Assets | B48: ='Financial Statements'!B54/'Financial Statements'!B42 -> 0 | C48: ='Financial Statements'!C54/'Financial Statements'!C42 -> 0 | D48: ='Financial Statements'!D54/'Financial Statements'!D42 -> 0 | E48: ='Financial Statements'!E54/'Financial Statements'!E42 -> 0 | F48: ='Financial Statements'!F54/'Financial Statements'!F42 -> 0 | G48: =F48-($F48-$Q48)/11 -> 0 | H48: =G48-($G48-$Q48)/10 -> 0 | I48: =H48-($H48-$Q48)/9 -> 0 | J48: =I48-($I48-$Q48)/8 -> 0 | K48: =J48-($J48-$Q48)/7 -> 0 | L48: =K48-($K48-$Q48)/6 -> 0 | M48: =L48-($L48-$Q48)/5 -> 0 | N48: =M48-($M48-$Q48)/4 -> 0 | O48: =N48-($N48-$Q48)/3 -> 0 | P48: =O48-($O48-$Q48)/2 -> 0 | Q48: =$F48 -> 0 | R48: =$Q48 -> 0
A49: Dividend Payout Ratio | B49: =IF('Financial Statements'!B29=0,0,-'Financial Statements'!B64/'Financial Statements'!B29) -> 0 | C49: =IF('Financial Statements'!C29=0,0,-'Financial Statements'!C64/'Financial Statements'!C29) -> 0 | D49: =IF('Financial Statements'!D29=0,0,-'Financial Statements'!D64/'Financial Statements'!D29) -> 0 | E49: =IF('Financial Statements'!E29=0,0,-'Financial Statements'!E64/'Financial Statements'!E29) -> 0 | F49: =IF('Financial Statements'!F29=0,0,-'Financial Statements'!F64/'Financial Statements'!F29) -> 0 | G49: =F49-($F49-$Q49)/11 -> 0 | H49: =G49-($G49-$Q49)/10 -> 0 | I49: =H49-($H49-$Q49)/9 -> 0 | J49: =I49-($I49-$Q49)/8 -> 0 | K49: =J49-($J49-$Q49)/7 -> 0 | L49: =K49-($K49-$Q49)/6 -> 0 | M49: =L49-($L49-$Q49)/5 -> 0 | N49: =M49-($M49-$Q49)/4 -> 0 | O49: =N49-($N49-$Q49)/3 -> 0 | P49: =O49-($O49-$Q49)/2 -> 0 | Q49: =$F49 -> 0 | R49: =$Q49 -> 0

Sheet Valuation Parameters
A1: Valuation Parameters
A4: ="Estimated Price/Share="&DOLLAR(B24) -> Estimated Price/Share=£105.41
A6: Company Name: | C6: ='Financial Statements'!B4 -> DOLLAR TREE 2021
A8: Required Valuation Parameters (to compute value of common equity):
B9: Enter Cost of Equity Capital: | J9: 0.1
B10: Enter Value of Contingent Claims on Common Equity ($000): | H10: (Link to Calculator) | J10: 0
B11: Enter Date of Valuation: | J11: =TODAY() -> 44549
B12: Enter Dilution Factor for Splits Occurring Since Latest Fiscal Year End: | J12: 1
A14: Optional Valuation Parameters (to compute value to all investors):
B15: Enter Cost of Net Debt: | J15: 0.08
B16: Enter Cost of Preferred Stock: | J16: 0.09
B17: Enter Cost of Noncontrolling Interest: | J17: 0.1
B19: Adjust the Weighted Average Cost of Capital Input | J19: =J24 -> 0.096743496 | K19: =IF(E24>B24,"up","down") -> down
B20: such that the two equity values below are approximately equal:
B22: Equity Value computed directly | E22: Equity Value computed indirectly | I22: approximate weighted average
B23: from flows to equityholders: | E23: as the Entity Value less non-equity claims: | I23: cost of capital to use as starting point:
B24: ='Residual Income Valuations'!B27 -> 105.40825 | E24: ='Residual Income Valuations'!B68 -> 104.41075 | J24: =('Residual Income Valuations'!B21*J9+'Residual Income Valuations'!B40*(J15*(1-'Forecasting Assumptions'!Q21))+'Residual Income Valuations'!B46*J16+'Residual Income Valuations'!B52*J17)/('Residual Income Valuations'!B21+'Residual Income Valuations'!B40+'Residual Income Valuations'!B46+'Residual Income Valuations'!B52) -> 0.096743496
A29: Black Scholes Option Value Calculator | G29: (Back to Valuation Parameters)
A32: Input Parameters:
B33: Current Stock Price (S) | J33: 50
B34: Option Exercise Price (K) | J34: 50
B35: Years to Expiration (t) | J35: 5
B36: Forecasted Annual Dividend Yield (y) | J36: 0.02
B37: Risk-Free Rate (r) | J37: 0.0366
B38: Standard Deviation of Stock Return (s) | J38: 0.62
B40: Value of Call Option | J40: =J33*EXP(-J36*J35)*_xlfn.NORM.DIST((LN(J33/J34)+(J37-J36+J38^2/2)*J35)/(J38*J35^0.5),0,1,TRUE)-J34*EXP(-J37*J35)*_xlfn.NORM.DIST((LN(J33/J34)+(J37-J36+J38^2/2)*J35)/(J38*J35^0.5)-J38*J35^0.5,0,1,TRUE) -> 24.068399

Sheet Residual Income Valuations
A1: Residual Income Valuation | B1: ($000)
A4: Company Name | B4: ='Financial Statements'!B4 -> DOLLAR TREE 2021
A5: Most Recent Fiscal Year End | B5: ='Financial Statements'!F8 -> 43130
A6: Date of Valuation | B6: ='Valuation Parameters'!J11 -> 44549
A7: Cost of Common Equity | B7: ='Valuation Parameters'!J9 -> 0.1
A8: Teriminal Growth Rate | B8: ='Forecasting Assumptions'!Q14 -> 0.03
A10: Fiscal Year of Forecast | B10: ='Financial Statements'!G8 -> 43495 | C10: ='Financial Statements'!H8 -> 43860 | D10: ='Financial Statements'!I8 -> 44226 | E10: ='Financial Statements'!J8 -> 44591 | F10: ='Financial Statements'!K8 -> 44956 | G10: ='Financial Statements'!L8 -> 45321 | H10: ='Financial Statements'!M8 -> 45687 | I10: ='Financial Statements'!N8 -> 46052 | ... M10: ='Financial Statements'!R8 -> 47513
A11: =B21+B40+B46-B58 -> 153968.78
A12: Valuation to Common Equity
A13: Net Income | B13: ='Financial Statements'!G29 -> 1368000.9 | C13: ='Financial Statements'!H29 -> 1411074.1 | D13: ='Financial Statements'!I29 -> 1455269.1 | E13: ='Financial Statements'!J29 -> 1500606.4 | F13: ='Financial Statements'!K29 -> 1547106.9 | G13: ='Financial Statements'!L29 -> 1594791.2 | H13: ='Financial Statements'!M29 -> 1643680.3 | I13: ='Financial Statements'!N29 -> 1693795 | ... M13: ='Financial Statements'!R29 -> 1907253.3
A14: Common Equity at Beginning of Year | B14: ='Financial Statements'!F57 -> 7718500 | C14: ='Financial Statements'!G57 -> 7962879 | D14: ='Financial Statements'!H57 -> 8213672.4 | E14: ='Financial Statements'!I57 -> 8470999.9 | F14: ='Financial Statements'!J57 -> 8734981.9 | G14: ='Financial Statements'!K57 -> 9005739 | H14: ='Financial Statements'!L57 -> 9283392.6 | I14: ='Financial Statements'!M57 -> 9568063.9 | ... M14: ='Financial Statements'!Q57 -> 10779366
A15: Residual Income | B15: =B13-B7*B14 -> 596150.93 | C15: =C13-B7*C14 -> 614786.21 | D15: =D13-B7*D14 -> 633901.82 | E15: =E13-B7*E14 -> 653506.41 | F15: =F13-B7*F14 -> 673608.68 | G15: =G13-B7*G14 -> 694217.32 | H15: =H13-B7*H14 -> 715341.07 | I15: =I13-B7*I14 -> 736988.65 | J15: =J13-$B$7*J14 -> 759168.82 | K15: =K13-$B$7*K14 -> 781890.31 | L15: =L13-$B$7*L14 -> 805161.86 | M15: =M13-$B$7*M14 -> 829316.72
A16: Present Value of Residual Income | B16: =B15/(1+$B$7)^1 -> 541955.39 | C16: =C15/(1+$B$7)^2 -> 508087.78 | D16: =D15/(1+$B$7)^3 -> 476259.82 | E16: =E15/(1+$B$7)^4 -> 446353.67 | F16: =F15/(1+$B$7)^5 -> 418257.99 | G16: =G15/(1+$B$7)^6 -> 391867.58 | H16: =H15/(1+$B$7)^7 -> 367083.08 | I16: =I15/(1+$B$7)^8 -> 343810.65 | J16: =J15/(1+$B$7)^9 -> 321961.69 | K16: =K15/(1+$B$7)^10 -> 301452.56 | L16: =L15/(1+$B$7)^11 -> 282204.32 | M16: =M15/(1+$B$7)^12 -> 264245.86
A17: Present Value Beyond 10 Years | B17: =L16+(M15/($B$7-$B$8))/(1+$B$7)^11 -> 4434639.3 | C17: =IF(($B$7-$B$8)<=0,"Error! cost of equity capital <= growth rate"," ")
A18: Present Value of First 10 Years | B18: =SUM(B16:K16) -> 4117090.2
A19: Common Equity as of
A20: ='Financial Statements'!F8 -> 43130 | B20: =B14 -> 7718500
A21: Forecast Equity Value Before Time Adj. | B21: =B17+B18+B20 -> 16270230
A22: Forecasted Value as of Valuation Date | B22: =B21*(1+(B7/2))*(1+B7*(DAYS360(B5,B6)/360)) -> 23727418
A23: Less Value of Contingent Equity Claims | B23: =-'Valuation Parameters'!J10 -> 0
A24: Value Attributable to Common Equity | B24: =B22+B23 -> 23727418
A25: Common Shares Outstanding at BS Date | B25: ='Financial Statements'!B5 -> 225100.2
A26: Equivalent Shares at Valuation Date | B26: =B25*'Valuation Parameters'!J12 -> 225100.2
A27: Forecast Price/Share | B27: =B24/B26 -> 105.40825
A30: Valuation to All Investors
A31: Cost of Debt | B31: ='Valuation Parameters'!J15 -> 0.08
A32: Cost of Preferred Stock | B32: ='Valuation Parameters'!J16 -> 0.09
A33: Cost of Noncontrolling Interest | B33: ='Valuation Parameters'!J17 -> 0.1
A34: After Tax Weighted Average Cost of Capital | B34: ='Valuation Parameters'!J19 -> 0.096743496
A36: Net Interest Expense to Net Debtholders | B36: =-'Financial Statements'!G20 -> 186951.66 | C36: =-'Financial Statements'!H20 -> 192855.05 | D36: =-'Financial Statements'!I20 -> 198912.82 | E36: =-'Financial Statements'!J20 -> 205127.81 | F36: =-'Financial Statements'!K20 -> 211502.91 | G36: =-'Financial Statements'!L20 -> 218041 | H36: =-'Financial Statements'!M20 -> 224744.98 | I36: =-'Financial Statements'!N20 -> 231617.74 | ... M36: =-'Financial Statements'!R20 -> 260876.13
A37: Beginning Book Value of Debt | B37: ='Financial Statements'!F44+'Financial Statements'!F49 -> 3417000 | C37: ='Financial Statements'!G44+'Financial Statements'!G49 -> 3525187.2 | D37: ='Financial Statements'!H44+'Financial Statements'!H49 -> 3636214.1 | E37: ='Financial Statements'!I44+'Financial Statements'!I49 -> 3750133.7 | F37: ='Financial Statements'!J44+'Financial Statements'!J49 -> 3866999.2 | G37: ='Financial Statements'!K44+'Financial Statements'!K49 -> 3986864.1 | H37: ='Financial Statements'!L44+'Financial Statements'!L49 -> 4109782 | I37: ='Financial Statements'!M44+'Financial Statements'!M49 -> 4235806.8 | ... M37: ='Financial Statements'!Q44+'Financial Statements'!Q49 -> 4772053.3
A38: Residual Interest Expense | B38: =B36-($B$31*B37) -> -86408.336 | C38: =C36-($B$31*C37) -> -89159.923 | D38: =D36-($B$31*D37) -> -91984.313 | E38: =E36-($B$31*E37) -> -94882.884 | F38: =F36-($B$31*F37) -> -97857.023 | G38: =G36-($B$31*G37) -> -100908.12 | H38: =H36-($B$31*H37) -> -104037.58 | I38: =I36-($B$31*I37) -> -107246.8 | ... M38: =M36-($B$31*M37) -> -120888.14
A39: Present Value of Residual Interest Income | B39: =B38/(1+$B$31)^1 -> -80007.719 | C39: =C38/(1+$B$31)^2 -> -76440.263 | D39: =D38/(1+$B$31)^3 -> -73020.113 | E39: =E38/(1+$B$31)^4 -> -69741.752 | F39: =F38/(1+$B$31)^5 -> -66599.846 | G39: =G38/(1+$B$31)^6 -> -63589.235 | H39: =H38/(1+$B$31)^7 -> -60704.931 | I39: =I38/(1+$B$31)^8 -> -57942.112 | J39: =J38/(1+$B$31)^9 -> -55296.118 | K39: =K38/(1+$B$31)^10 -> -52762.446 | L39: =L38/(1+$B$31)^11 -> -50336.748 | M39: =M38/(1+$B$31)^12 -> -48006.343
A40: Value of Debt | B40: =IF($B$31-$B$8>0,B37+SUM(B39:L39)+(M38/($B$31-$B$8))/(1+$B$31)^11,IF(NOT(M38=0),#N/A,B37+SUM(B39:M39))) -> 1673621.7 | C40: =IF($B$31-$B$8>0," ",IF(NOT(M38=0),"Error! cost of debt <= growth rate"," "))
A42: Dividends to Preferred Stockholders | B42: ='Financial Statements'!G28 -> 0 | C42: ='Financial Statements'!H28 -> 0 | D42: ='Financial Statements'!I28 -> 0 | E42: ='Financial Statements'!J28 -> 0 | F42: ='Financial Statements'!K28 -> 0 | G42: ='Financial Statements'!L28 -> 0 | H42: ='Financial Statements'!M28 -> 0 | I42: ='Financial Statements'!N28 -> 0 | ... M42: ='Financial Statements'!R28 -> 0
A43: Beginning Book Value of Preferred Stock | B43: ='Financial Statements'!F54 -> 0 | C43: ='Financial Statements'!G54 -> 0 | D43: ='Financial Statements'!H54 -> 0 | E43: ='Financial Statements'!I54 -> 0 | F43: ='Financial Statements'!J54 -> 0 | G43: ='Financial Statements'!K54 -> 0 | H43: ='Financial Statements'!L54 -> 0 | I43: ='Financial Statements'!M54 -> 0 | ... M43: ='Financial Statements'!Q54 -> 0
A44: Residual Income to Preferred Stock | B44: =B42-($B$32*B43) -> 0 | C44: =C42-($B$32*C43) -> 0 | D44: =D42-($B$32*D43) -> 0 | E44: =E42-($B$32*E43) -> 0 | F44: =F42-($B$32*F43) -> 0 | G44: =G42-($B$32*G43) -> 0 | H44: =H42-($B$32*H43) -> 0 | I44: =I42-($B$32*I43) -> 0 | ... M44: =M42-($B$32*M43) -> 0
A45: Present Value of Preferred Residual Income | B45: =B44/(1+$B$32)^1 -> 0 | C45: =C44/(1+$B$32)^2 -> 0 | D45: =D44/(1+$B$32)^3 -> 0 | E45: =E44/(1+$B$32)^4 -> 0 | F45: =F44/(1+$B$32)^5 -> 0 | G45: =G44/(1+$B$32)^6 -> 0 | H45: =H44/(1+$B$32)^7 -> 0 | I45: =I44/(1+$B$32)^8 -> 0 | J45: =J44/(1+$B$32)^9 -> 0 | K45: =K44/(1+$B$32)^10 -> 0 | L45: =L44/(1+$B$32)^11 -> 0 | M45: =M44/(1+$B$32)^12 -> 0
A46: Value of Preferred Stock | B46: =IF($B$32-$B$8>0,B43+SUM(B45:L45)+(M44/($B$32-$B$8))/(1+$B$32)^11,IF(NOT(M44=0),#N/A,B43+SUM(B45:M45))) -> 0 | C46: =IF($B$32-$B$8>0," ",IF(NOT(M44=0),"Error! cost of preferred stock <= growth rate"," "))
A48: Noncontrolling Interest in Earnings | B48: =-'Financial Statements'!G27 -> 0 | C48: =-'Financial Statements'!H27 -> 0 | D48: =-'Financial Statements'!I27 -> 0 | E48: =-'Financial Statements'!J27 -> 0 | F48: =-'Financial Statements'!K27 -> 0 | G48: =-'Financial Statements'!L27 -> 0 | H48: =-'Financial Statements'!M27 -> 0 | I48: =-'Financial Statements'!N27 -> 0 | ... M48: =-'Financial Statements'!R27 -> 0
A49: Beginning Book Value of Noncontrolling Interest | B49: ='Financial Statements'!F53 -> 0 | C49: ='Financial Statements'!G53 -> 0 | D49: ='Financial Statements'!H53 -> 0 | E49: ='Financial Statements'!I53 -> 0 | F49: ='Financial Statements'!J53 -> 0 | G49: ='Financial Statements'!K53 -> 0 | H49: ='Financial Statements'!L53 -> 0 | I49: ='Financial Statements'!M53 -> 0 | ... M49: ='Financial Statements'!Q53 -> 0
A50: Residual Income to Noncontrolling Interest | B50: =B48-$B$33*B49 -> 0 | C50: =C48-$B$33*C49 -> 0 | D50: =D48-$B$33*D49 -> 0 | E50: =E48-$B$33*E49 -> 0 | F50: =F48-$B$33*F49 -> 0 | G50: =G48-$B$33*G49 -> 0 | H50: =H48-$B$33*H49 -> 0 | I50: =I48-$B$33*I49 -> 0 | ... M50: =M48-$B$33*M49 -> 0
A51: Present Value of MI Residual Income | B51: =B50/(1+$B$33)^1 -> 0 | C51: =C50/(1+$B$33)^2 -> 0 | D51: =D50/(1+$B$33)^3 -> 0 | E51: =E50/(1+$B$33)^4 -> 0 | F51: =F50/(1+$B$33)^5 -> 0 | G51: =G50/(1+$B$33)^6 -> 0 | H51: =H50/(1+$B$33)^7 -> 0 | I51: =I50/(1+$B$33)^8 -> 0 | J51: =J50/(1+$B$33)^9 -> 0 | K51: =K50/(1+$B$33)^10 -> 0 | L51: =L50/(1+$B$33)^11 -> 0 | M51: =M50/(1+$B$33)^12 -> 0
A52: Value of Noncontrolling Interest | B52: =IF($B$33-$B$8>0,B49+SUM(B51:L51)+(M50/($B$33-$B$8))/(1+$B$33)^11,IF(NOT(M50=0),#N/A,B49+SUM(B51:M51))) -> 0 | C52: =IF($B$33-$B$8>0," ",IF(NOT(M50=0),"Error! cost of noncontrolling interest <= growth rate"," "))
A54: Net Operating Income | B54: ='Financial Statements'!G71 -> 1520098.2 | C54: ='Financial Statements'!H71 -> 1567974.1 | D54: ='Financial Statements'!I71 -> 1617097.5 | E54: ='Financial Statements'!J71 -> 1667491.1 | F54: ='Financial Statements'!K71 -> 1719178.1 | G54: ='Financial Statements'!L71 -> 1772181.6 | H54: ='Financial Statements'!M71 -> 1826524.9 | I54: ='Financial Statements'!N71 -> 1882231 | ... M54: ='Financial Statements'!R71 -> 2119492.9
A55: Beginning Net Operating Assets | B55: ='Financial Statements'!F75 -> 11135500 | C55: ='Financial Statements'!G75 -> 11488066 | D55: ='Financial Statements'!H75 -> 11849886 | E55: ='Financial Statements'!I75 -> 12221134 | F55: ='Financial Statements'!J75 -> 12601981 | G55: ='Financial Statements'!K75 -> 12992603 | H55: ='Financial Statements'!L75 -> 13393175 | I55: ='Financial Statements'!M75 -> 13803871 | ... M55: ='Financial Statements'!Q75 -> 15551419
A56: Residual Income to all Investors | B56: =B54-($B$34*B55) -> 442810.97 | C56: =C54-($B$34*C55) -> 456578.46 | D56: =D54-($B$34*D55) -> 470698.03 | E56: =E54-($B$34*E55) -> 485175.93 | F56: =F54-($B$34*F55) -> 500018.43 | G56: =G54-($B$34*G55) -> 515231.81 | H56: =H54-($B$34*H55) -> 530822.34 | I56: =I54-($B$34*I55) -> 546796.32 | ... M56: =M54-($B$34*M55) -> 614994.21
A57: Present Value of Residual Investor Income | B57: =B56/(1+$B$34)^1 -> 403750.72 | C57: =C56/(1+$B$34)^2 -> 379581.71 | D57: =D56/(1+$B$34)^3 -> 356801.91 | E57: =E56/(1+$B$34)^4 -> 335335.07 | F57: =F56/(1+$B$34)^5 -> 315108.91 | G57: =G56/(1+$B$34)^6 -> 296054.91 | H57: =H56/(1+$B$34)^7 -> 278108.15 | I57: =I56/(1+$B$34)^8 -> 261207.14 | J57: =J56/(1+$B$34)^9 -> 245293.6 | K57: =K56/(1+$B$34)^10 -> 230312.35 | L57: =L56/(1+$B$34)^11 -> 216211.14 | M57: =M56/(1+$B$34)^12 -> 203053.38
A58: Entity Value | B58: =IF(ISNA($B$34),#N/A,B55+SUM(B57:L57)+(M56/($B$34-$B$8))/(1+$B$34)^11) -> 17789882 | C58: =IF(($B$34-$B$8)<=0,"Error! weighted average cost of capital <= growth rate"," ")
A59: Less Value of Debt | B59: =-B40 -> -1673621.7
A60: Less Value of Preferred Stock | B60: =-B46 -> 0
A61: Less Value of Noncontrolling Interest | B61: =-B52 -> 0
A62: Forecast Equity Value Before Time Adj. | B62: =B58+B59+B60+B61 -> 16116261
A63: Forecasted Value as of Valuation Date | B63: =B62*(1+($B$7/2))*(1+$B$7*(DAYS360(B5,B6)/360)) -> 23502880
A64: Less Value of Contingent Equity Claims | B64: =-'Valuation Parameters'!J10 -> 0
A65: Value Attributable to Common Equity | B65: =B63+B64 -> 23502880
A66: Common Shares Outstanding at BS Date | B66: ='Financial Statements'!B5 -> 225100.2
A67: Equivalent Shares at Valuation Date | B67: =B66*'Valuation Parameters'!J12 -> 225100.2
A68: Forecast Price/Share | B68: =B65/B67 -> 104.41075

Sheet DCF Valuations
A1: DCF Valuations | B1: ($000)
A4: Company Name | B4: ='Financial Statements'!B4 -> DOLLAR TREE 2021
A5: Most Recent Fiscal Year End | B5: ='Financial Statements'!F8 -> 43130
A6: Date of Valuation | B6: ='Valuation Parameters'!J11 -> 44549
A7: Cost of Common Equity | B7: ='Valuation Parameters'!J9 -> 0.1
A8: Terminal Growth Rate | B8: ='Forecasting Assumptions'!Q14 -> 0.03
A10: Fiscal Year of Forecast | B10: ='Financial Statements'!G8 -> 43495 | C10: ='Financial Statements'!H8 -> 43860 | D10: ='Financial Statements'!I8 -> 44226 | E10: ='Financial Statements'!J8 -> 44591 | F10: ='Financial Statements'!K8 -> 44956 | G10: ='Financial Statements'!L8 -> 45321 | H10: ='Financial Statements'!M8 -> 45687 | I10: ='Financial Statements'!N8 -> 46052 | ... M10: ='Financial Statements'!R8 -> 47513
A11: =B17+B33+B37-B45 -> 153968.78
A12: Valuation to Common Equity
A13: Free Cash Flow to Common Equity | B13: ='Cash Flow Analysis'!F64 -> 1123621.9 | C13: ='Cash Flow Analysis'!G64 -> 1160280.7 | D13: ='Cash Flow Analysis'!H64 -> 1197941.5 | E13: ='Cash Flow Analysis'!I64 -> 1236624.4 | F13: ='Cash Flow Analysis'!J64 -> 1276349.7 | G13: ='Cash Flow Analysis'!K64 -> 1317137.7 | H13: ='Cash Flow Analysis'!L64 -> 1359008.9 | I13: ='Cash Flow Analysis'!M64 -> 1401984 | ... M13: ='Cash Flow Analysis'!Q64 -> 1583872.3
A14: Present Value of FCF | B14: =B13/(1+$B$7)^1 -> 1021474.5 | C14: =C13/(1+$B$7)^2 -> 958909.69 | D14: =D13/(1+$B$7)^3 -> 900031.2 | E14: =E13/(1+$B$7)^4 -> 844631.13 | F14: =F13/(1+$B$7)^5 -> 792512.75 | G14: =G13/(1+$B$7)^6 -> 743489.9 | H14: =H13/(1+$B$7)^7 -> 697386.47 | I14: =I13/(1+$B$7)^8 -> 654035.9 | J14: =J13/(1+$B$7)^9 -> 613280.66 | K14: =K13/(1+$B$7)^10 -> 574971.8 | L14: =L13/(1+$B$7)^11 -> 538968.54 | M14: =M13/(1+$B$7)^12 -> 504670.54
A15: Present Value Beyond 10 Years | B15: =L14+(M13/($B$7-$B$8))/(1+$B$7)^11 -> 8469505.6 | C15: =IF(($B$7-$B$8)<0,"Error! cost of equity capital < growth rate"," ")
A16: Present Value of First 10 Years | B16: =SUM(B14:K14) -> 7800724
A17: Forecast Equity Value Before Time Adj. | B17: =B15+B16 -> 16270230
A18: Forecasted Value as of Valuation Date | B18: =B17*(1+(B7/2))*(1+B7*(DAYS360(B5,B6)/360)) -> 23727418
A19: Less Value of Contingent Equity Claims | B19: =-'Valuation Parameters'!J10 -> 0
A20: Value Attributable to Common Equity | B20: =B18+B19 -> 23727418
A21: Common Shares Outstanding at BS Date | B21: ='Financial Statements'!B5 -> 225100.2
A22: Equivalent Shares at Valuation Date | B22: =B21*'Valuation Parameters'!J12 -> 225100.2
A23: Forecast Price/Share | B23: =B20/B22 -> 105.40825
A25: Valuation to All Investors
A26: Cost of Net Debt | B26: ='Valuation Parameters'!J15 -> 0.08
A27: Cost of Preferred Stock | B27: ='Valuation Parameters'!J16 -> 0.09
A28: Cost of Noncontrolling Interest | B28: ='Valuation Parameters'!J17 -> 0.1
A29: After Tax Weighted Average Cost of Capital | B29: ='Valuation Parameters'!J19 -> 0.096743496
A31: Free Cash Flow to Debt | B31: ='Cash Flow Analysis'!F90+'Cash Flow Analysis'!F95 -> 78764.449 | C31: ='Cash Flow Analysis'!G90+'Cash Flow Analysis'!G95 -> 81828.17 | D31: ='Cash Flow Analysis'!H90+'Cash Flow Analysis'!H95 -> 84993.248 | E31: ='Cash Flow Analysis'!I90+'Cash Flow Analysis'!I95 -> 88262.307 | F31: ='Cash Flow Analysis'!J90+'Cash Flow Analysis'!J95 -> 91638.012 | G31: ='Cash Flow Analysis'!K90+'Cash Flow Analysis'!K95 -> 95123.068 | H31: ='Cash Flow Analysis'!L90+'Cash Flow Analysis'!L95 -> 98720.218 | I31: ='Cash Flow Analysis'!M90+'Cash Flow Analysis'!M95 -> 102432.24 | ... M31: ='Cash Flow Analysis'!Q90+'Cash Flow Analysis'!Q95 -> 117714.53
A32: Present Value of FCF to Debt | B32: =B31/(1+$B$26)^1 -> 72930.045 | C32: =C31/(1+$B$26)^2 -> 70154.467 | D32: =D31/(1+$B$26)^3 -> 67470.38 | E32: =E31/(1+$B$26)^4 -> 64875.43 | F32: =F31/(1+$B$26)^5 -> 62367.291 | G32: =G31/(1+$B$26)^6 -> 59943.669 | H32: =H31/(1+$B$26)^7 -> 57602.299 | I32: =I31/(1+$B$26)^8 -> 55340.954 | J32: =J31/(1+$B$26)^9 -> 53157.438 | K32: =K31/(1+$B$26)^10 -> 51049.589 | L32: =L31/(1+$B$26)^11 -> 49015.285 | M32: =M31/(1+$B$26)^12 -> 46746.058
A33: Value of Debt | B33: =IF($B$26-$B$8>0,SUM(B32:L32)+(M31/($B$26-$B$8))/(1+$B$26)^11,IF(NOT(M31=0),#N/A,SUM(B32:M32))) -> 1673621.7 | C33: =IF($B$26-$B$8>0," ",IF(NOT(M31=0),"Error! cost of debt <= growth rate"," "))
A35: Free Cash Flow to Preferred Stock | B35: ='Cash Flow Analysis'!F92+'Cash Flow Analysis'!F96 -> 0 | C35: ='Cash Flow Analysis'!G92+'Cash Flow Analysis'!G96 -> 0 | D35: ='Cash Flow Analysis'!H92+'Cash Flow Analysis'!H96 -> 0 | E35: ='Cash Flow Analysis'!I92+'Cash Flow Analysis'!I96 -> 0 | F35: ='Cash Flow Analysis'!J92+'Cash Flow Analysis'!J96 -> 0 | G35: ='Cash Flow Analysis'!K92+'Cash Flow Analysis'!K96 -> 0 | H35: ='Cash Flow Analysis'!L92+'Cash Flow Analysis'!L96 -> 0 | I35: ='Cash Flow Analysis'!M92+'Cash Flow Analysis'!M96 -> 0 | ... M35: ='Cash Flow Analysis'!Q92+'Cash Flow Analysis'!Q96 -> 0
A36: Present Value of FCF to Preferred Stock | B36: =B35/(1+$B$27)^1 -> 0 | C36: =C35/(1+$B$27)^2 -> 0 | D36: =D35/(1+$B$27)^3 -> 0 | E36: =E35/(1+$B$27)^4 -> 0 | F36: =F35/(1+$B$27)^5 -> 0 | G36: =G35/(1+$B$27)^6 -> 0 | H36: =H35/(1+$B$27)^7 -> 0 | I36: =I35/(1+$B$27)^8 -> 0 | J36: =J35/(1+$B$27)^9 -> 0 | K36: =K35/(1+$B$27)^10 -> 0 | L36: =L35/(1+$B$27)^11 -> 0 | M36: =M35/(1+$B$27)^12 -> 0
A37: Value of Preferred Stock | B37: =IF($B$27-$B$8>0,SUM(B36:L36)+(M35/($B$27-$B$8))/(1+$B$27)^11,IF(NOT(M35=0),#N/A,SUM(B36:M36))) -> 0 | C37: =IF($B$27-$B$8>0," ",IF(NOT(M35=0),"Error! cost of preferred stock <= growth rate"," "))
A39: Free Cash Flow to Noncontrolling Interest | B39: ='Cash Flow Analysis'!F93 -> 0 | C39: ='Cash Flow Analysis'!G93 -> 0 | D39: ='Cash Flow Analysis'!H93 -> 0 | E39: ='Cash Flow Analysis'!I93 -> 0 | F39: ='Cash Flow Analysis'!J93 -> 0 | G39: ='Cash Flow Analysis'!K93 -> 0 | H39: ='Cash Flow Analysis'!L93 -> 0 | I39: ='Cash Flow Analysis'!M93 -> 0 | ... M39: ='Cash Flow Analysis'!Q93 -> 0
A40: Present Value of FCF to Noncontrolling Interest | B40: =B39/(1+$B$28)^1 -> 0 | C40: =C39/(1+$B$28)^2 -> 0 | D40: =D39/(1+$B$28)^3 -> 0 | E40: =E39/(1+$B$28)^4 -> 0 | F40: =F39/(1+$B$28)^5 -> 0 | G40: =G39/(1+$B$28)^6 -> 0 | H40: =H39/(1+$B$28)^7 -> 0 | I40: =I39/(1+$B$28)^8 -> 0 | J40: =J39/(1+$B$28)^9 -> 0 | K40: =K39/(1+$B$28)^10 -> 0 | L40: =L39/(1+$B$28)^11 -> 0 | M40: =M39/(1+$B$28)^12 -> 0
A41: Value of Noncontrolling Interest | B41: =IF($B$28-$B$8>0,SUM(B40:L40)+(M39/($B$28-$B$8))/(1+$B$28)^11,IF(NOT(M39=0),#N/A,SUM(B40:M40))) -> 0 | C41: =IF($B$28-$B$8>0," ",IF(NOT(M39=0),"Error! cost of noncontrolling interest <= growth rate"," "))
A43: Free Cash Flows to Investors | B43: ='Cash Flow Analysis'!F97 -> 1167532 | C43: ='Cash Flow Analysis'!G97 -> 1206153.9 | D43: ='Cash Flow Analysis'!H97 -> 1245850.4 | E43: ='Cash Flow Analysis'!I97 -> 1286643.6 | F43: ='Cash Flow Analysis'!J97 -> 1328556.1 | G43: ='Cash Flow Analysis'!K97 -> 1371610.2 | H43: ='Cash Flow Analysis'!L97 -> 1415828.7 | I43: ='Cash Flow Analysis'!M97 -> 1461234.5 | ... M43: ='Cash Flow Analysis'!Q97 -> 1652950.3
A44: Present Value of FCF to Investors | B44: =B43/(1+$B$29)^1 -> 1064544.2 | C44: =C43/(1+$B$29)^2 -> 1002749.8 | D44: =D43/(1+$B$29)^3 -> 944388.48 | E44: =E43/(1+$B$29)^4 -> 889278.94 | F44: =F43/(1+$B$29)^5 -> 837248.83 | G44: =G43/(1+$B$29)^6 -> 788134.43 | H44: =H43/(1+$B$29)^7 -> 741780.22 | I44: =I43/(1+$B$29)^8 -> 698038.51 | J44: =J43/(1+$B$29)^9 -> 656769.08 | K44: =K43/(1+$B$29)^10 -> 617838.81 | L44: =L43/(1+$B$29)^11 -> 581121.35 | M44: =M43/(1+$B$29)^12 -> 545756.59
A45: Entity Value | B45: =IF(ISNA($B$29),#N/A,SUM(B44:L44)+(M43/($B$29-$B$8))/(1+$B$29)^11) -> 17789882 | C45: =IF(($B$29-$B$8)<=0,"Error! weighted average cost of capital <= growth rate"," ")
A46: Less Value of Net Debt | B46: =-B33 -> -1673621.7
A47: Less Value of Preferred Stock | B47: =-B37 -> 0
A48: Less Value of Noncontrolling Interest | B48: =-B41 -> 0
A49: Forecast Equity Value Before Time Adj. | B49: =B45+B46+B47+B48 -> 16116261
A50: Forecasted Value as of Valuation Date | B50: =B49*(1+(B7/2))*(1+B7*(DAYS360(B5,B6)/360)) -> 23502880
A51: Less Value of Contingent Equity Claims | B51: =-'Valuation Parameters'!J10 -> 0
A52: Value Attributable to Common Equity | B52: =B50+B51 -> 23502880
A53: Common Shares Outstanding at BS Date | B53: ='Financial Statements'!B5 -> 225100.2
A54: Equivalent Shares at Valuation Date | B54: =B53*'Valuation Parameters'!J12 -> 225100.2
A55: Forecast Price/Share | B55: =B52/B54 -> 104.41075

Sheet EPS Forecaster
A1: EPS Forecaster | B1: ($000, except per share amounts)
A4: Company Name | B4: ='Financial Statements'!B4 -> DOLLAR TREE 2021
A5: Common Shares Outstanding at BS Date | B5: ='Financial Statements'!B5 -> 225100.2
A6: Equivalent Shares at Valuation Date | B6: =B5*'Valuation Parameters'!J12 -> 225100.2
A7: Forecasted Price at Valuation Date | B7: ='Residual Income Valuations'!B27 -> 105.40825
B9: Forecast | C9: Forecast | D9: Forecast | E9: Forecast | F9: Forecast | G9: Forecast | H9: Forecast | I9: Forecast | J9: Forecast | K9: Forecast | L9: Forecast | M9: Forecast
A10: Fiscal Year of Forecast | B10: ='Financial Statements'!G8 -> 43495 | C10: ='Financial Statements'!H8 -> 43860 | D10: ='Financial Statements'!I8 -> 44226 | E10: ='Financial Statements'!J8 -> 44591 | F10: ='Financial Statements'!K8 -> 44956 | G10: ='Financial Statements'!L8 -> 45321 | H10: ='Financial Statements'!M8 -> 45687 | I10: ='Financial Statements'!N8 -> 46052 | ... M10: ='Financial Statements'!R8 -> 47513
A11: Net Income | B11: ='Financial Statements'!G29 -> 1368000.9 | C11: ='Financial Statements'!H29 -> 1411074.1 | D11: ='Financial Statements'!I29 -> 1455269.1 | E11: ='Financial Statements'!J29 -> 1500606.4 | F11: ='Financial Statements'!K29 -> 1547106.9 | G11: ='Financial Statements'!L29 -> 1594791.2 | H11: ='Financial Statements'!M29 -> 1643680.3 | I11: ='Financial Statements'!N29 -> 1693795 | ... M11: ='Financial Statements'!R29 -> 1907253.3
A12: Common Equity Issued (Repurchased) | B12: ='Cash Flow Analysis'!F39 -> -1123621.9 | C12: ='Cash Flow Analysis'!G39 -> -1160280.7 | D12: ='Cash Flow Analysis'!H39 -> -1197941.5 | E12: ='Cash Flow Analysis'!I39 -> -1236624.4 | F12: ='Cash Flow Analysis'!J39 -> -1276349.7 | G12: ='Cash Flow Analysis'!K39 -> -1317137.7 | H12: ='Cash Flow Analysis'!L39 -> -1359008.9 | I12: ='Cash Flow Analysis'!M39 -> -1401984 | ... M12: ='Cash Flow Analysis'!Q39 -> -1583872.3
A13: Forecasted Price at Year End | B13: =B7*(1+'Valuation Parameters'!J9*(DAYS360('Residual Income Valuations'!B6,'Residual Income Valuations'!B10)/360))+('Financial Statements'!G64/'EPS Forecaster'!B6)*(DAYS360('Residual Income Valuations'!B6,'Residual Income Valuations'!B10)/360) -> 74.986258 | C13: =(B13*(1+'Valuation Parameters'!J9))+('Financial Statements'!H64/'EPS Forecaster'!B15) -> 82.484884 | D13: =(C13*(1+'Valuation Parameters'!J9))+('Financial Statements'!I64/'EPS Forecaster'!C15) -> 90.733373 | E13: =(D13*(1+'Valuation Parameters'!J9))+('Financial Statements'!J64/'EPS Forecaster'!D15) -> 99.80671 | F13: =(E13*(1+'Valuation Parameters'!J9))+('Financial Statements'!K64/'EPS Forecaster'!E15) -> 109.78738 | G13: =(F13*(1+'Valuation Parameters'!J9))+('Financial Statements'!L64/'EPS Forecaster'!F15) -> 120.76612 | H13: =(G13*(1+'Valuation Parameters'!J9))+('Financial Statements'!M64/'EPS Forecaster'!G15) -> 132.84273 | I13: =(H13*(1+'Valuation Parameters'!J9))+('Financial Statements'!N64/'EPS Forecaster'!H15) -> 146.127 | J13: =(I13*(1+'Valuation Parameters'!$J$9))+('Financial Statements'!O64/'EPS Forecaster'!I15) -> 160.7397 | K13: =(J13*(1+'Valuation Parameters'!$J$9))+('Financial Statements'!P64/'EPS Forecaster'!J15) -> 176.81367 | L13: =(K13*(1+'Valuation Parameters'!$J$9))+('Financial Statements'!Q64/'EPS Forecaster'!K15) -> 194.49504 | M13: =(L13*(1+'Valuation Parameters'!$J$9))+('Financial Statements'!R64/'EPS Forecaster'!L15) -> 213.94455
A14: New Shares Issued (Repurchased) | B14: =B12/B13 -> -14984.371 | C14: =C12/C13 -> -14066.586 | D14: =D12/D13 -> -13202.877 | E14: =E12/E13 -> -12390.193 | F14: =F12/F13 -> -11625.65 | G14: =G12/G13 -> -10906.517 | H14: =H12/H13 -> -10230.209 | I14: =I12/I13 -> -9594.2844 | ... M14: =M12/M13 -> -7403.191
A15: Shares Outstanding at End of Year | B15: =B6+B14 -> 210115.83 | C15: =B15+C14 -> 196049.24 | D15: =C15+D14 -> 182846.36 | E15: =D15+E14 -> 170456.17 | F15: =E15+F14 -> 158830.52 | G15: =F15+G14 -> 147924 | H15: =G15+H14 -> 137693.79 | I15: =H15+I14 -> 128099.51 | J15: =I15+J14 -> 119103.08 | ... M15: =L15+M14 -> 95359.102
A16: Forecast EPS | B16: =B11/((B6+B15)/2) -> 6.2865375 | C16: =C11/((B15+C15)/2) -> 6.948279 | D16: =D11/((C15+D15)/2) -> 7.681636 | E16: =E11/((D15+E15)/2) -> 8.494739 | F16: =F11/((E15+F15)/2) -> 9.3967167 | G16: =G11/((F15+G15)/2) -> 10.397833 | H16: =H11/((G15+H15)/2) -> 11.509649 | I16: =I11/((H15+I15)/2) -> 12.745205 | J16: =J11/((I15+J15)/2) -> 14.11924 | ... M16: =M11/((L15+M15)/2) -> 19.253381
A17: Consensus Analyst Forecast of EPS
A19: Forecast Five Year Growth Rate in EPS | B19: =(G16/B16)^(1/5)-1 -> 0.10587558
A20: Consensus Analyst Forecast of Growth Rate
C23: =HYPERLINK(CONCATENATE("http://biz.yahoo.com/z/a/",LEFT(TRIM('Financial Statements'!D4),1),"/",TRIM('Financial Statements'!D4),".html"),"To obtain analyst forecasts, click here") -> To obtain analyst forecasts, click here

Sheet Model Summary
A1: Model Summary
A4: Historical Data For:
A5: ='Financial Statements'!B4 -> DOLLAR TREE 2021
A6: Most Recent Fiscal Year End: | B6: ='Financial Statements'!F8 -> 43130
A7: Average ROE (last five years) | B7: =AVERAGE('Ratio Analysis'!C19:F19) -> 0.066541023
A8: Sales Growth (last five years) | B8: =(('Financial Statements'!F12/'Financial Statements'!B12)^(1/4))-1 -> 0.042955739
A10: Forecast Data:
A11: Forecast Horizon | B11: 10 years
A12: This Year's ROE | B12: ='Ratio Analysis'!G19 -> 0.17447457
A13: Terminal Year's ROE | B13: ='Ratio Analysis'!Q19 -> 0.17432076
A14: This Year's Sales Growth | B14: ='Ratio Analysis'!G10 -> 0.031661462
A15: Terminal Year's Sales Growth | B15: ='Ratio Analysis'!Q10 -> 0.03
A16: This Year's Forecast EPS | B16: ='EPS Forecaster'!B16 -> 6.2865375
A17: Forecast 5 Year EPS Growth | B17: ='EPS Forecaster'!B19 -> 0.10587558
A19: Valuation Data:
A20: Cost of Equity Capital | B20: ='Valuation Parameters'!J9 -> 0.1
A21: Valuation Date | B21: ='Valuation Parameters'!J11 -> 44549
A22: Estimated Price/Share | B22: ='Residual Income Valuations'!B27 -> 105.40825
A23: Estimated Price/Earnings Ratio | B23: =B22/'Model Summary'!B16 -> 16.767298
A24: Estimated Market/Book Ratio | B24: =(B22*'Residual Income Valuations'!B26)/'Financial Statements'!F57 -> 3.074097

Sheet Case Data
A1: Click a company link below to select the associated yellow data block. Then, copy and paste the yellow data block to cell range B82:F116 on the Financial Statements sheet.
A2: AMAZON.COM INC 2000 | B2: COUNTY CINEMA 1998 | D2: NORDSTROM INC 2010 | G2: Sporting Goods Stores 2008
A3: AMERICA ONLINE INC 1999 | B3: DOLLAR TREE 2021 | D3: OVERSTOCK.COM INC 2003 | G3: TARGET 2021
A4: APPLE INC 2009 | B4: FOUR MODELS | D4: ROSS STORES INC 2010 | G4: TESLA MOTORS INC 2015
A5: CABELA'S INC 2008 | B5: INTEL CORP 1999 | D5: ROYAL CARIBBEAN CRUISES LTD 1998 | G5: VERIZON COMMUNICATIONS 2008
A6: CARNIVAL CORP 1998 | B6: INTERNATIONAL BUSINESS MACHINES CORP 2009 | D6: ROYAL CARIBBEAN CRUISES LTD 2010 | G6: WALMART 2021
A7: CARNIVAL CORP/PLC (USA) 2010 | B7: KOHL'S CORP 2010 | D7: SALTON INC 2000 | G7: ZYNGA, INC. 2011
A8: CITY SCREENS 1999 | B8: NETFLIX INC 2004 | D8: SIRIUS SATELLITE RADIO INC 2005
A10: Company Name, Ticker and SIC | B10: AMERICA ONLINE INC | D10: AOL | F10: 7374
A11: Common Shares Outstanding (000) | B11: 2255000
A12: Fiscal Year End (YYYY-MM-DD) | B12: 33418 | C12: 33784 | D12: 34149 | E12: 34514 | F12: 34879
A13: Sales (Net) | B13: 394290 | C13: 1094000 | D13: 2197000 | E13: 3091000 | F13: 4777000
A14: Cost of Goods Sold | B14: -229724 | C14: -654000 | D14: -1770000 | E14: -2434000 | F14: -3465000
A15: R&D Expense | B15: -64598 | C15: -75000 | D15: -204000 | E15: -333000 | F15: -286000
A16: SG&A Expense | B16: -119764 | C16: -293000 | D16: -605000 | E16: -328000 | F16: -408000
A17: Depreciation & Amortization | B17: -1653 | C17: -7000 | D17: -6000 | E17: -24000 | F17: -65000
A18: Interest Expense | B18: 0 | C18: 0 | D18: 0 | E18: 0 | F18: 0
A19: Non-Operating Income (Loss) | B19: 867 | C19: -3000 | D19: -87000 | E19: -62000 | F19: 543000
A20: Income Taxes | B20: -15169 | C20: -32000 | D20: -10000 | E20: 16000 | F20: -334000
A21: Noncontrolling Interest in Earnings | B21: 0 | C21: 0 | D21: 0 | E21: 0 | F21: 0
A22: Other Income (Loss) | B22: 0 | C22: 0 | D22: 0 | E22: 0 | F22: 0
A23: Ext. Items & Disc. Ops. | B23: 0 | C23: 0 | D23: 0 | E23: 0 | F23: 0
... A43: Retained Earnings | B43: -36623 | C43: -7767 | D43: -507000 | E43: -590000 | F43: 151000
A44: Common Dividends | C44: 0 | D44: 0 | E44: 0 | F44: 0
A48: Company Name, Ticker and SIC | B48: AMAZON.COM INC | D48: AMZN | F48: 5961 | G48: back to top
A49: Common Shares Outstanding (000) | B49: 357140
A50: Fiscal Year End (YYYY-MM-DD) | B50: 33968 | C50: 34333 | D50: 34698 | E50: 35063 | F50: 35429
A51: Sales (Net) | B51: 15746 | C51: 147787 | D51: 609819 | E51: 1639839 | F51: 2761983
A52: Cost of Goods Sold | B52: -12287 | C52: -118969 | D52: -476155 | E52: -1349194 | F52: -2106206
A53: R&D Expense | B53: -2401 | C53: 0 | D53: 0 | E53: 0 | F53: 0
