Workbook

Sheet Case Data
A9: Item | B9: Year 1 | C9: Year 2 | D9: Year 3 | E9: Year 4 | F9: Year 5
A10: Company Name | B10: Zoom Communications, Inc. | C10: Ticker | D10: ZM | E10: SIC
A11: Common Shares Outstanding
A12: Fiscal Year End | B12: 44560
A13: Sales | B13: 4665.433
A14: Cost of Goods Sold
A15: R&D | B15: 852.415
A16: SG&A
A17: Depreciation
A18: Interest Expense
A19: Non-Operating Income | B19: 325.147
A20: Income Tax | B20: 305.346
A21: Noncontrolling Interest
A22: Other Income | B22: 325.147
A23: Extraordinary Items
A24: Preferred Dividends
A25: Cash and Cash Equivalents | B25: 1349.38
A26: Receivables | B26: 495.228
A27: Inventories
A28: Other Current Assets | B28: 200.679
A29: Property, Plant and Equipment | B29: 330.475
A30: Investments | B30: 591.481
A31: Intangible Assets | B31: 307.295
A32: Other Assets
A33: Current Debt
A34: Accounts Payable | B34: 8.345
A35: Income Taxes Payable
A36: Other Current Liabilities | B36: 558.562
A37: Long-Term Debt
A38: Other Liabilities
A39: Deferred Taxes | B39: 749.759
A40: Noncontrolling Interest
A41: Preferred Stock
A42: Paid in Capital | B42: 0.305
A43: Retained Earnings | B43: 3799.518

Sheet Intro
A19: STEPS:
A20: 1) enter financial data on the Financial Statements sheet,
A21: 2) examine the Ratio Analysis and Cash Flow Analysis,
A22: 3) enter forecasts on the Forecasting Assumptions sheet to predict the future Financial Statements,
A23: 4) enter cost of capital assumptions on the Valuation Parameters Sheet to determine the company's value,
A24: 5) evaluate the details of the resulting valuation using either the Residual Income or Discounted Cash Flow Valuations.

Sheet Financial Statements
A1: Financial Statements | B1: ($000s) | C1: Data can be entered manually in financial statements or as a block cut-and-paste from the Case Data Sheet to the Raw Data Input section below.
C3: Jump to Raw Data Input
A4: Company Name, Ticker and SIC | B4: =B82 | D4: =D82 | E4: =F82 | F4: =IF(D4="","",HYPERLINK(CONCATENATE("http://www.sec.gov/cgi-bin/browse-edgar?type=10-K&action=getcompany&CIK=",D4),"Link to Form 10-Ks"))
A5: Common Shares Outstanding | B5: =B83 | C5: (in 000s at most recent fiscal year end) | F5: Link to Industry Comps
A6: ="Estimated Price/Share="&DOLLAR('Valuation Parameters'!B24)
B7: Actual | C7: Actual | D7: Actual | E7: Actual | F7: Actual | G7: Forecast | H7: Forecast | I7: Forecast | J7: Forecast | K7: Forecast | L7: Forecast | M7: Forecast | N7: Forecast | O7: Forecast | P7: Forecast | Q7: Forecast | R7: Forecast
A8: Fiscal Year End (YYYY-MM-DD) | B8: =B84 | C8: =C84 | D8: =D84 | E8: =E84 | F8: =F84 | G8: =DATE(YEAR(F8)+1,MONTH(F8),DAY(F8)) | H8: =DATE(YEAR(G8)+1,MONTH(G8),DAY(G8)) | I8: =DATE(YEAR(H8)+1,MONTH(H8),DAY(H8)) | J8: =DATE(YEAR(I8)+1,MONTH(I8),DAY(I8)) | K8: =DATE(YEAR(J8)+1,MONTH(J8),DAY(J8)) | L8: =DATE(YEAR(K8)+1,MONTH(K8),DAY(K8)) | M8: =DATE(YEAR(L8)+1,MONTH(L8),DAY(L8)) | N8: =DATE(YEAR(M8)+1,MONTH(M8),DAY(M8)) | ... R8: =DATE(YEAR(Q8)+1,MONTH(Q8),DAY(Q8))
A10: Income Statement
A12: Sales (Net) | B12: =B85 | C12: =C85 | D12: =D85 | E12: =E85 | F12: =F85 | G12: =F12*(1+'Forecasting Assumptions'!G14) | H12: =G12*(1+'Forecasting Assumptions'!H14) | I12: =H12*(1+'Forecasting Assumptions'!I14) | J12: =I12*(1+'Forecasting Assumptions'!J14) | K12: =J12*(1+'Forecasting Assumptions'!K14) | L12: =K12*(1+'Forecasting Assumptions'!L14) | M12: =L12*(1+'Forecasting Assumptions'!M14) | N12: =M12*(1+'Forecasting Assumptions'!N14) | ... R12: =Q12*(1+'Forecasting Assumptions'!R14)
A13: Cost of Goods Sold | B13: =B86 | C13: =C86 | D13: =D86 | E13: =E86 | F13: =F86 | G13: =-G12*'Forecasting Assumptions'!G15 | H13: =-H12*'Forecasting Assumptions'!H15 | I13: =-I12*'Forecasting Assumptions'!I15 | J13: =-J12*'Forecasting Assumptions'!J15 | K13: =-K12*'Forecasting Assumptions'!K15 | L13: =-L12*'Forecasting Assumptions'!L15 | M13: =-M12*'Forecasting Assumptions'!M15 | N13: =-N12*'Forecasting Assumptions'!N15 | ... R13: =-R12*'Forecasting Assumptions'!R15
A14: Gross Profit | B14: =B12+B13 | C14: =C12+C13 | D14: =D12+D13 | E14: =E12+E13 | F14: =F12+F13 | G14: =G12+G13 | H14: =H12+H13 | I14: =I12+I13 | ... R14: =R12+R13
A15: R&D Expense | B15: =B87 | C15: =C87 | D15: =D87 | E15: =E87 | F15: =F87 | G15: =-G12*'Forecasting Assumptions'!G16 | H15: =-H12*'Forecasting Assumptions'!H16 | I15: =-I12*'Forecasting Assumptions'!I16 | J15: =-J12*'Forecasting Assumptions'!J16 | K15: =-K12*'Forecasting Assumptions'!K16 | L15: =-L12*'Forecasting Assumptions'!L16 | M15: =-M12*'Forecasting Assumptions'!M16 | N15: =-N12*'Forecasting Assumptions'!N16 | ... R15: =-R12*'Forecasting Assumptions'!R16
A16: SG&A Expense | B16: =B88 | C16: =C88 | D16: =D88 | E16: =E88 | F16: =F88 | G16: =-G12*'Forecasting Assumptions'!G17 | H16: =-H12*'Forecasting Assumptions'!H17 | I16: =-I12*'Forecasting Assumptions'!I17 | J16: =-J12*'Forecasting Assumptions'!J17 | K16: =-K12*'Forecasting Assumptions'!K17 | L16: =-L12*'Forecasting Assumptions'!L17 | M16: =-M12*'Forecasting Assumptions'!M17 | N16: =-N12*'Forecasting Assumptions'!N17 | ... R16: =-R12*'Forecasting Assumptions'!R17
A17: EBITDA | B17: =B14+B15+B16 | C17: =C14+C15+C16 | D17: =D14+D15+D16 | E17: =E14+E15+E16 | F17: =F14+F15+F16 | G17: =G14+G15+G16 | H17: =H14+H15+H16 | I17: =I14+I15+I16 | ... R17: =R14+R15+R16
A18: Depreciation & Amortization | B18: =B89 | C18: =C89 | D18: =D89 | E18: =E89 | F18: =F89 | G18: =-((F38+G38+F40+G40)/2)*'Forecasting Assumptions'!G18 | H18: =-((G38+H38+G40+H40)/2)*'Forecasting Assumptions'!H18 | I18: =-((H38+I38+H40+I40)/2)*'Forecasting Assumptions'!I18 | J18: =-((I38+J38+I40+J40)/2)*'Forecasting Assumptions'!J18 | K18: =-((J38+K38+J40+K40)/2)*'Forecasting Assumptions'!K18 | L18: =-((K38+L38+K40+L40)/2)*'Forecasting Assumptions'!L18 | M18: =-((L38+M38+L40+M40)/2)*'Forecasting Assumptions'!M18 | N18: =-((M38+N38+M40+N40)/2)*'Forecasting Assumptions'!N18 | ... R18: =-((Q38+R38+Q40+R40)/2)*'Forecasting Assumptions'!R18
A19: EBIT | B19: =B17+B18 | C19: =C17+C18 | D19: =D17+D18 | E19: =E17+E18 | F19: =F17+F18 | G19: =G17+G18 | H19: =H17+H18 | I19: =I17+I18 | ... R19: =R17+R18
A20: Net Interest Expense | B20: =B90 | C20: =C90 | D20: =D90 | E20: =E90 | F20: =F90 | G20: =-((F44+G44+F49+G49)/2)*'Forecasting Assumptions'!G19 | H20: =-((G44+H44+G49+H49)/2)*'Forecasting Assumptions'!H19 | I20: =-((H44+I44+H49+I49)/2)*'Forecasting Assumptions'!I19 | J20: =-((I44+J44+I49+J49)/2)*'Forecasting Assumptions'!J19 | K20: =-((J44+K44+J49+K49)/2)*'Forecasting Assumptions'!K19 | L20: =-((K44+L44+K49+L49)/2)*'Forecasting Assumptions'!L19 | M20: =-((L44+M44+L49+M49)/2)*'Forecasting Assumptions'!M19 | N20: =-((M44+N44+M49+N49)/2)*'Forecasting Assumptions'!N19 | ... R20: =-((Q44+R44+Q49+R49)/2)*'Forecasting Assumptions'!R19
A21: Non-Operating Income (Loss) | B21: =B91 | C21: =C91 | D21: =D91 | E21: =E91 | F21: =F91 | G21: =G12*'Forecasting Assumptions'!G20 | H21: =H12*'Forecasting Assumptions'!H20 | I21: =I12*'Forecasting Assumptions'!I20 | J21: =J12*'Forecasting Assumptions'!J20 | K21: =K12*'Forecasting Assumptions'!K20 | L21: =L12*'Forecasting Assumptions'!L20 | M21: =M12*'Forecasting Assumptions'!M20 | N21: =N12*'Forecasting Assumptions'!N20 | ... R21: =R12*'Forecasting Assumptions'!R20
A22: EBT | B22: =B19+B20+B21 | C22: =C19+C20+C21 | D22: =D19+D20+D21 | E22: =E19+E20+E21 | F22: =F19+F20+F21 | G22: =G19+G20+G21 | H22: =H19+H20+H21 | I22: =I19+I20+I21 | ... R22: =R19+R20+R21
A23: Income Taxes | B23: =B92 | C23: =C92 | D23: =D92 | E23: =E92 | F23: =F92 | G23: =-G22*'Forecasting Assumptions'!G21 | H23: =-H22*'Forecasting Assumptions'!H21 | I23: =-I22*'Forecasting Assumptions'!I21 | J23: =-J22*'Forecasting Assumptions'!J21 | K23: =-K22*'Forecasting Assumptions'!K21 | L23: =-L22*'Forecasting Assumptions'!L21 | M23: =-M22*'Forecasting Assumptions'!M21 | N23: =-N22*'Forecasting Assumptions'!N21 | ... R23: =-R22*'Forecasting Assumptions'!R21
A24: Other Income (Loss) | B24: =B94 | C24: =C94 | D24: =D94 | E24: =E94 | F24: =F94 | G24: =G12*'Forecasting Assumptions'!G23 | H24: =H12*'Forecasting Assumptions'!H23 | I24: =I12*'Forecasting Assumptions'!I23 | J24: =J12*'Forecasting Assumptions'!J23 | K24: =K12*'Forecasting Assumptions'!K23 | L24: =L12*'Forecasting Assumptions'!L23 | M24: =M12*'Forecasting Assumptions'!M23 | N24: =N12*'Forecasting Assumptions'!N23 | ... R24: =R12*'Forecasting Assumptions'!R23
A25: Net Income Before Ext. Items | B25: =B22+B23+B24 | C25: =C22+C23+C24 | D25: =D22+D23+D24 | E25: =E22+E23+E24 | F25: =F22+F23+F24 | G25: =G22+G23+G24 | H25: =H22+H23+H24 | I25: =I22+I23+I24 | ... R25: =R22+R23+R24
A26: Ext. Items & Disc. Ops. | B26: =B95 | C26: =C95 | D26: =D95 | E26: =E95 | F26: =F95 | G26: =G12*'Forecasting Assumptions'!G24 | H26: =H12*'Forecasting Assumptions'!H24 | I26: =I12*'Forecasting Assumptions'!I24 | J26: =J12*'Forecasting Assumptions'!J24 | K26: =K12*'Forecasting Assumptions'!K24 | L26: =L12*'Forecasting Assumptions'!L24 | M26: =M12*'Forecasting Assumptions'!M24 | N26: =N12*'Forecasting Assumptions'!N24 | ... R26: =R12*'Forecasting Assumptions'!R24
A27: Noncontrolling Interest in Earnings | B27: =B93 | C27: =C93 | D27: =D93 | E27: =E93 | F27: =F93 | G27: =-(G22+G23)*'Forecasting Assumptions'!G22 | H27: =-(H22+H23)*'Forecasting Assumptions'!H22 | I27: =-(I22+I23)*'Forecasting Assumptions'!I22 | J27: =-(J22+J23)*'Forecasting Assumptions'!J22 | K27: =-(K22+K23)*'Forecasting Assumptions'!K22 | L27: =-(L22+L23)*'Forecasting Assumptions'!L22 | M27: =-(M22+M23)*'Forecasting Assumptions'!M22 | N27: =-(N22+N23)*'Forecasting Assumptions'!N22 | ... R27: =-(R22+R23)*'Forecasting Assumptions'!R22
A28: Preferred Dividends | B28: =B96 | C28: =C96 | D28: =D96 | E28: =E96 | F28: =F96 | G28: =-((G54+F54)/2)*'Forecasting Assumptions'!G25 | H28: =-((H54+G54)/2)*'Forecasting Assumptions'!H25 | I28: =-((I54+H54)/2)*'Forecasting Assumptions'!I25 | J28: =-((J54+I54)/2)*'Forecasting Assumptions'!J25 | K28: =-((K54+J54)/2)*'Forecasting Assumptions'!K25 | L28: =-((L54+K54)/2)*'Forecasting Assumptions'!L25 | M28: =-((M54+L54)/2)*'Forecasting Assumptions'!M25 | N28: =-((N54+M54)/2)*'Forecasting Assumptions'!N25 | ... R28: =-((R54+Q54)/2)*'Forecasting Assumptions'!R25
A29: Net Income (available to common) | B29: =B25+B26+B27+B28 | C29: =C25+C26+C27+C28 | D29: =D25+D26+D27+D28 | E29: =E25+E26+E27+E28 | F29: =F25+F26+F27+F28 | G29: =G25+G26+G27+G28 | H29: =H25+H26+H27+H28 | I29: =I25+I26+I27+I28 | ... R29: =R25+R26+R27+R28
B30: =IF(B13>0,"Error! -Exp?",IF(B15>0,"Error! -Exp?",IF(B16>0,"Error! -Exp?","")))
A31: Balance Sheet
A33: Operating Cash and Market. Sec. | B33: =B97 | C33: =C97 | D33: =D97 | E33: =E97 | F33: =F97 | G33: =G12*'Forecasting Assumptions'!G29 | H33: =H12*'Forecasting Assumptions'!H29 | I33: =I12*'Forecasting Assumptions'!I29 | J33: =J12*'Forecasting Assumptions'!J29 | K33: =K12*'Forecasting Assumptions'!K29 | L33: =L12*'Forecasting Assumptions'!L29 | M33: =M12*'Forecasting Assumptions'!M29 | N33: =N12*'Forecasting Assumptions'!N29 | ... R33: =R12*'Forecasting Assumptions'!R29
A34: Receivables | B34: =B98 | C34: =C98 | D34: =D98 | E34: =E98 | F34: =F98 | G34: =G12*'Forecasting Assumptions'!G30 | H34: =H12*'Forecasting Assumptions'!H30 | I34: =I12*'Forecasting Assumptions'!I30 | J34: =J12*'Forecasting Assumptions'!J30 | K34: =K12*'Forecasting Assumptions'!K30 | L34: =L12*'Forecasting Assumptions'!L30 | M34: =M12*'Forecasting Assumptions'!M30 | N34: =N12*'Forecasting Assumptions'!N30 | ... R34: =R12*'Forecasting Assumptions'!R30
A35: Inventories | B35: =B99 | C35: =C99 | D35: =D99 | E35: =E99 | F35: =F99 | G35: =-G13*'Forecasting Assumptions'!G31 | H35: =-H13*'Forecasting Assumptions'!H31 | I35: =-I13*'Forecasting Assumptions'!I31 | J35: =-J13*'Forecasting Assumptions'!J31 | K35: =-K13*'Forecasting Assumptions'!K31 | L35: =-L13*'Forecasting Assumptions'!L31 | M35: =-M13*'Forecasting Assumptions'!M31 | N35: =-N13*'Forecasting Assumptions'!N31 | ... R35: =-R13*'Forecasting Assumptions'!R31
A36: Other Current Assets | B36: =B100 | C36: =C100 | D36: =D100 | E36: =E100 | F36: =F100 | G36: =G12*'Forecasting Assumptions'!G32 | H36: =H12*'Forecasting Assumptions'!H32 | I36: =I12*'Forecasting Assumptions'!I32 | J36: =J12*'Forecasting Assumptions'!J32 | K36: =K12*'Forecasting Assumptions'!K32 | L36: =L12*'Forecasting Assumptions'!L32 | M36: =M12*'Forecasting Assumptions'!M32 | N36: =N12*'Forecasting Assumptions'!N32 | ... R36: =R12*'Forecasting Assumptions'!R32
A37: Total Current Assets | B37: =SUM(B33:B36) | C37: =SUM(C33:C36) | D37: =SUM(D33:D36) | E37: =SUM(E33:E36) | F37: =SUM(F33:F36) | G37: =SUM(G33:G36) | H37: =SUM(H33:H36) | I37: =SUM(I33:I36) | ... R37: =SUM(R33:R36)
A38: PP&E (Net) | B38: =B101 | C38: =C101 | D38: =D101 | E38: =E101 | F38: =F101 | G38: =G12*'Forecasting Assumptions'!G37 | H38: =H12*'Forecasting Assumptions'!H37 | I38: =I12*'Forecasting Assumptions'!I37 | J38: =J12*'Forecasting Assumptions'!J37 | K38: =K12*'Forecasting Assumptions'!K37 | L38: =L12*'Forecasting Assumptions'!L37 | M38: =M12*'Forecasting Assumptions'!M37 | N38: =N12*'Forecasting Assumptions'!N37 | ... R38: =R12*'Forecasting Assumptions'!R37
A39: Investments | B39: =B102 | C39: =C102 | D39: =D102 | E39: =E102 | F39: =F102 | G39: =G12*'Forecasting Assumptions'!G38 | H39: =H12*'Forecasting Assumptions'!H38 | I39: =I12*'Forecasting Assumptions'!I38 | J39: =J12*'Forecasting Assumptions'!J38 | K39: =K12*'Forecasting Assumptions'!K38 | L39: =L12*'Forecasting Assumptions'!L38 | M39: =M12*'Forecasting Assumptions'!M38 | N39: =N12*'Forecasting Assumptions'!N38 | ... R39: =R12*'Forecasting Assumptions'!R38
A40: Intangibles | B40: =B103 | C40: =C103 | D40: =D103 | E40: =E103 | F40: =F103 | G40: =G12*'Forecasting Assumptions'!G39 | H40: =H12*'Forecasting Assumptions'!H39 | I40: =I12*'Forecasting Assumptions'!I39 | J40: =J12*'Forecasting Assumptions'!J39 | K40: =K12*'Forecasting Assumptions'!K39 | L40: =L12*'Forecasting Assumptions'!L39 | M40: =M12*'Forecasting Assumptions'!M39 | N40: =N12*'Forecasting Assumptions'!N39 | ... R40: =R12*'Forecasting Assumptions'!R39
A41: Other Assets | B41: =B104 | C41: =C104 | D41: =D104 | E41: =E104 | F41: =F104 | G41: =G12*'Forecasting Assumptions'!G40 | H41: =H12*'Forecasting Assumptions'!H40 | I41: =I12*'Forecasting Assumptions'!I40 | J41: =J12*'Forecasting Assumptions'!J40 | K41: =K12*'Forecasting Assumptions'!K40 | L41: =L12*'Forecasting Assumptions'!L40 | M41: =M12*'Forecasting Assumptions'!M40 | N41: =N12*'Forecasting Assumptions'!N40 | ... R41: =R12*'Forecasting Assumptions'!R40
A42: Total Assets | B42: =SUM(B37:B41) | C42: =SUM(C37:C41) | D42: =SUM(D37:D41) | E42: =SUM(E37:E41) | F42: =SUM(F37:F41) | G42: =G37+G38+G39+G40+G41 | H42: =H37+H38+H39+H40+H41 | I42: =I37+I38+I39+I40+I41 | J42: =J37+J38+J39+J40+J41 | K42: =K37+K38+K39+K40+K41 | L42: =L37+L38+L39+L40+L41 | M42: =M37+M38+M39+M40+M41 | N42: =N37+N38+N39+N40+N41 | ... R42: =R37+R38+R39+R40+R41
A44: Current Debt | B44: =B105 | C44: =C105 | D44: =D105 | E44: =E105 | F44: =F105 | G44: =G42*'Forecasting Assumptions'!G45 | H44: =H42*'Forecasting Assumptions'!H45 | I44: =I42*'Forecasting Assumptions'!I45 | J44: =J42*'Forecasting Assumptions'!J45 | K44: =K42*'Forecasting Assumptions'!K45 | L44: =L42*'Forecasting Assumptions'!L45 | M44: =M42*'Forecasting Assumptions'!M45 | N44: =N42*'Forecasting Assumptions'!N45 | ... R44: =R42*'Forecasting Assumptions'!R45
A45: Accounts Payable | B45: =B106 | C45: =C106 | D45: =D106 | E45: =E106 | F45: =F106 | G45: =-G13*'Forecasting Assumptions'!G33 | H45: =-H13*'Forecasting Assumptions'!H33 | I45: =-I13*'Forecasting Assumptions'!I33 | J45: =-J13*'Forecasting Assumptions'!J33 | K45: =-K13*'Forecasting Assumptions'!K33 | L45: =-L13*'Forecasting Assumptions'!L33 | M45: =-M13*'Forecasting Assumptions'!M33 | N45: =-N13*'Forecasting Assumptions'!N33 | ... R45: =-R13*'Forecasting Assumptions'!R33
A46: Income Taxes Payable | B46: =B107 | C46: =C107 | D46: =D107 | E46: =E107 | F46: =F107 | G46: =G12*'Forecasting Assumptions'!G34 | H46: =H12*'Forecasting Assumptions'!H34 | I46: =I12*'Forecasting Assumptions'!I34 | J46: =J12*'Forecasting Assumptions'!J34 | K46: =K12*'Forecasting Assumptions'!K34 | L46: =L12*'Forecasting Assumptions'!L34 | M46: =M12*'Forecasting Assumptions'!M34 | N46: =N12*'Forecasting Assumptions'!N34 | ... R46: =R12*'Forecasting Assumptions'!R34
A47: Other Current Liabilities | B47: =B108 | C47: =C108 | D47: =D108 | E47: =E108 | F47: =F108 | G47: =G12*'Forecasting Assumptions'!G35 | H47: =H12*'Forecasting Assumptions'!H35 | I47: =I12*'Forecasting Assumptions'!I35 | J47: =J12*'Forecasting Assumptions'!J35 | K47: =K12*'Forecasting Assumptions'!K35 | L47: =L12*'Forecasting Assumptions'!L35 | M47: =M12*'Forecasting Assumptions'!M35 | N47: =N12*'Forecasting Assumptions'!N35 | ... R47: =R12*'Forecasting Assumptions'!R35
A48: Total Current Liabilities | B48: =SUM(B44:B47) | C48: =SUM(C44:C47) | D48: =SUM(D44:D47) | E48: =SUM(E44:E47) | F48: =SUM(F44:F47) | G48: =G44+G45+G46+G47 | H48: =H44+H45+H46+H47 | I48: =I44+I45+I46+I47 | J48: =J44+J45+J46+J47 | K48: =K44+K45+K46+K47 | L48: =L44+L45+L46+L47 | M48: =M44+M45+M46+M47 | N48: =N44+N45+N46+N47 | ... R48: =R44+R45+R46+R47
A49: Long-Term Debt | B49: =B109 | C49: =C109 | D49: =D109 | E49: =E109 | F49: =F109 | G49: =G42*'Forecasting Assumptions'!G46 | H49: =H42*'Forecasting Assumptions'!H46 | I49: =I42*'Forecasting Assumptions'!I46 | J49: =J42*'Forecasting Assumptions'!J46 | K49: =K42*'Forecasting Assumptions'!K46 | L49: =L42*'Forecasting Assumptions'!L46 | M49: =M42*'Forecasting Assumptions'!M46 | N49: =N42*'Forecasting Assumptions'!N46 | ... R49: =R42*'Forecasting Assumptions'!R46
A50: Other Liabilities | B50: =B110 | C50: =C110 | D50: =D110 | E50: =E110 | F50: =F110 | G50: =G12*'Forecasting Assumptions'!G42 | H50: =H12*'Forecasting Assumptions'!H42 | I50: =I12*'Forecasting Assumptions'!I42 | J50: =J12*'Forecasting Assumptions'!J42 | K50: =K12*'Forecasting Assumptions'!K42 | L50: =L12*'Forecasting Assumptions'!L42 | M50: =M12*'Forecasting Assumptions'!M42 | N50: =N12*'Forecasting Assumptions'!N42 | ... R50: =R12*'Forecasting Assumptions'!R42
A51: Deferred Taxes | B51: =B111 | C51: =C111 | D51: =D111 | E51: =E111 | F51: =F111 | G51: =G12*'Forecasting Assumptions'!G43 | H51: =H12*'Forecasting Assumptions'!H43 | I51: =I12*'Forecasting Assumptions'!I43 | J51: =J12*'Forecasting Assumptions'!J43 | K51: =K12*'Forecasting Assumptions'!K43 | L51: =L12*'Forecasting Assumptions'!L43 | M51: =M12*'Forecasting Assumptions'!M43 | N51: =N12*'Forecasting Assumptions'!N43 | ... R51: =R12*'Forecasting Assumptions'!R43
A52: Total Liabilities | B52: =SUM(B48:B51) | C52: =SUM(C48:C51) | D52: =SUM(D48:D51) | E52: =SUM(E48:E51) | F52: =SUM(F48:F51) | G52: =SUM(G48:G51) | H52: =SUM(H48:H51) | I52: =SUM(I48:I51) | ... R52: =SUM(R48:R51)
A53: Noncontrolling Interest | B53: =B112 | C53: =C112 | D53: =D112 | E53: =E112 | F53: =F112 | G53: =G42*'Forecasting Assumptions'!G47 | H53: =H42*'Forecasting Assumptions'!H47 | I53: =I42*'Forecasting Assumptions'!I47 | J53: =J42*'Forecasting Assumptions'!J47 | K53: =K42*'Forecasting Assumptions'!K47 | L53: =L42*'Forecasting Assumptions'!L47 | M53: =M42*'Forecasting Assumptions'!M47 | N53: =N42*'Forecasting Assumptions'!N47 | ... R53: =R42*'Forecasting Assumptions'!R47
A54: Preferred Stock | B54: =B113 | C54: =C113 | D54: =D113 | E54: =E113 | F54: =F113 | G54: =G42*'Forecasting Assumptions'!G48 | H54: =H42*'Forecasting Assumptions'!H48 | I54: =I42*'Forecasting Assumptions'!I48 | J54: =J42*'Forecasting Assumptions'!J48 | K54: =K42*'Forecasting Assumptions'!K48 | L54: =L42*'Forecasting Assumptions'!L48 | M54: =M42*'Forecasting Assumptions'!M48 | N54: =N42*'Forecasting Assumptions'!N48 | ... R54: =R42*'Forecasting Assumptions'!R48
A55: Paid in Common Capital (Net) | B55: =B114 | C55: =C114 | D55: =D114 | E55: =E114 | F55: =F114 | G55: =G57-G56 | H55: =H57-H56 | I55: =I57-I56 | J55: =J57-J56 | K55: =K57-K56 | L55: =L57-L56 | M55: =M57-M56 | N55: =N57-N56 | ... R55: =R57-R56
A56: Retained Earnings | B56: =B115 | C56: =C115 | D56: =D115 | E56: =E115 | F56: =F115 | G56: =G66 | H56: =H66 | I56: =I66 | J56: =J66 | K56: =K66 | L56: =L66 | M56: =M66 | N56: =N66 | ... R56: =R66
A57: Total Common Equity | B57: =SUM(B55:B56) | C57: =SUM(C55:C56) | D57: =SUM(D55:D56) | E57: =SUM(E55:E56) | F57: =SUM(F55:F56) | G57: =G58-G52-G53-G54 | H57: =H58-H52-H53-H54 | I57: =I58-I52-I53-I54 | J57: =J58-J52-J53-J54 | K57: =K58-K52-K53-K54 | L57: =L58-L52-L53-L54 | M57: =M58-M52-M53-M54 | N57: =N58-N52-N53-N54 | ... R57: =R58-R52-R53-R54
A58: Total Liabilities and Equity | B58: =SUM(B52:B56) | C58: =SUM(C52:C56) | D58: =SUM(D52:D56) | E58: =SUM(E52:E56) | F58: =SUM(F52:F56) | G58: =G42 | H58: =H42 | I58: =I42 | J58: =J42 | K58: =K42 | L58: =L42 | M58: =M42 | N58: =N42 | ... R58: =R42
B59: =IF(B58=B42," ","Error! A =L+E?") | C59: =IF(C58=C42," ","Error! A =L+E?") | D59: =IF(D58=D42," ","Error! A =L+E?") | E59: =IF(E58=E42," ","Error! A =L+E?") | F59: =IF(F58=F42," ","Error! A =L+E?") | G59: =IF(G58=G42," ","Error! A =L+E?") | H59: =IF(H58=H42," ","Error! A =L+E?") | I59: =IF(I58=I42," ","Error! A =L+E?") | ... R59: =IF(R58=R42," ","Error! A =L+E?")
A60: Statement of Retained Earnings
A62: Beg. Retained Earnings | C62: =B56 | D62: =C56 | E62: =D56 | F62: =E56 | G62: =F56 | H62: =G56 | I62: =H56 | J62: =I56 | ... R62: =Q56
A63: +Net Income | C63: =C29 | D63: =D29 | E63: =E29 | F63: =F29 | G63: =G29 | H63: =H29 | I63: =I29 | J63: =J29 | ... R63: =R29
A64: -Common Dividends | B64: =-B116 | C64: =-C116 | D64: =-D116 | E64: =-E116 | F64: =-F116 | G64: =-G29*'Forecasting Assumptions'!G49 | H64: =-H29*'Forecasting Assumptions'!H49 | I64: =-I29*'Forecasting Assumptions'!I49 | J64: =-J29*'Forecasting Assumptions'!J49 | K64: =-K29*'Forecasting Assumptions'!K49 | L64: =-L29*'Forecasting Assumptions'!L49 | M64: =-M29*'Forecasting Assumptions'!M49 | N64: =-N29*'Forecasting Assumptions'!N49 | ... R64: =-R29*'Forecasting Assumptions'!R49
A65: +/-Clean Surplus Plug (Ignore) | C65: =C66-C62-C63-C64 | D65: =D66-D62-D63-D64 | E65: =E66-E62-E63-E64 | F65: =F66-F62-F63-F64 | G65: 0 | H65: 0 | I65: 0 | J65: 0 | K65: 0 | L65: 0 | M65: 0 | N65: 0 | O65: 0 | P65: 0 | Q65: 0 | R65: 0
A66: =End. Retained Earnings | C66: =C56 | D66: =D56 | E66: =E56 | F66: =F56 | G66: =G62+G63+G64+G65 | H66: =H62+H63+H64+H65 | I66: =I62+I63+I64+I65 | J66: =J62+J63+J64+J65 | K66: =K62+K63+K64+K65 | L66: =L62+L63+L64+L65 | M66: =M62+M63+M64+M65 | N66: =N62+N63+N64+N65 | ... R66: =R62+R63+R64+R65
A69: Values for Dupont Analysis and Valuation
A71: Net Operating Income | B71: =B73-B72 | C71: =C73-C72 | D71: =D73-D72 | E71: =E73-E72 | F71: =F73-F72 | G71: =G73-G72 | H71: =H73-H72 | I71: =I73-I72 | ... R71: =R73-R72
A72: Net Financial Expense | B72: =B20*(1-B74)+B28+B27 | C72: =C20*(1-C74)+C28+C27 | D72: =D20*(1-D74)+D28+D27 | E72: =E20*(1-E74)+E28+E27 | F72: =F20*(1-F74)+F28+F27 | G72: =G20*(1-G74)+G28+G27 | H72: =H20*(1-H74)+H28+H27 | I72: =I20*(1-I74)+I28+I27 | ... R72: =R20*(1-R74)+R28+R27
A73: Net Income | B73: =B29 | C73: =C29 | D73: =D29 | E73: =E29 | F73: =F29 | G73: =G29 | H73: =H29 | I73: =I29 | ... R73: =R29
A74: Effective Tax Rate | B74: =-B23/B22 | C74: =-C23/C22 | D74: =-D23/D22 | E74: =-E23/E22 | F74: =-F23/F22 | G74: =-G23/G22 | H74: =-H23/H22 | I74: =-I23/I22 | ... R74: =-R23/R22
A75: Net Operating Assets | B75: =B77+B76 | C75: =C77+C76 | D75: =D77+D76 | E75: =E77+E76 | F75: =F77+F76 | G75: =G77+G76 | H75: =H77+H76 | I75: =I77+I76 | ... R75: =R77+R76
A76: Net Financial Obligations | B76: =B44+B49+B54+B53 | C76: =C44+C49+C54+C53 | D76: =D44+D49+D54+D53 | E76: =E44+E49+E54+E53 | F76: =F44+F49+F54+F53 | G76: =G44+G49+G54+G53 | H76: =H44+H49+H54+H53 | I76: =I44+I49+I54+I53 | ... R76: =R44+R49+R54+R53
A77: Total Common Equity | B77: =B57 | C77: =C57 | D77: =D57 | E77: =E57 | F77: =F57 | G77: =G57 | H77: =H57 | I77: =I57 | ... R77: =R57
A80: Raw Data Inputs | B80: cut-and-paste raw data block from DataMaker file here
A82: Company Name and Ticker | B82: Zoom Communications, Inc. ZM | D82: DLTR | F82: 5331 | G82: A Windows vs Macintosh issue can cause the fiscal year end dates to be off by roughly 4 years. If this occurs, select and copy the 1462 cell below, select the cells with the dates, choose Paste Special Values and select Subtract or Add.
A83: Common Shares Outstanding
A84: Fiscal Year End (YYYY-MM-DD) | B84: 44560 | C84: 42034 | D84: 42399 | E84: 42765 | F84: 43130
A85: Sales (Net) | B85: 4665.433 | C85: 22823300 | D85: 23610800 | E85: 25509300 | F85: 26321200
A86: Cost of Goods Sold | C86: -15875800 | D86: -16570100 | E86: -17721900 | F86: -18595300
A87: R&D Expense | B87: 852.415 | C87: 0 | D87: 0 | E87: 0 | F87: 0 | G87: 1462
A88: SG&A Expense | C88: -7887000 | D88: -5778500 | E88: -5899500 | F88: -5914500
A89: Depreciation & Amortization | C89: 0 | D89: 0 | E89: 0 | F89: 0
A90: Interest Expense | C90: -370000 | D90: -162100 | E90: -147300 | F90: -178900
A91: Non-Operating Income (Loss) | B91: 325.147 | C91: 500 | D91: -1400 | E91: -800 | F91: -300
A92: Income Taxes | B92: 305.346 | C92: -281800 | D92: -271700 | E92: -397900 | F92: -304300
A93: Noncontrolling Interest in Earnings | C93: 0 | D93: 0 | E93: 0 | F93: 0
A94: Other Income (Loss) | B94: 325.147 | C94: 0 | D94: 0 | E94: 0 | F94: 0
A95: Ext. Items & Disc. Ops. | B95: 0 | C95: 0 | D95: 0 | E95: 0 | F95: 0
A96: Preferred Dividends | B96: 0 | C96: 0 | D96: 0 | E96: 0 | F96: 0
A97: Operating Cash and Market. Sec. | B97: 1097800 | C97: 446700 | D97: 586000 | E97: 1463600 | F97: 1038300
A98: Receivables | B98: 0 | C98: 100900 | D98: 0 | E98: 0 | F98: 0
A99: Inventories | B99: 3169300 | C99: 3536000 | D99: 3522000 | E99: 3427000 | F99: 4367300
A100: Other Current Assets | B100: 309200 | C100: 209700 | D100: 161400 | E100: 160200 | F100: 203600
A101: PP&E (Net) | B101: 3200700 | C101: 3445300 | D101: 3881800 | E101: 4116300 | F101: 4477300
A102: Investments | B102: 0 | C102: 0 | D102: 0 | E102: 0 | F102: 0
A103: Intangibles | B103: 5025200 | C103: 5685300 | D103: 5083300 | E103: 5084400 | F103: 5084400
A104: Other Assets | B104: 3530600 | C104: 77300 | D104: 6340100 | E104: 6444500 | F104: 6550900
A105: Current Debt | B105: 915900 | C105: 0 | D105: 250000 | E105: 0 | F105: 0
... A116: Common Dividends | B116: 0 | C116: 0 | D116: 0 | E116: 0 | F116: 0
A119: Industry Analysis | B119: Link to Financial Statements
A121: Sector (Fama-French 12 Industry) | B121: =VLOOKUP(E4,Master!$F$1:$I$445,2,FALSE)
A122: Industry (Fama-French 49 Industry) | B122: =VLOOKUP(E4,Master!$F$1:$I$445,3,FALSE)
A123: Sub-Industry (SEC SIC Code Title) | B123: =VLOOKUP(E4,Master!$F$1:$I$445,4,FALSE)
A125: Comparables (Same SIC Code)
A126: Ticker | B126: Company Name
...

Sheet Ratio Analysis
A1: Ratio Analysis
A4: Company Name | B4: ='Financial Statements'!B4
B6: Actual | C6: Actual | D6: Actual | E6: Actual | F6: Actual | G6: Forecast | H6: Forecast | I6: Forecast | J6: Forecast | K6: Forecast | L6: Forecast | M6: Forecast | N6: Forecast | O6: Forecast | P6: Forecast | Q6: Forecast | R6: Forecast
A7: Fiscal Year End Date | B7: ='Financial Statements'!B8 | C7: ='Financial Statements'!C8 | D7: ='Financial Statements'!D8 | E7: ='Financial Statements'!E8 | F7: ='Financial Statements'!F8 | G7: ='Financial Statements'!G8 | H7: ='Financial Statements'!H8 | I7: ='Financial Statements'!I8 | ... R7: ='Financial Statements'!R8
A9: Annual Growth Rates
A10: Sales | C10: ='Financial Statements'!C12/'Financial Statements'!B12-1 | D10: ='Financial Statements'!D12/'Financial Statements'!C12-1 | E10: ='Financial Statements'!E12/'Financial Statements'!D12-1 | F10: ='Financial Statements'!F12/'Financial Statements'!E12-1 | G10: ='Financial Statements'!G12/'Financial Statements'!F12-1 | H10: ='Financial Statements'!H12/'Financial Statements'!G12-1 | I10: ='Financial Statements'!I12/'Financial Statements'!H12-1 | J10: ='Financial Statements'!J12/'Financial Statements'!I12-1 | ... R10: ='Financial Statements'!R12/'Financial Statements'!Q12-1
A11: Assets | C11: =IF('Financial Statements'!B42<=0,#N/A,'Financial Statements'!C42/'Financial Statements'!B42-1) | D11: =IF('Financial Statements'!C42<=0,#N/A,'Financial Statements'!D42/'Financial Statements'!C42-1) | E11: =IF('Financial Statements'!D42<=0,#N/A,'Financial Statements'!E42/'Financial Statements'!D42-1) | F11: =IF('Financial Statements'!E42<=0,#N/A,'Financial Statements'!F42/'Financial Statements'!E42-1) | G11: =IF('Financial Statements'!F42<=0,#N/A,'Financial Statements'!G42/'Financial Statements'!F42-1) | H11: =IF('Financial Statements'!G42<=0,#N/A,'Financial Statements'!H42/'Financial Statements'!G42-1) | I11: =IF('Financial Statements'!H42<=0,#N/A,'Financial Statements'!I42/'Financial Statements'!H42-1) | J11: =IF('Financial Statements'!I42<=0,#N/A,'Financial Statements'!J42/'Financial Statements'!I42-1) | ... R11: =IF('Financial Statements'!Q42<=0,#N/A,'Financial Statements'!R42/'Financial Statements'!Q42-1)
A12: Common Equity | C12: =IF('Financial Statements'!B57<=0,#N/A,'Financial Statements'!C57/'Financial Statements'!B57-1) | D12: =IF('Financial Statements'!C57<=0,#N/A,'Financial Statements'!D57/'Financial Statements'!C57-1) | E12: =IF('Financial Statements'!D57<=0,#N/A,'Financial Statements'!E57/'Financial Statements'!D57-1) | F12: =IF('Financial Statements'!E57<=0,#N/A,'Financial Statements'!F57/'Financial Statements'!E57-1) | G12: =IF('Financial Statements'!F57<=0,#N/A,'Financial Statements'!G57/'Financial Statements'!F57-1) | H12: =IF('Financial Statements'!G57<=0,#N/A,'Financial Statements'!H57/'Financial Statements'!G57-1) | I12: =IF('Financial Statements'!H57<=0,#N/A,'Financial Statements'!I57/'Financial Statements'!H57-1) | J12: =IF('Financial Statements'!I57<=0,#N/A,'Financial Statements'!J57/'Financial Statements'!I57-1) | ... R12: =IF('Financial Statements'!Q57<=0,#N/A,'Financial Statements'!R57/'Financial Statements'!Q57-1)
A13: Earnings | C13: =IF('Financial Statements'!B29<=0,#N/A,'Financial Statements'!C29/'Financial Statements'!B29-1) | D13: =IF('Financial Statements'!C29<=0,#N/A,'Financial Statements'!D29/'Financial Statements'!C29-1) | E13: =IF('Financial Statements'!D29<=0,#N/A,'Financial Statements'!E29/'Financial Statements'!D29-1) | F13: =IF('Financial Statements'!E29<=0,#N/A,'Financial Statements'!F29/'Financial Statements'!E29-1) | G13: =IF('Financial Statements'!F29<=0,#N/A,'Financial Statements'!G29/'Financial Statements'!F29-1) | H13: =IF('Financial Statements'!G29<=0,#N/A,'Financial Statements'!H29/'Financial Statements'!G29-1) | I13: =IF('Financial Statements'!H29<=0,#N/A,'Financial Statements'!I29/'Financial Statements'!H29-1) | J13: =IF('Financial Statements'!I29<=0,#N/A,'Financial Statements'!J29/'Financial Statements'!I29-1) | ... R13: =IF('Financial Statements'!Q29<=0,#N/A,'Financial Statements'!R29/'Financial Statements'!Q29-1)
A14: Free Cash Flow to Investors | D14: =IF('Cash Flow Analysis'!B116<=0,#N/A,'Cash Flow Analysis'!C116/'Cash Flow Analysis'!B116-1) | E14: =IF('Cash Flow Analysis'!C116<=0,#N/A,'Cash Flow Analysis'!D116/'Cash Flow Analysis'!C116-1) | F14: =IF('Cash Flow Analysis'!D116<=0,#N/A,'Cash Flow Analysis'!E116/'Cash Flow Analysis'!D116-1) | G14: =IF('Cash Flow Analysis'!E116<=0,#N/A,'Cash Flow Analysis'!F116/'Cash Flow Analysis'!E116-1) | H14: =IF('Cash Flow Analysis'!F116<=0,#N/A,'Cash Flow Analysis'!G116/'Cash Flow Analysis'!F116-1) | I14: =IF('Cash Flow Analysis'!G116<=0,#N/A,'Cash Flow Analysis'!H116/'Cash Flow Analysis'!G116-1) | J14: =IF('Cash Flow Analysis'!H116<=0,#N/A,'Cash Flow Analysis'!I116/'Cash Flow Analysis'!H116-1) | K14: =IF('Cash Flow Analysis'!I116<=0,#N/A,'Cash Flow Analysis'!J116/'Cash Flow Analysis'!I116-1) | ... R14: =IF('Cash Flow Analysis'!P116<=0,#N/A,'Cash Flow Analysis'!Q116/'Cash Flow Analysis'!P116-1)
A15: Sustainable Growth Rate | D15: =D19*(1-'Forecasting Assumptions'!D49) | E15: =E19*(1-'Forecasting Assumptions'!E49) | F15: =F19*(1-'Forecasting Assumptions'!F49) | G15: =G19*(1-'Forecasting Assumptions'!G49) | H15: =H19*(1-'Forecasting Assumptions'!H49) | I15: =I19*(1-'Forecasting Assumptions'!I49) | J15: =J19*(1-'Forecasting Assumptions'!J49) | K15: =K19*(1-'Forecasting Assumptions'!K49) | ... R15: =R19*(1-'Forecasting Assumptions'!R49)
A18: Profitability
A19: Return on Equity | C19: ='Financial Statements'!C73/(('Financial Statements'!B77+'Financial Statements'!C77)/2) | D19: ='Financial Statements'!D73/(('Financial Statements'!C77+'Financial Statements'!D77)/2) | E19: ='Financial Statements'!E73/(('Financial Statements'!D77+'Financial Statements'!E77)/2) | F19: ='Financial Statements'!F73/(('Financial Statements'!E77+'Financial Statements'!F77)/2) | G19: ='Financial Statements'!G73/(('Financial Statements'!F77+'Financial Statements'!G77)/2) | H19: ='Financial Statements'!H73/(('Financial Statements'!G77+'Financial Statements'!H77)/2) | I19: ='Financial Statements'!I73/(('Financial Statements'!H77+'Financial Statements'!I77)/2) | J19: ='Financial Statements'!J73/(('Financial Statements'!I77+'Financial Statements'!J77)/2) | ... R19: ='Financial Statements'!R73/(('Financial Statements'!Q77+'Financial Statements'!R77)/2)
A20: Return on Equity (b4 non-recurring) | C20: =('Financial Statements'!C29-'Financial Statements'!C26-'Financial Statements'!C24-((IF('Financial Statements'!C22=0,0,('Financial Statements'!C22+'Financial Statements'!C23)/'Financial Statements'!C22))*'Financial Statements'!C21))/(('Financial Statements'!B77+'Financial Statements'!C77)/2) | D20: =('Financial Statements'!D29-'Financial Statements'!D26-'Financial Statements'!D24-((IF('Financial Statements'!D22=0,0,('Financial Statements'!D22+'Financial Statements'!D23)/'Financial Statements'!D22))*'Financial Statements'!D21))/(('Financial Statements'!C77+'Financial Statements'!D77)/2) | E20: =('Financial Statements'!E29-'Financial Statements'!E26-'Financial Statements'!E24-((IF('Financial Statements'!E22=0,0,('Financial Statements'!E22+'Financial Statements'!E23)/'Financial Statements'!E22))*'Financial Statements'!E21))/(('Financial Statements'!D77+'Financial Statements'!E77)/2) | F20: =('Financial Statements'!F29-'Financial Statements'!F26-'Financial Statements'!F24-((IF('Financial Statements'!F22=0,0,('Financial Statements'!F22+'Financial Statements'!F23)/'Financial Statements'!F22))*'Financial Statements'!F21))/(('Financial Statements'!E77+'Financial Statements'!F77)/2) | G20: =('Financial Statements'!G29-'Financial Statements'!G26-'Financial Statements'!G24-((IF('Financial Statements'!G22=0,0,('Financial Statements'!G22+'Financial Statements'!G23)/'Financial Statements'!G22))*'Financial Statements'!G21))/(('Financial Statements'!F77+'Financial Statements'!G77)/2) | H20: =('Financial Statements'!H29-'Financial Statements'!H26-'Financial Statements'!H24-((IF('Financial Statements'!H22=0,0,('Financial Statements'!H22+'Financial Statements'!H23)/'Financial Statements'!H22))*'Financial Statements'!H21))/(('Financial Statements'!G77+'Financial Statements'!H77)/2) | I20: =('Financial Statements'!I29-'Financial Statements'!I26-'Financial Statements'!I24-((IF('Financial Statements'!I22=0,0,('Financial Statements'!I22+'Financial Statements'!I23)/'Financial Statements'!I22))*'Financial Statements'!I21))/(('Financial Statements'!H77+'Financial Statements'!I77)/2) | J20: =('Financial Statements'!J29-'Financial Statements'!J26-'Financial Statements'!J24-((IF('Financial Statements'!J22=0,0,('Financial Statements'!J22+'Financial Statements'!J23)/'Financial Statements'!J22))*'Financial Statements'!J21))/(('Financial Statements'!I77+'Financial Statements'!J77)/2) | ... R20: =('Financial Statements'!R29-'Financial Statements'!R26-'Financial Statements'!R24-((IF('Financial Statements'!R22=0,0,('Financial Statements'!R22+'Financial Statements'!R23)/'Financial Statements'!R22))*'Financial Statements'!R21))/(('Financial Statements'!Q77+'Financial Statements'!R77)/2)
A21: Return on Net Operating Assets | C21: ='Financial Statements'!C71/(('Financial Statements'!B75+'Financial Statements'!C75)/2) | D21: ='Financial Statements'!D71/(('Financial Statements'!C75+'Financial Statements'!D75)/2) | E21: ='Financial Statements'!E71/(('Financial Statements'!D75+'Financial Statements'!E75)/2) | F21: ='Financial Statements'!F71/(('Financial Statements'!E75+'Financial Statements'!F75)/2) | G21: ='Financial Statements'!G71/(('Financial Statements'!F75+'Financial Statements'!G75)/2) | H21: ='Financial Statements'!H71/(('Financial Statements'!G75+'Financial Statements'!H75)/2) | I21: ='Financial Statements'!I71/(('Financial Statements'!H75+'Financial Statements'!I75)/2) | J21: ='Financial Statements'!J71/(('Financial Statements'!I75+'Financial Statements'!J75)/2) | ... R21: ='Financial Statements'!R71/(('Financial Statements'!Q75+'Financial Statements'!R75)/2)
A23: Basic Dupont Model
A24: Net Profit Margin | B24: ='Financial Statements'!B29/'Financial Statements'!B12 | C24: ='Financial Statements'!C29/'Financial Statements'!C12 | D24: ='Financial Statements'!D29/'Financial Statements'!D12 | E24: ='Financial Statements'!E29/'Financial Statements'!E12 | F24: ='Financial Statements'!F29/'Financial Statements'!F12 | G24: ='Financial Statements'!G29/'Financial Statements'!G12 | H24: ='Financial Statements'!H29/'Financial Statements'!H12 | I24: ='Financial Statements'!I29/'Financial Statements'!I12 | ... R24: ='Financial Statements'!R29/'Financial Statements'!R12
A25: x Total Asset Turnover | C25: ='Financial Statements'!C12/(('Financial Statements'!B42+'Financial Statements'!C42)/2) | D25: ='Financial Statements'!D12/(('Financial Statements'!C42+'Financial Statements'!D42)/2) | E25: ='Financial Statements'!E12/(('Financial Statements'!D42+'Financial Statements'!E42)/2) | F25: ='Financial Statements'!F12/(('Financial Statements'!E42+'Financial Statements'!F42)/2) | G25: ='Financial Statements'!G12/(('Financial Statements'!F42+'Financial Statements'!G42)/2) | H25: ='Financial Statements'!H12/(('Financial Statements'!G42+'Financial Statements'!H42)/2) | I25: ='Financial Statements'!I12/(('Financial Statements'!H42+'Financial Statements'!I42)/2) | J25: ='Financial Statements'!J12/(('Financial Statements'!I42+'Financial Statements'!J42)/2) | ... R25: ='Financial Statements'!R12/(('Financial Statements'!Q42+'Financial Statements'!R42)/2)
A26: x Total Leverage | C26: =('Financial Statements'!B58+'Financial Statements'!C58)/('Financial Statements'!B57+'Financial Statements'!C57) | D26: =('Financial Statements'!C58+'Financial Statements'!D58)/('Financial Statements'!C57+'Financial Statements'!D57) | E26: =('Financial Statements'!D58+'Financial Statements'!E58)/('Financial Statements'!D57+'Financial Statements'!E57) | F26: =('Financial Statements'!E58+'Financial Statements'!F58)/('Financial Statements'!E57+'Financial Statements'!F57) | G26: =('Financial Statements'!F58+'Financial Statements'!G58)/('Financial Statements'!F57+'Financial Statements'!G57) | H26: =('Financial Statements'!G58+'Financial Statements'!H58)/('Financial Statements'!G57+'Financial Statements'!H57) | I26: =('Financial Statements'!H58+'Financial Statements'!I58)/('Financial Statements'!H57+'Financial Statements'!I57) | J26: =('Financial Statements'!I58+'Financial Statements'!J58)/('Financial Statements'!I57+'Financial Statements'!J57) | ... R26: =('Financial Statements'!Q58+'Financial Statements'!R58)/('Financial Statements'!Q57+'Financial Statements'!R57)
A27: = Return on Equity | C27: =C24*C25*C26 | D27: =D24*D25*D26 | E27: =E24*E25*E26 | F27: =F24*F25*F26 | G27: =G24*G25*G26 | H27: =H24*H25*H26 | I27: =I24*I25*I26 | J27: =J24*J25*J26 | ... R27: =R24*R25*R26
A29: Advanced Dupont Model
A30: Net Operating Margin | B30: ='Financial Statements'!B71/'Financial Statements'!B12 | C30: ='Financial Statements'!C71/'Financial Statements'!C12 | D30: ='Financial Statements'!D71/'Financial Statements'!D12 | E30: ='Financial Statements'!E71/'Financial Statements'!E12 | F30: ='Financial Statements'!F71/'Financial Statements'!F12 | G30: ='Financial Statements'!G71/'Financial Statements'!G12 | H30: ='Financial Statements'!H71/'Financial Statements'!H12 | I30: ='Financial Statements'!I71/'Financial Statements'!I12 | ... R30: ='Financial Statements'!R71/'Financial Statements'!R12
A31: x Net Operating Asset Turnover | C31: ='Financial Statements'!C12/(('Financial Statements'!B75+'Financial Statements'!C75)/2) | D31: ='Financial Statements'!D12/(('Financial Statements'!C75+'Financial Statements'!D75)/2) | E31: ='Financial Statements'!E12/(('Financial Statements'!D75+'Financial Statements'!E75)/2) | F31: ='Financial Statements'!F12/(('Financial Statements'!E75+'Financial Statements'!F75)/2) | G31: ='Financial Statements'!G12/(('Financial Statements'!F75+'Financial Statements'!G75)/2) | H31: ='Financial Statements'!H12/(('Financial Statements'!G75+'Financial Statements'!H75)/2) | I31: ='Financial Statements'!I12/(('Financial Statements'!H75+'Financial Statements'!I75)/2) | J31: ='Financial Statements'!J12/(('Financial Statements'!I75+'Financial Statements'!J75)/2) | ... R31: ='Financial Statements'!R12/(('Financial Statements'!Q75+'Financial Statements'!R75)/2)
A32: = Return on Net Operating Assets | C32: =C30*C31 | D32: =D30*D31 | E32: =E30*E31 | F32: =F30*F31 | G32: =G30*G31 | H32: =H30*H31 | I32: =I30*I31 | J32: =J30*J31 | ... R32: =R30*R31
A33: Net Borrowing Cost (NBC) | C33: =-'Financial Statements'!C72/(('Financial Statements'!B76+'Financial Statements'!C76)/2) | D33: =-'Financial Statements'!D72/(('Financial Statements'!C76+'Financial Statements'!D76)/2) | E33: =-'Financial Statements'!E72/(('Financial Statements'!D76+'Financial Statements'!E76)/2) | F33: =-'Financial Statements'!F72/(('Financial Statements'!E76+'Financial Statements'!F76)/2) | G33: =-'Financial Statements'!G72/(('Financial Statements'!F76+'Financial Statements'!G76)/2) | H33: =-'Financial Statements'!H72/(('Financial Statements'!G76+'Financial Statements'!H76)/2) | I33: =-'Financial Statements'!I72/(('Financial Statements'!H76+'Financial Statements'!I76)/2) | J33: =-'Financial Statements'!J72/(('Financial Statements'!I76+'Financial Statements'!J76)/2) | ... R33: =-'Financial Statements'!R72/(('Financial Statements'!Q76+'Financial Statements'!R76)/2)
A34: Spread (RNOA - NBC) | C34: =C32-C33 | D34: =D32-D33 | E34: =E32-E33 | F34: =F32-F33 | G34: =G32-G33 | H34: =H32-H33 | I34: =I32-I33 | J34: =J32-J33 | ... R34: =R32-R33
A35: Financial Leverage (LEV) | C35: =('Financial Statements'!B76+'Financial Statements'!C76)/('Financial Statements'!B77+'Financial Statements'!C77) | D35: =('Financial Statements'!C76+'Financial Statements'!D76)/('Financial Statements'!C77+'Financial Statements'!D77) | E35: =('Financial Statements'!D76+'Financial Statements'!E76)/('Financial Statements'!D77+'Financial Statements'!E77) | F35: =('Financial Statements'!E76+'Financial Statements'!F76)/('Financial Statements'!E77+'Financial Statements'!F77) | G35: =('Financial Statements'!F76+'Financial Statements'!G76)/('Financial Statements'!F77+'Financial Statements'!G77) | H35: =('Financial Statements'!G76+'Financial Statements'!H76)/('Financial Statements'!G77+'Financial Statements'!H77) | I35: =('Financial Statements'!H76+'Financial Statements'!I76)/('Financial Statements'!H77+'Financial Statements'!I77) | J35: =('Financial Statements'!I76+'Financial Statements'!J76)/('Financial Statements'!I77+'Financial Statements'!J77) | ... R35: =('Financial Statements'!Q76+'Financial Statements'!R76)/('Financial Statements'!Q77+'Financial Statements'!R77)
A36: ROE = RNOA + LEV*Spread | C36: =C32+(C35*C34) | D36: =D32+(D35*D34) | E36: =E32+(E35*E34) | F36: =F32+(F35*F34) | G36: =G32+(G35*G34) | H36: =H32+(H35*H34) | I36: =I32+(I35*I34) | J36: =J32+(J35*J34) | ... R36: =R32+(R35*R34)
A39: Margin Analysis
A40: Gross Margin | B40: ='Financial Statements'!B14/'Financial Statements'!B12 | C40: ='Financial Statements'!C14/'Financial Statements'!C12 | D40: ='Financial Statements'!D14/'Financial Statements'!D12 | E40: ='Financial Statements'!E14/'Financial Statements'!E12 | F40: ='Financial Statements'!F14/'Financial Statements'!F12 | G40: ='Financial Statements'!G14/'Financial Statements'!G12 | H40: ='Financial Statements'!H14/'Financial Statements'!H12 | I40: ='Financial Statements'!I14/'Financial Statements'!I12 | ... R40: ='Financial Statements'!R14/'Financial Statements'!R12
A41: EBITDA Margin | B41: ='Financial Statements'!B17/'Financial Statements'!B12 | C41: ='Financial Statements'!C17/'Financial Statements'!C12 | D41: ='Financial Statements'!D17/'Financial Statements'!D12 | E41: ='Financial Statements'!E17/'Financial Statements'!E12 | F41: ='Financial Statements'!F17/'Financial Statements'!F12 | G41: ='Financial Statements'!G17/'Financial Statements'!G12 | H41: ='Financial Statements'!H17/'Financial Statements'!H12 | I41: ='Financial Statements'!I17/'Financial Statements'!I12 | ... R41: ='Financial Statements'!R17/'Financial Statements'!R12
A42: EBIT Margin | B42: ='Financial Statements'!B19/'Financial Statements'!B12 | C42: ='Financial Statements'!C19/'Financial Statements'!C12 | D42: ='Financial Statements'!D19/'Financial Statements'!D12 | E42: ='Financial Statements'!E19/'Financial Statements'!E12 | F42: ='Financial Statements'!F19/'Financial Statements'!F12 | G42: ='Financial Statements'!G19/'Financial Statements'!G12 | H42: ='Financial Statements'!H19/'Financial Statements'!H12 | I42: ='Financial Statements'!I19/'Financial Statements'!I12 | ... R42: ='Financial Statements'!R19/'Financial Statements'!R12
A43: Net Operating Margin (b4 non-rec.) | B43: =('Financial Statements'!B71-'Financial Statements'!B21*(1-'Forecasting Assumptions'!B21)-'Financial Statements'!B26-'Financial Statements'!B24)/'Financial Statements'!B12 | C43: =('Financial Statements'!C71-'Financial Statements'!C21*(1-'Forecasting Assumptions'!C21)-'Financial Statements'!C26-'Financial Statements'!C24)/'Financial Statements'!C12 | D43: =('Financial Statements'!D71-'Financial Statements'!D21*(1-'Forecasting Assumptions'!D21)-'Financial Statements'!D26-'Financial Statements'!D24)/'Financial Statements'!D12 | E43: =('Financial Statements'!E71-'Financial Statements'!E21*(1-'Forecasting Assumptions'!E21)-'Financial Statements'!E26-'Financial Statements'!E24)/'Financial Statements'!E12 | F43: =('Financial Statements'!F71-'Financial Statements'!F21*(1-'Forecasting Assumptions'!F21)-'Financial Statements'!F26-'Financial Statements'!F24)/'Financial Statements'!F12 | G43: =('Financial Statements'!G71-'Financial Statements'!G21*(1-'Forecasting Assumptions'!G21)-'Financial Statements'!G26-'Financial Statements'!G24)/'Financial Statements'!G12 | H43: =('Financial Statements'!H71-'Financial Statements'!H21*(1-'Forecasting Assumptions'!H21)-'Financial Statements'!H26-'Financial Statements'!H24)/'Financial Statements'!H12 | I43: =('Financial Statements'!I71-'Financial Statements'!I21*(1-'Forecasting Assumptions'!I21)-'Financial Statements'!I26-'Financial Statements'!I24)/'Financial Statements'!I12 | ... R43: =('Financial Statements'!R71-'Financial Statements'!R21*(1-'Forecasting Assumptions'!R21)-'Financial Statements'!R26-'Financial Statements'!R24)/'Financial Statements'!R12
A44: Net Operating Margin | B44: ='Financial Statements'!B71/'Financial Statements'!B12 | C44: ='Financial Statements'!C71/'Financial Statements'!C12 | D44: ='Financial Statements'!D71/'Financial Statements'!D12 | E44: ='Financial Statements'!E71/'Financial Statements'!E12 | F44: ='Financial Statements'!F71/'Financial Statements'!F12 | G44: ='Financial Statements'!G71/'Financial Statements'!G12 | H44: ='Financial Statements'!H71/'Financial Statements'!H12 | I44: ='Financial Statements'!I71/'Financial Statements'!I12 | ... R44: ='Financial Statements'!R71/'Financial Statements'!R12
A46: Turnover Analysis
A47: Net Operating Asset Turnover | C47: ='Financial Statements'!C12/(('Financial Statements'!C75+'Financial Statements'!B75)/2) | D47: ='Financial Statements'!D12/(('Financial Statements'!D75+'Financial Statements'!C75)/2) | E47: ='Financial Statements'!E12/(('Financial Statements'!E75+'Financial Statements'!D75)/2) | F47: ='Financial Statements'!F12/(('Financial Statements'!F75+'Financial Statements'!E75)/2) | G47: ='Financial Statements'!G12/(('Financial Statements'!G75+'Financial Statements'!F75)/2) | H47: ='Financial Statements'!H12/(('Financial Statements'!H75+'Financial Statements'!G75)/2) | I47: ='Financial Statements'!I12/(('Financial Statements'!I75+'Financial Statements'!H75)/2) | J47: ='Financial Statements'!J12/(('Financial Statements'!J75+'Financial Statements'!I75)/2) | ... R47: ='Financial Statements'!R12/(('Financial Statements'!R75+'Financial Statements'!Q75)/2)
A48: Net Working Capital Turnover | C48: ='Financial Statements'!C12/(('Financial Statements'!B37-'Financial Statements'!B48+'Financial Statements'!B44+'Financial Statements'!C37-'Financial Statements'!C48+'Financial Statements'!C44)/2) | D48: ='Financial Statements'!D12/(('Financial Statements'!C37-'Financial Statements'!C48+'Financial Statements'!C44+'Financial Statements'!D37-'Financial Statements'!D48+'Financial Statements'!D44)/2) | E48: ='Financial Statements'!E12/(('Financial Statements'!D37-'Financial Statements'!D48+'Financial Statements'!D44+'Financial Statements'!E37-'Financial Statements'!E48+'Financial Statements'!E44)/2) | F48: ='Financial Statements'!F12/(('Financial Statements'!E37-'Financial Statements'!E48+'Financial Statements'!E44+'Financial Statements'!F37-'Financial Statements'!F48+'Financial Statements'!F44)/2) | G48: ='Financial Statements'!G12/(('Financial Statements'!F37-'Financial Statements'!F48+'Financial Statements'!F44+'Financial Statements'!G37-'Financial Statements'!G48+'Financial Statements'!G44)/2) | H48: ='Financial Statements'!H12/(('Financial Statements'!G37-'Financial Statements'!G48+'Financial Statements'!G44+'Financial Statements'!H37-'Financial Statements'!H48+'Financial Statements'!H44)/2) | I48: ='Financial Statements'!I12/(('Financial Statements'!H37-'Financial Statements'!H48+'Financial Statements'!H44+'Financial Statements'!I37-'Financial Statements'!I48+'Financial Statements'!I44)/2) | J48: ='Financial Statements'!J12/(('Financial Statements'!I37-'Financial Statements'!I48+'Financial Statements'!I44+'Financial Statements'!J37-'Financial Statements'!J48+'Financial Statements'!J44)/2) | ... R48: ='Financial Statements'!R12/(('Financial Statements'!Q37-'Financial Statements'!Q48+'Financial Statements'!Q44+'Financial Statements'!R37-'Financial Statements'!R48+'Financial Statements'!R44)/2)
A49: Avge Days to Collect Receivables | C49: =365*((('Financial Statements'!B34+'Financial Statements'!C34)/2)/'Financial Statements'!C12) | D49: =365*((('Financial Statements'!C34+'Financial Statements'!D34)/2)/'Financial Statements'!D12) | E49: =365*((('Financial Statements'!D34+'Financial Statements'!E34)/2)/'Financial Statements'!E12) | F49: =365*((('Financial Statements'!E34+'Financial Statements'!F34)/2)/'Financial Statements'!F12) | G49: =365*((('Financial Statements'!F34+'Financial Statements'!G34)/2)/'Financial Statements'!G12) | H49: =365*((('Financial Statements'!G34+'Financial Statements'!H34)/2)/'Financial Statements'!H12) | I49: =365*((('Financial Statements'!H34+'Financial Statements'!I34)/2)/'Financial Statements'!I12) | J49: =365*((('Financial Statements'!I34+'Financial Statements'!J34)/2)/'Financial Statements'!J12) | ... R49: =365*((('Financial Statements'!Q34+'Financial Statements'!R34)/2)/'Financial Statements'!R12)
A50: Avge Inventory Holding Period | C50: =-365*((('Financial Statements'!B35+'Financial Statements'!C35)/2)/'Financial Statements'!C13) | D50: =-365*((('Financial Statements'!C35+'Financial Statements'!D35)/2)/'Financial Statements'!D13) | E50: =-365*((('Financial Statements'!D35+'Financial Statements'!E35)/2)/'Financial Statements'!E13) | F50: =-365*((('Financial Statements'!E35+'Financial Statements'!F35)/2)/'Financial Statements'!F13) | G50: =-365*((('Financial Statements'!F35+'Financial Statements'!G35)/2)/'Financial Statements'!G13) | H50: =-365*((('Financial Statements'!G35+'Financial Statements'!H35)/2)/'Financial Statements'!H13) | I50: =-365*((('Financial Statements'!H35+'Financial Statements'!I35)/2)/'Financial Statements'!I13) | J50: =-365*((('Financial Statements'!I35+'Financial Statements'!J35)/2)/'Financial Statements'!J13) | ... R50: =-365*((('Financial Statements'!Q35+'Financial Statements'!R35)/2)/'Financial Statements'!R13)
A51: Avge Days to Pay Payables | C51: =365*((('Financial Statements'!B45+'Financial Statements'!C45)/2)/(-'Financial Statements'!C13+'Financial Statements'!C35-'Financial Statements'!B35)) | D51: =365*((('Financial Statements'!C45+'Financial Statements'!D45)/2)/(-'Financial Statements'!D13+'Financial Statements'!D35-'Financial Statements'!C35)) | E51: =365*((('Financial Statements'!D45+'Financial Statements'!E45)/2)/(-'Financial Statements'!E13+'Financial Statements'!E35-'Financial Statements'!D35)) | F51: =365*((('Financial Statements'!E45+'Financial Statements'!F45)/2)/(-'Financial Statements'!F13+'Financial Statements'!F35-'Financial Statements'!E35)) | G51: =365*((('Financial Statements'!F45+'Financial Statements'!G45)/2)/(-'Financial Statements'!G13+'Financial Statements'!G35-'Financial Statements'!F35)) | H51: =365*((('Financial Statements'!G45+'Financial Statements'!H45)/2)/(-'Financial Statements'!H13+'Financial Statements'!H35-'Financial Statements'!G35)) | I51: =365*((('Financial Statements'!H45+'Financial Statements'!I45)/2)/(-'Financial Statements'!I13+'Financial Statements'!I35-'Financial Statements'!H35)) | J51: =365*((('Financial Statements'!I45+'Financial Statements'!J45)/2)/(-'Financial Statements'!J13+'Financial Statements'!J35-'Financial Statements'!I35)) | ... R51: =365*((('Financial Statements'!Q45+'Financial Statements'!R45)/2)/(-'Financial Statements'!R13+'Financial Statements'!R35-'Financial Statements'!Q35))
A52: PP&E Turnover | C52: ='Financial Statements'!C12/(('Financial Statements'!B38+'Financial Statements'!C38)/2) | D52: ='Financial Statements'!D12/(('Financial Statements'!C38+'Financial Statements'!D38)/2) | E52: ='Financial Statements'!E12/(('Financial Statements'!D38+'Financial Statements'!E38)/2) | F52: ='Financial Statements'!F12/(('Financial Statements'!E38+'Financial Statements'!F38)/2) | G52: ='Financial Statements'!G12/(('Financial Statements'!F38+'Financial Statements'!G38)/2) | H52: ='Financial Statements'!H12/(('Financial Statements'!G38+'Financial Statements'!H38)/2) | I52: ='Financial Statements'!I12/(('Financial Statements'!H38+'Financial Statements'!I38)/2) | J52: ='Financial Statements'!J12/(('Financial Statements'!I38+'Financial Statements'!J38)/2) | ... R52: ='Financial Statements'!R12/(('Financial Statements'!Q38+'Financial Statements'!R38)/2)
A54: Analysis of Leverage
A55: - Long-Term Capital Structure
A56: Debt to Equity Ratio | B56: =('Financial Statements'!B44+'Financial Statements'!B49)/('Financial Statements'!B57) | C56: =('Financial Statements'!C44+'Financial Statements'!C49)/('Financial Statements'!C57) | D56: =('Financial Statements'!D44+'Financial Statements'!D49)/('Financial Statements'!D57) | E56: =('Financial Statements'!E44+'Financial Statements'!E49)/('Financial Statements'!E57) | F56: =('Financial Statements'!F44+'Financial Statements'!F49)/('Financial Statements'!F57) | G56: =('Financial Statements'!G44+'Financial Statements'!G49)/('Financial Statements'!G57) | H56: =('Financial Statements'!H44+'Financial Statements'!H49)/('Financial Statements'!H57) | I56: =('Financial Statements'!I44+'Financial Statements'!I49)/('Financial Statements'!I57) | ... R56: =('Financial Statements'!R44+'Financial Statements'!R49)/('Financial Statements'!R57)
A57: FFO to Total Debt | C57: ='Cash Flow Analysis'!B17/(('Financial Statements'!C44+'Financial Statements'!C49+'Financial Statements'!B44+'Financial Statements'!B49)/2) | D57: ='Cash Flow Analysis'!C17/(('Financial Statements'!D44+'Financial Statements'!D49+'Financial Statements'!C44+'Financial Statements'!C49)/2) | E57: ='Cash Flow Analysis'!D17/(('Financial Statements'!E44+'Financial Statements'!E49+'Financial Statements'!D44+'Financial Statements'!D49)/2) | F57: ='Cash Flow Analysis'!E17/(('Financial Statements'!F44+'Financial Statements'!F49+'Financial Statements'!E44+'Financial Statements'!E49)/2) | G57: ='Cash Flow Analysis'!F17/(('Financial Statements'!G44+'Financial Statements'!G49+'Financial Statements'!F44+'Financial Statements'!F49)/2) | H57: ='Cash Flow Analysis'!G17/(('Financial Statements'!H44+'Financial Statements'!H49+'Financial Statements'!G44+'Financial Statements'!G49)/2) | I57: ='Cash Flow Analysis'!H17/(('Financial Statements'!I44+'Financial Statements'!I49+'Financial Statements'!H44+'Financial Statements'!H49)/2) | J57: ='Cash Flow Analysis'!I17/(('Financial Statements'!J44+'Financial Statements'!J49+'Financial Statements'!I44+'Financial Statements'!I49)/2) | ... R57: ='Cash Flow Analysis'!Q17/(('Financial Statements'!R44+'Financial Statements'!R49+'Financial Statements'!Q44+'Financial Statements'!Q49)/2)
A58: CFO to Total Debt | C58: ='Cash Flow Analysis'!B24/(('Financial Statements'!C44+'Financial Statements'!C49+'Financial Statements'!B44+'Financial Statements'!B49)/2) | D58: ='Cash Flow Analysis'!C24/(('Financial Statements'!D44+'Financial Statements'!D49+'Financial Statements'!C44+'Financial Statements'!C49)/2) | E58: ='Cash Flow Analysis'!D24/(('Financial Statements'!E44+'Financial Statements'!E49+'Financial Statements'!D44+'Financial Statements'!D49)/2) | F58: ='Cash Flow Analysis'!E24/(('Financial Statements'!F44+'Financial Statements'!F49+'Financial Statements'!E44+'Financial Statements'!E49)/2) | G58: ='Cash Flow Analysis'!F24/(('Financial Statements'!G44+'Financial Statements'!G49+'Financial Statements'!F44+'Financial Statements'!F49)/2) | H58: ='Cash Flow Analysis'!G24/(('Financial Statements'!H44+'Financial Statements'!H49+'Financial Statements'!G44+'Financial Statements'!G49)/2) | I58: ='Cash Flow Analysis'!H24/(('Financial Statements'!I44+'Financial Statements'!I49+'Financial Statements'!H44+'Financial Statements'!H49)/2) | J58: ='Cash Flow Analysis'!I24/(('Financial Statements'!J44+'Financial Statements'!J49+'Financial Statements'!I44+'Financial Statements'!I49)/2) | ... R58: ='Cash Flow Analysis'!Q24/(('Financial Statements'!R44+'Financial Statements'!R49+'Financial Statements'!Q44+'Financial Statements'!Q49)/2)
A60: Analysis of Leverage
A61: - Short-Term Liquidity
A62: Current Ratio | B62: ='Financial Statements'!B37/'Financial Statements'!B48 | C62: ='Financial Statements'!C37/'Financial Statements'!C48 | D62: ='Financial Statements'!D37/'Financial Statements'!D48 | E62: ='Financial Statements'!E37/'Financial Statements'!E48 | F62: ='Financial Statements'!F37/'Financial Statements'!F48 | G62: ='Financial Statements'!G37/'Financial Statements'!G48 | H62: ='Financial Statements'!H37/'Financial Statements'!H48 | I62: ='Financial Statements'!I37/'Financial Statements'!I48 | ... R62: ='Financial Statements'!R37/'Financial Statements'!R48
A63: Quick Ratio | B63: =('Financial Statements'!B33+'Financial Statements'!B34)/'Financial Statements'!B48 | C63: =('Financial Statements'!C33+'Financial Statements'!C34)/'Financial Statements'!C48 | D63: =('Financial Statements'!D33+'Financial Statements'!D34)/'Financial Statements'!D48 | E63: =('Financial Statements'!E33+'Financial Statements'!E34)/'Financial Statements'!E48 | F63: =('Financial Statements'!F33+'Financial Statements'!F34)/'Financial Statements'!F48 | G63: =('Financial Statements'!G33+'Financial Statements'!G34)/'Financial Statements'!G48 | H63: =('Financial Statements'!H33+'Financial Statements'!H34)/'Financial Statements'!H48 | I63: =('Financial Statements'!I33+'Financial Statements'!I34)/'Financial Statements'!I48 | ... R63: =('Financial Statements'!R33+'Financial Statements'!R34)/'Financial Statements'!R48
A64: EBIT Interest Coverage | B64: =-'Financial Statements'!B19/'Financial Statements'!B20 | C64: =-'Financial Statements'!C19/'Financial Statements'!C20 | D64: =-'Financial Statements'!D19/'Financial Statements'!D20 | E64: =-'Financial Statements'!E19/'Financial Statements'!E20 | F64: =-'Financial Statements'!F19/'Financial Statements'!F20 | G64: =-'Financial Statements'!G19/'Financial Statements'!G20 | H64: =-'Financial Statements'!H19/'Financial Statements'!H20 | I64: =-'Financial Statements'!I19/'Financial Statements'!I20 | ... R64: =-'Financial Statements'!R19/'Financial Statements'!R20
A65: EBITDA Interest Coverage | B65: =-'Financial Statements'!B17/'Financial Statements'!B20 | C65: =-'Financial Statements'!C17/'Financial Statements'!C20 | D65: =-'Financial Statements'!D17/'Financial Statements'!D20 | E65: =-'Financial Statements'!E17/'Financial Statements'!E20 | F65: =-'Financial Statements'!F17/'Financial Statements'!F20 | G65: =-'Financial Statements'!G17/'Financial Statements'!G20 | H65: =-'Financial Statements'!H17/'Financial Statements'!H20 | I65: =-'Financial Statements'!I17/'Financial Statements'!I20 | ... R65: =-'Financial Statements'!R17/'Financial Statements'!R20
A67: Fiscal Year | B67: =IF(MONTH(B7)>6,YEAR(B7),YEAR(B7)-1) | C67: =IF(MONTH(C7)>6,YEAR(C7),YEAR(C7)-1) | D67: =IF(MONTH(D7)>6,YEAR(D7),YEAR(D7)-1) | E67: =IF(MONTH(E7)>6,YEAR(E7),YEAR(E7)-1) | F67: =IF(MONTH(F7)>6,YEAR(F7),YEAR(F7)-1) | G67: =IF(MONTH(G7)>6,YEAR(G7),YEAR(G7)-1) | H67: =IF(MONTH(H7)>6,YEAR(H7),YEAR(H7)-1) | I67: =IF(MONTH(I7)>6,YEAR(I7),YEAR(I7)-1) | ... R67: =IF(MONTH(R7)>6,YEAR(R7),YEAR(R7)-1)

Sheet Cash Flow Analysis
A1: Cash Flow Analysis | B1: ($000)
A4: Company Name | B4: ='Financial Statements'!B4
B6: Actual | C6: Actual | D6: Actual | E6: Actual | F6: Forecast | G6: Forecast | H6: Forecast | I6: Forecast | J6: Forecast | K6: Forecast | L6: Forecast | M6: Forecast | N6: Forecast | O6: Forecast | P6: Forecast | Q6: Forecast
A7: Fiscal Year End Date | B7: ='Financial Statements'!C8 | C7: ='Financial Statements'!D8 | D7: ='Financial Statements'!E8 | E7: ='Financial Statements'!F8 | F7: ='Financial Statements'!G8 | G7: ='Financial Statements'!H8 | H7: ='Financial Statements'!I8 | I7: ='Financial Statements'!J8 | ... Q7: ='Financial Statements'!R8
A8: Pro Forma Statement of Cash Flows
A10: Operating:
A11: Net Income | B11: ='Financial Statements'!C29 | C11: ='Financial Statements'!D29 | D11: ='Financial Statements'!E29 | E11: ='Financial Statements'!F29 | F11: ='Financial Statements'!G29 | G11: ='Financial Statements'!H29 | H11: ='Financial Statements'!I29 | I11: ='Financial Statements'!J29 | ... Q11: ='Financial Statements'!R29
A12: +Depreciation & Amortization | B12: =-'Financial Statements'!C18 | C12: =-'Financial Statements'!D18 | D12: =-'Financial Statements'!E18 | E12: =-'Financial Statements'!F18 | F12: =-'Financial Statements'!G18 | G12: =-'Financial Statements'!H18 | H12: =-'Financial Statements'!I18 | I12: =-'Financial Statements'!J18 | ... Q12: =-'Financial Statements'!R18
A13: +Increase in Deferred Taxes | B13: ='Financial Statements'!C51-'Financial Statements'!B51 | C13: ='Financial Statements'!D51-'Financial Statements'!C51 | D13: ='Financial Statements'!E51-'Financial Statements'!D51 | E13: ='Financial Statements'!F51-'Financial Statements'!E51 | F13: ='Financial Statements'!G51-'Financial Statements'!F51 | G13: ='Financial Statements'!H51-'Financial Statements'!G51 | H13: ='Financial Statements'!I51-'Financial Statements'!H51 | I13: ='Financial Statements'!J51-'Financial Statements'!I51 | ... Q13: ='Financial Statements'!R51-'Financial Statements'!Q51
A14: +Increase in Other Liabilities | B14: ='Financial Statements'!C50-'Financial Statements'!B50 | C14: ='Financial Statements'!D50-'Financial Statements'!C50 | D14: ='Financial Statements'!E50-'Financial Statements'!D50 | E14: ='Financial Statements'!F50-'Financial Statements'!E50 | F14: ='Financial Statements'!G50-'Financial Statements'!F50 | G14: ='Financial Statements'!H50-'Financial Statements'!G50 | H14: ='Financial Statements'!I50-'Financial Statements'!H50 | I14: ='Financial Statements'!J50-'Financial Statements'!I50 | ... Q14: ='Financial Statements'!R50-'Financial Statements'!Q50
A15: +Noncontrolling Interest in Earnings | B15: =-'Financial Statements'!C27 | C15: =-'Financial Statements'!D27 | D15: =-'Financial Statements'!E27 | E15: =-'Financial Statements'!F27 | F15: =-'Financial Statements'!G27 | G15: =-'Financial Statements'!H27 | H15: =-'Financial Statements'!I27 | I15: =-'Financial Statements'!J27 | ... Q15: =-'Financial Statements'!R27
A16: +Preferred Dividends | B16: =-'Financial Statements'!C28 | C16: =-'Financial Statements'!D28 | D16: =-'Financial Statements'!E28 | E16: =-'Financial Statements'!F28 | F16: =-'Financial Statements'!G28 | G16: =-'Financial Statements'!H28 | H16: =-'Financial Statements'!I28 | I16: =-'Financial Statements'!J28 | ... Q16: =-'Financial Statements'!R28
A17: =Funds From Operations | B17: =B11+B12+B13+B14+B15+B16 | C17: =C11+C12+C13+C14+C15+C16 | D17: =D11+D12+D13+D14+D15+D16 | E17: =E11+E12+E13+E14+E15+E16 | F17: =F11+F12+F13+F14+F15+F16 | G17: =G11+G12+G13+G14+G15+G16 | H17: =H11+H12+H13+H14+H15+H16 | I17: =I11+I12+I13+I14+I15+I16 | ... Q17: =Q11+Q12+Q13+Q14+Q15+Q16
A18: -Increase in Receivables | B18: =-('Financial Statements'!C34-'Financial Statements'!B34) | C18: =-('Financial Statements'!D34-'Financial Statements'!C34) | D18: =-('Financial Statements'!E34-'Financial Statements'!D34) | E18: =-('Financial Statements'!F34-'Financial Statements'!E34) | F18: =-('Financial Statements'!G34-'Financial Statements'!F34) | G18: =-('Financial Statements'!H34-'Financial Statements'!G34) | H18: =-('Financial Statements'!I34-'Financial Statements'!H34) | I18: =-('Financial Statements'!J34-'Financial Statements'!I34) | ... Q18: =-('Financial Statements'!R34-'Financial Statements'!Q34)
A19: -Increase in Inventory | B19: =-('Financial Statements'!C35-'Financial Statements'!B35) | C19: =-('Financial Statements'!D35-'Financial Statements'!C35) | D19: =-('Financial Statements'!E35-'Financial Statements'!D35) | E19: =-('Financial Statements'!F35-'Financial Statements'!E35) | F19: =-('Financial Statements'!G35-'Financial Statements'!F35) | G19: =-('Financial Statements'!H35-'Financial Statements'!G35) | H19: =-('Financial Statements'!I35-'Financial Statements'!H35) | I19: =-('Financial Statements'!J35-'Financial Statements'!I35) | ... Q19: =-('Financial Statements'!R35-'Financial Statements'!Q35)
A20: -Increase in Other Current Assets | B20: =-('Financial Statements'!C36-'Financial Statements'!B36) | C20: =-('Financial Statements'!D36-'Financial Statements'!C36) | D20: =-('Financial Statements'!E36-'Financial Statements'!D36) | E20: =-('Financial Statements'!F36-'Financial Statements'!E36) | F20: =-('Financial Statements'!G36-'Financial Statements'!F36) | G20: =-('Financial Statements'!H36-'Financial Statements'!G36) | H20: =-('Financial Statements'!I36-'Financial Statements'!H36) | I20: =-('Financial Statements'!J36-'Financial Statements'!I36) | ... Q20: =-('Financial Statements'!R36-'Financial Statements'!Q36)
A21: +Increase in Accounts Payable | B21: =('Financial Statements'!C45-'Financial Statements'!B45) | C21: =('Financial Statements'!D45-'Financial Statements'!C45) | D21: =('Financial Statements'!E45-'Financial Statements'!D45) | E21: =('Financial Statements'!F45-'Financial Statements'!E45) | F21: =('Financial Statements'!G45-'Financial Statements'!F45) | G21: =('Financial Statements'!H45-'Financial Statements'!G45) | H21: =('Financial Statements'!I45-'Financial Statements'!H45) | I21: =('Financial Statements'!J45-'Financial Statements'!I45) | ... Q21: =('Financial Statements'!R45-'Financial Statements'!Q45)
A22: +Increase in Taxes Payable | B22: =('Financial Statements'!C46-'Financial Statements'!B46) | C22: =('Financial Statements'!D46-'Financial Statements'!C46) | D22: =('Financial Statements'!E46-'Financial Statements'!D46) | E22: =('Financial Statements'!F46-'Financial Statements'!E46) | F22: =('Financial Statements'!G46-'Financial Statements'!F46) | G22: =('Financial Statements'!H46-'Financial Statements'!G46) | H22: =('Financial Statements'!I46-'Financial Statements'!H46) | I22: =('Financial Statements'!J46-'Financial Statements'!I46) | ... Q22: =('Financial Statements'!R46-'Financial Statements'!Q46)
A23: +Increase in Other Curr. Liabilities | B23: =('Financial Statements'!C47-'Financial Statements'!B47) | C23: =('Financial Statements'!D47-'Financial Statements'!C47) | D23: =('Financial Statements'!E47-'Financial Statements'!D47) | E23: =('Financial Statements'!F47-'Financial Statements'!E47) | F23: =('Financial Statements'!G47-'Financial Statements'!F47) | G23: =('Financial Statements'!H47-'Financial Statements'!G47) | H23: =('Financial Statements'!I47-'Financial Statements'!H47) | I23: =('Financial Statements'!J47-'Financial Statements'!I47) | ... Q23: =('Financial Statements'!R47-'Financial Statements'!Q47)
A24: =Cash From Operations | B24: =B17+B18+B19+B20+B21+B22+B23 | C24: =C17+C18+C19+C20+C21+C22+C23 | D24: =D17+D18+D19+D20+D21+D22+D23 | E24: =E17+E18+E19+E20+E21+E22+E23 | F24: =F17+F18+F19+F20+F21+F22+F23 | G24: =G17+G18+G19+G20+G21+G22+G23 | H24: =H17+H18+H19+H20+H21+H22+H23 | I24: =I17+I18+I19+I20+I21+I22+I23 | ... Q24: =Q17+Q18+Q19+Q20+Q21+Q22+Q23
A26: Investing:
A27: -Capital Expenditures | B27: =-('Financial Statements'!C38-'Financial Statements'!B38-'Financial Statements'!C18) | C27: =-('Financial Statements'!D38-'Financial Statements'!C38-'Financial Statements'!D18) | D27: =-('Financial Statements'!E38-'Financial Statements'!D38-'Financial Statements'!E18) | E27: =-('Financial Statements'!F38-'Financial Statements'!E38-'Financial Statements'!F18) | F27: =-('Financial Statements'!G38-'Financial Statements'!F38-'Financial Statements'!G18) | G27: =-('Financial Statements'!H38-'Financial Statements'!G38-'Financial Statements'!H18) | H27: =-('Financial Statements'!I38-'Financial Statements'!H38-'Financial Statements'!I18) | I27: =-('Financial Statements'!J38-'Financial Statements'!I38-'Financial Statements'!J18) | ... Q27: =-('Financial Statements'!R38-'Financial Statements'!Q38-'Financial Statements'!R18)
A28: -Increase in Investments | B28: =-('Financial Statements'!C39-'Financial Statements'!B39) | C28: =-('Financial Statements'!D39-'Financial Statements'!C39) | D28: =-('Financial Statements'!E39-'Financial Statements'!D39) | E28: =-('Financial Statements'!F39-'Financial Statements'!E39) | F28: =-('Financial Statements'!G39-'Financial Statements'!F39) | G28: =-('Financial Statements'!H39-'Financial Statements'!G39) | H28: =-('Financial Statements'!I39-'Financial Statements'!H39) | I28: =-('Financial Statements'!J39-'Financial Statements'!I39) | ... Q28: =-('Financial Statements'!R39-'Financial Statements'!Q39)
A29: -Purchases of Intangibles | B29: =-('Financial Statements'!C40-'Financial Statements'!B40) | C29: =-('Financial Statements'!D40-'Financial Statements'!C40) | D29: =-('Financial Statements'!E40-'Financial Statements'!D40) | E29: =-('Financial Statements'!F40-'Financial Statements'!E40) | F29: =-('Financial Statements'!G40-'Financial Statements'!F40) | G29: =-('Financial Statements'!H40-'Financial Statements'!G40) | H29: =-('Financial Statements'!I40-'Financial Statements'!H40) | I29: =-('Financial Statements'!J40-'Financial Statements'!I40) | ... Q29: =-('Financial Statements'!R40-'Financial Statements'!Q40)
A30: -Increase in Other Assets | B30: =-('Financial Statements'!C41-'Financial Statements'!B41) | C30: =-('Financial Statements'!D41-'Financial Statements'!C41) | D30: =-('Financial Statements'!E41-'Financial Statements'!D41) | E30: =-('Financial Statements'!F41-'Financial Statements'!E41) | F30: =-('Financial Statements'!G41-'Financial Statements'!F41) | G30: =-('Financial Statements'!H41-'Financial Statements'!G41) | H30: =-('Financial Statements'!I41-'Financial Statements'!H41) | I30: =-('Financial Statements'!J41-'Financial Statements'!I41) | ... Q30: =-('Financial Statements'!R41-'Financial Statements'!Q41)
A31: =Cash From Investing | B31: =B27+B28+B29+B30 | C31: =C27+C28+C29+C30 | D31: =D27+D28+D29+D30 | E31: =E27+E28+E29+E30 | F31: =F27+F28+F29+F30 | G31: =G27+G28+G29+G30 | H31: =H27+H28+H29+H30 | I31: =I27+I28+I29+I30 | ... Q31: =Q27+Q28+Q29+Q30
A33: Financing:
A34: +Increase in Debt | B34: =('Financial Statements'!C44+'Financial Statements'!C49-'Financial Statements'!B44-'Financial Statements'!B49) | C34: =('Financial Statements'!D44+'Financial Statements'!D49-'Financial Statements'!C44-'Financial Statements'!C49) | D34: =('Financial Statements'!E44+'Financial Statements'!E49-'Financial Statements'!D44-'Financial Statements'!D49) | E34: =('Financial Statements'!F44+'Financial Statements'!F49-'Financial Statements'!E44-'Financial Statements'!E49) | F34: =('Financial Statements'!G44+'Financial Statements'!G49-'Financial Statements'!F44-'Financial Statements'!F49) | G34: =('Financial Statements'!H44+'Financial Statements'!H49-'Financial Statements'!G44-'Financial Statements'!G49) | H34: =('Financial Statements'!I44+'Financial Statements'!I49-'Financial Statements'!H44-'Financial Statements'!H49) | I34: =('Financial Statements'!J44+'Financial Statements'!J49-'Financial Statements'!I44-'Financial Statements'!I49) | ... Q34: =('Financial Statements'!R44+'Financial Statements'!R49-'Financial Statements'!Q44-'Financial Statements'!Q49)
A35: -Dividends Paid to Noncontrolling Interest | B35: ='Financial Statements'!C27+'Financial Statements'!C53-'Financial Statements'!B53 | C35: ='Financial Statements'!D27+'Financial Statements'!D53-'Financial Statements'!C53 | D35: ='Financial Statements'!E27+'Financial Statements'!E53-'Financial Statements'!D53 | E35: ='Financial Statements'!F27+'Financial Statements'!F53-'Financial Statements'!E53 | F35: ='Financial Statements'!G27+'Financial Statements'!G53-'Financial Statements'!F53 | G35: ='Financial Statements'!H27+'Financial Statements'!H53-'Financial Statements'!G53 | H35: ='Financial Statements'!I27+'Financial Statements'!I53-'Financial Statements'!H53 | I35: ='Financial Statements'!J27+'Financial Statements'!J53-'Financial Statements'!I53 | ... Q35: ='Financial Statements'!R27+'Financial Statements'!R53-'Financial Statements'!Q53
A36: -Dividends Paid on Preferred | B36: ='Financial Statements'!C28 | C36: ='Financial Statements'!D28 | D36: ='Financial Statements'!E28 | E36: ='Financial Statements'!F28 | F36: ='Financial Statements'!G28 | G36: ='Financial Statements'!H28 | H36: ='Financial Statements'!I28 | I36: ='Financial Statements'!J28 | ... Q36: ='Financial Statements'!R28
A37: +Increase in Pref. Stock | B37: ='Financial Statements'!C54-'Financial Statements'!B54 | C37: ='Financial Statements'!D54-'Financial Statements'!C54 | D37: ='Financial Statements'!E54-'Financial Statements'!D54 | E37: ='Financial Statements'!F54-'Financial Statements'!E54 | F37: ='Financial Statements'!G54-'Financial Statements'!F54 | G37: ='Financial Statements'!H54-'Financial Statements'!G54 | H37: ='Financial Statements'!I54-'Financial Statements'!H54 | I37: ='Financial Statements'!J54-'Financial Statements'!I54 | ... Q37: ='Financial Statements'!R54-'Financial Statements'!Q54
A38: -Dividends Paid on Common | B38: ='Financial Statements'!C64 | C38: ='Financial Statements'!D64 | D38: ='Financial Statements'!E64 | E38: ='Financial Statements'!F64 | F38: ='Financial Statements'!G64 | G38: ='Financial Statements'!H64 | H38: ='Financial Statements'!I64 | I38: ='Financial Statements'!J64 | ... Q38: ='Financial Statements'!R64
A39: +/-Net Issuance of Common Stock | B39: ='Financial Statements'!C55-'Financial Statements'!B55 | C39: ='Financial Statements'!D55-'Financial Statements'!C55 | D39: ='Financial Statements'!E55-'Financial Statements'!D55 | E39: ='Financial Statements'!F55-'Financial Statements'!E55 | F39: ='Financial Statements'!G55-'Financial Statements'!F55 | G39: ='Financial Statements'!H55-'Financial Statements'!G55 | H39: ='Financial Statements'!I55-'Financial Statements'!H55 | I39: ='Financial Statements'!J55-'Financial Statements'!I55 | ... Q39: ='Financial Statements'!R55-'Financial Statements'!Q55
A40: +/-Clean Surplus Plug (Ignore) | B40: ='Financial Statements'!C65 | C40: ='Financial Statements'!D65 | D40: ='Financial Statements'!E65 | E40: ='Financial Statements'!F65 | F40: ='Financial Statements'!G65 | G40: ='Financial Statements'!H65 | H40: ='Financial Statements'!I65 | I40: ='Financial Statements'!J65 | ... Q40: ='Financial Statements'!R65
A41: =Cash From Financing | B41: =SUM(B34:B40) | C41: =SUM(C34:C40) | D41: =SUM(D34:D40) | E41: =SUM(E34:E40) | F41: =SUM(F34:F40) | G41: =SUM(G34:G40) | H41: =SUM(H34:H40) | I41: =SUM(I34:I40) | ... Q41: =SUM(Q34:Q40)
A43: Net Change in Cash | B43: =B24+B31+B41 | C43: =C24+C31+C41 | D43: =D24+D31+D41 | E43: =E24+E31+E41 | F43: =F24+F31+F41 | G43: =G24+G31+G41 | H43: =H24+H31+H41 | I43: =I24+I31+I41 | ... Q43: =Q24+Q31+Q41
A44: + Beginning Cash Balance | B44: ='Financial Statements'!B33 | C44: ='Financial Statements'!C33 | D44: ='Financial Statements'!D33 | E44: ='Financial Statements'!E33 | F44: ='Financial Statements'!F33 | G44: ='Financial Statements'!G33 | H44: ='Financial Statements'!H33 | I44: ='Financial Statements'!I33 | ... Q44: ='Financial Statements'!Q33
A45: = Ending Cash Balance | B45: =B43+B44 | C45: =C43+C44 | D45: =D43+D44 | E45: =E43+E44 | F45: =F43+F44 | G45: =G43+G44 | H45: =H43+H44 | I45: =I43+I44 | ... Q45: =Q43+Q44
A48: Free Cash Flow to Common Equity
A50: Net Income | B50: ='Financial Statements'!C29 | C50: ='Financial Statements'!D29 | D50: ='Financial Statements'!E29 | E50: ='Financial Statements'!F29 | F50: ='Financial Statements'!G29 | G50: ='Financial Statements'!H29 | H50: ='Financial Statements'!I29 | I50: ='Financial Statements'!J29 | ... Q50: ='Financial Statements'!R29
A51: - Increase in Common Equity | B51: =-('Financial Statements'!C57-'Financial Statements'!B57) | C51: =-('Financial Statements'!D57-'Financial Statements'!C57) | D51: =-('Financial Statements'!E57-'Financial Statements'!D57) | E51: =-('Financial Statements'!F57-'Financial Statements'!E57) | F51: =-('Financial Statements'!G57-'Financial Statements'!F57) | G51: =-('Financial Statements'!H57-'Financial Statements'!G57) | H51: =-('Financial Statements'!I57-'Financial Statements'!H57) | I51: =-('Financial Statements'!J57-'Financial Statements'!I57) | ... Q51: =-('Financial Statements'!R57-'Financial Statements'!Q57)
A52: +/-Clean Surplus Plug (Ignore) | B52: ='Financial Statements'!C65 | C52: ='Financial Statements'!D65 | D52: ='Financial Statements'!E65 | E52: ='Financial Statements'!F65 | F52: ='Financial Statements'!G65 | G52: ='Financial Statements'!H65 | H52: ='Financial Statements'!I65 | I52: ='Financial Statements'!J65 | ... Q52: ='Financial Statements'!R65
A53: =Free Cash Flow to Common Equity | B53: =SUM(B50:B52) | C53: =SUM(C50:C52) | D53: =SUM(D50:D52) | E53: =SUM(E50:E52) | F53: =SUM(F50:F52) | G53: =SUM(G50:G52) | H53: =SUM(H50:H52) | I53: =SUM(I50:I52) | ... Q53: =SUM(Q50:Q52)
A55: Computation based on SCF:
A56: +Cash From Operations | B56: =B24 | C56: =C24 | D56: =D24 | E56: =E24 | F56: =F24 | G56: =G24 | H56: =H24 | I56: =I24 | ... Q56: =Q24
A57: -Increase in Cash | B57: =-B43 | C57: =-C43 | D57: =-D43 | E57: =-E43 | F57: =-F43 | G57: =-G43 | H57: =-H43 | I57: =-I43 | ... Q57: =-Q43
A58: +Cash From Investing | B58: =B31 | C58: =C31 | D58: =D31 | E58: =E31 | F58: =F31 | G58: =G31 | H58: =H31 | I58: =I31 | ... Q58: =Q31
A59: +Increase in Debt | B59: =B34 | C59: =C34 | D59: =D34 | E59: =E34 | F59: =F34 | G59: =G34 | H59: =H34 | I59: =I34 | ... Q59: =Q34
A60: -Dividends Paid to Noncontrolling Interest | B60: =B35 | C60: =C35 | D60: =D35 | E60: =E35 | F60: =F35 | G60: =G35 | H60: =H35 | I60: =I35 | ... Q60: =Q35
A61: -Dividends Paid on Preferred | B61: ='Financial Statements'!C28 | C61: ='Financial Statements'!D28 | D61: ='Financial Statements'!E28 | E61: ='Financial Statements'!F28 | F61: ='Financial Statements'!G28 | G61: ='Financial Statements'!H28 | H61: ='Financial Statements'!I28 | I61: ='Financial Statements'!J28 | ... Q61: ='Financial Statements'!R28
A62: +Increase in Preferred Stock | B62: =B37 | C62: =C37 | D62: =D37 | E62: =E37 | F62: =F37 | G62: =G37 | H62: =H37 | I62: =I37 | ... Q62: =Q37
A63: +/-Clean Surplus Plug (Ignore) | B63: ='Financial Statements'!C65 | C63: ='Financial Statements'!D65 | D63: ='Financial Statements'!E65 | E63: ='Financial Statements'!F65 | F63: ='Financial Statements'!G65 | G63: ='Financial Statements'!H65 | H63: ='Financial Statements'!I65 | I63: ='Financial Statements'!J65 | ... Q63: ='Financial Statements'!R65
A64: =Free Cash Flow to Common Equity | B64: =SUM(B56:B63) | C64: =SUM(C56:C63) | D64: =SUM(D56:D63) | E64: =SUM(E56:E63) | F64: =SUM(F56:F63) | G64: =SUM(G56:G63) | H64: =SUM(H56:H63) | I64: =SUM(I56:I63) | ... Q64: =SUM(Q56:Q63)
A66: Financing Flows:
A67: +Dividends Paid | B67: =-'Financial Statements'!C64 | C67: =-'Financial Statements'!D64 | D67: =-'Financial Statements'!E64 | E67: =-'Financial Statements'!F64 | F67: =-'Financial Statements'!G64 | G67: =-'Financial Statements'!H64 | H67: =-'Financial Statements'!I64 | I67: =-'Financial Statements'!J64 | ... Q67: =-'Financial Statements'!R64
A68: -Net Issuance of Common Stock | B68: =-('Financial Statements'!C55-'Financial Statements'!B55) | C68: =-('Financial Statements'!D55-'Financial Statements'!C55) | D68: =-('Financial Statements'!E55-'Financial Statements'!D55) | E68: =-('Financial Statements'!F55-'Financial Statements'!E55) | F68: =-('Financial Statements'!G55-'Financial Statements'!F55) | G68: =-('Financial Statements'!H55-'Financial Statements'!G55) | H68: =-('Financial Statements'!I55-'Financial Statements'!H55) | I68: =-('Financial Statements'!J55-'Financial Statements'!I55) | ... Q68: =-('Financial Statements'!R55-'Financial Statements'!Q55)
A69: = Free Cash Flow to Common Equity | B69: =B67+B68 | C69: =C67+C68 | D69: =D67+D68 | E69: =E67+E68 | F69: =F67+F68 | G69: =G67+G68 | H69: =H67+H68 | I69: =I67+I68 | ... Q69: =Q67+Q68
A72: Free Cash Flow to all Investors
A74: Net Operating Income | B74: ='Financial Statements'!C71 | C74: ='Financial Statements'!D71 | D74: ='Financial Statements'!E71 | E74: ='Financial Statements'!F71 | F74: ='Financial Statements'!G71 | G74: ='Financial Statements'!H71 | H74: ='Financial Statements'!I71 | I74: ='Financial Statements'!J71 | ... Q74: ='Financial Statements'!R71
A75: - Increase in Net Operating Assets | B75: =-('Financial Statements'!C75-'Financial Statements'!B75) | C75: =-('Financial Statements'!D75-'Financial Statements'!C75) | D75: =-('Financial Statements'!E75-'Financial Statements'!D75) | E75: =-('Financial Statements'!F75-'Financial Statements'!E75) | F75: =-('Financial Statements'!G75-'Financial Statements'!F75) | G75: =-('Financial Statements'!H75-'Financial Statements'!G75) | H75: =-('Financial Statements'!I75-'Financial Statements'!H75) | I75: =-('Financial Statements'!J75-'Financial Statements'!I75) | ... Q75: =-('Financial Statements'!R75-'Financial Statements'!Q75)
A76: +/-Clean Surplus Plug (Ignore) | B76: ='Financial Statements'!C65 | C76: ='Financial Statements'!D65 | D76: ='Financial Statements'!E65 | E76: ='Financial Statements'!F65 | F76: ='Financial Statements'!G65 | G76: ='Financial Statements'!H65 | H76: ='Financial Statements'!I65 | I76: ='Financial Statements'!J65 | ... Q76: ='Financial Statements'!R65
A77: =Free Cash Flow to Investors | B77: =SUM(B74:B76) | C77: =SUM(C74:C76) | D77: =SUM(D74:D76) | E77: =SUM(E74:E76) | F77: =SUM(F74:F76) | G77: =SUM(G74:G76) | H77: =SUM(H74:H76) | I77: =SUM(I74:I76) | ... Q77: =SUM(Q74:Q76)
A79: Computation based on SCF:
A80: Cash From Operations | B80: =B24 | C80: =C24 | D80: =D24 | E80: =E24 | F80: =F24 | G80: =G24 | H80: =H24 | I80: =I24 | ... Q80: =Q24
A81: -Increase in Operating Cash | B81: =-('Financial Statements'!C33-'Financial Statements'!B33) | C81: =-('Financial Statements'!D33-'Financial Statements'!C33) | D81: =-('Financial Statements'!E33-'Financial Statements'!D33) | E81: =-('Financial Statements'!F33-'Financial Statements'!E33) | F81: =-('Financial Statements'!G33-'Financial Statements'!F33) | G81: =-('Financial Statements'!H33-'Financial Statements'!G33) | H81: =-('Financial Statements'!I33-'Financial Statements'!H33) | I81: =-('Financial Statements'!J33-'Financial Statements'!I33) | ... Q81: =-('Financial Statements'!R33-'Financial Statements'!Q33)
A82: +Cash from Investing | B82: =B31 | C82: =C31 | D82: =D31 | E82: =E31 | F82: =F31 | G82: =G31 | H82: =H31 | I82: =I31 | ... Q82: =Q31
A83: +Interest Expense | B83: =-'Financial Statements'!C20 | C83: =-'Financial Statements'!D20 | D83: =-'Financial Statements'!E20 | E83: =-'Financial Statements'!F20 | F83: =-'Financial Statements'!G20 | G83: =-'Financial Statements'!H20 | H83: =-'Financial Statements'!I20 | I83: =-'Financial Statements'!J20 | ... Q83: =-'Financial Statements'!R20
A84: -Tax Shield on Interest | B84: =-(IF('Financial Statements'!C22=0,0,(-'Financial Statements'!C23)/'Financial Statements'!C22))*B83 | C84: =-(IF('Financial Statements'!D22=0,0,(-'Financial Statements'!D23)/'Financial Statements'!D22))*C83 | D84: =-(IF('Financial Statements'!E22=0,0,(-'Financial Statements'!E23)/'Financial Statements'!E22))*D83 | E84: =-(IF('Financial Statements'!F22=0,0,(-'Financial Statements'!F23)/'Financial Statements'!F22))*E83 | F84: =-(IF('Financial Statements'!G22=0,0,(-'Financial Statements'!G23)/'Financial Statements'!G22))*F83 | G84: =-(IF('Financial Statements'!H22=0,0,(-'Financial Statements'!H23)/'Financial Statements'!H22))*G83 | H84: =-(IF('Financial Statements'!I22=0,0,(-'Financial Statements'!I23)/'Financial Statements'!I22))*H83 | I84: =-(IF('Financial Statements'!J22=0,0,(-'Financial Statements'!J23)/'Financial Statements'!J22))*I83 | ... Q84: =-(IF('Financial Statements'!R22=0,0,(-'Financial Statements'!R23)/'Financial Statements'!R22))*Q83
A85: +/-Clean Surplus Plug (Ignore) | B85: ='Financial Statements'!C65 | C85: ='Financial Statements'!D65 | D85: ='Financial Statements'!E65 | E85: ='Financial Statements'!F65 | F85: ='Financial Statements'!G65 | G85: ='Financial Statements'!H65 | H85: ='Financial Statements'!I65 | I85: ='Financial Statements'!J65 | ... Q85: ='Financial Statements'!R65
A86: =Free Cash Flow to Investors | B86: =SUM(B80:B85) | C86: =SUM(C80:C85) | D86: =SUM(D80:D85) | E86: =SUM(E80:E85) | F86: =SUM(F80:F85) | G86: =SUM(G80:G85) | H86: =SUM(H80:H85) | I86: =SUM(I80:I85) | ... Q86: =SUM(Q80:Q85)
A88: Financing Flows:
A89: +Dividends on Common Stock | B89: =-'Financial Statements'!C64 | C89: =-'Financial Statements'!D64 | D89: =-'Financial Statements'!E64 | E89: =-'Financial Statements'!F64 | F89: =-'Financial Statements'!G64 | G89: =-'Financial Statements'!H64 | H89: =-'Financial Statements'!I64 | I89: =-'Financial Statements'!J64 | ... Q89: =-'Financial Statements'!R64
A90: +Interest Expense | B90: =-'Financial Statements'!C20 | C90: =-'Financial Statements'!D20 | D90: =-'Financial Statements'!E20 | E90: =-'Financial Statements'!F20 | F90: =-'Financial Statements'!G20 | G90: =-'Financial Statements'!H20 | H90: =-'Financial Statements'!I20 | I90: =-'Financial Statements'!J20 | ... Q90: =-'Financial Statements'!R20
A91: -Tax Shield on Interest | B91: =-(IF('Financial Statements'!C22=0,0,(-'Financial Statements'!C23)/'Financial Statements'!C22))*B90 | C91: =-(IF('Financial Statements'!D22=0,0,(-'Financial Statements'!D23)/'Financial Statements'!D22))*C90 | D91: =-(IF('Financial Statements'!E22=0,0,(-'Financial Statements'!E23)/'Financial Statements'!E22))*D90 | E91: =-(IF('Financial Statements'!F22=0,0,(-'Financial Statements'!F23)/'Financial Statements'!F22))*E90 | F91: =-(IF('Financial Statements'!G22=0,0,(-'Financial Statements'!G23)/'Financial Statements'!G22))*F90 | G91: =-(IF('Financial Statements'!H22=0,0,(-'Financial Statements'!H23)/'Financial Statements'!H22))*G90 | H91: =-(IF('Financial Statements'!I22=0,0,(-'Financial Statements'!I23)/'Financial Statements'!I22))*H90 | I91: =-(IF('Financial Statements'!J22=0,0,(-'Financial Statements'!J23)/'Financial Statements'!J22))*I90 | ... Q91: =-(IF('Financial Statements'!R22=0,0,(-'Financial Statements'!R23)/'Financial Statements'!R22))*Q90
A92: +Dividends on Preferred Stock | B92: =-'Financial Statements'!C28 | C92: =-'Financial Statements'!D28 | D92: =-'Financial Statements'!E28 | E92: =-'Financial Statements'!F28 | F92: =-'Financial Statements'!G28 | G92: =-'Financial Statements'!H28 | H92: =-'Financial Statements'!I28 | I92: =-'Financial Statements'!J28 | ... Q92: =-'Financial Statements'!R28
A93: +Dividends Paid to Noncontrolling Interest | B93: =-'Financial Statements'!C27-('Financial Statements'!C53-'Financial Statements'!B53) | C93: =-'Financial Statements'!D27-('Financial Statements'!D53-'Financial Statements'!C53) | D93: =-'Financial Statements'!E27-('Financial Statements'!E53-'Financial Statements'!D53) | E93: =-'Financial Statements'!F27-('Financial Statements'!F53-'Financial Statements'!E53) | F93: =-'Financial Statements'!G27-('Financial Statements'!G53-'Financial Statements'!F53) | G93: =-'Financial Statements'!H27-('Financial Statements'!H53-'Financial Statements'!G53) | H93: =-'Financial Statements'!I27-('Financial Statements'!I53-'Financial Statements'!H53) | I93: =-'Financial Statements'!J27-('Financial Statements'!J53-'Financial Statements'!I53) | ... Q93: =-'Financial Statements'!R27-('Financial Statements'!R53-'Financial Statements'!Q53)
A94: -Net Issuance of Common Stock | B94: =-('Financial Statements'!C55-'Financial Statements'!B55) | C94: =-('Financial Statements'!D55-'Financial Statements'!C55) | D94: =-('Financial Statements'!E55-'Financial Statements'!D55) | E94: =-('Financial Statements'!F55-'Financial Statements'!E55) | F94: =-('Financial Statements'!G55-'Financial Statements'!F55) | G94: =-('Financial Statements'!H55-'Financial Statements'!G55) | H94: =-('Financial Statements'!I55-'Financial Statements'!H55) | I94: =-('Financial Statements'!J55-'Financial Statements'!I55) | ... Q94: =-('Financial Statements'!R55-'Financial Statements'!Q55)
A95: -Net Issuance of Debt | B95: =-('Financial Statements'!C44+'Financial Statements'!C49-'Financial Statements'!B49-'Financial Statements'!B44) | C95: =-('Financial Statements'!D44+'Financial Statements'!D49-'Financial Statements'!C49-'Financial Statements'!C44) | D95: =-('Financial Statements'!E44+'Financial Statements'!E49-'Financial Statements'!D49-'Financial Statements'!D44) | E95: =-('Financial Statements'!F44+'Financial Statements'!F49-'Financial Statements'!E49-'Financial Statements'!E44) | F95: =-('Financial Statements'!G44+'Financial Statements'!G49-'Financial Statements'!F49-'Financial Statements'!F44) | G95: =-('Financial Statements'!H44+'Financial Statements'!H49-'Financial Statements'!G49-'Financial Statements'!G44) | H95: =-('Financial Statements'!I44+'Financial Statements'!I49-'Financial Statements'!H49-'Financial Statements'!H44) | I95: =-('Financial Statements'!J44+'Financial Statements'!J49-'Financial Statements'!I49-'Financial Statements'!I44) | ... Q95: =-('Financial Statements'!R44+'Financial Statements'!R49-'Financial Statements'!Q49-'Financial Statements'!Q44)
A96: -Net Issuance of Preferred Stock | B96: =-('Financial Statements'!C54-'Financial Statements'!B54) | C96: =-('Financial Statements'!D54-'Financial Statements'!C54) | D96: =-('Financial Statements'!E54-'Financial Statements'!D54) | E96: =-('Financial Statements'!F54-'Financial Statements'!E54) | F96: =-('Financial Statements'!G54-'Financial Statements'!F54) | G96: =-('Financial Statements'!H54-'Financial Statements'!G54) | H96: =-('Financial Statements'!I54-'Financial Statements'!H54) | I96: =-('Financial Statements'!J54-'Financial Statements'!I54) | ... Q96: =-('Financial Statements'!R54-'Financial Statements'!Q54)
A97: =Free Cash Flow to Investors | B97: =SUM(B89:B96) | C97: =SUM(C89:C96) | D97: =SUM(D89:D96) | E97: =SUM(E89:E96) | F97: =SUM(F89:F96) | G97: =SUM(G89:G96) | H97: =SUM(H89:H96) | I97: =SUM(I89:I96) | ... Q97: =SUM(Q89:Q96)
A99: Traditional Computation of FCF:
A100: EBIT | B100: ='Financial Statements'!C19 | C100: ='Financial Statements'!D19 | D100: ='Financial Statements'!E19 | E100: ='Financial Statements'!F19 | F100: ='Financial Statements'!G19 | G100: ='Financial Statements'!H19 | H100: ='Financial Statements'!I19 | I100: ='Financial Statements'!J19 | ... Q100: ='Financial Statements'!R19
A101: -Taxes on EBIT | B101: ='Financial Statements'!C23+(IF('Financial Statements'!C22=0,0,(-'Financial Statements'!C23)/'Financial Statements'!C22))*'Financial Statements'!C20 | C101: ='Financial Statements'!D23+(IF('Financial Statements'!D22=0,0,(-'Financial Statements'!D23)/'Financial Statements'!D22))*'Financial Statements'!D20 | D101: ='Financial Statements'!E23+(IF('Financial Statements'!E22=0,0,(-'Financial Statements'!E23)/'Financial Statements'!E22))*'Financial Statements'!E20 | E101: ='Financial Statements'!F23+(IF('Financial Statements'!F22=0,0,(-'Financial Statements'!F23)/'Financial Statements'!F22))*'Financial Statements'!F20 | F101: ='Financial Statements'!G23+(IF('Financial Statements'!G22=0,0,(-'Financial Statements'!G23)/'Financial Statements'!G22))*'Financial Statements'!G20 | G101: ='Financial Statements'!H23+(IF('Financial Statements'!H22=0,0,(-'Financial Statements'!H23)/'Financial Statements'!H22))*'Financial Statements'!H20 | H101: ='Financial Statements'!I23+(IF('Financial Statements'!I22=0,0,(-'Financial Statements'!I23)/'Financial Statements'!I22))*'Financial Statements'!I20 | I101: ='Financial Statements'!J23+(IF('Financial Statements'!J22=0,0,(-'Financial Statements'!J23)/'Financial Statements'!J22))*'Financial Statements'!J20 | ... Q101: ='Financial Statements'!R23+(IF('Financial Statements'!R22=0,0,(-'Financial Statements'!R23)/'Financial Statements'!R22))*'Financial Statements'!R20
A102: +Increase in Deferred Taxes | B102: ='Financial Statements'!C51-'Financial Statements'!B51 | C102: ='Financial Statements'!D51-'Financial Statements'!C51 | D102: ='Financial Statements'!E51-'Financial Statements'!D51 | E102: ='Financial Statements'!F51-'Financial Statements'!E51 | F102: ='Financial Statements'!G51-'Financial Statements'!F51 | G102: ='Financial Statements'!H51-'Financial Statements'!G51 | H102: ='Financial Statements'!I51-'Financial Statements'!H51 | I102: ='Financial Statements'!J51-'Financial Statements'!I51 | ... Q102: ='Financial Statements'!R51-'Financial Statements'!Q51
A103: = NOPLAT | B103: =SUM(B100:B102) | C103: =SUM(C100:C102) | D103: =SUM(D100:D102) | E103: =SUM(E100:E102) | F103: =SUM(F100:F102) | G103: =SUM(G100:G102) | H103: =SUM(H100:H102) | I103: =SUM(I100:I102) | ... Q103: =SUM(Q100:Q102)
A104: +Depreciation & Amortization | B104: =-'Financial Statements'!C18 | C104: =-'Financial Statements'!D18 | D104: =-'Financial Statements'!E18 | E104: =-'Financial Statements'!F18 | F104: =-'Financial Statements'!G18 | G104: =-'Financial Statements'!H18 | H104: =-'Financial Statements'!I18 | I104: =-'Financial Statements'!J18 | ... Q104: =-'Financial Statements'!R18
A105: +Non-Operating Income (Loss) | B105: ='Financial Statements'!C21 | C105: ='Financial Statements'!D21 | D105: ='Financial Statements'!E21 | E105: ='Financial Statements'!F21 | F105: ='Financial Statements'!G21 | G105: ='Financial Statements'!H21 | H105: ='Financial Statements'!I21 | I105: ='Financial Statements'!J21 | ... Q105: ='Financial Statements'!R21
A106: +Other Income (Loss) | B106: ='Financial Statements'!C24 | C106: ='Financial Statements'!D24 | D106: ='Financial Statements'!E24 | E106: ='Financial Statements'!F24 | F106: ='Financial Statements'!G24 | G106: ='Financial Statements'!H24 | H106: ='Financial Statements'!I24 | I106: ='Financial Statements'!J24 | ... Q106: ='Financial Statements'!R24
A107: +Ext. Items & Disc. Ops. | B107: ='Financial Statements'!C26 | C107: ='Financial Statements'!D26 | D107: ='Financial Statements'!E26 | E107: ='Financial Statements'!F26 | F107: ='Financial Statements'!G26 | G107: ='Financial Statements'!H26 | H107: ='Financial Statements'!I26 | I107: ='Financial Statements'!J26 | ... Q107: ='Financial Statements'!R26
A108: =Gross Cash Flow | B108: =SUM(B103:B107) | C108: =SUM(C103:C107) | D108: =SUM(D103:D107) | E108: =SUM(E103:E107) | F108: =SUM(F103:F107) | G108: =SUM(G103:G107) | H108: =SUM(H103:H107) | I108: =SUM(I103:I107) | ... Q108: =SUM(Q103:Q107)
A109: -Increase in Working Capital | B109: =-('Financial Statements'!C37-'Financial Statements'!B37)+('Financial Statements'!C48-'Financial Statements'!C44-'Financial Statements'!B48+'Financial Statements'!B44) | C109: =-('Financial Statements'!D37-'Financial Statements'!C37)+('Financial Statements'!D48-'Financial Statements'!D44-'Financial Statements'!C48+'Financial Statements'!C44) | D109: =-('Financial Statements'!E37-'Financial Statements'!D37)+('Financial Statements'!E48-'Financial Statements'!E44-'Financial Statements'!D48+'Financial Statements'!D44) | E109: =-('Financial Statements'!F37-'Financial Statements'!E37)+('Financial Statements'!F48-'Financial Statements'!F44-'Financial Statements'!E48+'Financial Statements'!E44) | F109: =-('Financial Statements'!G37-'Financial Statements'!F37)+('Financial Statements'!G48-'Financial Statements'!G44-'Financial Statements'!F48+'Financial Statements'!F44) | G109: =-('Financial Statements'!H37-'Financial Statements'!G37)+('Financial Statements'!H48-'Financial Statements'!H44-'Financial Statements'!G48+'Financial Statements'!G44) | H109: =-('Financial Statements'!I37-'Financial Statements'!H37)+('Financial Statements'!I48-'Financial Statements'!I44-'Financial Statements'!H48+'Financial Statements'!H44) | I109: =-('Financial Statements'!J37-'Financial Statements'!I37)+('Financial Statements'!J48-'Financial Statements'!J44-'Financial Statements'!I48+'Financial Statements'!I44) | ... Q109: =-('Financial Statements'!R37-'Financial Statements'!Q37)+('Financial Statements'!R48-'Financial Statements'!R44-'Financial Statements'!Q48+'Financial Statements'!Q44)
A110: -Capital Expenditures | B110: =-('Financial Statements'!C38-'Financial Statements'!B38-'Financial Statements'!C18) | C110: =-('Financial Statements'!D38-'Financial Statements'!C38-'Financial Statements'!D18) | D110: =-('Financial Statements'!E38-'Financial Statements'!D38-'Financial Statements'!E18) | E110: =-('Financial Statements'!F38-'Financial Statements'!E38-'Financial Statements'!F18) | F110: =-('Financial Statements'!G38-'Financial Statements'!F38-'Financial Statements'!G18) | G110: =-('Financial Statements'!H38-'Financial Statements'!G38-'Financial Statements'!H18) | H110: =-('Financial Statements'!I38-'Financial Statements'!H38-'Financial Statements'!I18) | I110: =-('Financial Statements'!J38-'Financial Statements'!I38-'Financial Statements'!J18) | ... Q110: =-('Financial Statements'!R38-'Financial Statements'!Q38-'Financial Statements'!R18)
A111: -Increase in Investments | B111: =-('Financial Statements'!C39-'Financial Statements'!B39) | C111: =-('Financial Statements'!D39-'Financial Statements'!C39) | D111: =-('Financial Statements'!E39-'Financial Statements'!D39) | E111: =-('Financial Statements'!F39-'Financial Statements'!E39) | F111: =-('Financial Statements'!G39-'Financial Statements'!F39) | G111: =-('Financial Statements'!H39-'Financial Statements'!G39) | H111: =-('Financial Statements'!I39-'Financial Statements'!H39) | I111: =-('Financial Statements'!J39-'Financial Statements'!I39) | ... Q111: =-('Financial Statements'!R39-'Financial Statements'!Q39)
A112: -Purchases of Intangibles | B112: =-('Financial Statements'!C40-'Financial Statements'!B40) | C112: =-('Financial Statements'!D40-'Financial Statements'!C40) | D112: =-('Financial Statements'!E40-'Financial Statements'!D40) | E112: =-('Financial Statements'!F40-'Financial Statements'!E40) | F112: =-('Financial Statements'!G40-'Financial Statements'!F40) | G112: =-('Financial Statements'!H40-'Financial Statements'!G40) | H112: =-('Financial Statements'!I40-'Financial Statements'!H40) | I112: =-('Financial Statements'!J40-'Financial Statements'!I40) | ... Q112: =-('Financial Statements'!R40-'Financial Statements'!Q40)
A113: -Increase in Other Assets | B113: =-('Financial Statements'!C41-'Financial Statements'!B41) | C113: =-('Financial Statements'!D41-'Financial Statements'!C41) | D113: =-('Financial Statements'!E41-'Financial Statements'!D41) | E113: =-('Financial Statements'!F41-'Financial Statements'!E41) | F113: =-('Financial Statements'!G41-'Financial Statements'!F41) | G113: =-('Financial Statements'!H41-'Financial Statements'!G41) | H113: =-('Financial Statements'!I41-'Financial Statements'!H41) | I113: =-('Financial Statements'!J41-'Financial Statements'!I41) | ... Q113: =-('Financial Statements'!R41-'Financial Statements'!Q41)
A114: +Increase in Other Liabilities | B114: =('Financial Statements'!C50-'Financial Statements'!B50) | C114: =('Financial Statements'!D50-'Financial Statements'!C50) | D114: =('Financial Statements'!E50-'Financial Statements'!D50) | E114: =('Financial Statements'!F50-'Financial Statements'!E50) | F114: =('Financial Statements'!G50-'Financial Statements'!F50) | G114: =('Financial Statements'!H50-'Financial Statements'!G50) | H114: =('Financial Statements'!I50-'Financial Statements'!H50) | I114: =('Financial Statements'!J50-'Financial Statements'!I50) | ... Q114: =('Financial Statements'!R50-'Financial Statements'!Q50)
A115: +/-Clean Surplus Plug (Ignore) | B115: ='Financial Statements'!C65 | C115: ='Financial Statements'!D65 | D115: ='Financial Statements'!E65 | E115: ='Financial Statements'!F65 | F115: ='Financial Statements'!G65 | G115: ='Financial Statements'!H65 | H115: ='Financial Statements'!I65 | I115: ='Financial Statements'!J65 | ... Q115: ='Financial Statements'!R65
A116: =Free Cash Flow to Investors | B116: =SUM(B108:B115) | C116: =SUM(C108:C115) | D116: =SUM(D108:D115) | E116: =SUM(E108:E115) | F116: =SUM(F108:F115) | G116: =SUM(G108:G115) | H116: =SUM(H108:H115) | I116: =SUM(I108:I115) | ... Q116: =SUM(Q108:Q115)
A118: Analysis of Earnings Quality
A119: (Red Shading = Quality Flag)
...

Sheet Credit Analysis
A1: Credit Analysis
A4: Company Name | B4: ='Financial Statements'!B4
B6: Actual | C6: Actual | D6: Actual | E6: Actual | F6: Actual | G6: Forecast | H6: Forecast | I6: Forecast | J6: Forecast | K6: Forecast | L6: Forecast | M6: Forecast | N6: Forecast | O6: Forecast | P6: Forecast | Q6: Forecast | R6: Forecast
A7: Fiscal Year End Date | B7: ='Financial Statements'!B8 | C7: ='Financial Statements'!C8 | D7: ='Financial Statements'!D8 | E7: ='Financial Statements'!E8 | F7: ='Financial Statements'!F8 | G7: ='Financial Statements'!G8 | H7: ='Financial Statements'!H8 | I7: ='Financial Statements'!I8 | ... R7: ='Financial Statements'!R8
A9: Analysis of Leverage
A10: - Long-Term Capital Structure
A11: Debt to Equity Ratio | B11: =('Financial Statements'!B44+'Financial Statements'!B49)/('Financial Statements'!B57) | C11: =('Financial Statements'!C44+'Financial Statements'!C49)/('Financial Statements'!C57) | D11: =('Financial Statements'!D44+'Financial Statements'!D49)/('Financial Statements'!D57) | E11: =('Financial Statements'!E44+'Financial Statements'!E49)/('Financial Statements'!E57) | F11: =('Financial Statements'!F44+'Financial Statements'!F49)/('Financial Statements'!F57) | G11: =('Financial Statements'!G44+'Financial Statements'!G49)/('Financial Statements'!G57) | H11: =('Financial Statements'!H44+'Financial Statements'!H49)/('Financial Statements'!H57) | I11: =('Financial Statements'!I44+'Financial Statements'!I49)/('Financial Statements'!I57) | ... R11: =('Financial Statements'!R44+'Financial Statements'!R49)/('Financial Statements'!R57)
A12: FFO to Total Debt | C12: ='Cash Flow Analysis'!B17/(('Financial Statements'!C44+'Financial Statements'!C49+'Financial Statements'!B44+'Financial Statements'!B49)/2) | D12: ='Cash Flow Analysis'!C17/(('Financial Statements'!D44+'Financial Statements'!D49+'Financial Statements'!C44+'Financial Statements'!C49)/2) | E12: ='Cash Flow Analysis'!D17/(('Financial Statements'!E44+'Financial Statements'!E49+'Financial Statements'!D44+'Financial Statements'!D49)/2) | F12: ='Cash Flow Analysis'!E17/(('Financial Statements'!F44+'Financial Statements'!F49+'Financial Statements'!E44+'Financial Statements'!E49)/2) | G12: ='Cash Flow Analysis'!F17/(('Financial Statements'!G44+'Financial Statements'!G49+'Financial Statements'!F44+'Financial Statements'!F49)/2) | H12: ='Cash Flow Analysis'!G17/(('Financial Statements'!H44+'Financial Statements'!H49+'Financial Statements'!G44+'Financial Statements'!G49)/2) | I12: ='Cash Flow Analysis'!H17/(('Financial Statements'!I44+'Financial Statements'!I49+'Financial Statements'!H44+'Financial Statements'!H49)/2) | J12: ='Cash Flow Analysis'!I17/(('Financial Statements'!J44+'Financial Statements'!J49+'Financial Statements'!I44+'Financial Statements'!I49)/2) | ... R12: ='Cash Flow Analysis'!Q17/(('Financial Statements'!R44+'Financial Statements'!R49+'Financial Statements'!Q44+'Financial Statements'!Q49)/2)
A13: CFO to Total Debt | C13: ='Cash Flow Analysis'!B24/(('Financial Statements'!C44+'Financial Statements'!C49+'Financial Statements'!B44+'Financial Statements'!B49)/2) | D13: ='Cash Flow Analysis'!C24/(('Financial Statements'!D44+'Financial Statements'!D49+'Financial Statements'!C44+'Financial Statements'!C49)/2) | E13: ='Cash Flow Analysis'!D24/(('Financial Statements'!E44+'Financial Statements'!E49+'Financial Statements'!D44+'Financial Statements'!D49)/2) | F13: ='Cash Flow Analysis'!E24/(('Financial Statements'!F44+'Financial Statements'!F49+'Financial Statements'!E44+'Financial Statements'!E49)/2) | G13: ='Cash Flow Analysis'!F24/(('Financial Statements'!G44+'Financial Statements'!G49+'Financial Statements'!F44+'Financial Statements'!F49)/2) | H13: ='Cash Flow Analysis'!G24/(('Financial Statements'!H44+'Financial Statements'!H49+'Financial Statements'!G44+'Financial Statements'!G49)/2) | I13: ='Cash Flow Analysis'!H24/(('Financial Statements'!I44+'Financial Statements'!I49+'Financial Statements'!H44+'Financial Statements'!H49)/2) | J13: ='Cash Flow Analysis'!I24/(('Financial Statements'!J44+'Financial Statements'!J49+'Financial Statements'!I44+'Financial Statements'!I49)/2) | ... R13: ='Cash Flow Analysis'!Q24/(('Financial Statements'!R44+'Financial Statements'!R49+'Financial Statements'!Q44+'Financial Statements'!Q49)/2)
A15: Analysis of Leverage
A16: - Short-Term Liquidity
A17: Current Ratio | B17: ='Financial Statements'!B37/'Financial Statements'!B48 | C17: ='Financial Statements'!C37/'Financial Statements'!C48 | D17: ='Financial Statements'!D37/'Financial Statements'!D48 | E17: ='Financial Statements'!E37/'Financial Statements'!E48 | F17: ='Financial Statements'!F37/'Financial Statements'!F48 | G17: ='Financial Statements'!G37/'Financial Statements'!G48 | H17: ='Financial Statements'!H37/'Financial Statements'!H48 | I17: ='Financial Statements'!I37/'Financial Statements'!I48 | ... R17: ='Financial Statements'!R37/'Financial Statements'!R48
A18: Quick Ratio | B18: =('Financial Statements'!B33+'Financial Statements'!B34)/'Financial Statements'!B48 | C18: =('Financial Statements'!C33+'Financial Statements'!C34)/'Financial Statements'!C48 | D18: =('Financial Statements'!D33+'Financial Statements'!D34)/'Financial Statements'!D48 | E18: =('Financial Statements'!E33+'Financial Statements'!E34)/'Financial Statements'!E48 | F18: =('Financial Statements'!F33+'Financial Statements'!F34)/'Financial Statements'!F48 | G18: =('Financial Statements'!G33+'Financial Statements'!G34)/'Financial Statements'!G48 | H18: =('Financial Statements'!H33+'Financial Statements'!H34)/'Financial Statements'!H48 | I18: =('Financial Statements'!I33+'Financial Statements'!I34)/'Financial Statements'!I48 | ... R18: =('Financial Statements'!R33+'Financial Statements'!R34)/'Financial Statements'!R48
A19: EBIT Interest Coverage | B19: =-'Financial Statements'!B19/'Financial Statements'!B20 | C19: =-'Financial Statements'!C19/'Financial Statements'!C20 | D19: =-'Financial Statements'!D19/'Financial Statements'!D20 | E19: =-'Financial Statements'!E19/'Financial Statements'!E20 | F19: =-'Financial Statements'!F19/'Financial Statements'!F20 | G19: =-'Financial Statements'!G19/'Financial Statements'!G20 | H19: =-'Financial Statements'!H19/'Financial Statements'!H20 | I19: =-'Financial Statements'!I19/'Financial Statements'!I20 | ... R19: =-'Financial Statements'!R19/'Financial Statements'!R20
A20: EBITDA Interest Coverage | B20: =-'Financial Statements'!B17/'Financial Statements'!B20 | C20: =-'Financial Statements'!C17/'Financial Statements'!C20 | D20: =-'Financial Statements'!D17/'Financial Statements'!D20 | E20: =-'Financial Statements'!E17/'Financial Statements'!E20 | F20: =-'Financial Statements'!F17/'Financial Statements'!F20 | G20: =-'Financial Statements'!G17/'Financial Statements'!G20 | H20: =-'Financial Statements'!H17/'Financial Statements'!H20 | I20: =-'Financial Statements'!I17/'Financial Statements'!I20 | ... R20: =-'Financial Statements'!R17/'Financial Statements'!R20
A22: Analysis of Credit Risk
A23: Net Income to Total Assets | B23: ='Financial Statements'!B25/'Financial Statements'!B42 | C23: ='Financial Statements'!C25/'Financial Statements'!C42 | D23: ='Financial Statements'!D25/'Financial Statements'!D42 | E23: ='Financial Statements'!E25/'Financial Statements'!E42 | F23: ='Financial Statements'!F25/'Financial Statements'!F42 | G23: ='Financial Statements'!G25/'Financial Statements'!G42 | H23: ='Financial Statements'!H25/'Financial Statements'!H42 | I23: ='Financial Statements'!I25/'Financial Statements'!I42 | ... R23: ='Financial Statements'!R25/'Financial Statements'!R42
A24: implied default probability | B24: =IF(B23<$C44,$B45,HLOOKUP(B23,$C44:$K45,2,TRUE)) | C24: =IF(C23<$C44,$B45,HLOOKUP(C23,$C44:$K45,2,TRUE)) | D24: =IF(D23<$C44,$B45,HLOOKUP(D23,$C44:$K45,2,TRUE)) | E24: =IF(E23<$C44,$B45,HLOOKUP(E23,$C44:$K45,2,TRUE)) | F24: =IF(F23<$C44,$B45,HLOOKUP(F23,$C44:$K45,2,TRUE)) | G24: =IF(G23<$C44,$B45,HLOOKUP(G23,$C44:$K45,2,TRUE)) | H24: =IF(H23<$C44,$B45,HLOOKUP(H23,$C44:$K45,2,TRUE)) | I24: =IF(I23<$C44,$B45,HLOOKUP(I23,$C44:$K45,2,TRUE)) | ... R24: =IF(R23<$C44,$B45,HLOOKUP(R23,$C44:$K45,2,TRUE))
A25: Total Liabilities to Total Assets | B25: ='Financial Statements'!B52/'Financial Statements'!B42 | C25: ='Financial Statements'!C52/'Financial Statements'!C42 | D25: ='Financial Statements'!D52/'Financial Statements'!D42 | E25: ='Financial Statements'!E52/'Financial Statements'!E42 | F25: ='Financial Statements'!F52/'Financial Statements'!F42 | G25: ='Financial Statements'!G52/'Financial Statements'!G42 | H25: ='Financial Statements'!H52/'Financial Statements'!H42 | I25: ='Financial Statements'!I52/'Financial Statements'!I42 | ... R25: ='Financial Statements'!R52/'Financial Statements'!R42
A26: implied default probability | B26: =IF(B25<$C46,$B47,HLOOKUP(B25,$C46:$K47,2,TRUE)) | C26: =IF(C25<$C46,$B47,HLOOKUP(C25,$C46:$K47,2,TRUE)) | D26: =IF(D25<$C46,$B47,HLOOKUP(D25,$C46:$K47,2,TRUE)) | E26: =IF(E25<$C46,$B47,HLOOKUP(E25,$C46:$K47,2,TRUE)) | F26: =IF(F25<$C46,$B47,HLOOKUP(F25,$C46:$K47,2,TRUE)) | G26: =IF(G25<$C46,$B47,HLOOKUP(G25,$C46:$K47,2,TRUE)) | H26: =IF(H25<$C46,$B47,HLOOKUP(H25,$C46:$K47,2,TRUE)) | I26: =IF(I25<$C46,$B47,HLOOKUP(I25,$C46:$K47,2,TRUE)) | ... R26: =IF(R25<$C46,$B47,HLOOKUP(R25,$C46:$K47,2,TRUE))
A27: Quick Ratio | B27: =B18 | C27: =C18 | D27: =D18 | E27: =E18 | F27: =F18 | G27: =G18 | H27: =H18 | I27: =I18 | ... R27: =R18
A28: implied default probability | B28: =IF(B27<$C48,$B49,HLOOKUP(B27,$C48:$K49,2,TRUE)) | C28: =IF(C27<$C48,$B49,HLOOKUP(C27,$C48:$K49,2,TRUE)) | D28: =IF(D27<$C48,$B49,HLOOKUP(D27,$C48:$K49,2,TRUE)) | E28: =IF(E27<$C48,$B49,HLOOKUP(E27,$C48:$K49,2,TRUE)) | F28: =IF(F27<$C48,$B49,HLOOKUP(F27,$C48:$K49,2,TRUE)) | G28: =IF(G27<$C48,$B49,HLOOKUP(G27,$C48:$K49,2,TRUE)) | H28: =IF(H27<$C48,$B49,HLOOKUP(H27,$C48:$K49,2,TRUE)) | I28: =IF(I27<$C48,$B49,HLOOKUP(I27,$C48:$K49,2,TRUE)) | ... R28: =IF(R27<$C48,$B49,HLOOKUP(R27,$C48:$K49,2,TRUE))
A29: EBIT to Interest Expense | B29: =B19 | C29: =C19 | D29: =D19 | E29: =E19 | F29: =F19 | G29: =G19 | H29: =H19 | I29: =I19 | ... R29: =R19
A30: implied default probability | B30: =IF(B29<$C50,$B51,HLOOKUP(B29,$C50:$K51,2,TRUE)) | C30: =IF(C29<$C50,$B51,HLOOKUP(C29,$C50:$K51,2,TRUE)) | D30: =IF(D29<$C50,$B51,HLOOKUP(D29,$C50:$K51,2,TRUE)) | E30: =IF(E29<$C50,$B51,HLOOKUP(E29,$C50:$K51,2,TRUE)) | F30: =IF(F29<$C50,$B51,HLOOKUP(F29,$C50:$K51,2,TRUE)) | G30: =IF(G29<$C50,$B51,HLOOKUP(G29,$C50:$K51,2,TRUE)) | H30: =IF(H29<$C50,$B51,HLOOKUP(H29,$C50:$K51,2,TRUE)) | I30: =IF(I29<$C50,$B51,HLOOKUP(I29,$C50:$K51,2,TRUE)) | ... R30: =IF(R29<$C50,$B51,HLOOKUP(R29,$C50:$K51,2,TRUE))
A31: Inventory Holding Period | B31: =-365*'Financial Statements'!B35/'Financial Statements'!B13 | C31: =-365*'Financial Statements'!C35/'Financial Statements'!C13 | D31: =-365*'Financial Statements'!D35/'Financial Statements'!D13 | E31: =-365*'Financial Statements'!E35/'Financial Statements'!E13 | F31: =-365*'Financial Statements'!F35/'Financial Statements'!F13 | G31: =-365*'Financial Statements'!G35/'Financial Statements'!G13 | H31: =-365*'Financial Statements'!H35/'Financial Statements'!H13 | I31: =-365*'Financial Statements'!I35/'Financial Statements'!I13 | ... R31: =-365*'Financial Statements'!R35/'Financial Statements'!R13
A32: implied default probability | B32: =IF(B31<$C52,$B53,HLOOKUP(B31,$C52:$K53,2,TRUE)) | C32: =IF(C31<$C52,$B53,HLOOKUP(C31,$C52:$K53,2,TRUE)) | D32: =IF(D31<$C52,$B53,HLOOKUP(D31,$C52:$K53,2,TRUE)) | E32: =IF(E31<$C52,$B53,HLOOKUP(E31,$C52:$K53,2,TRUE)) | F32: =IF(F31<$C52,$B53,HLOOKUP(F31,$C52:$K53,2,TRUE)) | G32: =IF(G31<$C52,$B53,HLOOKUP(G31,$C52:$K53,2,TRUE)) | H32: =IF(H31<$C52,$B53,HLOOKUP(H31,$C52:$K53,2,TRUE)) | I32: =IF(I31<$C52,$B53,HLOOKUP(I31,$C52:$K53,2,TRUE)) | ... R32: =IF(R31<$C52,$B53,HLOOKUP(R31,$C52:$K53,2,TRUE))
A33: Annual Sales Growth | B33: ='Ratio Analysis'!B10 | C33: ='Ratio Analysis'!C10 | D33: ='Ratio Analysis'!D10 | E33: ='Ratio Analysis'!E10 | F33: ='Ratio Analysis'!F10 | G33: ='Ratio Analysis'!G10 | H33: ='Ratio Analysis'!H10 | I33: ='Ratio Analysis'!I10 | ... R33: ='Ratio Analysis'!R10
A34: implied default probability | B34: =IF(B33<$C54,$B55,HLOOKUP(B33,$C54:$K55,2,TRUE)) | C34: =IF(C33<$C54,$B55,HLOOKUP(C33,$C54:$K55,2,TRUE)) | D34: =IF(D33<$C54,$B55,HLOOKUP(D33,$C54:$K55,2,TRUE)) | E34: =IF(E33<$C54,$B55,HLOOKUP(E33,$C54:$K55,2,TRUE)) | F34: =IF(F33<$C54,$B55,HLOOKUP(F33,$C54:$K55,2,TRUE)) | G34: =IF(G33<$C54,$B55,HLOOKUP(G33,$C54:$K55,2,TRUE)) | H34: =IF(H33<$C54,$B55,HLOOKUP(H33,$C54:$K55,2,TRUE)) | I34: =IF(I33<$C54,$B55,HLOOKUP(I33,$C54:$K55,2,TRUE)) | ... R34: =IF(R33<$C54,$B55,HLOOKUP(R33,$C54:$K55,2,TRUE))
A35: Average Implied Default Probability | B35: =AVERAGE(B24,B26,B28,B30,B32,B34) | C35: =AVERAGE(C24,C26,C28,C30,C32,C34) | D35: =AVERAGE(D24,D26,D28,D30,D32,D34) | E35: =AVERAGE(E24,E26,E28,E30,E32,E34) | F35: =AVERAGE(F24,F26,F28,F30,F32,F34) | G35: =AVERAGE(G24,G26,G28,G30,G32,G34) | H35: =AVERAGE(H24,H26,H28,H30,H32,H34) | I35: =AVERAGE(I24,I26,I28,I30,I32,I34) | ... R35: =AVERAGE(R24,R26,R28,R30,R32,R34)
A37: Fiscal Year | B37: =IF(MONTH(B7)>6,YEAR(B7),YEAR(B7)-1) | C37: =IF(MONTH(C7)>6,YEAR(C7),YEAR(C7)-1) | D37: =IF(MONTH(D7)>6,YEAR(D7),YEAR(D7)-1) | E37: =IF(MONTH(E7)>6,YEAR(E7),YEAR(E7)-1) | F37: =IF(MONTH(F7)>6,YEAR(F7),YEAR(F7)-1) | G37: =IF(MONTH(G7)>6,YEAR(G7),YEAR(G7)-1) | H37: =IF(MONTH(H7)>6,YEAR(H7),YEAR(H7)-1) | I37: =IF(MONTH(I7)>6,YEAR(I7),YEAR(I7)-1) | ... R37: =IF(MONTH(R7)>6,YEAR(R7),YEAR(R7)-1)
A39: Default Probability Color Scale | B39: Low | C39: Medium | D39: High
A43: Lookup Table of default probability | B43: decile 1 | C43: min decile 2 | D43: min decile 3 | E43: min decile 4 | F43: min decile 5 | G43: min decile 6 | H43: min decile 7 | I43: min decile 8 | J43: min decile 9 | K43: min decile 10 | L43: Min | M43: Max
A44: NI to TA thresholds | C44: -0.448 | D44: -0.161 | E44: -0.049 | F44: 0.001 | G44: 0.022 | H44: 0.038 | I44: 0.056 | J44: 0.079 | K44: 0.118
A45: NI to TA default rates | B45: 0.083 | C45: 0.08 | D45: 0.072 | E45: 0.055 | F45: 0.045 | G45: 0.03 | H45: 0.025 | I45: 0.02 | J45: 0.02 | K45: 0.02 | L45: =K45 | M45: =B45 | N45: =AVERAGE(L45:M45)
A46: TL to TA thresholds | C46: 0.175 | D46: 0.283 | E46: 0.385 | F46: 0.476 | G46: 0.558 | H46: 0.633 | I46: 0.709 | J46: 0.816 | K46: 1.03
A47: TL to TA default rates | B47: 0.02 | C47: 0.022 | D47: 0.025 | E47: 0.03 | F47: 0.035 | G47: 0.045 | H47: 0.055 | I47: 0.07 | J47: 0.09 | K47: 0.1 | L47: =B47 | M47: =K47 | N47: =AVERAGE(L47:M47)
A48: Quick Ratio thresholds | C48: 0.382 | D48: 0.522 | E48: 0.809 | F48: 0.994 | G48: 1.2 | H48: 1.47 | I48: 1.89 | J48: 2.53 | K48: 4.55
A49: Quick Ratio default rates | B49: 0.09 | C49: 0.065 | D49: 0.05 | E49: 0.042 | F49: 0.04 | G49: 0.035 | H49: 0.025 | I49: 0.02 | J49: 0.015 | K49: 0.01 | L49: =K49 | M49: =B49 | N49: =AVERAGE(L49:M49)
A50: EBIT to Int thresholds | C50: -17.4 | D50: -3.6 | E50: -0.139 | F50: 1.25 | G50: 2.21 | H50: 3.38 | I50: 5.21 | J50: 9.16 | K50: 23.8
A51: EBIT to Int default rates | B51: 0.075 | C51: 0.09 | D51: 0.085 | E51: 0.07 | F51: 0.05 | G51: 0.03 | H51: 0.021 | I51: 0.018 | J51: 0.015 | K51: 0.01 | L51: =K51 | M51: =B51 | N51: =AVERAGE(L51:M51)
A52: Inv Holding thresholds | C52: 0.365 | D52: 2.56 | E52: 14.24 | F52: 31.39 | G52: 50 | H52: 70.08 | I52: 91.98 | J52: 121.54 | K52: 174.47
A53: Inv Holding default rates | B53: 0.03 | C53: 0.035 | D53: 0.039 | E53: 0.04 | F53: 0.042 | G53: 0.045 | H53: 0.049 | I53: 0.055 | J53: 0.06 | K53: 0.07 | L53: =B53 | M53: =K53 | N53: =AVERAGE(L53:M53)
A54: Sales Growth thresholds | C54: -0.203 | D54: -0.063 | E54: 0.003 | F54: 0.05 | G54: 0.098 | H54: 0.158 | I54: 0.244 | J54: 0.398 | K54: 0.797
A55: Sales Growth default rates | B55: 0.069 | C55: 0.055 | D55: 0.042 | E55: 0.032 | F55: 0.03 | G55: 0.03 | H55: 0.032 | I55: 0.042 | J55: 0.05 | K55: 0.065 | L55: =F55 | M55: =B55 | N55: =AVERAGE(L55:M55)
L56: =AVERAGE(L45,L47,L49,L51,L53) | M56: =AVERAGE(M45,M47,M49,M51,M53) | N56: =AVERAGE(L56:M56)

Sheet Forecasting Assumptions
A1: Forecasting Assumptions
C3: 0.15
C4: 0.2
A5: Company Name | B5: ='Financial Statements'!B4
Q6: TERMINAL
A7: ="Estimated Price/Share="&DOLLAR('Model Summary'!B22) | Q7: YEAR
B8: Actual | C8: Actual | D8: Actual | E8: Actual | F8: Actual | G8: Forecast | H8: Forecast | I8: Forecast | J8: Forecast | K8: Forecast | L8: Forecast | M8: Forecast | N8: Forecast | O8: Forecast | P8: Forecast | Q8: Forecast | R8: Forecast
A9: Fiscal Year End Date | B9: ='Financial Statements'!B8 | C9: ='Financial Statements'!C8 | D9: ='Financial Statements'!D8 | E9: ='Financial Statements'!E8 | F9: ='Financial Statements'!F8 | G9: ='Financial Statements'!G8 | H9: ='Financial Statements'!H8 | I9: ='Financial Statements'!I8 | ... R9: ='Financial Statements'!R8
A11: Implied Return on Equity | C11: ='Financial Statements'!C29/(('Financial Statements'!C57+'Financial Statements'!B57)/2) | D11: ='Financial Statements'!D29/(('Financial Statements'!D57+'Financial Statements'!C57)/2) | E11: ='Financial Statements'!E29/(('Financial Statements'!E57+'Financial Statements'!D57)/2) | F11: ='Financial Statements'!F29/(('Financial Statements'!F57+'Financial Statements'!E57)/2) | G11: ='Financial Statements'!G29/(('Financial Statements'!G57+'Financial Statements'!F57)/2) | H11: ='Financial Statements'!H29/(('Financial Statements'!H57+'Financial Statements'!G57)/2) | I11: ='Financial Statements'!I29/(('Financial Statements'!I57+'Financial Statements'!H57)/2) | J11: ='Financial Statements'!J29/(('Financial Statements'!J57+'Financial Statements'!I57)/2) | ... R11: ='Financial Statements'!R29/(('Financial Statements'!R57+'Financial Statements'!Q57)/2)
A13: Income Statement Assumptions
A14: Sales Growth | C14: ='Financial Statements'!C12/'Financial Statements'!B12-1 | D14: ='Financial Statements'!D12/'Financial Statements'!C12-1 | E14: ='Financial Statements'!E12/'Financial Statements'!D12-1 | F14: ='Financial Statements'!F12/'Financial Statements'!E12-1 | G14: =F14-($F14-$Q14)/11 | H14: =G14-($G14-$Q14)/10 | I14: =H14-($H14-$Q14)/9 | J14: =I14-($I14-$Q14)/8 | K14: =J14-($J14-$Q14)/7 | L14: =K14-($K14-$Q14)/6 | M14: =L14-($L14-$Q14)/5 | N14: =M14-($M14-$Q14)/4 | O14: =N14-($N14-$Q14)/3 | P14: =O14-($O14-$Q14)/2 | Q14: 0.03 | R14: =$Q14
A15: Cost of Goods Sold/Sales | B15: =-'Financial Statements'!B13/'Financial Statements'!B12 | C15: =-'Financial Statements'!C13/'Financial Statements'!C12 | D15: =-'Financial Statements'!D13/'Financial Statements'!D12 | E15: =-'Financial Statements'!E13/'Financial Statements'!E12 | F15: =-'Financial Statements'!F13/'Financial Statements'!F12 | G15: =F15-($F15-$Q15)/11 | H15: =G15-($G15-$Q15)/10 | I15: =H15-($H15-$Q15)/9 | J15: =I15-($I15-$Q15)/8 | K15: =J15-($J15-$Q15)/7 | L15: =K15-($K15-$Q15)/6 | M15: =L15-($L15-$Q15)/5 | N15: =M15-($M15-$Q15)/4 | O15: =N15-($N15-$Q15)/3 | P15: =O15-($O15-$Q15)/2 | Q15: =$F15 | R15: =$Q15
A16: R&D/Sales | B16: =-'Financial Statements'!B15/'Financial Statements'!B12 | C16: =-'Financial Statements'!C15/'Financial Statements'!C12 | D16: =-'Financial Statements'!D15/'Financial Statements'!D12 | E16: =-'Financial Statements'!E15/'Financial Statements'!E12 | F16: =-'Financial Statements'!F15/'Financial Statements'!F12 | G16: =F16-($F16-$Q16)/11 | H16: =G16-($G16-$Q16)/10 | I16: =H16-($H16-$Q16)/9 | J16: =I16-($I16-$Q16)/8 | K16: =J16-($J16-$Q16)/7 | L16: =K16-($K16-$Q16)/6 | M16: =L16-($L16-$Q16)/5 | N16: =M16-($M16-$Q16)/4 | O16: =N16-($N16-$Q16)/3 | P16: =O16-($O16-$Q16)/2 | Q16: =$F16 | R16: =$Q16
A17: SG&A/Sales | B17: =-'Financial Statements'!B16/'Financial Statements'!B12 | C17: =-'Financial Statements'!C16/'Financial Statements'!C12 | D17: =-'Financial Statements'!D16/'Financial Statements'!D12 | E17: =-'Financial Statements'!E16/'Financial Statements'!E12 | F17: =-'Financial Statements'!F16/'Financial Statements'!F12 | G17: =F17-($F17-$Q17)/11 | H17: =G17-($G17-$Q17)/10 | I17: =H17-($H17-$Q17)/9 | J17: =I17-($I17-$Q17)/8 | K17: =J17-($J17-$Q17)/7 | L17: =K17-($K17-$Q17)/6 | M17: =L17-($L17-$Q17)/5 | N17: =M17-($M17-$Q17)/4 | O17: =N17-($N17-$Q17)/3 | P17: =O17-($O17-$Q17)/2 | Q17: =$F17 | R17: =$Q17
A18: Dep&Amort/Avge PP&E and Intang. | C18: =IF((('Financial Statements'!B38+'Financial Statements'!C38+'Financial Statements'!B40+'Financial Statements'!C40)/2)=0,0,-'Financial Statements'!C18/(('Financial Statements'!B38+'Financial Statements'!C38+'Financial Statements'!B40+'Financial Statements'!C40)/2)) | D18: =IF((('Financial Statements'!C38+'Financial Statements'!D38+'Financial Statements'!C40+'Financial Statements'!D40)/2)=0,0,-'Financial Statements'!D18/(('Financial Statements'!C38+'Financial Statements'!D38+'Financial Statements'!C40+'Financial Statements'!D40)/2)) | E18: =IF((('Financial Statements'!D38+'Financial Statements'!E38+'Financial Statements'!D40+'Financial Statements'!E40)/2)=0,0,-'Financial Statements'!E18/(('Financial Statements'!D38+'Financial Statements'!E38+'Financial Statements'!D40+'Financial Statements'!E40)/2)) | F18: =IF((('Financial Statements'!E38+'Financial Statements'!F38+'Financial Statements'!E40+'Financial Statements'!F40)/2)=0,0,-'Financial Statements'!F18/(('Financial Statements'!E38+'Financial Statements'!F38+'Financial Statements'!E40+'Financial Statements'!F40)/2)) | G18: =F18-($F18-$Q18)/11 | H18: =G18-($G18-$Q18)/10 | I18: =H18-($H18-$Q18)/9 | J18: =I18-($I18-$Q18)/8 | K18: =J18-($J18-$Q18)/7 | L18: =K18-($K18-$Q18)/6 | M18: =L18-($L18-$Q18)/5 | N18: =M18-($M18-$Q18)/4 | O18: =N18-($N18-$Q18)/3 | P18: =O18-($O18-$Q18)/2 | Q18: =$F18 | R18: =$Q18
A19: Net Interest Expense/Avge Net Debt | C19: =IF((('Financial Statements'!B44+'Financial Statements'!C44+'Financial Statements'!C49+'Financial Statements'!B49)/2)=0,0,-'Financial Statements'!C20/(('Financial Statements'!B44+'Financial Statements'!C44+'Financial Statements'!C49+'Financial Statements'!B49)/2)) | D19: =IF((('Financial Statements'!C44+'Financial Statements'!D44+'Financial Statements'!D49+'Financial Statements'!C49)/2)=0,0,-'Financial Statements'!D20/(('Financial Statements'!C44+'Financial Statements'!D44+'Financial Statements'!D49+'Financial Statements'!C49)/2)) | E19: =IF((('Financial Statements'!D44+'Financial Statements'!E44+'Financial Statements'!E49+'Financial Statements'!D49)/2)=0,0,-'Financial Statements'!E20/(('Financial Statements'!D44+'Financial Statements'!E44+'Financial Statements'!E49+'Financial Statements'!D49)/2)) | F19: =IF((('Financial Statements'!E44+'Financial Statements'!F44+'Financial Statements'!F49+'Financial Statements'!E49)/2)=0,0,-'Financial Statements'!F20/(('Financial Statements'!E44+'Financial Statements'!F44+'Financial Statements'!F49+'Financial Statements'!E49)/2)) | G19: =F19-($F19-$Q19)/11 | H19: =G19-($G19-$Q19)/10 | I19: =H19-($H19-$Q19)/9 | J19: =I19-($I19-$Q19)/8 | K19: =J19-($J19-$Q19)/7 | L19: =K19-($K19-$Q19)/6 | M19: =L19-($L19-$Q19)/5 | N19: =M19-($M19-$Q19)/4 | O19: =N19-($N19-$Q19)/3 | P19: =O19-($O19-$Q19)/2 | Q19: =$F19 | R19: =$Q19
A20: Non-Operating Income/Sales | B20: ='Financial Statements'!B21/'Financial Statements'!B12 | C20: ='Financial Statements'!C21/'Financial Statements'!C12 | D20: ='Financial Statements'!D21/'Financial Statements'!D12 | E20: ='Financial Statements'!E21/'Financial Statements'!E12 | F20: ='Financial Statements'!F21/'Financial Statements'!F12 | G20: =F20-($F20-$Q20)/11 | H20: =G20-($G20-$Q20)/10 | I20: =H20-($H20-$Q20)/9 | J20: =I20-($I20-$Q20)/8 | K20: =J20-($J20-$Q20)/7 | L20: =K20-($K20-$Q20)/6 | M20: =L20-($L20-$Q20)/5 | N20: =M20-($M20-$Q20)/4 | O20: =N20-($N20-$Q20)/3 | P20: =O20-($O20-$Q20)/2 | Q20: =$F20 | R20: =$Q20
A21: Effective Tax Rate | B21: =IF('Financial Statements'!B22=0,0,-'Financial Statements'!B23/'Financial Statements'!B22) | C21: =IF('Financial Statements'!C22=0,0,-'Financial Statements'!C23/'Financial Statements'!C22) | D21: =IF('Financial Statements'!D22=0,0,-'Financial Statements'!D23/'Financial Statements'!D22) | E21: =IF('Financial Statements'!E22=0,0,-'Financial Statements'!E23/'Financial Statements'!E22) | F21: =IF('Financial Statements'!F22=0,0,-'Financial Statements'!F23/'Financial Statements'!F22) | G21: =F21-($F21-$Q21)/11 | H21: =G21-($G21-$Q21)/10 | I21: =H21-($H21-$Q21)/9 | J21: =I21-($I21-$Q21)/8 | K21: =J21-($J21-$Q21)/7 | L21: =K21-($K21-$Q21)/6 | M21: =L21-($L21-$Q21)/5 | N21: =M21-($M21-$Q21)/4 | O21: =N21-($N21-$Q21)/3 | P21: =O21-($O21-$Q21)/2 | Q21: =$F21 | R21: =$Q21
A22: Noncontrolling Interest/After Tax Income | B22: =IF(('Financial Statements'!B22+'Financial Statements'!B23)=0,0,-'Financial Statements'!B27/('Financial Statements'!B22+'Financial Statements'!B23)) | C22: =IF(('Financial Statements'!C22+'Financial Statements'!C23)=0,0,-'Financial Statements'!C27/('Financial Statements'!C22+'Financial Statements'!C23)) | D22: =IF(('Financial Statements'!D22+'Financial Statements'!D23)=0,0,-'Financial Statements'!D27/('Financial Statements'!D22+'Financial Statements'!D23)) | E22: =IF(('Financial Statements'!E22+'Financial Statements'!E23)=0,0,-'Financial Statements'!E27/('Financial Statements'!E22+'Financial Statements'!E23)) | F22: =IF(('Financial Statements'!F22+'Financial Statements'!F23)=0,0,-'Financial Statements'!F27/('Financial Statements'!F22+'Financial Statements'!F23)) | G22: =F22-($F22-$Q22)/11 | H22: =G22-($G22-$Q22)/10 | I22: =H22-($H22-$Q22)/9 | J22: =I22-($I22-$Q22)/8 | K22: =J22-($J22-$Q22)/7 | L22: =K22-($K22-$Q22)/6 | M22: =L22-($L22-$Q22)/5 | N22: =M22-($M22-$Q22)/4 | O22: =N22-($N22-$Q22)/3 | P22: =O22-($O22-$Q22)/2 | Q22: =$F22 | R22: =$Q22
A23: Other Income/Sales | B23: ='Financial Statements'!B24/'Financial Statements'!B12 | C23: ='Financial Statements'!C24/'Financial Statements'!C12 | D23: ='Financial Statements'!D24/'Financial Statements'!D12 | E23: ='Financial Statements'!E24/'Financial Statements'!E12 | F23: ='Financial Statements'!F24/'Financial Statements'!F12 | G23: 0 | H23: =G23 | I23: =H23 | J23: =I23 | K23: =J23 | L23: =K23 | M23: =L23 | N23: =M23 | O23: =N23 | ... Q23: =P23 | R23: =$Q23
A24: Ext. Items & Disc. Ops./Sales | B24: ='Financial Statements'!B26/'Financial Statements'!B12 | C24: ='Financial Statements'!C26/'Financial Statements'!C12 | D24: ='Financial Statements'!D26/'Financial Statements'!D12 | E24: ='Financial Statements'!E26/'Financial Statements'!E12 | F24: ='Financial Statements'!F26/'Financial Statements'!F12 | G24: 0 | H24: =G24 | I24: =H24 | J24: =I24 | K24: =J24 | L24: =K24 | M24: =L24 | N24: =M24 | O24: =N24 | ... Q24: =P24 | R24: =$Q24
A25: Pref. Dividends/Avge Pref. Stock | C25: =IF((('Financial Statements'!C54+'Financial Statements'!B54)/2)=0,0,-'Financial Statements'!C28/(('Financial Statements'!C54+'Financial Statements'!B54)/2)) | D25: =IF((('Financial Statements'!D54+'Financial Statements'!C54)/2)=0,0,-'Financial Statements'!D28/(('Financial Statements'!D54+'Financial Statements'!C54)/2)) | E25: =IF((('Financial Statements'!E54+'Financial Statements'!D54)/2)=0,0,-'Financial Statements'!E28/(('Financial Statements'!E54+'Financial Statements'!D54)/2)) | F25: =IF((('Financial Statements'!F54+'Financial Statements'!E54)/2)=0,0,-'Financial Statements'!F28/(('Financial Statements'!F54+'Financial Statements'!E54)/2)) | G25: =F25-($F25-$Q25)/11 | H25: =G25-($G25-$Q25)/10 | I25: =H25-($H25-$Q25)/9 | J25: =I25-($I25-$Q25)/8 | K25: =J25-($J25-$Q25)/7 | L25: =K25-($K25-$Q25)/6 | M25: =L25-($L25-$Q25)/5 | N25: =M25-($M25-$Q25)/4 | O25: =N25-($N25-$Q25)/3 | P25: =O25-($O25-$Q25)/2 | Q25: =$F25 | R25: =$Q25
A27: Balance Sheet Assumptions
A28: Working Capital Assumptions
A29: Ending Operating Cash/Sales | B29: ='Financial Statements'!B33/'Financial Statements'!B12 | C29: ='Financial Statements'!C33/'Financial Statements'!C12 | D29: ='Financial Statements'!D33/'Financial Statements'!D12 | E29: ='Financial Statements'!E33/'Financial Statements'!E12 | F29: ='Financial Statements'!F33/'Financial Statements'!F12 | G29: =F29-($F29-$Q29)/11 | H29: =G29-($G29-$Q29)/10 | I29: =H29-($H29-$Q29)/9 | J29: =I29-($I29-$Q29)/8 | K29: =J29-($J29-$Q29)/7 | L29: =K29-($K29-$Q29)/6 | M29: =L29-($L29-$Q29)/5 | N29: =M29-($M29-$Q29)/4 | O29: =N29-($N29-$Q29)/3 | P29: =O29-($O29-$Q29)/2 | Q29: =$F29 | R29: =$Q29
A30: Ending Receivables/Sales | B30: ='Financial Statements'!B34/'Financial Statements'!B12 | C30: ='Financial Statements'!C34/'Financial Statements'!C12 | D30: ='Financial Statements'!D34/'Financial Statements'!D12 | E30: ='Financial Statements'!E34/'Financial Statements'!E12 | F30: ='Financial Statements'!F34/'Financial Statements'!F12 | G30: =F30-($F30-$Q30)/11 | H30: =G30-($G30-$Q30)/10 | I30: =H30-($H30-$Q30)/9 | J30: =I30-($I30-$Q30)/8 | K30: =J30-($J30-$Q30)/7 | L30: =K30-($K30-$Q30)/6 | M30: =L30-($L30-$Q30)/5 | N30: =M30-($M30-$Q30)/4 | O30: =N30-($N30-$Q30)/3 | P30: =O30-($O30-$Q30)/2 | Q30: =$F30 | R30: =$Q30
A31: Ending Inventories/COGS | B31: =IF('Financial Statements'!B13=0,0,-'Financial Statements'!B35/'Financial Statements'!B13) | C31: =IF('Financial Statements'!C13=0,0,-'Financial Statements'!C35/'Financial Statements'!C13) | D31: =IF('Financial Statements'!D13=0,0,-'Financial Statements'!D35/'Financial Statements'!D13) | E31: =IF('Financial Statements'!E13=0,0,-'Financial Statements'!E35/'Financial Statements'!E13) | F31: =IF('Financial Statements'!F13=0,0,-'Financial Statements'!F35/'Financial Statements'!F13) | G31: =F31-($F31-$Q31)/11 | H31: =G31-($G31-$Q31)/10 | I31: =H31-($H31-$Q31)/9 | J31: =I31-($I31-$Q31)/8 | K31: =J31-($J31-$Q31)/7 | L31: =K31-($K31-$Q31)/6 | M31: =L31-($L31-$Q31)/5 | N31: =M31-($M31-$Q31)/4 | O31: =N31-($N31-$Q31)/3 | P31: =O31-($O31-$Q31)/2 | Q31: =$F31 | R31: =$Q31
A32: Ending Other Current Assets/Sales | B32: ='Financial Statements'!B36/'Financial Statements'!B12 | C32: ='Financial Statements'!C36/'Financial Statements'!C12 | D32: ='Financial Statements'!D36/'Financial Statements'!D12 | E32: ='Financial Statements'!E36/'Financial Statements'!E12 | F32: ='Financial Statements'!F36/'Financial Statements'!F12 | G32: =F32-($F32-$Q32)/11 | H32: =G32-($G32-$Q32)/10 | I32: =H32-($H32-$Q32)/9 | J32: =I32-($I32-$Q32)/8 | K32: =J32-($J32-$Q32)/7 | L32: =K32-($K32-$Q32)/6 | M32: =L32-($L32-$Q32)/5 | N32: =M32-($M32-$Q32)/4 | O32: =N32-($N32-$Q32)/3 | P32: =O32-($O32-$Q32)/2 | Q32: =$F32 | R32: =$Q32
A33: Ending Accounts Payable/COGS | B33: =IF('Financial Statements'!B13=0,0,-'Financial Statements'!B45/'Financial Statements'!B13) | C33: =IF('Financial Statements'!C13=0,0,-'Financial Statements'!C45/'Financial Statements'!C13) | D33: =IF('Financial Statements'!D13=0,0,-'Financial Statements'!D45/'Financial Statements'!D13) | E33: =IF('Financial Statements'!E13=0,0,-'Financial Statements'!E45/'Financial Statements'!E13) | F33: =IF('Financial Statements'!F13=0,0,-'Financial Statements'!F45/'Financial Statements'!F13) | G33: =F33-($F33-$Q33)/11 | H33: =G33-($G33-$Q33)/10 | I33: =H33-($H33-$Q33)/9 | J33: =I33-($I33-$Q33)/8 | K33: =J33-($J33-$Q33)/7 | L33: =K33-($K33-$Q33)/6 | M33: =L33-($L33-$Q33)/5 | N33: =M33-($M33-$Q33)/4 | O33: =N33-($N33-$Q33)/3 | P33: =O33-($O33-$Q33)/2 | Q33: =$F33 | R33: =$Q33
A34: Ending Taxes Payable/Sales | B34: ='Financial Statements'!B46/'Financial Statements'!B12 | C34: ='Financial Statements'!C46/'Financial Statements'!C12 | D34: ='Financial Statements'!D46/'Financial Statements'!D12 | E34: ='Financial Statements'!E46/'Financial Statements'!E12 | F34: ='Financial Statements'!F46/'Financial Statements'!F12 | G34: =F34-($F34-$Q34)/11 | H34: =G34-($G34-$Q34)/10 | I34: =H34-($H34-$Q34)/9 | J34: =I34-($I34-$Q34)/8 | K34: =J34-($J34-$Q34)/7 | L34: =K34-($K34-$Q34)/6 | M34: =L34-($L34-$Q34)/5 | N34: =M34-($M34-$Q34)/4 | O34: =N34-($N34-$Q34)/3 | P34: =O34-($O34-$Q34)/2 | Q34: =$F34 | R34: =$Q34
A35: Ending Other Current Liabs/Sales | B35: ='Financial Statements'!B47/'Financial Statements'!B12 | C35: ='Financial Statements'!C47/'Financial Statements'!C12 | D35: ='Financial Statements'!D47/'Financial Statements'!D12 | E35: ='Financial Statements'!E47/'Financial Statements'!E12 | F35: ='Financial Statements'!F47/'Financial Statements'!F12 | G35: =F35-($F35-$Q35)/11 | H35: =G35-($G35-$Q35)/10 | I35: =H35-($H35-$Q35)/9 | J35: =I35-($I35-$Q35)/8 | K35: =J35-($J35-$Q35)/7 | L35: =K35-($K35-$Q35)/6 | M35: =L35-($L35-$Q35)/5 | N35: =M35-($M35-$Q35)/4 | O35: =N35-($N35-$Q35)/3 | P35: =O35-($O35-$Q35)/2 | Q35: =$F35 | R35: =$Q35
A36: Other Operating Asset Assumptions
A37: Ending Net PP&E/Sales | B37: ='Financial Statements'!B38/'Financial Statements'!B12 | C37: ='Financial Statements'!C38/'Financial Statements'!C12 | D37: ='Financial Statements'!D38/'Financial Statements'!D12 | E37: ='Financial Statements'!E38/'Financial Statements'!E12 | F37: ='Financial Statements'!F38/'Financial Statements'!F12 | G37: =F37-($F37-$Q37)/11 | H37: =G37-($G37-$Q37)/10 | I37: =H37-($H37-$Q37)/9 | J37: =I37-($I37-$Q37)/8 | K37: =J37-($J37-$Q37)/7 | L37: =K37-($K37-$Q37)/6 | M37: =L37-($L37-$Q37)/5 | N37: =M37-($M37-$Q37)/4 | O37: =N37-($N37-$Q37)/3 | P37: =O37-($O37-$Q37)/2 | Q37: =$F37 | R37: =$Q37
A38: Ending Investments/Sales | B38: ='Financial Statements'!B39/'Financial Statements'!B12 | C38: ='Financial Statements'!C39/'Financial Statements'!C12 | D38: ='Financial Statements'!D39/'Financial Statements'!D12 | E38: ='Financial Statements'!E39/'Financial Statements'!E12 | F38: ='Financial Statements'!F39/'Financial Statements'!F12 | G38: =F38-($F38-$Q38)/11 | H38: =G38-($G38-$Q38)/10 | I38: =H38-($H38-$Q38)/9 | J38: =I38-($I38-$Q38)/8 | K38: =J38-($J38-$Q38)/7 | L38: =K38-($K38-$Q38)/6 | M38: =L38-($L38-$Q38)/5 | N38: =M38-($M38-$Q38)/4 | O38: =N38-($N38-$Q38)/3 | P38: =O38-($O38-$Q38)/2 | Q38: =$F38 | R38: =$Q38
A39: Ending Intangibles/Sales | B39: ='Financial Statements'!B40/'Financial Statements'!B12 | C39: ='Financial Statements'!C40/'Financial Statements'!C12 | D39: ='Financial Statements'!D40/'Financial Statements'!D12 | E39: ='Financial Statements'!E40/'Financial Statements'!E12 | F39: ='Financial Statements'!F40/'Financial Statements'!F12 | G39: =F39-($F39-$Q39)/11 | H39: =G39-($G39-$Q39)/10 | I39: =H39-($H39-$Q39)/9 | J39: =I39-($I39-$Q39)/8 | K39: =J39-($J39-$Q39)/7 | L39: =K39-($K39-$Q39)/6 | M39: =L39-($L39-$Q39)/5 | N39: =M39-($M39-$Q39)/4 | O39: =N39-($N39-$Q39)/3 | P39: =O39-($O39-$Q39)/2 | Q39: =$F39 | R39: =$Q39
A40: Ending Other Assets/Sales | B40: ='Financial Statements'!B41/'Financial Statements'!B12 | C40: ='Financial Statements'!C41/'Financial Statements'!C12 | D40: ='Financial Statements'!D41/'Financial Statements'!D12 | E40: ='Financial Statements'!E41/'Financial Statements'!E12 | F40: ='Financial Statements'!F41/'Financial Statements'!F12 | G40: =F40-($F40-$Q40)/11 | H40: =G40-($G40-$Q40)/10 | I40: =H40-($H40-$Q40)/9 | J40: =I40-($I40-$Q40)/8 | K40: =J40-($J40-$Q40)/7 | L40: =K40-($K40-$Q40)/6 | M40: =L40-($L40-$Q40)/5 | N40: =M40-($M40-$Q40)/4 | O40: =N40-($N40-$Q40)/3 | P40: =O40-($O40-$Q40)/2 | Q40: =$F40 | R40: =$Q40
A41: Other Operating Liability Assumptions
A42: Other Liabilities/Sales | B42: ='Financial Statements'!B50/'Financial Statements'!B12 | C42: ='Financial Statements'!C50/'Financial Statements'!C12 | D42: ='Financial Statements'!D50/'Financial Statements'!D12 | E42: ='Financial Statements'!E50/'Financial Statements'!E12 | F42: ='Financial Statements'!F50/'Financial Statements'!F12 | G42: =F42-($F42-$Q42)/11 | H42: =G42-($G42-$Q42)/10 | I42: =H42-($H42-$Q42)/9 | J42: =I42-($I42-$Q42)/8 | K42: =J42-($J42-$Q42)/7 | L42: =K42-($K42-$Q42)/6 | M42: =L42-($L42-$Q42)/5 | N42: =M42-($M42-$Q42)/4 | O42: =N42-($N42-$Q42)/3 | P42: =O42-($O42-$Q42)/2 | Q42: =$F42 | R42: =$Q42
A43: Deferred Taxes/Sales | B43: ='Financial Statements'!B51/'Financial Statements'!B12 | C43: ='Financial Statements'!C51/'Financial Statements'!C12 | D43: ='Financial Statements'!D51/'Financial Statements'!D12 | E43: ='Financial Statements'!E51/'Financial Statements'!E12 | F43: ='Financial Statements'!F51/'Financial Statements'!F12 | G43: =F43-($F43-$Q43)/11 | H43: =G43-($G43-$Q43)/10 | I43: =H43-($H43-$Q43)/9 | J43: =I43-($I43-$Q43)/8 | K43: =J43-($J43-$Q43)/7 | L43: =K43-($K43-$Q43)/6 | M43: =L43-($L43-$Q43)/5 | N43: =M43-($M43-$Q43)/4 | O43: =N43-($N43-$Q43)/3 | P43: =O43-($O43-$Q43)/2 | Q43: =$F43 | R43: =$Q43
A44: Financing Assumptions
A45: Current Debt/Total Assets | B45: ='Financial Statements'!B44/'Financial Statements'!B42 | C45: ='Financial Statements'!C44/'Financial Statements'!C42 | D45: ='Financial Statements'!D44/'Financial Statements'!D42 | E45: ='Financial Statements'!E44/'Financial Statements'!E42 | F45: ='Financial Statements'!F44/'Financial Statements'!F42 | G45: =F45-($F45-$Q45)/11 | H45: =G45-($G45-$Q45)/10 | I45: =H45-($H45-$Q45)/9 | J45: =I45-($I45-$Q45)/8 | K45: =J45-($J45-$Q45)/7 | L45: =K45-($K45-$Q45)/6 | M45: =L45-($L45-$Q45)/5 | N45: =M45-($M45-$Q45)/4 | O45: =N45-($N45-$Q45)/3 | P45: =O45-($O45-$Q45)/2 | Q45: =$F45 | R45: =$Q45
A46: Long-Term Debt/Total Assets | B46: ='Financial Statements'!B49/'Financial Statements'!B42 | C46: ='Financial Statements'!C49/'Financial Statements'!C42 | D46: ='Financial Statements'!D49/'Financial Statements'!D42 | E46: ='Financial Statements'!E49/'Financial Statements'!E42 | F46: ='Financial Statements'!F49/'Financial Statements'!F42 | G46: =F46-($F46-$Q46)/11 | H46: =G46-($G46-$Q46)/10 | I46: =H46-($H46-$Q46)/9 | J46: =I46-($I46-$Q46)/8 | K46: =J46-($J46-$Q46)/7 | L46: =K46-($K46-$Q46)/6 | M46: =L46-($L46-$Q46)/5 | N46: =M46-($M46-$Q46)/4 | O46: =N46-($N46-$Q46)/3 | P46: =O46-($O46-$Q46)/2 | Q46: =$F46 | R46: =$Q46
A47: Noncontrolling Interest/Total Assets | B47: ='Financial Statements'!B53/'Financial Statements'!B42 | C47: ='Financial Statements'!C53/'Financial Statements'!C42 | D47: ='Financial Statements'!D53/'Financial Statements'!D42 | E47: ='Financial Statements'!E53/'Financial Statements'!E42 | F47: ='Financial Statements'!F53/'Financial Statements'!F42 | G47: =F47-($F47-$Q47)/11 | H47: =G47-($G47-$Q47)/10 | I47: =H47-($H47-$Q47)/9 | J47: =I47-($I47-$Q47)/8 | K47: =J47-($J47-$Q47)/7 | L47: =K47-($K47-$Q47)/6 | M47: =L47-($L47-$Q47)/5 | N47: =M47-($M47-$Q47)/4 | O47: =N47-($N47-$Q47)/3 | P47: =O47-($O47-$Q47)/2 | Q47: =$F47 | R47: =$Q47
A48: Preferred Stock/Total Assets | B48: ='Financial Statements'!B54/'Financial Statements'!B42 | C48: ='Financial Statements'!C54/'Financial Statements'!C42 | D48: ='Financial Statements'!D54/'Financial Statements'!D42 | E48: ='Financial Statements'!E54/'Financial Statements'!E42 | F48: ='Financial Statements'!F54/'Financial Statements'!F42 | G48: =F48-($F48-$Q48)/11 | H48: =G48-($G48-$Q48)/10 | I48: =H48-($H48-$Q48)/9 | J48: =I48-($I48-$Q48)/8 | K48: =J48-($J48-$Q48)/7 | L48: =K48-($K48-$Q48)/6 | M48: =L48-($L48-$Q48)/5 | N48: =M48-($M48-$Q48)/4 | O48: =N48-($N48-$Q48)/3 | P48: =O48-($O48-$Q48)/2 | Q48: =$F48 | R48: =$Q48
A49: Dividend Payout Ratio | B49: =IF('Financial Statements'!B29=0,0,-'Financial Statements'!B64/'Financial Statements'!B29) | C49: =IF('Financial Statements'!C29=0,0,-'Financial Statements'!C64/'Financial Statements'!C29) | D49: =IF('Financial Statements'!D29=0,0,-'Financial Statements'!D64/'Financial Statements'!D29) | E49: =IF('Financial Statements'!E29=0,0,-'Financial Statements'!E64/'Financial Statements'!E29) | F49: =IF('Financial Statements'!F29=0,0,-'Financial Statements'!F64/'Financial Statements'!F29) | G49: =F49-($F49-$Q49)/11 | H49: =G49-($G49-$Q49)/10 | I49: =H49-($H49-$Q49)/9 | J49: =I49-($I49-$Q49)/8 | K49: =J49-($J49-$Q49)/7 | L49: =K49-($K49-$Q49)/6 | M49: =L49-($L49-$Q49)/5 | N49: =M49-($M49-$Q49)/4 | O49: =N49-($N49-$Q49)/3 | P49: =O49-($O49-$Q49)/2 | Q49: =$F49 | R49: =$Q49

Sheet Valuation Parameters
A1: Valuation Parameters
B3: 0.03
A4: ="Estimated Price/Share="&DOLLAR(B24) | B4: 0.025
A6: Company Name: | C6: ='Financial Statements'!B4
A8: Required Valuation Parameters (to compute value of common equity):
B9: Enter Cost of Equity Capital: | J9: 0.1
B10: Enter Value of Contingent Claims on Common Equity ($000): | H10: (Link to Calculator) | J10: 0
B11: Enter Date of Valuation: | J11: =TODAY()
B12: Enter Dilution Factor for Splits Occurring Since Latest Fiscal Year End: | J12: 1
A14: Optional Valuation Parameters (to compute value to all investors):
B15: Enter Cost of Net Debt: | J15: 0.08
B16: Enter Cost of Preferred Stock: | J16: 0.09
B17: Enter Cost of Noncontrolling Interest: | J17: 0.1
B19: Adjust the Weighted Average Cost of Capital Input | J19: =J24 | K19: =IF(E24>B24,"up","down")
B20: such that the two equity values below are approximately equal:
B22: Equity Value computed directly | E22: Equity Value computed indirectly | I22: approximate weighted average
B23: from flows to equityholders: | E23: as the Entity Value less non-equity claims: | I23: cost of capital to use as starting point:
B24: ='Residual Income Valuations'!B27 | E24: ='Residual Income Valuations'!B68 | J24: =('Residual Income Valuations'!B21*J9+'Residual Income Valuations'!B40*(J15*(1-'Forecasting Assumptions'!Q21))+'Residual Income Valuations'!B46*J16+'Residual Income Valuations'!B52*J17)/('Residual Income Valuations'!B21+'Residual Income Valuations'!B40+'Residual Income Valuations'!B46+'Residual Income Valuations'!B52)
A29: Black Scholes Option Value Calculator | G29: (Back to Valuation Parameters)
A32: Input Parameters:
B33: Current Stock Price (S) | J33: 50
B34: Option Exercise Price (K) | J34: 50
B35: Years to Expiration (t) | J35: 5
B36: Forecasted Annual Dividend Yield (y) | J36: 0.02
B37: Risk-Free Rate (r) | J37: 0.0366
B38: Standard Deviation of Stock Return (s) | J38: 0.62
B40: Value of Call Option | J40: =J33*EXP(-J36*J35)*_xlfn.NORM.DIST((LN(J33/J34)+(J37-J36+J38^2/2)*J35)/(J38*J35^0.5),0,1,TRUE)-J34*EXP(-J37*J35)*_xlfn.NORM.DIST((LN(J33/J34)+(J37-J36+J38^2/2)*J35)/(J38*J35^0.5)-J38*J35^0.5,0,1,TRUE)

Sheet Residual Income Valuations
A1: Residual Income Valuation | B1: ($000)
A4: Company Name | B4: ='Financial Statements'!B4
A5: Most Recent Fiscal Year End | B5: ='Financial Statements'!F8
A6: Date of Valuation | B6: ='Valuation Parameters'!J11
A7: Cost of Common Equity | B7: ='Valuation Parameters'!J9
A8: Teriminal Growth Rate | B8: ='Forecasting Assumptions'!Q14
A10: Fiscal Year of Forecast | B10: ='Financial Statements'!G8 | C10: ='Financial Statements'!H8 | D10: ='Financial Statements'!I8 | E10: ='Financial Statements'!J8 | F10: ='Financial Statements'!K8 | G10: ='Financial Statements'!L8 | H10: ='Financial Statements'!M8 | I10: ='Financial Statements'!N8 | ... M10: ='Financial Statements'!R8
A11: =B21+B40+B46-B58
A12: Valuation to Common Equity
A13: Net Income | B13: ='Financial Statements'!G29 | C13: ='Financial Statements'!H29 | D13: ='Financial Statements'!I29 | E13: ='Financial Statements'!J29 | F13: ='Financial Statements'!K29 | G13: ='Financial Statements'!L29 | H13: ='Financial Statements'!M29 | I13: ='Financial Statements'!N29 | ... M13: ='Financial Statements'!R29
A14: Common Equity at Beginning of Year | B14: ='Financial Statements'!F57 | C14: ='Financial Statements'!G57 | D14: ='Financial Statements'!H57 | E14: ='Financial Statements'!I57 | F14: ='Financial Statements'!J57 | G14: ='Financial Statements'!K57 | H14: ='Financial Statements'!L57 | I14: ='Financial Statements'!M57 | ... M14: ='Financial Statements'!Q57
A15: Residual Income | B15: =B13-B7*B14 | C15: =C13-B7*C14 | D15: =D13-B7*D14 | E15: =E13-B7*E14 | F15: =F13-B7*F14 | G15: =G13-B7*G14 | H15: =H13-B7*H14 | I15: =I13-B7*I14 | J15: =J13-$B$7*J14 | K15: =K13-$B$7*K14 | L15: =L13-$B$7*L14 | M15: =M13-$B$7*M14
A16: Present Value of Residual Income | B16: =B15/(1+$B$7)^1 | C16: =C15/(1+$B$7)^2 | D16: =D15/(1+$B$7)^3 | E16: =E15/(1+$B$7)^4 | F16: =F15/(1+$B$7)^5 | G16: =G15/(1+$B$7)^6 | H16: =H15/(1+$B$7)^7 | I16: =I15/(1+$B$7)^8 | J16: =J15/(1+$B$7)^9 | K16: =K15/(1+$B$7)^10 | L16: =L15/(1+$B$7)^11 | M16: =M15/(1+$B$7)^12
A17: Present Value Beyond 10 Years | B17: =L16+(M15/($B$7-$B$8))/(1+$B$7)^11 | C17: =IF(($B$7-$B$8)<=0,"Error! cost of equity capital <= growth rate"," ")
A18: Present Value of First 10 Years | B18: =SUM(B16:K16)
A19: Common Equity as of
A20: ='Financial Statements'!F8 | B20: =B14
A21: Forecast Equity Value Before Time Adj. | B21: =B17+B18+B20
A22: Forecasted Value as of Valuation Date | B22: =B21*(1+(B7/2))*(1+B7*(DAYS360(B5,B6)/360))
A23: Less Value of Contingent Equity Claims | B23: =-'Valuation Parameters'!J10
A24: Value Attributable to Common Equity | B24: =B22+B23
A25: Common Shares Outstanding at BS Date | B25: ='Financial Statements'!B5
A26: Equivalent Shares at Valuation Date | B26: =B25*'Valuation Parameters'!J12
A27: Forecast Price/Share | B27: =B24/B26
A30: Valuation to All Investors
A31: Cost of Debt | B31: ='Valuation Parameters'!J15
A32: Cost of Preferred Stock | B32: ='Valuation Parameters'!J16
A33: Cost of Noncontrolling Interest | B33: ='Valuation Parameters'!J17
A34: After Tax Weighted Average Cost of Capital | B34: ='Valuation Parameters'!J19
A36: Net Interest Expense to Net Debtholders | B36: =-'Financial Statements'!G20 | C36: =-'Financial Statements'!H20 | D36: =-'Financial Statements'!I20 | E36: =-'Financial Statements'!J20 | F36: =-'Financial Statements'!K20 | G36: =-'Financial Statements'!L20 | H36: =-'Financial Statements'!M20 | I36: =-'Financial Statements'!N20 | ... M36: =-'Financial Statements'!R20
A37: Beginning Book Value of Debt | B37: ='Financial Statements'!F44+'Financial Statements'!F49 | C37: ='Financial Statements'!G44+'Financial Statements'!G49 | D37: ='Financial Statements'!H44+'Financial Statements'!H49 | E37: ='Financial Statements'!I44+'Financial Statements'!I49 | F37: ='Financial Statements'!J44+'Financial Statements'!J49 | G37: ='Financial Statements'!K44+'Financial Statements'!K49 | H37: ='Financial Statements'!L44+'Financial Statements'!L49 | I37: ='Financial Statements'!M44+'Financial Statements'!M49 | ... M37: ='Financial Statements'!Q44+'Financial Statements'!Q49
A38: Residual Interest Expense | B38: =B36-($B$31*B37) | C38: =C36-($B$31*C37) | D38: =D36-($B$31*D37) | E38: =E36-($B$31*E37) | F38: =F36-($B$31*F37) | G38: =G36-($B$31*G37) | H38: =H36-($B$31*H37) | I38: =I36-($B$31*I37) | ... M38: =M36-($B$31*M37)
A39: Present Value of Residual Interest Income | B39: =B38/(1+$B$31)^1 | C39: =C38/(1+$B$31)^2 | D39: =D38/(1+$B$31)^3 | E39: =E38/(1+$B$31)^4 | F39: =F38/(1+$B$31)^5 | G39: =G38/(1+$B$31)^6 | H39: =H38/(1+$B$31)^7 | I39: =I38/(1+$B$31)^8 | J39: =J38/(1+$B$31)^9 | K39: =K38/(1+$B$31)^10 | L39: =L38/(1+$B$31)^11 | M39: =M38/(1+$B$31)^12
A40: Value of Debt | B40: =IF($B$31-$B$8>0,B37+SUM(B39:L39)+(M38/($B$31-$B$8))/(1+$B$31)^11,IF(NOT(M38=0),#N/A,B37+SUM(B39:M39))) | C40: =IF($B$31-$B$8>0," ",IF(NOT(M38=0),"Error! cost of debt <= growth rate"," "))
A42: Dividends to Preferred Stockholders | B42: ='Financial Statements'!G28 | C42: ='Financial Statements'!H28 | D42: ='Financial Statements'!I28 | E42: ='Financial Statements'!J28 | F42: ='Financial Statements'!K28 | G42: ='Financial Statements'!L28 | H42: ='Financial Statements'!M28 | I42: ='Financial Statements'!N28 | ... M42: ='Financial Statements'!R28
A43: Beginning Book Value of Preferred Stock | B43: ='Financial Statements'!F54 | C43: ='Financial Statements'!G54 | D43: ='Financial Statements'!H54 | E43: ='Financial Statements'!I54 | F43: ='Financial Statements'!J54 | G43: ='Financial Statements'!K54 | H43: ='Financial Statements'!L54 | I43: ='Financial Statements'!M54 | ... M43: ='Financial Statements'!Q54
A44: Residual Income to Preferred Stock | B44: =B42-($B$32*B43) | C44: =C42-($B$32*C43) | D44: =D42-($B$32*D43) | E44: =E42-($B$32*E43) | F44: =F42-($B$32*F43) | G44: =G42-($B$32*G43) | H44: =H42-($B$32*H43) | I44: =I42-($B$32*I43) | ... M44: =M42-($B$32*M43)
A45: Present Value of Preferred Residual Income | B45: =B44/(1+$B$32)^1 | C45: =C44/(1+$B$32)^2 | D45: =D44/(1+$B$32)^3 | E45: =E44/(1+$B$32)^4 | F45: =F44/(1+$B$32)^5 | G45: =G44/(1+$B$32)^6 | H45: =H44/(1+$B$32)^7 | I45: =I44/(1+$B$32)^8 | J45: =J44/(1+$B$32)^9 | K45: =K44/(1+$B$32)^10 | L45: =L44/(1+$B$32)^11 | M45: =M44/(1+$B$32)^12
A46: Value of Preferred Stock | B46: =IF($B$32-$B$8>0,B43+SUM(B45:L45)+(M44/($B$32-$B$8))/(1+$B$32)^11,IF(NOT(M44=0),#N/A,B43+SUM(B45:M45))) | C46: =IF($B$32-$B$8>0," ",IF(NOT(M44=0),"Error! cost of preferred stock <= growth rate"," "))
A48: Noncontrolling Interest in Earnings | B48: =-'Financial Statements'!G27 | C48: =-'Financial Statements'!H27 | D48: =-'Financial Statements'!I27 | E48: =-'Financial Statements'!J27 | F48: =-'Financial Statements'!K27 | G48: =-'Financial Statements'!L27 | H48: =-'Financial Statements'!M27 | I48: =-'Financial Statements'!N27 | ... M48: =-'Financial Statements'!R27
A49: Beginning Book Value of Noncontrolling Interest | B49: ='Financial Statements'!F53 | C49: ='Financial Statements'!G53 | D49: ='Financial Statements'!H53 | E49: ='Financial Statements'!I53 | F49: ='Financial Statements'!J53 | G49: ='Financial Statements'!K53 | H49: ='Financial Statements'!L53 | I49: ='Financial Statements'!M53 | ... M49: ='Financial Statements'!Q53
A50: Residual Income to Noncontrolling Interest | B50: =B48-$B$33*B49 | C50: =C48-$B$33*C49 | D50: =D48-$B$33*D49 | E50: =E48-$B$33*E49 | F50: =F48-$B$33*F49 | G50: =G48-$B$33*G49 | H50: =H48-$B$33*H49 | I50: =I48-$B$33*I49 | ... M50: =M48-$B$33*M49
A51: Present Value of MI Residual Income | B51: =B50/(1+$B$33)^1 | C51: =C50/(1+$B$33)^2 | D51: =D50/(1+$B$33)^3 | E51: =E50/(1+$B$33)^4 | F51: =F50/(1+$B$33)^5 | G51: =G50/(1+$B$33)^6 | H51: =H50/(1+$B$33)^7 | I51: =I50/(1+$B$33)^8 | J51: =J50/(1+$B$33)^9 | K51: =K50/(1+$B$33)^10 | L51: =L50/(1+$B$33)^11 | M51: =M50/(1+$B$33)^12
A52: Value of Noncontrolling Interest | B52: =IF($B$33-$B$8>0,B49+SUM(B51:L51)+(M50/($B$33-$B$8))/(1+$B$33)^11,IF(NOT(M50=0),#N/A,B49+SUM(B51:M51))) | C52: =IF($B$33-$B$8>0," ",IF(NOT(M50=0),"Error! cost of noncontrolling interest <= growth rate"," "))
A54: Net Operating Income | B54: ='Financial Statements'!G71 | C54: ='Financial Statements'!H71 | D54: ='Financial Statements'!I71 | E54: ='Financial Statements'!J71 | F54: ='Financial Statements'!K71 | G54: ='Financial Statements'!L71 | H54: ='Financial Statements'!M71 | I54: ='Financial Statements'!N71 | ... M54: ='Financial Statements'!R71
A55: Beginning Net Operating Assets | B55: ='Financial Statements'!F75 | C55: ='Financial Statements'!G75 | D55: ='Financial Statements'!H75 | E55: ='Financial Statements'!I75 | F55: ='Financial Statements'!J75 | G55: ='Financial Statements'!K75 | H55: ='Financial Statements'!L75 | I55: ='Financial Statements'!M75 | ... M55: ='Financial Statements'!Q75
A56: Residual Income to all Investors | B56: =B54-($B$34*B55) | C56: =C54-($B$34*C55) | D56: =D54-($B$34*D55) | E56: =E54-($B$34*E55) | F56: =F54-($B$34*F55) | G56: =G54-($B$34*G55) | H56: =H54-($B$34*H55) | I56: =I54-($B$34*I55) | ... M56: =M54-($B$34*M55)
A57: Present Value of Residual Investor Income | B57: =B56/(1+$B$34)^1 | C57: =C56/(1+$B$34)^2 | D57: =D56/(1+$B$34)^3 | E57: =E56/(1+$B$34)^4 | F57: =F56/(1+$B$34)^5 | G57: =G56/(1+$B$34)^6 | H57: =H56/(1+$B$34)^7 | I57: =I56/(1+$B$34)^8 | J57: =J56/(1+$B$34)^9 | K57: =K56/(1+$B$34)^10 | L57: =L56/(1+$B$34)^11 | M57: =M56/(1+$B$34)^12
A58: Entity Value | B58: =IF(ISNA($B$34),#N/A,B55+SUM(B57:L57)+(M56/($B$34-$B$8))/(1+$B$34)^11) | C58: =IF(($B$34-$B$8)<=0,"Error! weighted average cost of capital <= growth rate"," ")
A59: Less Value of Debt | B59: =-B40
A60: Less Value of Preferred Stock | B60: =-B46
A61: Less Value of Noncontrolling Interest | B61: =-B52
A62: Forecast Equity Value Before Time Adj. | B62: =B58+B59+B60+B61
A63: Forecasted Value as of Valuation Date | B63: =B62*(1+($B$7/2))*(1+$B$7*(DAYS360(B5,B6)/360))
A64: Less Value of Contingent Equity Claims | B64: =-'Valuation Parameters'!J10
A65: Value Attributable to Common Equity | B65: =B63+B64
A66: Common Shares Outstanding at BS Date | B66: ='Financial Statements'!B5
A67: Equivalent Shares at Valuation Date | B67: =B66*'Valuation Parameters'!J12
A68: Forecast Price/Share | B68: =B65/B67

Sheet DCF Valuations
A1: DCF Valuations | B1: ($000)
A4: Company Name | B4: ='Financial Statements'!B4
A5: Most Recent Fiscal Year End | B5: ='Financial Statements'!F8
A6: Date of Valuation | B6: ='Valuation Parameters'!J11
A7: Cost of Common Equity | B7: ='Valuation Parameters'!J9
A8: Terminal Growth Rate | B8: ='Forecasting Assumptions'!Q14
A10: Fiscal Year of Forecast | B10: ='Financial Statements'!G8 | C10: ='Financial Statements'!H8 | D10: ='Financial Statements'!I8 | E10: ='Financial Statements'!J8 | F10: ='Financial Statements'!K8 | G10: ='Financial Statements'!L8 | H10: ='Financial Statements'!M8 | I10: ='Financial Statements'!N8 | ... M10: ='Financial Statements'!R8
A11: =B17+B33+B37-B45
A12: Valuation to Common Equity
A13: Free Cash Flow to Common Equity | B13: ='Cash Flow Analysis'!F64 | C13: ='Cash Flow Analysis'!G64 | D13: ='Cash Flow Analysis'!H64 | E13: ='Cash Flow Analysis'!I64 | F13: ='Cash Flow Analysis'!J64 | G13: ='Cash Flow Analysis'!K64 | H13: ='Cash Flow Analysis'!L64 | I13: ='Cash Flow Analysis'!M64 | ... M13: ='Cash Flow Analysis'!Q64
A14: Present Value of FCF | B14: =B13/(1+$B$7)^1 | C14: =C13/(1+$B$7)^2 | D14: =D13/(1+$B$7)^3 | E14: =E13/(1+$B$7)^4 | F14: =F13/(1+$B$7)^5 | G14: =G13/(1+$B$7)^6 | H14: =H13/(1+$B$7)^7 | I14: =I13/(1+$B$7)^8 | J14: =J13/(1+$B$7)^9 | K14: =K13/(1+$B$7)^10 | L14: =L13/(1+$B$7)^11 | M14: =M13/(1+$B$7)^12
A15: Present Value Beyond 10 Years | B15: =L14+(M13/($B$7-$B$8))/(1+$B$7)^11 | C15: =IF(($B$7-$B$8)<0,"Error! cost of equity capital < growth rate"," ")
A16: Present Value of First 10 Years | B16: =SUM(B14:K14)
A17: Forecast Equity Value Before Time Adj. | B17: =B15+B16
A18: Forecasted Value as of Valuation Date | B18: =B17*(1+(B7/2))*(1+B7*(DAYS360(B5,B6)/360))
A19: Less Value of Contingent Equity Claims | B19: =-'Valuation Parameters'!J10
A20: Value Attributable to Common Equity | B20: =B18+B19
A21: Common Shares Outstanding at BS Date | B21: ='Financial Statements'!B5
A22: Equivalent Shares at Valuation Date | B22: =B21*'Valuation Parameters'!J12
A23: Forecast Price/Share | B23: =B20/B22
A25: Valuation to All Investors
A26: Cost of Net Debt | B26: ='Valuation Parameters'!J15
A27: Cost of Preferred Stock | B27: ='Valuation Parameters'!J16
A28: Cost of Noncontrolling Interest | B28: ='Valuation Parameters'!J17
A29: After Tax Weighted Average Cost of Capital | B29: ='Valuation Parameters'!J19
A31: Free Cash Flow to Debt | B31: ='Cash Flow Analysis'!F90+'Cash Flow Analysis'!F95 | C31: ='Cash Flow Analysis'!G90+'Cash Flow Analysis'!G95 | D31: ='Cash Flow Analysis'!H90+'Cash Flow Analysis'!H95 | E31: ='Cash Flow Analysis'!I90+'Cash Flow Analysis'!I95 | F31: ='Cash Flow Analysis'!J90+'Cash Flow Analysis'!J95 | G31: ='Cash Flow Analysis'!K90+'Cash Flow Analysis'!K95 | H31: ='Cash Flow Analysis'!L90+'Cash Flow Analysis'!L95 | I31: ='Cash Flow Analysis'!M90+'Cash Flow Analysis'!M95 | ... M31: ='Cash Flow Analysis'!Q90+'Cash Flow Analysis'!Q95
A32: Present Value of FCF to Debt | B32: =B31/(1+$B$26)^1 | C32: =C31/(1+$B$26)^2 | D32: =D31/(1+$B$26)^3 | E32: =E31/(1+$B$26)^4 | F32: =F31/(1+$B$26)^5 | G32: =G31/(1+$B$26)^6 | H32: =H31/(1+$B$26)^7 | I32: =I31/(1+$B$26)^8 | J32: =J31/(1+$B$26)^9 | K32: =K31/(1+$B$26)^10 | L32: =L31/(1+$B$26)^11 | M32: =M31/(1+$B$26)^12
A33: Value of Debt | B33: =IF($B$26-$B$8>0,SUM(B32:L32)+(M31/($B$26-$B$8))/(1+$B$26)^11,IF(NOT(M31=0),#N/A,SUM(B32:M32))) | C33: =IF($B$26-$B$8>0," ",IF(NOT(M31=0),"Error! cost of debt <= growth rate"," "))
A35: Free Cash Flow to Preferred Stock | B35: ='Cash Flow Analysis'!F92+'Cash Flow Analysis'!F96 | C35: ='Cash Flow Analysis'!G92+'Cash Flow Analysis'!G96 | D35: ='Cash Flow Analysis'!H92+'Cash Flow Analysis'!H96 | E35: ='Cash Flow Analysis'!I92+'Cash Flow Analysis'!I96 | F35: ='Cash Flow Analysis'!J92+'Cash Flow Analysis'!J96 | G35: ='Cash Flow Analysis'!K92+'Cash Flow Analysis'!K96 | H35: ='Cash Flow Analysis'!L92+'Cash Flow Analysis'!L96 | I35: ='Cash Flow Analysis'!M92+'Cash Flow Analysis'!M96 | ... M35: ='Cash Flow Analysis'!Q92+'Cash Flow Analysis'!Q96
A36: Present Value of FCF to Preferred Stock | B36: =B35/(1+$B$27)^1 | C36: =C35/(1+$B$27)^2 | D36: =D35/(1+$B$27)^3 | E36: =E35/(1+$B$27)^4 | F36: =F35/(1+$B$27)^5 | G36: =G35/(1+$B$27)^6 | H36: =H35/(1+$B$27)^7 | I36: =I35/(1+$B$27)^8 | J36: =J35/(1+$B$27)^9 | K36: =K35/(1+$B$27)^10 | L36: =L35/(1+$B$27)^11 | M36: =M35/(1+$B$27)^12
A37: Value of Preferred Stock | B37: =IF($B$27-$B$8>0,SUM(B36:L36)+(M35/($B$27-$B$8))/(1+$B$27)^11,IF(NOT(M35=0),#N/A,SUM(B36:M36))) | C37: =IF($B$27-$B$8>0," ",IF(NOT(M35=0),"Error! cost of preferred stock <= growth rate"," "))
A39: Free Cash Flow to Noncontrolling Interest | B39: ='Cash Flow Analysis'!F93 | C39: ='Cash Flow Analysis'!G93 | D39: ='Cash Flow Analysis'!H93 | E39: ='Cash Flow Analysis'!I93 | F39: ='Cash Flow Analysis'!J93 | G39: ='Cash Flow Analysis'!K93 | H39: ='Cash Flow Analysis'!L93 | I39: ='Cash Flow Analysis'!M93 | ... M39: ='Cash Flow Analysis'!Q93
A40: Present Value of FCF to Noncontrolling Interest | B40: =B39/(1+$B$28)^1 | C40: =C39/(1+$B$28)^2 | D40: =D39/(1+$B$28)^3 | E40: =E39/(1+$B$28)^4 | F40: =F39/(1+$B$28)^5 | G40: =G39/(1+$B$28)^6 | H40: =H39/(1+$B$28)^7 | I40: =I39/(1+$B$28)^8 | J40: =J39/(1+$B$28)^9 | K40: =K39/(1+$B$28)^10 | L40: =L39/(1+$B$28)^11 | M40: =M39/(1+$B$28)^12
A41: Value of Noncontrolling Interest | B41: =IF($B$28-$B$8>0,SUM(B40:L40)+(M39/($B$28-$B$8))/(1+$B$28)^11,IF(NOT(M39=0),#N/A,SUM(B40:M40))) | C41: =IF($B$28-$B$8>0," ",IF(NOT(M39=0),"Error! cost of noncontrolling interest <= growth rate"," "))
A43: Free Cash Flows to Investors | B43: ='Cash Flow Analysis'!F97 | C43: ='Cash Flow Analysis'!G97 | D43: ='Cash Flow Analysis'!H97 | E43: ='Cash Flow Analysis'!I97 | F43: ='Cash Flow Analysis'!J97 | G43: ='Cash Flow Analysis'!K97 | H43: ='Cash Flow Analysis'!L97 | I43: ='Cash Flow Analysis'!M97 | ... M43: ='Cash Flow Analysis'!Q97
A44: Present Value of FCF to Investors | B44: =B43/(1+$B$29)^1 | C44: =C43/(1+$B$29)^2 | D44: =D43/(1+$B$29)^3 | E44: =E43/(1+$B$29)^4 | F44: =F43/(1+$B$29)^5 | G44: =G43/(1+$B$29)^6 | H44: =H43/(1+$B$29)^7 | I44: =I43/(1+$B$29)^8 | J44: =J43/(1+$B$29)^9 | K44: =K43/(1+$B$29)^10 | L44: =L43/(1+$B$29)^11 | M44: =M43/(1+$B$29)^12
A45: Entity Value | B45: =IF(ISNA($B$29),#N/A,SUM(B44:L44)+(M43/($B$29-$B$8))/(1+$B$29)^11) | C45: =IF(($B$29-$B$8)<=0,"Error! weighted average cost of capital <= growth rate"," ")
A46: Less Value of Net Debt | B46: =-B33
A47: Less Value of Preferred Stock | B47: =-B37
A48: Less Value of Noncontrolling Interest | B48: =-B41
A49: Forecast Equity Value Before Time Adj. | B49: =B45+B46+B47+B48
A50: Forecasted Value as of Valuation Date | B50: =B49*(1+(B7/2))*(1+B7*(DAYS360(B5,B6)/360))
A51: Less Value of Contingent Equity Claims | B51: =-'Valuation Parameters'!J10
A52: Value Attributable to Common Equity | B52: =B50+B51
A53: Common Shares Outstanding at BS Date | B53: ='Financial Statements'!B5
A54: Equivalent Shares at Valuation Date | B54: =B53*'Valuation Parameters'!J12
A55: Forecast Price/Share | B55: =B52/B54

Sheet EPS Forecaster
A1: EPS Forecaster | B1: ($000, except per share amounts)
A4: Company Name | B4: ='Financial Statements'!B4
A5: Common Shares Outstanding at BS Date | B5: ='Financial Statements'!B5
A6: Equivalent Shares at Valuation Date | B6: =B5*'Valuation Parameters'!J12
A7: Forecasted Price at Valuation Date | B7: ='Residual Income Valuations'!B27
B9: Forecast | C9: Forecast | D9: Forecast | E9: Forecast | F9: Forecast | G9: Forecast | H9: Forecast | I9: Forecast | J9: Forecast | K9: Forecast | L9: Forecast | M9: Forecast
A10: Fiscal Year of Forecast | B10: ='Financial Statements'!G8 | C10: ='Financial Statements'!H8 | D10: ='Financial Statements'!I8 | E10: ='Financial Statements'!J8 | F10: ='Financial Statements'!K8 | G10: ='Financial Statements'!L8 | H10: ='Financial Statements'!M8 | I10: ='Financial Statements'!N8 | ... M10: ='Financial Statements'!R8
A11: Net Income | B11: ='Financial Statements'!G29 | C11: ='Financial Statements'!H29 | D11: ='Financial Statements'!I29 | E11: ='Financial Statements'!J29 | F11: ='Financial Statements'!K29 | G11: ='Financial Statements'!L29 | H11: ='Financial Statements'!M29 | I11: ='Financial Statements'!N29 | ... M11: ='Financial Statements'!R29
A12: Common Equity Issued (Repurchased) | B12: ='Cash Flow Analysis'!F39 | C12: ='Cash Flow Analysis'!G39 | D12: ='Cash Flow Analysis'!H39 | E12: ='Cash Flow Analysis'!I39 | F12: ='Cash Flow Analysis'!J39 | G12: ='Cash Flow Analysis'!K39 | H12: ='Cash Flow Analysis'!L39 | I12: ='Cash Flow Analysis'!M39 | ... M12: ='Cash Flow Analysis'!Q39
A13: Forecasted Price at Year End | B13: =B7*(1+'Valuation Parameters'!J9*(DAYS360('Residual Income Valuations'!B6,'Residual Income Valuations'!B10)/360))+('Financial Statements'!G64/'EPS Forecaster'!B6)*(DAYS360('Residual Income Valuations'!B6,'Residual Income Valuations'!B10)/360) | C13: =(B13*(1+'Valuation Parameters'!J9))+('Financial Statements'!H64/'EPS Forecaster'!B15) | D13: =(C13*(1+'Valuation Parameters'!J9))+('Financial Statements'!I64/'EPS Forecaster'!C15) | E13: =(D13*(1+'Valuation Parameters'!J9))+('Financial Statements'!J64/'EPS Forecaster'!D15) | F13: =(E13*(1+'Valuation Parameters'!J9))+('Financial Statements'!K64/'EPS Forecaster'!E15) | G13: =(F13*(1+'Valuation Parameters'!J9))+('Financial Statements'!L64/'EPS Forecaster'!F15) | H13: =(G13*(1+'Valuation Parameters'!J9))+('Financial Statements'!M64/'EPS Forecaster'!G15) | I13: =(H13*(1+'Valuation Parameters'!J9))+('Financial Statements'!N64/'EPS Forecaster'!H15) | J13: =(I13*(1+'Valuation Parameters'!$J$9))+('Financial Statements'!O64/'EPS Forecaster'!I15) | K13: =(J13*(1+'Valuation Parameters'!$J$9))+('Financial Statements'!P64/'EPS Forecaster'!J15) | L13: =(K13*(1+'Valuation Parameters'!$J$9))+('Financial Statements'!Q64/'EPS Forecaster'!K15) | M13: =(L13*(1+'Valuation Parameters'!$J$9))+('Financial Statements'!R64/'EPS Forecaster'!L15)
A14: New Shares Issued (Repurchased) | B14: =B12/B13 | C14: =C12/C13 | D14: =D12/D13 | E14: =E12/E13 | F14: =F12/F13 | G14: =G12/G13 | H14: =H12/H13 | I14: =I12/I13 | ... M14: =M12/M13
A15: Shares Outstanding at End of Year | B15: =B6+B14 | C15: =B15+C14 | D15: =C15+D14 | E15: =D15+E14 | F15: =E15+F14 | G15: =F15+G14 | H15: =G15+H14 | I15: =H15+I14 | J15: =I15+J14 | ... M15: =L15+M14
A16: Forecast EPS | B16: =B11/((B6+B15)/2) | C16: =C11/((B15+C15)/2) | D16: =D11/((C15+D15)/2) | E16: =E11/((D15+E15)/2) | F16: =F11/((E15+F15)/2) | G16: =G11/((F15+G15)/2) | H16: =H11/((G15+H15)/2) | I16: =I11/((H15+I15)/2) | J16: =J11/((I15+J15)/2) | ... M16: =M11/((L15+M15)/2)
A17: Consensus Analyst Forecast of EPS
A19: Forecast Five Year Growth Rate in EPS | B19: =(G16/B16)^(1/5)-1
A20: Consensus Analyst Forecast of Growth Rate
C23: =HYPERLINK(CONCATENATE("http://biz.yahoo.com/z/a/",LEFT(TRIM('Financial Statements'!D4),1),"/",TRIM('Financial Statements'!D4),".html"),"To obtain analyst forecasts, click here")

Sheet Model Summary
A1: Model Summary
A4: Historical Data For:
A5: ='Financial Statements'!B4
A6: Most Recent Fiscal Year End: | B6: ='Financial Statements'!F8
A7: Average ROE (last five years) | B7: =AVERAGE('Ratio Analysis'!C19:F19)
A8: Sales Growth (last five years) | B8: =(('Financial Statements'!F12/'Financial Statements'!B12)^(1/4))-1
A10: Forecast Data:
A11: Forecast Horizon | B11: 10 years
A12: This Year's ROE | B12: ='Ratio Analysis'!G19
A13: Terminal Year's ROE | B13: ='Ratio Analysis'!Q19
A14: This Year's Sales Growth | B14: ='Ratio Analysis'!G10
A15: Terminal Year's Sales Growth | B15: ='Ratio Analysis'!Q10
A16: This Year's Forecast EPS | B16: ='EPS Forecaster'!B16
A17: Forecast 5 Year EPS Growth | B17: ='EPS Forecaster'!B19
A19: Valuation Data:
A20: Cost of Equity Capital | B20: ='Valuation Parameters'!J9
A21: Valuation Date | B21: ='Valuation Parameters'!J11
A22: Estimated Price/Share | B22: ='Residual Income Valuations'!B27
A23: Estimated Price/Earnings Ratio | B23: =B22/'Model Summary'!B16
A24: Estimated Market/Book Ratio | B24: =(B22*'Residual Income Valuations'!B26)/'Financial Statements'!F57

Sheet Master
A1: 1 800 FLOWERS COM INC | B1: FLWS | C1: 1 800 FLOWERS COM INC | D1: 5990 | F1: SIC | G1: FF12 | H1: FF49 | I1: SEC List Industry Title
A2: 10X GENOMICS, INC. | B2: TXG | C2: 10X GENOMICS, INC. | D2: 3826 | F2: 100 | G2: CONSUMER NONDURABLES | H2: AGRICULTURE | I2: AGRICULTURAL PRODUCTION-CROPS
A3: 111, INC. | B3: YI | C3: 111, INC. | D3: 5912 | F3: 200 | G3: CONSUMER NONDURABLES | H3: AGRICULTURE | I3: AGRICULTURAL PROD-LIVESTOCK & ANIMAL SPECIALTIES
A4: 17 EDUCATION & TECHNOLOGY GROUP INC. | B4: YQ | C4: 17 EDUCATION & TECHNOLOGY GROUP INC. | D4: 8200 | F4: 700 | G4: CONSUMER NONDURABLES | H4: AGRICULTURE | I4: AGRICULTURAL SERVICES
A5: 1847 GOEDEKER INC. | B5: GOED | C5: 1847 GOEDEKER INC. | D5: 5700 | F5: 800 | G5: CONSUMER NONDURABLES | H5: CONSTRUCTION MATERIALS | I5: FORESTRY
A6: 1895 BANCORP OF WISCONSIN, INC. /MD/ | B6: BCOW | C6: 1895 BANCORP OF WISCONSIN, INC. /MD/ | D6: 6036 | F6: 900 | G6: CONSUMER NONDURABLES | H6: RECREATION | I6: FISHING, HUNTING AND TRAPPING
A7: 1LIFE HEALTHCARE INC | B7: ONEM | C7: 1LIFE HEALTHCARE INC | D7: 8011 | F7: 1000 | G7: OTHER | H7: NON-METALLIC AND INDUSTRIAL METAL MINING | I7: METAL MINING
A8: 1ST SOURCE CORP | B8: SRCE | C8: 1ST SOURCE CORP | D8: 6022 | F8: 1040 | G8: OTHER | H8: PRECIOUS METALS | I8: GOLD AND SILVER ORES
A9: 1STDIBS.COM, INC. | B9: DIBS | C9: 1STDIBS.COM, INC. | D9: 5961 | F9: 1090 | G9: OTHER | H9: NON-METALLIC AND INDUSTRIAL METAL MINING | I9: MISCELLANEOUS METAL ORES
A10: 22ND CENTURY GROUP, INC. | B10: XXII | C10: 22ND CENTURY GROUP, INC. | D10: 2111 | F10: 1220 | G10: ENERGY | H10: COAL | I10: BITUMINOUS COAL & LIGNITE MINING
A11: 23ANDME HOLDING CO. | B11: ME | C11: 23ANDME HOLDING CO. | D11: 2834 | F11: 1221 | G11: ENERGY | H11: COAL | I11: BITUMINOUS COAL & LIGNITE SURFACE MINING
A12: 2SEVENTY BIO, INC. | B12: TSVT | C12: 2SEVENTY BIO, INC. | D12: 2834 | F12: 1311 | G12: ENERGY | H12: PETROLEUM AND NATURAL GAS | I12: CRUDE PETROLEUM & NATURAL GAS
A13: 2U, INC. | B13: TWOU | C13: 2U, INC. | D13: 7372 | F13: 1381 | G13: OTHER | H13: PETROLEUM AND NATURAL GAS | I13: DRILLING OIL & GAS WELLS
... A445: AXT INC | B445: AXTI | C445: AXT INC | D445: 3674 | F445: 9995 | G445: OTHER | H445: ALMOST NOTHING | I445: NON-OPERATING ESTABLISHMENTS
A446: AYALA PHARMACEUTICALS, INC. | B446: AYLA | C446: AYALA PHARMACEUTICALS, INC. | D446: 2836
A447: AYRO, INC. | B447: AYRO | C447: AYRO, INC. | D447: 4899
A448: AYTU BIOPHARMA, INC | B448: AYTU | C448: AYTU BIOPHARMA, INC | D448: 2834
A449: AZEK CO INC. | B449: AZEK | C449: AZEK CO INC. | D449: 3089
A450: AZIYO BIOLOGICS, INC. | B450: AZYO | C450: AZIYO BIOLOGICS, INC. | D450: 2836
A451: AZURE POWER GLOBAL LTD | B451: AZRE | C451: AZURE POWER GLOBAL LTD | D451: 4911
A452: AZZ INC | B452: AZZ | C452: AZZ INC | D452: 3640
A453: B&G FOODS, INC. | B453: BGS | C453: B&G FOODS, INC. | D453: 2000
A454: B. RILEY FINANCIAL, INC. | B454: RILY | C454: B. RILEY FINANCIAL, INC. | D454: 6282
A455: BABCOCK & WILCOX ENTERPRISES, INC. | B455: BW | C455: BABCOCK & WILCOX ENTERPRISES, INC. | D455: 3433
A456: BACKBLAZE, INC. | B456: BLZE | C456: BACKBLAZE, INC. | D456: 7372
A457: BADGER METER INC | B457: BMI | C457: BADGER METER INC | D457: 3824
... A4184: ZYNEX INC | B4184: ZYXI | C4184: ZYNEX INC | D4184: 3845
